Workbook
Name Country_list: Lookups!$H$3:$H$252
Name Currency_list: Lookups!$P$3:$P$163
Name current_date: Parameters!$D$9
Name Development_classes: Parameters!$C$14:$C$213
Name IQ_CH: 110000
Name IQ_CQ: 5000
Name IQ_CY: 10000
Name IQ_DAILY: 500000
Name IQ_FH: 100000
Name IQ_FQ: 500
Name IQ_FY: 1000
Name IQ_LTM: 2000
Name IQ_MONTH: 15000
Name IQ_NTM: 6000
Name IQ_WEEK: 50000
Name IQ_YTD: 3000
Name LDF_type_options: Lookups!$R$3:$R$6
Name LOBs_names: Lookups!$B$3:$B$25
Name month_final_development: Parameters!$D$8
Name month_first_development: Parameters!$D$5
Name P_NP_types: Lookups!$E$3:$E$6
Name Projection_classes: Parameters!$C$219:$C$418
Name re_insurance_list: Lookups!$N$3:$N$5
Name Region_list: Lookups!$K$3:$K$8
Name triangle_grouping_data: Parameters!$C$219:$AA$418
Name triangle_increments_months: Parameters!$D$6
Name triangle_start_date: Parameters!$D$4

Sheet Parameters
B3: Triangle Shape Parameters | E3: guide | F3: Checks
C4: Triangle start (t=0) date | D4: 36892 | E4: YYYY-MM-DD | F4: =triangle_start_date=Triangles!F3 -> TRUE | H4: Mandatory
C5: Month of first development | D5: 6 | E5: first month in triangle | H5: Optional
C6: Development period increments (months) | D6: 12 | E6: triangle increments (column)
C7: Origin period increments (months) | D7: 12 | E7: triangle increments (row)
C8: Month of final development | D8: 294 | E8: Latest month in the largest triangle | F8: =IF(ISERROR(MATCH(month_final_development,Triangles!$G$2:$FA$2, 0)), "Can't find this development month in triangle. Please be consistent with Triangle.", "OK") -> OK
C9: Inception Date | D9: 46023 | E9: YYYY-MM-DD
C10: Expiry Date | D10: 46387 | E10: YYYY-MM-DD
B11: Triangular data list (LOB/Class)
Q12: Cedant Business Segment Names (Optional)
B13: # | C13: Triangle Name | D13: Proportional/Non-proportional | E13: Start Year | F13: End Year | G13: Region | H13: Country | I13: Re/Ins/Retro | J13: LT LOB 1 (Dropdown List) | K13: LT LOB 1 Allocation | L13: LT LOB 2 (Dropdown List) | M13: LT LOB 2 Allocation | N13: LT LOB 3 (Dropdown List) | O13: LT LOB 3 Allocation | P13: LT LOB 4 (Dropdown List) | Q13: LT LOB 4 Allocation | R13: LT LOB 5 (Dropdown List) | S13: LT LOB 5 Allocation | T13: Allocation Check | U13: Currency | V13: Currency Rate | W13: Segment 1 | X13: Segment 2 | Y13: Segment 3 | Z13: Segment 4 | AA13: Segment 5 | AB13: Premium Triangle Source | AC13: Incurred Triangle Source | AD13: Paid Triangle Source | AE13: Ultimate Triangle Source
B14: 1 | C14: Umbrella Ex C V Starr | D14: Proportional | E14: 2001 | F14: 2025 | G14: North America | J14: Casualty | K14: 1 | T14: =IF(AND(C14<>"",SUM(K14,M14,O14,Q14,S14)=1),"pass",IF(AND(C14="",SUM(K14,M14,O14,Q14,S14)=0),"pass","fail")) -> pass | AB14: Cedant provided | AC14: Cedant provided | AD14: Cedant provided
B15: 2 | C15: General Liability ex ARL | D15: Proportional | E15: 2001 | F15: 2025 | G15: North America | J15: Casualty | K15: 1 | T15: =IF(AND(C15<>"",SUM(K15,M15,O15,Q15,S15)=1),"pass",IF(AND(C15="",SUM(K15,M15,O15,Q15,S15)=0),"pass","fail")) -> pass | AB15: Cedant provided | AC15: Cedant provided | AD15: Cedant provided
B16: 3 | C16: Risk Management | D16: Proportional | E16: 2001 | F16: 2025 | G16: North America | J16: Casualty | K16: 1 | T16: =IF(AND(C16<>"",SUM(K16,M16,O16,Q16,S16)=1),"pass",IF(AND(C16="",SUM(K16,M16,O16,Q16,S16)=0),"pass","fail")) -> pass | AB16: Cedant provided | AC16: Cedant provided | AD16: Cedant provided
B17: 4 | C17: Auto Liability | D17: Proportional | E17: 2001 | F17: 2025 | G17: North America | J17: Casualty | K17: 1 | T17: =IF(AND(C17<>"",SUM(K17,M17,O17,Q17,S17)=1),"pass",IF(AND(C17="",SUM(K17,M17,O17,Q17,S17)=0),"pass","fail")) -> pass | AB17: Cedant provided | AC17: Cedant provided | AD17: Cedant provided
B18: 5 | C18: EverSports | D18: Proportional | E18: 2001 | F18: 2025 | G18: North America | J18: Casualty | K18: 1 | T18: =IF(AND(C18<>"",SUM(K18,M18,O18,Q18,S18)=1),"pass",IF(AND(C18="",SUM(K18,M18,O18,Q18,S18)=0),"pass","fail")) -> pass | AB18: Cedant provided | AC18: Cedant provided | AD18: Cedant provided
B19: 6 | C19: California Workers Compensation | D19: Proportional | E19: 2001 | F19: 2025 | G19: North America | J19: Casualty | K19: 1 | T19: =IF(AND(C19<>"",SUM(K19,M19,O19,Q19,S19)=1),"pass",IF(AND(C19="",SUM(K19,M19,O19,Q19,S19)=0),"pass","fail")) -> pass | AB19: Cedant provided | AC19: Cedant provided | AD19: Cedant provided
B20: 7 | C20: Management Liability Excess | D20: Non Proportional | E20: 2001 | F20: 2025 | G20: North America | J20: Casualty | K20: 1 | T20: =IF(AND(C20<>"",SUM(K20,M20,O20,Q20,S20)=1),"pass",IF(AND(C20="",SUM(K20,M20,O20,Q20,S20)=0),"pass","fail")) -> pass
B21: 8 | C21: Management Liability Primary | D21: Proportional | E21: 2001 | F21: 2025 | G21: North America | J21: Casualty | K21: 1 | T21: =IF(AND(C21<>"",SUM(K21,M21,O21,Q21,S21)=1),"pass",IF(AND(C21="",SUM(K21,M21,O21,Q21,S21)=0),"pass","fail")) -> pass
B22: 9 | C22: Canada Casualty | D22: Proportional | E22: 2001 | F22: 2025 | G22: North America | J22: Casualty | K22: 1 | T22: =IF(AND(C22<>"",SUM(K22,M22,O22,Q22,S22)=1),"pass",IF(AND(C22="",SUM(K22,M22,O22,Q22,S22)=0),"pass","fail")) -> pass
B23: 10 | C23: Countrywide Workers Compensation | D23: Proportional | E23: 2001 | F23: 2025 | G23: North America | J23: Casualty | K23: 1 | T23: =IF(AND(C23<>"",SUM(K23,M23,O23,Q23,S23)=1),"pass",IF(AND(C23="",SUM(K23,M23,O23,Q23,S23)=0),"pass","fail")) -> pass
B24: 11 | C24: General Liability ARL | D24: Proportional | E24: 2001 | F24: 2025 | G24: North America | J24: Casualty | K24: 1 | T24: =IF(AND(C24<>"",SUM(K24,M24,O24,Q24,S24)=1),"pass",IF(AND(C24="",SUM(K24,M24,O24,Q24,S24)=0),"pass","fail")) -> pass
B25: 12 | T25: =IF(AND(C25<>"",SUM(K25,M25,O25,Q25,S25)=1),"pass",IF(AND(C25="",SUM(K25,M25,O25,Q25,S25)=0),"pass","fail")) -> pass
B26: 13 | T26: =IF(AND(C26<>"",SUM(K26,M26,O26,Q26,S26)=1),"pass",IF(AND(C26="",SUM(K26,M26,O26,Q26,S26)=0),"pass","fail")) -> pass
B27: 14 | T27: =IF(AND(C27<>"",SUM(K27,M27,O27,Q27,S27)=1),"pass",IF(AND(C27="",SUM(K27,M27,O27,Q27,S27)=0),"pass","fail")) -> pass
B28: 15 | T28: =IF(AND(C28<>"",SUM(K28,M28,O28,Q28,S28)=1),"pass",IF(AND(C28="",SUM(K28,M28,O28,Q28,S28)=0),"pass","fail")) -> pass
B29: 16 | T29: =IF(AND(C29<>"",SUM(K29,M29,O29,Q29,S29)=1),"pass",IF(AND(C29="",SUM(K29,M29,O29,Q29,S29)=0),"pass","fail")) -> pass
B30: 17 | T30: =IF(AND(C30<>"",SUM(K30,M30,O30,Q30,S30)=1),"pass",IF(AND(C30="",SUM(K30,M30,O30,Q30,S30)=0),"pass","fail")) -> pass
B31: 18 | T31: =IF(AND(C31<>"",SUM(K31,M31,O31,Q31,S31)=1),"pass",IF(AND(C31="",SUM(K31,M31,O31,Q31,S31)=0),"pass","fail")) -> pass
B32: 19 | T32: =IF(AND(C32<>"",SUM(K32,M32,O32,Q32,S32)=1),"pass",IF(AND(C32="",SUM(K32,M32,O32,Q32,S32)=0),"pass","fail")) -> pass
B33: 20 | T33: =IF(AND(C33<>"",SUM(K33,M33,O33,Q33,S33)=1),"pass",IF(AND(C33="",SUM(K33,M33,O33,Q33,S33)=0),"pass","fail")) -> pass
B34: 21 | T34: =IF(AND(C34<>"",SUM(K34,M34,O34,Q34,S34)=1),"pass",IF(AND(C34="",SUM(K34,M34,O34,Q34,S34)=0),"pass","fail")) -> pass
B35: 22 | T35: =IF(AND(C35<>"",SUM(K35,M35,O35,Q35,S35)=1),"pass",IF(AND(C35="",SUM(K35,M35,O35,Q35,S35)=0),"pass","fail")) -> pass
B36: 23 | T36: =IF(AND(C36<>"",SUM(K36,M36,O36,Q36,S36)=1),"pass",IF(AND(C36="",SUM(K36,M36,O36,Q36,S36)=0),"pass","fail")) -> pass
... B213: 200 | T213: =IF(AND(C213<>"",SUM(K213,M213,O213,Q213,S213)=1),"pass",IF(AND(C213="",SUM(K213,M213,O213,Q213,S213)=0),"pass","fail")) -> pass
B216: Define aggregation/grouping of triangles for projection
S217: Cedant Business Segment Names (Optional)
B218: # | C218: Description (free text) | D218: Proportional/Non-proportional | E218: Triangle 1 | F218: Triangle 2 | G218: Region | H218: Country | I218: Re/Ins/Retro | J218: LT LOB 1 (Dropdown List) | K218: LT LOB 1 Allocation | L218: LT LOB 2 (Dropdown List) | M218: LT LOB 2 Allocation | N218: LT LOB 3 (Dropdown List) | O218: LT LOB 3 Allocation | P218: LT LOB 4 (Dropdown List) | Q218: LT LOB 4 Allocation | R218: LT LOB 5 (Dropdown List) | S218: LT LOB 5 Allocation | T218: Allocation Check | U218: Currency | V218: Currency Rate | W218: Segment 1 | X218: Segment 2 | Y218: Segment 3 | Z218: Segment 4 | AA218: Segment 5
B219: 1 | C219: Umbrella Ex C V Starr | D219: Proportional | E219: Umbrella Ex C V Starr | G219: North America | J219: Casualty | K219: 1 | T219: =IF(AND(C219<>"",SUM(K219,M219,O219,Q219,S219)=1),"pass",IF(AND(C219="",SUM(K219,M219,O219,Q219,S219)=0),"pass","fail")) -> pass
B220: 2 | C220: General Liability ex ARL | D220: Proportional | E220: General Liability ex ARL | G220: North America | J220: Casualty | K220: 1 | T220: =IF(AND(C220<>"",SUM(K220,M220,O220,Q220,S220)=1),"pass",IF(AND(C220="",SUM(K220,M220,O220,Q220,S220)=0),"pass","fail")) -> pass
B221: 3 | C221: Risk Management | D221: Proportional | E221: Risk Management | G221: North America | J221: Casualty | K221: 1 | T221: =IF(AND(C221<>"",SUM(K221,M221,O221,Q221,S221)=1),"pass",IF(AND(C221="",SUM(K221,M221,O221,Q221,S221)=0),"pass","fail")) -> pass
B222: 4 | C222: Auto Liability | D222: Proportional | E222: Auto Liability | G222: North America | J222: Casualty | K222: 1 | T222: =IF(AND(C222<>"",SUM(K222,M222,O222,Q222,S222)=1),"pass",IF(AND(C222="",SUM(K222,M222,O222,Q222,S222)=0),"pass","fail")) -> pass
B223: 5 | C223: EverSports | D223: Proportional | E223: EverSports | G223: North America | J223: Casualty | K223: 1 | T223: =IF(AND(C223<>"",SUM(K223,M223,O223,Q223,S223)=1),"pass",IF(AND(C223="",SUM(K223,M223,O223,Q223,S223)=0),"pass","fail")) -> pass
B224: 6 | C224: California Workers Compensation | D224: Proportional | E224: California Workers Compensation | G224: North America | J224: Casualty | K224: 1 | T224: =IF(AND(C224<>"",SUM(K224,M224,O224,Q224,S224)=1),"pass",IF(AND(C224="",SUM(K224,M224,O224,Q224,S224)=0),"pass","fail")) -> pass
B225: 7 | C225: Management Liability Excess | D225: Non Proportional | E225: Management Liability Excess | G225: North America | J225: Casualty | K225: 1 | T225: =IF(AND(C225<>"",SUM(K225,M225,O225,Q225,S225)=1),"pass",IF(AND(C225="",SUM(K225,M225,O225,Q225,S225)=0),"pass","fail")) -> pass
B226: 8 | C226: Management Liability Primary | D226: Proportional | E226: Management Liability Primary | G226: North America | J226: Casualty | K226: 1 | T226: =IF(AND(C226<>"",SUM(K226,M226,O226,Q226,S226)=1),"pass",IF(AND(C226="",SUM(K226,M226,O226,Q226,S226)=0),"pass","fail")) -> pass
B227: 9 | C227: Canada Casualty | D227: Proportional | E227: Canada Casualty | G227: North America | J227: Casualty | K227: 1 | T227: =IF(AND(C227<>"",SUM(K227,M227,O227,Q227,S227)=1),"pass",IF(AND(C227="",SUM(K227,M227,O227,Q227,S227)=0),"pass","fail")) -> pass
B228: 10 | C228: Countrywide Workers Compensation | D228: Proportional | E228: Countrywide Workers Compensation | G228: North America | J228: Casualty | K228: 1 | T228: =IF(AND(C228<>"",SUM(K228,M228,O228,Q228,S228)=1),"pass",IF(AND(C228="",SUM(K228,M228,O228,Q228,S228)=0),"pass","fail")) -> pass
B229: 11 | C229: General Liability ARL | D229: Proportional | E229: General Liability ARL | G229: North America | J229: Casualty | K229: 1 | T229: =IF(AND(C229<>"",SUM(K229,M229,O229,Q229,S229)=1),"pass",IF(AND(C229="",SUM(K229,M229,O229,Q229,S229)=0),"pass","fail")) -> pass
B230: 12 | T230: =IF(AND(C230<>"",SUM(K230,M230,O230,Q230,S230)=1),"pass",IF(AND(C230="",SUM(K230,M230,O230,Q230,S230)=0),"pass","fail")) -> pass
B231: 13 | T231: =IF(AND(C231<>"",SUM(K231,M231,O231,Q231,S231)=1),"pass",IF(AND(C231="",SUM(K231,M231,O231,Q231,S231)=0),"pass","fail")) -> pass
B232: 14 | T232: =IF(AND(C232<>"",SUM(K232,M232,O232,Q232,S232)=1),"pass",IF(AND(C232="",SUM(K232,M232,O232,Q232,S232)=0),"pass","fail")) -> pass
B233: 15 | T233: =IF(AND(C233<>"",SUM(K233,M233,O233,Q233,S233)=1),"pass",IF(AND(C233="",SUM(K233,M233,O233,Q233,S233)=0),"pass","fail")) -> pass
B234: 16 | T234: =IF(AND(C234<>"",SUM(K234,M234,O234,Q234,S234)=1),"pass",IF(AND(C234="",SUM(K234,M234,O234,Q234,S234)=0),"pass","fail")) -> pass
B235: 17 | T235: =IF(AND(C235<>"",SUM(K235,M235,O235,Q235,S235)=1),"pass",IF(AND(C235="",SUM(K235,M235,O235,Q235,S235)=0),"pass","fail")) -> pass
B236: 18 | T236: =IF(AND(C236<>"",SUM(K236,M236,O236,Q236,S236)=1),"pass",IF(AND(C236="",SUM(K236,M236,O236,Q236,S236)=0),"pass","fail")) -> pass
B237: 19 | T237: =IF(AND(C237<>"",SUM(K237,M237,O237,Q237,S237)=1),"pass",IF(AND(C237="",SUM(K237,M237,O237,Q237,S237)=0),"pass","fail")) -> pass
B238: 20 | T238: =IF(AND(C238<>"",SUM(K238,M238,O238,Q238,S238)=1),"pass",IF(AND(C238="",SUM(K238,M238,O238,Q238,S238)=0),"pass","fail")) -> pass
B239: 21 | T239: =IF(AND(C239<>"",SUM(K239,M239,O239,Q239,S239)=1),"pass",IF(AND(C239="",SUM(K239,M239,O239,Q239,S239)=0),"pass","fail")) -> pass
B240: 22 | T240: =IF(AND(C240<>"",SUM(K240,M240,O240,Q240,S240)=1),"pass",IF(AND(C240="",SUM(K240,M240,O240,Q240,S240)=0),"pass","fail")) -> pass
B241: 23 | T241: =IF(AND(C241<>"",SUM(K241,M241,O241,Q241,S241)=1),"pass",IF(AND(C241="",SUM(K241,M241,O241,Q241,S241)=0),"pass","fail")) -> pass
... B418: 200 | T418: =IF(AND(C418<>"",SUM(K418,M418,O418,Q418,S418)=1),"pass",IF(AND(C418="",SUM(K418,M418,O418,Q418,S418)=0),"pass","fail")) -> pass

Sheet Triangles
G1: Development months
A2: LOB (dropdown) | B2: Type (Incurred / Paid …) | C2: Loss type | D2: Basis (Accident Year / UW Year) | E2: Currency (e.g. USD, GBP …) | F2: Origin Year | G2: =month_first_development -> 6 | H2: =G2+triangle_increments_months -> 18 | I2: =H2+triangle_increments_months -> 30 | J2: =I2+triangle_increments_months -> 42 | K2: =J2+triangle_increments_months -> 54 | L2: =K2+triangle_increments_months -> 66 | M2: =L2+triangle_increments_months -> 78 | N2: =M2+triangle_increments_months -> 90 | O2: =N2+triangle_increments_months -> 102 | ... FA2: =EZ2+triangle_increments_months -> 1806
A3: Umbrella Ex C V Starr | B3: Net Written Premium | C3: All | D3: UW Year | E3: USD | F3: 36892 | G3: 6423779.1 | H3: 6423779.1 | I3: 6423779.1 | J3: 6423779.1 | K3: 6423779.1 | L3: 6423779.1 | M3: 6423779.1 | N3: 6423779.1 | O3: 6423779.1 | P3: 6423779.1 | Q3: 6423779.1 | R3: 6423779.1 | S3: 6423779.1 | T3: 6423779.1 | U3: 6423779.1 | V3: 6423779.1 | W3: 6423779.1 | X3: 6423779.1 | Y3: 6423779.1 | Z3: 6423779.1 | AA3: 6423779.1 | AB3: 6423779.1 | AC3: 6423779.1 | AD3: 6423779.1 | AE3: 6423779.1
A4: Umbrella Ex C V Starr | B4: Net Written Premium | C4: All | D4: UW Year | E4: USD | F4: 37257 | G4: 2293989.5 | H4: 2293989.5 | I4: 2293989.5 | J4: 2293989.5 | K4: 2293989.5 | L4: 2293989.5 | M4: 2293989.5 | N4: 2293989.5 | O4: 2293989.5 | P4: 2293989.5 | Q4: 2293989.5 | R4: 2293989.5 | S4: 2293989.5 | T4: 2293989.5 | U4: 2293989.5 | V4: 2293989.5 | W4: 2293989.5 | X4: 2293989.5 | Y4: 2293989.5 | Z4: 2293989.5 | AA4: 2293989.5 | AB4: 2293989.5 | AC4: 2293989.5 | AD4: 2293989.5
A5: Umbrella Ex C V Starr | B5: Net Written Premium | C5: All | D5: UW Year | E5: USD | F5: 37622 | G5: 4382395.6 | H5: 4382395.6 | I5: 4382395.6 | J5: 4382395.6 | K5: 4382395.6 | L5: 4382395.6 | M5: 4382395.6 | N5: 4382395.6 | O5: 4382395.6 | P5: 4382395.6 | Q5: 4382395.6 | R5: 4382395.6 | S5: 4382395.6 | T5: 4382395.6 | U5: 4382395.6 | V5: 4382395.6 | W5: 4382395.6 | X5: 4382395.6 | Y5: 4382395.6 | Z5: 4382395.6 | AA5: 4382395.6 | AB5: 4382395.6 | AC5: 4382395.6
A6: Umbrella Ex C V Starr | B6: Net Written Premium | C6: All | D6: UW Year | E6: USD | F6: 37987 | G6: 12020857 | H6: 12020857 | I6: 12020857 | J6: 12020857 | K6: 12020857 | L6: 12020857 | M6: 12020857 | N6: 12020857 | O6: 12020857 | P6: 12020857 | Q6: 12020857 | R6: 12020857 | S6: 12020857 | T6: 12020857 | U6: 12020857 | V6: 12020857 | W6: 12020857 | X6: 12020857 | Y6: 12020857 | Z6: 12020857 | AA6: 12020857 | AB6: 12020857
A7: Umbrella Ex C V Starr | B7: Net Written Premium | C7: All | D7: UW Year | E7: USD | F7: 38353 | G7: 13122414 | H7: 13122414 | I7: 13122414 | J7: 13122414 | K7: 13122414 | L7: 13122414 | M7: 13122414 | N7: 13122414 | O7: 13122414 | P7: 13122414 | Q7: 13122414 | R7: 13122414 | S7: 13122414 | T7: 13122414 | U7: 13122414 | V7: 13122414 | W7: 13122414 | X7: 13122414 | Y7: 13122414 | Z7: 13122414 | AA7: 13122414
A8: Umbrella Ex C V Starr | B8: Net Written Premium | C8: All | D8: UW Year | E8: USD | F8: 38718 | G8: 14510011 | H8: 14510011 | I8: 14510011 | J8: 14510011 | K8: 14510011 | L8: 14510011 | M8: 14510011 | N8: 14510011 | O8: 14510011 | P8: 14510011 | Q8: 14510011 | R8: 14510011 | S8: 14510011 | T8: 14510011 | U8: 14510011 | V8: 14510011 | W8: 14510011 | X8: 14510011 | Y8: 14510011 | Z8: 14510011
A9: Umbrella Ex C V Starr | B9: Net Written Premium | C9: All | D9: UW Year | E9: USD | F9: 39083 | G9: 14938715 | H9: 14938715 | I9: 14938715 | J9: 14938715 | K9: 14938715 | L9: 14938715 | M9: 14938715 | N9: 14938715 | O9: 14938715 | P9: 14938715 | Q9: 14938715 | R9: 14938715 | S9: 14938715 | T9: 14938715 | U9: 14938715 | V9: 14938715 | W9: 14938715 | X9: 14938715 | Y9: 14938715
A10: Umbrella Ex C V Starr | B10: Net Written Premium | C10: All | D10: UW Year | E10: USD | F10: 39448 | G10: 15977949 | H10: 15977949 | I10: 15977949 | J10: 15977949 | K10: 15977949 | L10: 15977949 | M10: 15977949 | N10: 15977949 | O10: 15977949 | P10: 15977949 | Q10: 15977949 | R10: 15977949 | S10: 15977949 | T10: 15977949 | U10: 15977949 | V10: 15977949 | W10: 15977949 | X10: 15977949
A11: Umbrella Ex C V Starr | B11: Net Written Premium | C11: All | D11: UW Year | E11: USD | F11: 39814 | G11: 13641854 | H11: 13641854 | I11: 13641854 | J11: 13641854 | K11: 13641854 | L11: 13641854 | M11: 13641854 | N11: 13641854 | O11: 13641854 | P11: 13641854 | Q11: 13641854 | R11: 13641854 | S11: 13641854 | T11: 13641854 | U11: 13641854 | V11: 13641854 | W11: 13641854
A12: Umbrella Ex C V Starr | B12: Net Written Premium | C12: All | D12: UW Year | E12: USD | F12: 40179 | G12: 14844336 | H12: 14844336 | I12: 14844336 | J12: 14844336 | K12: 14844336 | L12: 14844336 | M12: 14844336 | N12: 14844336 | O12: 14844336 | P12: 14844336 | Q12: 14844336 | R12: 14844336 | S12: 14844336 | T12: 14844336 | U12: 14844336 | V12: 14844336
A13: Umbrella Ex C V Starr | B13: Net Written Premium | C13: All | D13: UW Year | E13: USD | F13: 40544 | G13: 13033878 | H13: 13033878 | I13: 13033878 | J13: 13033878 | K13: 13033878 | L13: 13033878 | M13: 13033878 | N13: 13033878 | O13: 13033878 | P13: 13033878 | Q13: 13033878 | R13: 13033878 | S13: 13033878 | T13: 13033878 | U13: 13033878
A14: Umbrella Ex C V Starr | B14: Net Written Premium | C14: All | D14: UW Year | E14: USD | F14: 40909 | G14: 14350697 | H14: 14350697 | I14: 14350697 | J14: 14350697 | K14: 14350697 | L14: 14350697 | M14: 14350697 | N14: 14350697 | O14: 14350697 | P14: 14350697 | Q14: 14350697 | R14: 14350697 | S14: 14350697 | T14: 14350697
A15: Umbrella Ex C V Starr | B15: Net Written Premium | C15: All | D15: UW Year | E15: USD | F15: 41275 | G15: 14692846 | H15: 14692846 | I15: 14692846 | J15: 14692846 | K15: 14692846 | L15: 14692846 | M15: 14692846 | N15: 14692846 | O15: 14692846 | P15: 14692846 | Q15: 14692846 | R15: 14692846 | S15: 14692846
A16: Umbrella Ex C V Starr | B16: Net Written Premium | C16: All | D16: UW Year | E16: USD | F16: 41640 | G16: 21571417 | H16: 21571417 | I16: 21571417 | J16: 21571417 | K16: 21571417 | L16: 21571417 | M16: 21571417 | N16: 21571417 | O16: 21571417 | P16: 21571417 | Q16: 21571417 | R16: 21571417
A17: Umbrella Ex C V Starr | B17: Net Written Premium | C17: All | D17: UW Year | E17: USD | F17: 42005 | G17: 31636740 | H17: 31636740 | I17: 31636740 | J17: 31636740 | K17: 31636740 | L17: 31636740 | M17: 31636740 | N17: 31636740 | O17: 31636740 | P17: 31636740 | Q17: 31636740
A18: Umbrella Ex C V Starr | B18: Net Written Premium | C18: All | D18: UW Year | E18: USD | F18: 42370 | G18: 45216769 | H18: 45216769 | I18: 45216769 | J18: 45216769 | K18: 45216769 | L18: 45216769 | M18: 45216769 | N18: 45216769 | O18: 45216769 | P18: 45216769
A19: Umbrella Ex C V Starr | B19: Net Written Premium | C19: All | D19: UW Year | E19: USD | F19: 42736 | G19: 84475419 | H19: 84475419 | I19: 84475419 | J19: 84475419 | K19: 84475419 | L19: 84475419 | M19: 84475419 | N19: 84475419 | O19: 84475419
A20: Umbrella Ex C V Starr | B20: Net Written Premium | C20: All | D20: UW Year | E20: USD | F20: 43101 | G20: 1.2918805e+08 | H20: 1.2918805e+08 | I20: 1.2918805e+08 | J20: 1.2918805e+08 | K20: 1.2918805e+08 | L20: 1.2918805e+08 | M20: 1.2918805e+08 | N20: 1.2918805e+08
A21: Umbrella Ex C V Starr | B21: Net Written Premium | C21: All | D21: UW Year | E21: USD | F21: 43466 | G21: 1.8996554e+08 | H21: 1.8996554e+08 | I21: 1.8996554e+08 | J21: 1.8996554e+08 | K21: 1.8996554e+08 | L21: 1.8996554e+08 | M21: 1.8996554e+08
A22: Umbrella Ex C V Starr | B22: Net Written Premium | C22: All | D22: UW Year | E22: USD | F22: 43831 | G22: 2.8354491e+08 | H22: 2.8354491e+08 | I22: 2.8354491e+08 | J22: 2.8354491e+08 | K22: 2.8354491e+08 | L22: 2.8354491e+08
A23: Umbrella Ex C V Starr | B23: Net Written Premium | C23: All | D23: UW Year | E23: USD | F23: 44197 | G23: 4.0386135e+08 | H23: 4.0386135e+08 | I23: 4.0386135e+08 | J23: 4.0386135e+08 | K23: 4.0386135e+08
A24: Umbrella Ex C V Starr | B24: Net Written Premium | C24: All | D24: UW Year | E24: USD | F24: 44562 | G24: 5.0969035e+08 | H24: 5.0969035e+08 | I24: 5.0969035e+08 | J24: 5.0969035e+08
A25: Umbrella Ex C V Starr | B25: Net Written Premium | C25: All | D25: UW Year | E25: USD | F25: 44927 | G25: 5.7445655e+08 | H25: 5.7445655e+08 | I25: 5.7445655e+08
A26: Umbrella Ex C V Starr | B26: Net Written Premium | C26: All | D26: UW Year | E26: USD | F26: 45292 | G26: 6.075255e+08 | H26: 6.075255e+08
A27: Umbrella Ex C V Starr | B27: Net Written Premium | C27: All | D27: UW Year | E27: USD | F27: 45658 | G27: 2.6266859e+08
A28: Umbrella Ex C V Starr | B28: Incurred | C28: All | D28: UW Year | E28: USD | F28: 36892 | G28: 0 | H28: 0 | I28: 0 | J28: 1125000 | K28: 1125000 | L28: 1148855.6 | M28: 1298425.8 | N28: 948379.12 | O28: 948379.12 | P28: 948379.12 | Q28: 948379.12 | R28: 948379.12 | S28: 948379.12 | T28: 948379.12 | U28: 948379.12 | V28: 948379.12 | W28: 948379.12 | X28: 948379.12 | Y28: 948381.12 | Z28: 948381.12 | AA28: 948379.12 | AB28: 948379.12 | AC28: 948379.12 | AD28: 948379.12 | AE28: 948379.12
A29: Umbrella Ex C V Starr | B29: Incurred | C29: All | D29: UW Year | E29: USD | F29: 37257 | G29: 0 | H29: 0 | I29: 0 | J29: 0 | K29: 0 | L29: 0 | M29: 0 | N29: 0 | O29: 0 | P29: 0 | Q29: 0 | R29: 0 | S29: 0 | T29: 0 | U29: 0 | V29: 0 | W29: 0 | X29: 0 | Y29: 0 | Z29: 0 | AA29: 0 | AB29: 0 | AC29: 0 | AD29: 0
A30: Umbrella Ex C V Starr | B30: Incurred | C30: All | D30: UW Year | E30: USD | F30: 37622 | G30: 0 | H30: 0 | I30: 1000000 | J30: 1000000 | K30: 1000000 | L30: 1000000 | M30: 1000000 | N30: 1000000 | O30: 1000000 | P30: 1000000 | Q30: 1000000 | R30: 1000000 | S30: 1000000 | T30: 1000000 | U30: 1000000 | V30: 1000000 | W30: 1000000 | X30: 1000000 | Y30: 1000000 | Z30: 1000000 | AA30: 1000000 | AB30: 1000000 | AC30: 1000000
A31: Umbrella Ex C V Starr | B31: Incurred | C31: All | D31: UW Year | E31: USD | F31: 37987 | G31: 0 | H31: 1146861.6 | I31: 1131855.4 | J31: 1506893.8 | K31: 1506893.8 | L31: 1514170.1 | M31: 1514170.1 | N31: 2264170.1 | O31: 2264170.1 | P31: 2264170.1 | Q31: 2264170.1 | R31: 2264170.1 | S31: 2264170.1 | T31: 2264170.1 | U31: 2264170.1 | V31: 2264170.1 | W31: 2264170.1 | X31: 2264170.1 | Y31: 2264170.1 | Z31: 2264170.1 | AA31: 2264170.1 | AB31: 2264170.1
A32: Umbrella Ex C V Starr | B32: Incurred | C32: All | D32: UW Year | E32: USD | F32: 38353 | G32: 0 | H32: 626198.92 | I32: 5107.92 | J32: 15068.81 | K32: 6980.41 | L32: 7274.41 | M32: 7274.41 | N32: 7274.41 | O32: 7274.41 | P32: 7274.41 | Q32: 7274.41 | R32: 7274.41 | S32: 7274.41 | T32: 7274.41 | U32: 7274.41 | V32: 7274.41 | W32: 7274.41 | X32: 7274.41 | Y32: 7274.41 | Z32: 7274.41 | AA32: 7274.41
A33: Umbrella Ex C V Starr | B33: Incurred | C33: All | D33: UW Year | E33: USD | F33: 38718 | G33: 24000 | H33: 26.89 | I33: 4271477 | J33: 5810139.8 | K33: 5860394.1 | L33: 5940633.1 | M33: 5631634 | N33: 5161751.8 | O33: 5162281.7 | P33: 5162281.7 | Q33: 5162567.3 | R33: 5162567.3 | S33: 5162567.3 | T33: 5162567.3 | U33: 5162567.3 | V33: 5162567.3 | W33: 5162567.3 | X33: 5162567.3 | Y33: 5162567.3 | Z33: 5162567.3
A34: Umbrella Ex C V Starr | B34: Incurred | C34: All | D34: UW Year | E34: USD | F34: 39083 | G34: 4500 | H34: 2238617.5 | I34: 2456175.7 | J34: 5041682.8 | K34: 6557920.2 | L34: 8804636.3 | M34: 9808177.2 | N34: 10412177 | O34: 10412177 | P34: 10412177 | Q34: 10412177 | R34: 10412177 | S34: 10412177 | T34: 10412177 | U34: 10412178 | V34: 10412178 | W34: 10412178 | X34: 10412177 | Y34: 10412177
A35: Umbrella Ex C V Starr | B35: Incurred | C35: All | D35: UW Year | E35: USD | F35: 39448 | G35: 1 | H35: 500020 | I35: 350000 | J35: 1356510.4 | K35: 1207305.4 | L35: 3047409.7 | M35: 4958369.8 | N35: 4958369.8 | O35: 7958368.8 | P35: 8958368.8 | Q35: 8958368.8 | R35: 8958368.8 | S35: 8958368.8 | T35: 8958368.8 | U35: 8958368.8 | V35: 8958368.8 | W35: 8958368.8 | X35: 8958368.8
A36: Umbrella Ex C V Starr | B36: Incurred | C36: All | D36: UW Year | E36: USD | F36: 39814 | G36: 0 | H36: 1 | I36: 0 | J36: 253112.5 | K36: 235529.84 | L36: 1562932.6 | M36: 1363121.4 | N36: 1363119.4 | O36: 1363119.4 | P36: 1363119.4 | Q36: 1363119.4 | R36: 1363119.4 | S36: 1363119.4 | T36: 1363119.4 | U36: 1363119.4 | V36: 1363119.4 | W36: 1363119.4
A37: Umbrella Ex C V Starr | B37: Incurred | C37: All | D37: UW Year | E37: USD | F37: 40179 | G37: 0 | H37: 1426155 | I37: 1236381.6 | J37: 1739334.6 | K37: 4936085.2 | L37: 4759236.5 | M37: 4760021.2 | N37: 4760054.2 | O37: 4760032.2 | P37: 4760021.2 | Q37: 4760021.2 | R37: 4760121.2 | S37: 4760021.2 | T37: 4760021.2 | U37: 4760021.2 | V37: 4760021.2
A38: Umbrella Ex C V Starr | B38: Incurred | C38: All | D38: UW Year | E38: USD | F38: 40544 | G38: 127 | H38: 6522 | I38: 2618753.2 | J38: 5395097.3 | K38: 6215757.9 | L38: 6790837 | M38: 8290799 | N38: 8295874 | O38: 8295869 | P38: 8295839 | Q38: 8295832 | R38: 7044798 | S38: 7044799 | T38: 11309876 | U38: 11308460
A39: Umbrella Ex C V Starr | B39: Incurred | C39: All | D39: UW Year | E39: USD | F39: 40909 | G39: 0 | H39: 260910.75 | I39: 256610.91 | J39: 256512.91 | K39: 2707011.9 | L39: 7135086.4 | M39: 9412908.4 | N39: 11301424 | O39: 11301424 | P39: 11301393 | Q39: 11281393 | R39: 11031724 | S39: 11031725 | T39: 11031723
A40: Umbrella Ex C V Starr | B40: Incurred | C40: All | D40: UW Year | E40: USD | F40: 41275 | G40: 0 | H40: 5037495 | I40: 5118925.6 | J40: 5133700.1 | K40: 5213669.4 | L40: 7209234.3 | M40: 6601360.4 | N40: 6601360.4 | O40: 6601416.4 | P40: 6601416.4 | Q40: 6601417.4 | R40: 6602812 | S40: 6605812
A41: Umbrella Ex C V Starr | B41: Incurred | C41: All | D41: UW Year | E41: USD | F41: 41640 | G41: 0 | H41: 500 | I41: 1000116 | J41: 3972133 | K41: 9485204 | L41: 11184340 | M41: 9884337 | N41: 8823203.1 | O41: 8823204.1 | P41: 8823202.1 | Q41: 8823204.1 | R41: 8858204.1
A42: Umbrella Ex C V Starr | B42: Incurred | C42: All | D42: UW Year | E42: USD | F42: 42005 | G42: 150 | H42: 2079810.4 | I42: 5536691.9 | J42: 12981295 | K42: 17140448 | L42: 19320732 | M42: 19631427 | N42: 24579536 | O42: 24587023 | P42: 27587023 | Q42: 29087022
A43: Umbrella Ex C V Starr | B43: Incurred | C43: All | D43: UW Year | E43: USD | F43: 42370 | G43: 1101 | H43: 513345 | I43: 1352221.4 | J43: 6201527.9 | K43: 9830879.8 | L43: 10199314 | M43: 21281083 | N43: 24239616 | O43: 28516345 | P43: 28586342
A44: Umbrella Ex C V Starr | B44: Incurred | C44: All | D44: UW Year | E44: USD | F44: 42736 | G44: 5021 | H44: 5955788.5 | I44: 41059813 | J44: 45339775 | K44: 69160039 | L44: 84160907 | M44: 89060978 | N44: 1.0632241e+08 | O44: 1.0661362e+08
A45: Umbrella Ex C V Starr | B45: Incurred | C45: All | D45: UW Year | E45: USD | F45: 43101 | G45: 44 | H45: 19530474 | I45: 47541218 | J45: 66722681 | K45: 78598514 | L45: 89537049 | M45: 1.1756871e+08 | N45: 1.3496104e+08
A46: Umbrella Ex C V Starr | B46: Incurred | C46: All | D46: UW Year | E46: USD | F46: 43466 | G46: 61 | H46: 13240829 | I46: 67424213 | J46: 1.0546402e+08 | K46: 1.2925225e+08 | L46: 1.8125866e+08 | M46: 2.2029346e+08
A47: Umbrella Ex C V Starr | B47: Incurred | C47: All | D47: UW Year | E47: USD | F47: 43831 | G47: 20223 | H47: 4309798.4 | I47: 19022590 | J47: 74546855 | K47: 1.2056962e+08 | L47: 1.5309416e+08
A48: Umbrella Ex C V Starr | B48: Incurred | C48: All | D48: UW Year | E48: USD | F48: 44197 | G48: 165 | H48: 23084616 | I48: 87811763 | J48: 1.7502524e+08 | K48: 2.902358e+08
A49: Umbrella Ex C V Starr | B49: Incurred | C49: All | D49: UW Year | E49: USD | F49: 44562 | G49: 333 | H49: 16496240 | I49: 72221999 | J49: 1.8208594e+08
A50: Umbrella Ex C V Starr | B50: Incurred | C50: All | D50: UW Year | E50: USD | F50: 44927 | G50: 357865.29 | H50: 16829196 | I50: 1.2615205e+08
A51: Umbrella Ex C V Starr | B51: Incurred | C51: All | D51: UW Year | E51: USD | F51: 45292 | G51: 1883 | H51: 25459221
A52: Umbrella Ex C V Starr | B52: Incurred | C52: All | D52: UW Year | E52: USD | F52: 45658 | G52: 28772
A53: Umbrella Ex C V Starr | B53: Paid | C53: All | D53: UW Year | E53: USD | F53: 36892 | G53: 0 | H53: 0 | I53: 0 | J53: 1125000 | K53: 1125000 | L53: 1148853.6 | M53: 1298425.8 | N53: 948379.12 | O53: 948379.12 | P53: 948379.12 | Q53: 948379.12 | R53: 948379.12 | S53: 948379.12 | T53: 948379.12 | U53: 948379.12 | V53: 948379.12 | W53: 948379.12 | X53: 948379.12 | Y53: 948379.12 | Z53: 948379.12 | AA53: 948379.12 | AB53: 948379.12 | AC53: 948379.12 | AD53: 948379.12 | AE53: 948379.12
A54: Umbrella Ex C V Starr | B54: Paid | C54: All | D54: UW Year | E54: USD | F54: 37257 | G54: 0 | H54: 0 | I54: 0 | J54: 0 | K54: 0 | L54: 0 | M54: 0 | N54: 0 | O54: 0 | P54: 0 | Q54: 0 | R54: 0 | S54: 0 | T54: 0 | U54: 0 | V54: 0 | W54: 0 | X54: 0 | Y54: 0 | Z54: 0 | AA54: 0 | AB54: 0 | AC54: 0 | AD54: 0
A55: Umbrella Ex C V Starr | B55: Paid | C55: All | D55: UW Year | E55: USD | F55: 37622 | G55: 0 | H55: 0 | I55: 0 | J55: 0 | K55: 0 | L55: 0 | M55: 1000000 | N55: 1000000 | O55: 1000000 | P55: 1000000 | Q55: 1000000 | R55: 1000000 | S55: 1000000 | T55: 1000000 | U55: 1000000 | V55: 1000000 | W55: 1000000 | X55: 1000000 | Y55: 1000000 | Z55: 1000000 | AA55: 1000000 | AB55: 1000000 | AC55: 1000000
A56: Umbrella Ex C V Starr | B56: Paid | C56: All | D56: UW Year | E56: USD | F56: 37987 | G56: 0 | H56: 1126900 | I56: 1131855.4 | J56: 1506893.8 | K56: 1506893.8 | L56: 1514170.1 | M56: 1514170.1 | N56: 2264170.1 | O56: 2264170.1 | P56: 2264170.1 | Q56: 2264170.1 | R56: 2264170.1 | S56: 2264170.1 | T56: 2264170.1 | U56: 2264170.1 | V56: 2264170.1 | W56: 2264170.1 | X56: 2264170.1 | Y56: 2264170.1 | Z56: 2264170.1 | AA56: 2264170.1 | AB56: 2264170.1
A57: Umbrella Ex C V Starr | B57: Paid | C57: All | D57: UW Year | E57: USD | F57: 38353 | G57: 0 | H57: 5104.49 | I57: 5103.79 | J57: 6568.81 | K57: 6980.41 | L57: 7274.41 | M57: 7274.41 | N57: 7274.41 | O57: 7274.41 | P57: 7274.41 | Q57: 7274.41 | R57: 7274.41 | S57: 7274.41 | T57: 7274.41 | U57: 7274.41 | V57: 7274.41 | W57: 7274.41 | X57: 7274.41 | Y57: 7274.41 | Z57: 7274.41 | AA57: 7274.41
A58: Umbrella Ex C V Starr | B58: Paid | C58: All | D58: UW Year | E58: USD | F58: 38718 | G58: 5.89 | H58: 26.89 | I58: 20773.7 | J58: 5800148.8 | K58: 5860394.1 | L58: 5940633.1 | M58: 5631634 | N58: 5161751.8 | O58: 5162281.7 | P58: 5162281.7 | Q58: 5162567.3 | R58: 5162567.3 | S58: 5162567.3 | T58: 5162567.3 | U58: 5162567.3 | V58: 5162567.3 | W58: 5162567.3 | X58: 5162567.3 | Y58: 5162567.3 | Z58: 5162567.3
A59: Umbrella Ex C V Starr | B59: Paid | C59: All | D59: UW Year | E59: USD | F59: 39083 | G59: 0 | H59: 2225043.5 | I59: 2225700.7 | J59: 4032179.8 | K59: 5532238.9 | L59: 6554634.7 | M59: 9558176.6 | N59: 10412177 | O59: 10412177 | P59: 10412177 | Q59: 10412177 | R59: 10412177 | S59: 10412177 | T59: 10412177 | U59: 10412177 | V59: 10412177 | W59: 10412177 | X59: 10412177 | Y59: 10412177
A60: Umbrella Ex C V Starr | B60: Paid | C60: All | D60: UW Year | E60: USD | F60: 39448 | G60: 0 | H60: 0 | I60: 200000 | J60: 1201406.1 | K60: 1202305.1 | L60: 3047406.7 | M60: 3958368.8 | N60: 3958368.8 | O60: 3958368.8 | P60: 8958368.8 | Q60: 8958368.8 | R60: 8958368.8 | S60: 8958368.8 | T60: 8958368.8 | U60: 8958368.8 | V60: 8958368.8 | W60: 8958368.8 | X60: 8958368.8
A61: Umbrella Ex C V Starr | B61: Paid | C61: All | D61: UW Year | E61: USD | F61: 39814 | G61: 0 | H61: 0 | I61: 0 | J61: 2912.5 | K61: 235429.84 | L61: 562930.65 | M61: 1363119.4 | N61: 1363119.4 | O61: 1363119.4 | P61: 1363119.4 | Q61: 1363119.4 | R61: 1363119.4 | S61: 1363119.4 | T61: 1363119.4 | U61: 1363119.4 | V61: 1363119.4 | W61: 1363119.4
A62: Umbrella Ex C V Starr | B62: Paid | C62: All | D62: UW Year | E62: USD | F62: 40179 | G62: 0 | H62: 637739 | I62: 1236177.6 | J62: 1237241.6 | K62: 4436084.2 | L62: 4759235.5 | M62: 4760021.2 | N62: 4760021.2 | O62: 4760021.2 | P62: 4760021.2 | Q62: 4760021.2 | R62: 4760021.2 | S62: 4760021.2 | T62: 4760021.2 | U62: 4760021.2 | V62: 4760021.2
A63: Umbrella Ex C V Starr | B63: Paid | C63: All | D63: UW Year | E63: USD | F63: 40544 | G63: 0 | H63: 27 | I63: 7658.97 | J63: 3209495.3 | K63: 6115594.9 | L63: 6290735 | M63: 7040735 | N63: 7044798 | O63: 7044798 | P63: 7044798 | Q63: 7044798 | R63: 7044798 | S63: 7044798 | T63: 11292906 | U63: 11308460
A64: Umbrella Ex C V Starr | B64: Paid | C64: All | D64: UW Year | E64: USD | F64: 40909 | G64: 0 | H64: 17.75 | I64: 1410.91 | J64: 1410.91 | K64: 1751410.9 | L64: 3609543.4 | M64: 6612865.4 | N64: 11031393 | O64: 11031393 | P64: 11031393 | Q64: 11031393 | R64: 11031723 | S64: 11031723 | T64: 11031723
A65: Umbrella Ex C V Starr | B65: Paid | C65: All | D65: UW Year | E65: USD | F65: 41275 | G65: 0 | H65: 2495 | I65: 5117425.6 | J65: 5126100.1 | K65: 5213591.4 | L65: 5209212.3 | M65: 6601360.4 | N65: 6601360.4 | O65: 6601416.4 | P65: 6601416.4 | Q65: 6601416.4 | R65: 6602812 | S65: 6602812
A66: Umbrella Ex C V Starr | B66: Paid | C66: All | D66: UW Year | E66: USD | F66: 41640 | G66: 0 | H66: 0 | I66: 9 | J66: 3055 | K66: 5881159 | L66: 8599631.8 | M66: 8601116.8 | N66: 8823202.1 | O66: 8823202.1 | P66: 8823202.1 | Q66: 8823202.1 | R66: 8823202.1
A67: Umbrella Ex C V Starr | B67: Paid | C67: All | D67: UW Year | E67: USD | F67: 42005 | G67: 0 | H67: 23187.38 | I67: 25695.88 | J67: 12391819 | K67: 15064123 | L67: 19062168 | M67: 19584307 | N67: 24579528 | O67: 24587017 | P67: 24587017 | Q67: 28987017
A68: Umbrella Ex C V Starr | B68: Paid | C68: All | D68: UW Year | E68: USD | F68: 42370 | G68: 0 | H68: 12764 | I68: 700693.85 | J68: 3827058.6 | K68: 9070492.4 | L68: 9367821.7 | M68: 16255940 | N68: 16268041 | O68: 26501010 | P68: 26525011
A69: Umbrella Ex C V Starr | B69: Paid | C69: All | D69: UW Year | E69: USD | F69: 42736 | G69: 4725 | H69: 5422474.1 | I69: 15688964 | J69: 19150444 | K69: 63417092 | L69: 69805916 | M69: 84868416 | N69: 91153129 | O69: 1.0285791e+08
A70: Umbrella Ex C V Starr | B70: Paid | C70: All | D70: UW Year | E70: USD | F70: 43101 | G70: 0 | H70: 9426887.9 | I70: 42878678 | J70: 61093078 | K70: 69110135 | L70: 80351723 | M70: 1.1255593e+08 | N70: 1.2788804e+08
A71: Umbrella Ex C V Starr | B71: Paid | C71: All | D71: UW Year | E71: USD | F71: 43466 | G71: 0 | H71: 5407795.2 | I71: 54576187 | J71: 83067246 | K71: 1.0953106e+08 | L71: 1.6996619e+08 | M71: 2.0677535e+08
A72: Umbrella Ex C V Starr | B72: Paid | C72: All | D72: UW Year | E72: USD | F72: 43831 | G72: 0 | H72: 4051618.9 | I72: 11908901 | J72: 35287158 | K72: 71685681 | L72: 1.2589532e+08
A73: Umbrella Ex C V Starr | B73: Paid | C73: All | D73: UW Year | E73: USD | F73: 44197 | G73: 0 | H73: 122098.67 | I73: 63348719 | J73: 1.2048221e+08 | K73: 2.1196018e+08
A74: Umbrella Ex C V Starr | B74: Paid | C74: All | D74: UW Year | E74: USD | F74: 44562 | G74: 0 | H74: 5189743.3 | I74: 69532480 | J74: 1.4617512e+08
A75: Umbrella Ex C V Starr | B75: Paid | C75: All | D75: UW Year | E75: USD | F75: 44927 | G75: 54671.54 | H75: 2600196 | I75: 46229519
A76: Umbrella Ex C V Starr | B76: Paid | C76: All | D76: UW Year | E76: USD | F76: 45292 | G76: 0 | H76: 1955716.8
A77: Umbrella Ex C V Starr | B77: Paid | C77: All | D77: UW Year | E77: USD | F77: 45658 | G77: 0
A78: General Liability ex ARL | B78: Net Written Premium | C78: All | D78: UW Year | E78: USD | F78: 36892 | G78: 10909748 | H78: 10909748 | I78: 10909748 | J78: 10909748 | K78: 10909748 | L78: 10909748 | M78: 10909748 | N78: 10909748 | O78: 10909748 | P78: 10909748 | Q78: 10909748 | R78: 10909748 | S78: 10909748 | T78: 10909748 | U78: 10909748 | V78: 10909748 | W78: 10909748 | X78: 10909748 | Y78: 10909748 | Z78: 10909748 | AA78: 10909748 | AB78: 10909748 | AC78: 10909748 | AD78: 10909748 | AE78: 10909748
A79: General Liability ex ARL | B79: Net Written Premium | C79: All | D79: UW Year | E79: USD | F79: 37257 | G79: 11207217 | H79: 11207217 | I79: 11207217 | J79: 11207217 | K79: 11207217 | L79: 11207217 | M79: 11207217 | N79: 11207217 | O79: 11207217 | P79: 11207217 | Q79: 11207217 | R79: 11207217 | S79: 11207217 | T79: 11207217 | U79: 11207217 | V79: 11207217 | W79: 11207217 | X79: 11207217 | Y79: 11207217 | Z79: 11207217 | AA79: 11207217 | AB79: 11207217 | AC79: 11207217 | AD79: 11207217
A80: General Liability ex ARL | B80: Net Written Premium | C80: All | D80: UW Year | E80: USD | F80: 37622 | G80: 15383326 | H80: 15383326 | I80: 15383326 | J80: 15383326 | K80: 15383326 | L80: 15383326 | M80: 15383326 | N80: 15383326 | O80: 15383326 | P80: 15383326 | Q80: 15383326 | R80: 15383326 | S80: 15383326 | T80: 15383326 | U80: 15383326 | V80: 15383326 | W80: 15383326 | X80: 15383326 | Y80: 15383326 | Z80: 15383326 | AA80: 15383326 | AB80: 15383326 | AC80: 15383326
A81: General Liability ex ARL | B81: Net Written Premium | C81: All | D81: UW Year | E81: USD | F81: 37987 | G81: 41897390 | H81: 41897390 | I81: 41897390 | J81: 41897390 | K81: 41897390 | L81: 41897390 | M81: 41897390 | N81: 41897390 | O81: 41897390 | P81: 41897390 | Q81: 41897390 | R81: 41897390 | S81: 41897390 | T81: 41897390 | U81: 41897390 | V81: 41897390 | W81: 41897390 | X81: 41897390 | Y81: 41897390 | Z81: 41897390 | AA81: 41897390 | AB81: 41897390
A82: General Liability ex ARL | B82: Net Written Premium | C82: All | D82: UW Year | E82: USD | F82: 38353 | G82: 54756795 | H82: 54756795 | I82: 54756795 | J82: 54756795 | K82: 54756795 | L82: 54756795 | M82: 54756795 | N82: 54756795 | O82: 54756795 | P82: 54756795 | Q82: 54756795 | R82: 54756795 | S82: 54756795 | T82: 54756795 | U82: 54756795 | V82: 54756795 | W82: 54756795 | X82: 54756795 | Y82: 54756795 | Z82: 54756795 | AA82: 54756795
A83: General Liability ex ARL | B83: Net Written Premium | C83: All | D83: UW Year | E83: USD | F83: 38718 | G83: 68039602 | H83: 68039602 | I83: 68039602 | J83: 68039602 | K83: 68039602 | L83: 68039602 | M83: 68039602 | N83: 68039602 | O83: 68039602 | P83: 68039602 | Q83: 68039602 | R83: 68039602 | S83: 68039602 | T83: 68039602 | U83: 68039602 | V83: 68039602 | W83: 68039602 | X83: 68039602 | Y83: 68039602 | Z83: 68039602
A84: General Liability ex ARL | B84: Net Written Premium | C84: All | D84: UW Year | E84: USD | F84: 39083 | G84: 75832313 | H84: 75832313 | I84: 75832313 | J84: 75832313 | K84: 75832313 | L84: 75832313 | M84: 75832313 | N84: 75832313 | O84: 75832313 | P84: 75832313 | Q84: 75832313 | R84: 75832313 | S84: 75832313 | T84: 75832313 | U84: 75832313 | V84: 75832313 | W84: 75832313 | X84: 75832313 | Y84: 75832313
A85: General Liability ex ARL | B85: Net Written Premium | C85: All | D85: UW Year | E85: USD | F85: 39448 | G85: 55575779 | H85: 55575779 | I85: 55575779 | J85: 55575779 | K85: 55575779 | L85: 55575779 | M85: 55575779 | N85: 55575779 | O85: 55575779 | P85: 55575779 | Q85: 55575779 | R85: 55575779 | S85: 55575779 | T85: 55575779 | U85: 55575779 | V85: 55575779 | W85: 55575779 | X85: 55575779
A86: General Liability ex ARL | B86: Net Written Premium | C86: All | D86: UW Year | E86: USD | F86: 39814 | G86: 28100078 | H86: 28100078 | I86: 28100078 | J86: 28100078 | K86: 28100078 | L86: 28100078 | M86: 28100078 | N86: 28100078 | O86: 28100078 | P86: 28100078 | Q86: 28100078 | R86: 28100078 | S86: 28100078 | T86: 28100078 | U86: 28100078 | V86: 28100078 | W86: 28100078
A87: General Liability ex ARL | B87: Net Written Premium | C87: All | D87: UW Year | E87: USD | F87: 40179 | G87: 17240443 | H87: 17240443 | I87: 17240443 | J87: 17240443 | K87: 17240443 | L87: 17240443 | M87: 17240443 | N87: 17240443 | O87: 17240443 | P87: 17240443 | Q87: 17240443 | R87: 17240443 | S87: 17240443 | T87: 17240443 | U87: 17240443 | V87: 17240443
A88: General Liability ex ARL | B88: Net Written Premium | C88: All | D88: UW Year | E88: USD | F88: 40544 | G88: 14303007 | H88: 14303007 | I88: 14303007 | J88: 14303007 | K88: 14303007 | L88: 14303007 | M88: 14303007 | N88: 14303007 | O88: 14303007 | P88: 14303007 | Q88: 14303007 | R88: 14303007 | S88: 14303007 | T88: 14303007 | U88: 14303007
A89: General Liability ex ARL | B89: Net Written Premium | C89: All | D89: UW Year | E89: USD | F89: 40909 | G89: 12576113 | H89: 12576113 | I89: 12576113 | J89: 12576113 | K89: 12576113 | L89: 12576113 | M89: 12576113 | N89: 12576113 | O89: 12576113 | P89: 12576113 | Q89: 12576113 | R89: 12576113 | S89: 12576113 | T89: 12576113
A90: General Liability ex ARL | B90: Net Written Premium | C90: All | D90: UW Year | E90: USD | F90: 41275 | G90: 16854762 | H90: 16854762 | I90: 16854762 | J90: 16854762 | K90: 16854762 | L90: 16854762 | M90: 16854762 | N90: 16854762 | O90: 16854762 | P90: 16854762 | Q90: 16854762 | R90: 16854762 | S90: 16854762
A91: General Liability ex ARL | B91: Net Written Premium | C91: All | D91: UW Year | E91: USD | F91: 41640 | G91: 27645768 | H91: 27645768 | I91: 27645768 | J91: 27645768 | K91: 27645768 | L91: 27645768 | M91: 27645768 | N91: 27645768 | O91: 27645768 | P91: 27645768 | Q91: 27645768 | R91: 27645768
A92: General Liability ex ARL | B92: Net Written Premium | C92: All | D92: UW Year | E92: USD | F92: 42005 | G92: 41320079 | H92: 41320079 | I92: 41320079 | J92: 41320079 | K92: 41320079 | L92: 41320079 | M92: 41320079 | N92: 41320079 | O92: 41320079 | P92: 41320079 | Q92: 41320079
A93: General Liability ex ARL | B93: Net Written Premium | C93: All | D93: UW Year | E93: USD | F93: 42370 | G93: 55218175 | H93: 55218175 | I93: 55218175 | J93: 55218175 | K93: 55218175 | L93: 55218175 | M93: 55218175 | N93: 55218175 | O93: 55218175 | P93: 55218175
A94: General Liability ex ARL | B94: Net Written Premium | C94: All | D94: UW Year | E94: USD | F94: 42736 | G94: 69724102 | H94: 69724102 | I94: 69724102 | J94: 69724102 | K94: 69724102 | L94: 69724102 | M94: 69724102 | N94: 69724102 | O94: 69724102
A95: General Liability ex ARL | B95: Net Written Premium | C95: All | D95: UW Year | E95: USD | F95: 43101 | G95: 94903395 | H95: 94903395 | I95: 94903395 | J95: 94903395 | K95: 94903395 | L95: 94903395 | M95: 94903395 | N95: 94903395
A96: General Liability ex ARL | B96: Net Written Premium | C96: All | D96: UW Year | E96: USD | F96: 43466 | G96: 1.3439482e+08 | H96: 1.3439482e+08 | I96: 1.3439482e+08 | J96: 1.3439482e+08 | K96: 1.3439482e+08 | L96: 1.3439482e+08 | M96: 1.3439482e+08
A97: General Liability ex ARL | B97: Net Written Premium | C97: All | D97: UW Year | E97: USD | F97: 43831 | G97: 1.5788018e+08 | H97: 1.5788018e+08 | I97: 1.5788018e+08 | J97: 1.5788018e+08 | K97: 1.5788018e+08 | L97: 1.5788018e+08
A98: General Liability ex ARL | B98: Net Written Premium | C98: All | D98: UW Year | E98: USD | F98: 44197 | G98: 1.9264266e+08 | H98: 1.9264266e+08 | I98: 1.9264266e+08 | J98: 1.9264266e+08 | K98: 1.9264266e+08
A99: General Liability ex ARL | B99: Net Written Premium | C99: All | D99: UW Year | E99: USD | F99: 44562 | G99: 2.5372504e+08 | H99: 2.5372504e+08 | I99: 2.5372504e+08 | J99: 2.5372504e+08
A100: General Liability ex ARL | B100: Net Written Premium | C100: All | D100: UW Year | E100: USD | F100: 44927 | G100: 2.9519828e+08 | H100: 2.9519828e+08 | I100: 2.9519828e+08
...

Sheet Projections
A1: Longtail Reference | B1: UW Year | C1: Ultimate GG Prem ($M) | D1: Latest GG Prem ($M) | E1: Latest GN Prem ($M) | F1: Acq Cost | G1: Cedant Provided Ultimate Loss Ratio | H1: Cedant Provided CoV | I1: Rate Change | J1: Inflation | K1: Historic Year Check | L1: Current Year Check | M1: Min Origin Year: | N1: =YEAR(triangle_start_date) -> 2001 | O1: Max Origin Year: | P1: =YEAR(current_date)-1 -> 2025 | R1: Checks
A2: Auto Liability | B2: 2001 | C2: 8.1366889 | D2: 8.1366889 | E2: 8.1366889 | K2: =IF(OR(B2<$N$1,B2>$P$1),"fail","pass") -> pass | L2: =IFERROR(IF(AND(MATCH(A2,Projection_classes,0),YEAR(current_date)=Projections!B2),"pass","fail"),"") -> fail | R2: =IF(S2>0, "RATE CHANGE COLUMN CONTAINS ERROR VALUES. PLEASE SET THEM TO 0s", "Rate Change column no error values.") -> Rate Change column no error values. | S2: {=SUMPRODUCT(--ISERROR(I2:I1000))} -> 0
A3: Auto Liability | B3: 2002 | C3: 8.0484384 | D3: 8.0484384 | E3: 8.0484384 | K3: =IF(OR(B3<$N$1,B3>$P$1),"fail","pass") -> pass | L3: =IFERROR(IF(AND(MATCH(A3,Projection_classes,0),YEAR(current_date)=Projections!B3),"pass","fail"),"") -> fail | R3: =IF(S3>0, "INFLATION COLUMN CONTAINS ERROR VALUES. PLEASE SET THEM TO 0s", "Inflation column no error values.") -> Inflation column no error values. | S3: {=SUMPRODUCT(--ISERROR(J2:J1000))} -> 0
A4: Auto Liability | B4: 2003 | C4: 11.940716 | D4: 11.940716 | E4: 11.940716 | K4: =IF(OR(B4<$N$1,B4>$P$1),"fail","pass") -> pass | L4: =IFERROR(IF(AND(MATCH(A4,Projection_classes,0),YEAR(current_date)=Projections!B4),"pass","fail"),"") -> fail
A5: Auto Liability | B5: 2004 | C5: 16.579211 | D5: 16.579211 | E5: 16.579211 | K5: =IF(OR(B5<$N$1,B5>$P$1),"fail","pass") -> pass | L5: =IFERROR(IF(AND(MATCH(A5,Projection_classes,0),YEAR(current_date)=Projections!B5),"pass","fail"),"") -> fail
A6: Auto Liability | B6: 2005 | C6: 18.825765 | D6: 18.825765 | E6: 18.825765 | K6: =IF(OR(B6<$N$1,B6>$P$1),"fail","pass") -> pass | L6: =IFERROR(IF(AND(MATCH(A6,Projection_classes,0),YEAR(current_date)=Projections!B6),"pass","fail"),"") -> fail | R6: Mandatory
A7: Auto Liability | B7: 2006 | C7: 19.523392 | D7: 19.523392 | E7: 19.523392 | K7: =IF(OR(B7<$N$1,B7>$P$1),"fail","pass") -> pass | L7: =IFERROR(IF(AND(MATCH(A7,Projection_classes,0),YEAR(current_date)=Projections!B7),"pass","fail"),"") -> fail | R7: Optional
A8: Auto Liability | B8: 2007 | C8: 20.315469 | D8: 20.315469 | E8: 20.315469 | I8: -0.0090413677 | J8: 0.087733472 | K8: =IF(OR(B8<$N$1,B8>$P$1),"fail","pass") -> pass | L8: =IFERROR(IF(AND(MATCH(A8,Projection_classes,0),YEAR(current_date)=Projections!B8),"pass","fail"),"") -> fail
A9: Auto Liability | B9: 2008 | C9: 34.46956 | D9: 34.46956 | E9: 34.46956 | I9: -0.050167356 | J9: 0.087236473 | K9: =IF(OR(B9<$N$1,B9>$P$1),"fail","pass") -> pass | L9: =IFERROR(IF(AND(MATCH(A9,Projection_classes,0),YEAR(current_date)=Projections!B9),"pass","fail"),"") -> fail
A10: Auto Liability | B10: 2009 | C10: 32.611351 | D10: 32.611351 | E10: 32.611351 | I10: -0.020910608 | J10: 0.075952758 | K10: =IF(OR(B10<$N$1,B10>$P$1),"fail","pass") -> pass | L10: =IFERROR(IF(AND(MATCH(A10,Projection_classes,0),YEAR(current_date)=Projections!B10),"pass","fail"),"") -> fail
A11: Auto Liability | B11: 2010 | C11: 23.565427 | D11: 23.565427 | E11: 23.565427 | I11: -0.00029274553 | J11: 0.071912051 | K11: =IF(OR(B11<$N$1,B11>$P$1),"fail","pass") -> pass | L11: =IFERROR(IF(AND(MATCH(A11,Projection_classes,0),YEAR(current_date)=Projections!B11),"pass","fail"),"") -> fail
A12: Auto Liability | B12: 2011 | C12: 17.298426 | D12: 17.298426 | E12: 17.298426 | I12: -0.005822788 | J12: 0.075227489 | K12: =IF(OR(B12<$N$1,B12>$P$1),"fail","pass") -> pass | L12: =IFERROR(IF(AND(MATCH(A12,Projection_classes,0),YEAR(current_date)=Projections!B12),"pass","fail"),"") -> fail
A13: Auto Liability | B13: 2012 | C13: 9.3987519 | D13: 9.3987519 | E13: 9.3987519 | I13: -0.0021910283 | J13: 0.074006983 | K13: =IF(OR(B13<$N$1,B13>$P$1),"fail","pass") -> pass | L13: =IFERROR(IF(AND(MATCH(A13,Projection_classes,0),YEAR(current_date)=Projections!B13),"pass","fail"),"") -> fail
A14: Auto Liability | B14: 2013 | C14: 11.234086 | D14: 11.234086 | E14: 11.234086 | I14: -0.0049192179 | J14: 0.069322035 | K14: =IF(OR(B14<$N$1,B14>$P$1),"fail","pass") -> pass | L14: =IFERROR(IF(AND(MATCH(A14,Projection_classes,0),YEAR(current_date)=Projections!B14),"pass","fail"),"") -> fail
A15: Auto Liability | B15: 2014 | C15: 19.154309 | D15: 19.154309 | E15: 19.154309 | I15: -0.016754683 | J15: 0.067044285 | K15: =IF(OR(B15<$N$1,B15>$P$1),"fail","pass") -> pass | L15: =IFERROR(IF(AND(MATCH(A15,Projection_classes,0),YEAR(current_date)=Projections!B15),"pass","fail"),"") -> fail
A16: Auto Liability | B16: 2015 | C16: 29.321088 | D16: 29.321088 | E16: 29.321088 | I16: -0.013229945 | J16: 0.069245491 | K16: =IF(OR(B16<$N$1,B16>$P$1),"fail","pass") -> pass | L16: =IFERROR(IF(AND(MATCH(A16,Projection_classes,0),YEAR(current_date)=Projections!B16),"pass","fail"),"") -> fail
A17: Auto Liability | B17: 2016 | C17: 34.072388 | D17: 34.072388 | E17: 34.072388 | I17: -0.0047554079 | J17: 0.069561773 | K17: =IF(OR(B17<$N$1,B17>$P$1),"fail","pass") -> pass | L17: =IFERROR(IF(AND(MATCH(A17,Projection_classes,0),YEAR(current_date)=Projections!B17),"pass","fail"),"") -> fail
A18: Auto Liability | B18: 2017 | C18: 52.802136 | D18: 52.802136 | E18: 52.802136 | I18: -0.0051204854 | J18: 0.079010008 | K18: =IF(OR(B18<$N$1,B18>$P$1),"fail","pass") -> pass | L18: =IFERROR(IF(AND(MATCH(A18,Projection_classes,0),YEAR(current_date)=Projections!B18),"pass","fail"),"") -> fail
A19: Auto Liability | B19: 2018 | C19: 89.615987 | D19: 89.615987 | E19: 89.615987 | I19: 0.012497099 | J19: 0.078738372 | K19: =IF(OR(B19<$N$1,B19>$P$1),"fail","pass") -> pass | L19: =IFERROR(IF(AND(MATCH(A19,Projection_classes,0),YEAR(current_date)=Projections!B19),"pass","fail"),"") -> fail
... A25: Auto Liability | B25: 2024 | C25: 262.54838 | D25: 262.54838 | E25: 262.54838 | I25: 0.077167475 | J25: 0.084594526 | K25: =IF(OR(B25<$N$1,B25>$P$1),"fail","pass") -> pass | L25: =IFERROR(IF(AND(MATCH(A25,Projection_classes,0),YEAR(current_date)=Projections!B25),"pass","fail"),"") -> fail
A26: Auto Liability | B26: 2025 | C26: 106.46804 | D26: 106.46804 | E26: 106.46804 | K26: =IF(OR(B26<$N$1,B26>$P$1),"fail","pass") -> pass | L26: =IFERROR(IF(AND(MATCH(A26,Projection_classes,0),YEAR(current_date)=Projections!B26),"pass","fail"),"") -> fail
A27: Auto Liability | B27: 2026 | C27: 246.43301 | D27: 0 | E27: 0 | K27: =IF(OR(B27<$N$1,B27>$P$1),"fail","pass") -> fail | L27: =IFERROR(IF(AND(MATCH(A27,Projection_classes,0),YEAR(current_date)=Projections!B27),"pass","fail"),"") -> pass
A28: California Workers Compensation | B28: 2001 | C28: 189.71905 | D28: 189.71905 | E28: 189.71905 | K28: =IF(OR(B28<$N$1,B28>$P$1),"fail","pass") -> pass | L28: =IFERROR(IF(AND(MATCH(A28,Projection_classes,0),YEAR(current_date)=Projections!B28),"pass","fail"),"") -> fail
A29: California Workers Compensation | B29: 2002 | C29: 388.93941 | D29: 388.93941 | E29: 388.93941 | K29: =IF(OR(B29<$N$1,B29>$P$1),"fail","pass") -> pass | L29: =IFERROR(IF(AND(MATCH(A29,Projection_classes,0),YEAR(current_date)=Projections!B29),"pass","fail"),"") -> fail
A30: California Workers Compensation | B30: 2003 | C30: 575.05219 | D30: 575.05219 | E30: 575.05219 | K30: =IF(OR(B30<$N$1,B30>$P$1),"fail","pass") -> pass | L30: =IFERROR(IF(AND(MATCH(A30,Projection_classes,0),YEAR(current_date)=Projections!B30),"pass","fail"),"") -> fail
A31: California Workers Compensation | B31: 2004 | C31: 576.24932 | D31: 576.24932 | E31: 576.24932 | K31: =IF(OR(B31<$N$1,B31>$P$1),"fail","pass") -> pass | L31: =IFERROR(IF(AND(MATCH(A31,Projection_classes,0),YEAR(current_date)=Projections!B31),"pass","fail"),"") -> fail
A32: California Workers Compensation | B32: 2005 | C32: 296.19873 | D32: 296.19873 | E32: 296.19873 | K32: =IF(OR(B32<$N$1,B32>$P$1),"fail","pass") -> pass | L32: =IFERROR(IF(AND(MATCH(A32,Projection_classes,0),YEAR(current_date)=Projections!B32),"pass","fail"),"") -> fail
A33: California Workers Compensation | B33: 2006 | C33: 192.98273 | D33: 192.98273 | E33: 192.98273 | K33: =IF(OR(B33<$N$1,B33>$P$1),"fail","pass") -> pass | L33: =IFERROR(IF(AND(MATCH(A33,Projection_classes,0),YEAR(current_date)=Projections!B33),"pass","fail"),"") -> fail
A34: California Workers Compensation | B34: 2007 | C34: 137.97028 | D34: 137.97028 | E34: 137.97028 | K34: =IF(OR(B34<$N$1,B34>$P$1),"fail","pass") -> pass | L34: =IFERROR(IF(AND(MATCH(A34,Projection_classes,0),YEAR(current_date)=Projections!B34),"pass","fail"),"") -> fail
A35: California Workers Compensation | B35: 2008 | C35: 108.99175 | D35: 108.99175 | E35: 108.99175 | K35: =IF(OR(B35<$N$1,B35>$P$1),"fail","pass") -> pass | L35: =IFERROR(IF(AND(MATCH(A35,Projection_classes,0),YEAR(current_date)=Projections!B35),"pass","fail"),"") -> fail
A36: California Workers Compensation | B36: 2009 | C36: 161.95013 | D36: 161.95013 | E36: 161.95013 | K36: =IF(OR(B36<$N$1,B36>$P$1),"fail","pass") -> pass | L36: =IFERROR(IF(AND(MATCH(A36,Projection_classes,0),YEAR(current_date)=Projections!B36),"pass","fail"),"") -> fail
A37: California Workers Compensation | B37: 2010 | C37: 215.04545 | D37: 215.04545 | E37: 215.04545 | K37: =IF(OR(B37<$N$1,B37>$P$1),"fail","pass") -> pass | L37: =IFERROR(IF(AND(MATCH(A37,Projection_classes,0),YEAR(current_date)=Projections!B37),"pass","fail"),"") -> fail
... A59: Canada Casualty | B59: 2006 | C59: 0 | D59: 0 | E59: 0 | K59: =IF(OR(B59<$N$1,B59>$P$1),"fail","pass") -> pass | L59: =IFERROR(IF(AND(MATCH(A59,Projection_classes,0),YEAR(current_date)=Projections!B59),"pass","fail"),"") -> fail
A60: Canada Casualty | B60: 2007 | C60: 0 | D60: 0 | E60: 0 | I60: -0.0090413677 | J60: 0.087733472 | K60: =IF(OR(B60<$N$1,B60>$P$1),"fail","pass") -> pass | L60: =IFERROR(IF(AND(MATCH(A60,Projection_classes,0),YEAR(current_date)=Projections!B60),"pass","fail"),"") -> fail
A61: Canada Casualty | B61: 2008 | C61: 0 | D61: 0 | E61: 0 | I61: -0.050167356 | J61: 0.087236473 | K61: =IF(OR(B61<$N$1,B61>$P$1),"fail","pass") -> pass | L61: =IFERROR(IF(AND(MATCH(A61,Projection_classes,0),YEAR(current_date)=Projections!B61),"pass","fail"),"") -> fail
A62: Canada Casualty | B62: 2009 | C62: 0 | D62: 0 | E62: 0 | I62: -0.020910608 | J62: 0.075952758 | K62: =IF(OR(B62<$N$1,B62>$P$1),"fail","pass") -> pass | L62: =IFERROR(IF(AND(MATCH(A62,Projection_classes,0),YEAR(current_date)=Projections!B62),"pass","fail"),"") -> fail
A63: Canada Casualty | B63: 2010 | C63: 0 | D63: 0 | E63: 0 | I63: -0.00029274553 | J63: 0.071912051 | K63: =IF(OR(B63<$N$1,B63>$P$1),"fail","pass") -> pass | L63: =IFERROR(IF(AND(MATCH(A63,Projection_classes,0),YEAR(current_date)=Projections!B63),"pass","fail"),"") -> fail
A64: Canada Casualty | B64: 2011 | C64: 5.599828 | D64: 5.599828 | E64: 5.599828 | I64: -0.005822788 | J64: 0.075227489 | K64: =IF(OR(B64<$N$1,B64>$P$1),"fail","pass") -> pass | L64: =IFERROR(IF(AND(MATCH(A64,Projection_classes,0),YEAR(current_date)=Projections!B64),"pass","fail"),"") -> fail
A65: Canada Casualty | B65: 2012 | C65: 13.658783 | D65: 13.658783 | E65: 13.658783 | I65: -0.0021910283 | J65: 0.074006983 | K65: =IF(OR(B65<$N$1,B65>$P$1),"fail","pass") -> pass | L65: =IFERROR(IF(AND(MATCH(A65,Projection_classes,0),YEAR(current_date)=Projections!B65),"pass","fail"),"") -> fail
A66: Canada Casualty | B66: 2013 | C66: 15.784148 | D66: 15.784148 | E66: 15.784148 | I66: -0.0049192179 | J66: 0.069322035 | K66: =IF(OR(B66<$N$1,B66>$P$1),"fail","pass") -> pass | L66: =IFERROR(IF(AND(MATCH(A66,Projection_classes,0),YEAR(current_date)=Projections!B66),"pass","fail"),"") -> fail
A67: Canada Casualty | B67: 2014 | C67: 25.262466 | D67: 25.262466 | E67: 25.262466 | I67: -0.016754683 | J67: 0.067044285 | K67: =IF(OR(B67<$N$1,B67>$P$1),"fail","pass") -> pass | L67: =IFERROR(IF(AND(MATCH(A67,Projection_classes,0),YEAR(current_date)=Projections!B67),"pass","fail"),"") -> fail
A68: Canada Casualty | B68: 2015 | C68: 42.256079 | D68: 42.256079 | E68: 42.256079 | I68: -0.013229945 | J68: 0.069245491 | K68: =IF(OR(B68<$N$1,B68>$P$1),"fail","pass") -> pass | L68: =IFERROR(IF(AND(MATCH(A68,Projection_classes,0),YEAR(current_date)=Projections!B68),"pass","fail"),"") -> fail
A69: Canada Casualty | B69: 2016 | C69: 52.746315 | D69: 52.746315 | E69: 52.746315 | I69: -0.0047554079 | J69: 0.069561773 | K69: =IF(OR(B69<$N$1,B69>$P$1),"fail","pass") -> pass | L69: =IFERROR(IF(AND(MATCH(A69,Projection_classes,0),YEAR(current_date)=Projections!B69),"pass","fail"),"") -> fail
A70: Canada Casualty | B70: 2017 | C70: 55.959254 | D70: 55.959254 | E70: 55.959254 | I70: -0.0051204854 | J70: 0.079010008 | K70: =IF(OR(B70<$N$1,B70>$P$1),"fail","pass") -> pass | L70: =IFERROR(IF(AND(MATCH(A70,Projection_classes,0),YEAR(current_date)=Projections!B70),"pass","fail"),"") -> fail
A71: Canada Casualty | B71: 2018 | C71: 61.755824 | D71: 61.755824 | E71: 61.755824 | I71: 0.012497099 | J71: 0.078738372 | K71: =IF(OR(B71<$N$1,B71>$P$1),"fail","pass") -> pass | L71: =IFERROR(IF(AND(MATCH(A71,Projection_classes,0),YEAR(current_date)=Projections!B71),"pass","fail"),"") -> fail
... A77: Canada Casualty | B77: 2024 | C77: 136.01499 | D77: 136.01499 | E77: 136.01499 | I77: 0.077167475 | J77: 0.084594526 | K77: =IF(OR(B77<$N$1,B77>$P$1),"fail","pass") -> pass | L77: =IFERROR(IF(AND(MATCH(A77,Projection_classes,0),YEAR(current_date)=Projections!B77),"pass","fail"),"") -> fail
A78: Canada Casualty | B78: 2025 | C78: 58.554584 | D78: 58.554584 | E78: 58.554584 | K78: =IF(OR(B78<$N$1,B78>$P$1),"fail","pass") -> pass | L78: =IFERROR(IF(AND(MATCH(A78,Projection_classes,0),YEAR(current_date)=Projections!B78),"pass","fail"),"") -> fail
A79: Canada Casualty | B79: 2026 | C79: 78.444239 | D79: 0 | E79: 0 | K79: =IF(OR(B79<$N$1,B79>$P$1),"fail","pass") -> fail | L79: =IFERROR(IF(AND(MATCH(A79,Projection_classes,0),YEAR(current_date)=Projections!B79),"pass","fail"),"") -> pass
A80: Countrywide Workers Compensation | B80: 2001 | C80: 0.01911092 | D80: 0.01911092 | E80: 0.01911092 | K80: =IF(OR(B80<$N$1,B80>$P$1),"fail","pass") -> pass | L80: =IFERROR(IF(AND(MATCH(A80,Projection_classes,0),YEAR(current_date)=Projections!B80),"pass","fail"),"") -> fail
A81: Countrywide Workers Compensation | B81: 2002 | C81: 0.5157373 | D81: 0.5157373 | E81: 0.5157373 | K81: =IF(OR(B81<$N$1,B81>$P$1),"fail","pass") -> pass | L81: =IFERROR(IF(AND(MATCH(A81,Projection_classes,0),YEAR(current_date)=Projections!B81),"pass","fail"),"") -> fail
A82: Countrywide Workers Compensation | B82: 2003 | C82: 0.72562763 | D82: 0.72562763 | E82: 0.72562763 | K82: =IF(OR(B82<$N$1,B82>$P$1),"fail","pass") -> pass | L82: =IFERROR(IF(AND(MATCH(A82,Projection_classes,0),YEAR(current_date)=Projections!B82),"pass","fail"),"") -> fail
A83: Countrywide Workers Compensation | B83: 2004 | C83: 1.89616 | D83: 1.89616 | E83: 1.89616 | K83: =IF(OR(B83<$N$1,B83>$P$1),"fail","pass") -> pass | L83: =IFERROR(IF(AND(MATCH(A83,Projection_classes,0),YEAR(current_date)=Projections!B83),"pass","fail"),"") -> fail
A84: Countrywide Workers Compensation | B84: 2005 | C84: 18.205793 | D84: 18.205793 | E84: 18.205793 | K84: =IF(OR(B84<$N$1,B84>$P$1),"fail","pass") -> pass | L84: =IFERROR(IF(AND(MATCH(A84,Projection_classes,0),YEAR(current_date)=Projections!B84),"pass","fail"),"") -> fail
A85: Countrywide Workers Compensation | B85: 2006 | C85: 32.330882 | D85: 32.330882 | E85: 32.330882 | K85: =IF(OR(B85<$N$1,B85>$P$1),"fail","pass") -> pass | L85: =IFERROR(IF(AND(MATCH(A85,Projection_classes,0),YEAR(current_date)=Projections!B85),"pass","fail"),"") -> fail
A86: Countrywide Workers Compensation | B86: 2007 | C86: 39.530359 | D86: 39.530359 | E86: 39.530359 | K86: =IF(OR(B86<$N$1,B86>$P$1),"fail","pass") -> pass | L86: =IFERROR(IF(AND(MATCH(A86,Projection_classes,0),YEAR(current_date)=Projections!B86),"pass","fail"),"") -> fail
A87: Countrywide Workers Compensation | B87: 2008 | C87: 40.7383 | D87: 40.7383 | E87: 40.7383 | K87: =IF(OR(B87<$N$1,B87>$P$1),"fail","pass") -> pass | L87: =IFERROR(IF(AND(MATCH(A87,Projection_classes,0),YEAR(current_date)=Projections!B87),"pass","fail"),"") -> fail
A88: Countrywide Workers Compensation | B88: 2009 | C88: 33.904752 | D88: 33.904752 | E88: 33.904752 | K88: =IF(OR(B88<$N$1,B88>$P$1),"fail","pass") -> pass | L88: =IFERROR(IF(AND(MATCH(A88,Projection_classes,0),YEAR(current_date)=Projections!B88),"pass","fail"),"") -> fail
A89: Countrywide Workers Compensation | B89: 2010 | C89: 32.850792 | D89: 32.850792 | E89: 32.850792 | K89: =IF(OR(B89<$N$1,B89>$P$1),"fail","pass") -> pass | L89: =IFERROR(IF(AND(MATCH(A89,Projection_classes,0),YEAR(current_date)=Projections!B89),"pass","fail"),"") -> fail
... A111: EverSports | B111: 2006 | C111: 0 | D111: 0 | E111: 0 | K111: =IF(OR(B111<$N$1,B111>$P$1),"fail","pass") -> pass | L111: =IFERROR(IF(AND(MATCH(A111,Projection_classes,0),YEAR(current_date)=Projections!B111),"pass","fail"),"") -> fail
A112: EverSports | B112: 2007 | C112: 0 | D112: 0 | E112: 0 | I112: -0.0090413677 | J112: 0.087733472 | K112: =IF(OR(B112<$N$1,B112>$P$1),"fail","pass") -> pass | L112: =IFERROR(IF(AND(MATCH(A112,Projection_classes,0),YEAR(current_date)=Projections!B112),"pass","fail"),"") -> fail
A113: EverSports | B113: 2008 | C113: 0 | D113: 0 | E113: 0 | I113: -0.050167356 | J113: 0.087236473 | K113: =IF(OR(B113<$N$1,B113>$P$1),"fail","pass") -> pass | L113: =IFERROR(IF(AND(MATCH(A113,Projection_classes,0),YEAR(current_date)=Projections!B113),"pass","fail"),"") -> fail
A114: EverSports | B114: 2009 | C114: 0 | D114: 0 | E114: 0 | I114: -0.020910608 | J114: 0.075952758 | K114: =IF(OR(B114<$N$1,B114>$P$1),"fail","pass") -> pass | L114: =IFERROR(IF(AND(MATCH(A114,Projection_classes,0),YEAR(current_date)=Projections!B114),"pass","fail"),"") -> fail
A115: EverSports | B115: 2010 | C115: 0 | D115: 0 | E115: 0 | I115: -0.00029274553 | J115: 0.071912051 | K115: =IF(OR(B115<$N$1,B115>$P$1),"fail","pass") -> pass | L115: =IFERROR(IF(AND(MATCH(A115,Projection_classes,0),YEAR(current_date)=Projections!B115),"pass","fail"),"") -> fail
A116: EverSports | B116: 2011 | C116: 0 | D116: 0 | E116: 0 | I116: -0.005822788 | J116: 0.075227489 | K116: =IF(OR(B116<$N$1,B116>$P$1),"fail","pass") -> pass | L116: =IFERROR(IF(AND(MATCH(A116,Projection_classes,0),YEAR(current_date)=Projections!B116),"pass","fail"),"") -> fail
A117: EverSports | B117: 2012 | C117: 0 | D117: 0 | E117: 0 | I117: -0.0021910283 | J117: 0.074006983 | K117: =IF(OR(B117<$N$1,B117>$P$1),"fail","pass") -> pass | L117: =IFERROR(IF(AND(MATCH(A117,Projection_classes,0),YEAR(current_date)=Projections!B117),"pass","fail"),"") -> fail
A118: EverSports | B118: 2013 | C118: 0.87111992 | D118: 0.87111992 | E118: 0.87111992 | I118: -0.0049192179 | J118: 0.069322035 | K118: =IF(OR(B118<$N$1,B118>$P$1),"fail","pass") -> pass | L118: =IFERROR(IF(AND(MATCH(A118,Projection_classes,0),YEAR(current_date)=Projections!B118),"pass","fail"),"") -> fail
A119: EverSports | B119: 2014 | C119: 11.848346 | D119: 11.848346 | E119: 11.848346 | I119: -0.016754683 | J119: 0.067044285 | K119: =IF(OR(B119<$N$1,B119>$P$1),"fail","pass") -> pass | L119: =IFERROR(IF(AND(MATCH(A119,Projection_classes,0),YEAR(current_date)=Projections!B119),"pass","fail"),"") -> fail
A120: EverSports | B120: 2015 | C120: 22.925659 | D120: 22.925659 | E120: 22.925659 | I120: -0.013229945 | J120: 0.069245491 | K120: =IF(OR(B120<$N$1,B120>$P$1),"fail","pass") -> pass | L120: =IFERROR(IF(AND(MATCH(A120,Projection_classes,0),YEAR(current_date)=Projections!B120),"pass","fail"),"") -> fail
A121: EverSports | B121: 2016 | C121: 27.11483 | D121: 27.11483 | E121: 27.11483 | I121: -0.0047554079 | J121: 0.069561773 | K121: =IF(OR(B121<$N$1,B121>$P$1),"fail","pass") -> pass | L121: =IFERROR(IF(AND(MATCH(A121,Projection_classes,0),YEAR(current_date)=Projections!B121),"pass","fail"),"") -> fail
A122: EverSports | B122: 2017 | C122: 38.059479 | D122: 38.059479 | E122: 38.059479 | I122: -0.0051204854 | J122: 0.079010008 | K122: =IF(OR(B122<$N$1,B122>$P$1),"fail","pass") -> pass | L122: =IFERROR(IF(AND(MATCH(A122,Projection_classes,0),YEAR(current_date)=Projections!B122),"pass","fail"),"") -> fail
A123: EverSports | B123: 2018 | C123: 52.866291 | D123: 52.866291 | E123: 52.866291 | I123: 0.012497099 | J123: 0.078738372 | K123: =IF(OR(B123<$N$1,B123>$P$1),"fail","pass") -> pass | L123: =IFERROR(IF(AND(MATCH(A123,Projection_classes,0),YEAR(current_date)=Projections!B123),"pass","fail"),"") -> fail
... A129: EverSports | B129: 2024 | C129: 99.062282 | D129: 99.062282 | E129: 99.062282 | I129: 0.077167475 | J129: 0.084594526 | K129: =IF(OR(B129<$N$1,B129>$P$1),"fail","pass") -> pass | L129: =IFERROR(IF(AND(MATCH(A129,Projection_classes,0),YEAR(current_date)=Projections!B129),"pass","fail"),"") -> fail
A130: EverSports | B130: 2025 | C130: 32.376575 | D130: 32.376575 | E130: 32.376575 | K130: =IF(OR(B130<$N$1,B130>$P$1),"fail","pass") -> pass | L130: =IFERROR(IF(AND(MATCH(A130,Projection_classes,0),YEAR(current_date)=Projections!B130),"pass","fail"),"") -> fail
A131: EverSports | B131: 2026 | C131: 136.80361 | D131: 0 | E131: 0 | K131: =IF(OR(B131<$N$1,B131>$P$1),"fail","pass") -> fail | L131: =IFERROR(IF(AND(MATCH(A131,Projection_classes,0),YEAR(current_date)=Projections!B131),"pass","fail"),"") -> pass
A132: General Liability ARL | B132: 2001 | C132: 0 | D132: 0 | E132: 0 | K132: =IF(OR(B132<$N$1,B132>$P$1),"fail","pass") -> pass | L132: =IFERROR(IF(AND(MATCH(A132,Projection_classes,0),YEAR(current_date)=Projections!B132),"pass","fail"),"") -> fail
A133: General Liability ARL | B133: 2002 | C133: 0.42720069 | D133: 0.42720069 | E133: 0.42720069 | K133: =IF(OR(B133<$N$1,B133>$P$1),"fail","pass") -> pass | L133: =IFERROR(IF(AND(MATCH(A133,Projection_classes,0),YEAR(current_date)=Projections!B133),"pass","fail"),"") -> fail
A134: General Liability ARL | B134: 2003 | C134: 31.75736 | D134: 31.75736 | E134: 31.75736 | K134: =IF(OR(B134<$N$1,B134>$P$1),"fail","pass") -> pass | L134: =IFERROR(IF(AND(MATCH(A134,Projection_classes,0),YEAR(current_date)=Projections!B134),"pass","fail"),"") -> fail
A135: General Liability ARL | B135: 2004 | C135: 55.531214 | D135: 55.531214 | E135: 55.531214 | K135: =IF(OR(B135<$N$1,B135>$P$1),"fail","pass") -> pass | L135: =IFERROR(IF(AND(MATCH(A135,Projection_classes,0),YEAR(current_date)=Projections!B135),"pass","fail"),"") -> fail
A136: General Liability ARL | B136: 2005 | C136: 60.40411 | D136: 60.40411 | E136: 60.40411 | K136: =IF(OR(B136<$N$1,B136>$P$1),"fail","pass") -> pass | L136: =IFERROR(IF(AND(MATCH(A136,Projection_classes,0),YEAR(current_date)=Projections!B136),"pass","fail"),"") -> fail
A137: General Liability ARL | B137: 2006 | C137: 64.834785 | D137: 64.834785 | E137: 64.834785 | K137: =IF(OR(B137<$N$1,B137>$P$1),"fail","pass") -> pass | L137: =IFERROR(IF(AND(MATCH(A137,Projection_classes,0),YEAR(current_date)=Projections!B137),"pass","fail"),"") -> fail
A138: General Liability ARL | B138: 2007 | C138: 63.167443 | D138: 63.167443 | E138: 63.167443 | I138: -0.0090413677 | J138: 0.087733472 | K138: =IF(OR(B138<$N$1,B138>$P$1),"fail","pass") -> pass | L138: =IFERROR(IF(AND(MATCH(A138,Projection_classes,0),YEAR(current_date)=Projections!B138),"pass","fail"),"") -> fail
A139: General Liability ARL | B139: 2008 | C139: 56.212328 | D139: 56.212328 | E139: 56.212328 | I139: -0.050167356 | J139: 0.087236473 | K139: =IF(OR(B139<$N$1,B139>$P$1),"fail","pass") -> pass | L139: =IFERROR(IF(AND(MATCH(A139,Projection_classes,0),YEAR(current_date)=Projections!B139),"pass","fail"),"") -> fail
A140: General Liability ARL | B140: 2009 | C140: 42.135833 | D140: 42.135833 | E140: 42.135833 | I140: -0.020910608 | J140: 0.075952758 | K140: =IF(OR(B140<$N$1,B140>$P$1),"fail","pass") -> pass | L140: =IFERROR(IF(AND(MATCH(A140,Projection_classes,0),YEAR(current_date)=Projections!B140),"pass","fail"),"") -> fail
A141: General Liability ARL | B141: 2010 | C141: 32.887354 | D141: 32.887354 | E141: 32.887354 | I141: -0.00029274553 | J141: 0.071912051 | K141: =IF(OR(B141<$N$1,B141>$P$1),"fail","pass") -> pass | L141: =IFERROR(IF(AND(MATCH(A141,Projection_classes,0),YEAR(current_date)=Projections!B141),"pass","fail"),"") -> fail
A142: General Liability ARL | B142: 2011 | C142: 35.019956 | D142: 35.019956 | E142: 35.019956 | I142: -0.005822788 | J142: 0.075227489 | K142: =IF(OR(B142<$N$1,B142>$P$1),"fail","pass") -> pass | L142: =IFERROR(IF(AND(MATCH(A142,Projection_classes,0),YEAR(current_date)=Projections!B142),"pass","fail"),"") -> fail
A143: General Liability ARL | B143: 2012 | C143: 38.221043 | D143: 38.221043 | E143: 38.221043 | I143: -0.0021910283 | J143: 0.074006983 | K143: =IF(OR(B143<$N$1,B143>$P$1),"fail","pass") -> pass | L143: =IFERROR(IF(AND(MATCH(A143,Projection_classes,0),YEAR(current_date)=Projections!B143),"pass","fail"),"") -> fail
A144: General Liability ARL | B144: 2013 | C144: 40.26456 | D144: 40.26456 | E144: 40.26456 | I144: -0.0049192179 | J144: 0.069322035 | K144: =IF(OR(B144<$N$1,B144>$P$1),"fail","pass") -> pass | L144: =IFERROR(IF(AND(MATCH(A144,Projection_classes,0),YEAR(current_date)=Projections!B144),"pass","fail"),"") -> fail
A145: General Liability ARL | B145: 2014 | C145: 41.578853 | D145: 41.578853 | E145: 41.578853 | I145: -0.016754683 | J145: 0.067044285 | K145: =IF(OR(B145<$N$1,B145>$P$1),"fail","pass") -> pass | L145: =IFERROR(IF(AND(MATCH(A145,Projection_classes,0),YEAR(current_date)=Projections!B145),"pass","fail"),"") -> fail
A146: General Liability ARL | B146: 2015 | C146: 43.155826 | D146: 43.155826 | E146: 43.155826 | I146: -0.013229945 | J146: 0.069245491 | K146: =IF(OR(B146<$N$1,B146>$P$1),"fail","pass") -> pass | L146: =IFERROR(IF(AND(MATCH(A146,Projection_classes,0),YEAR(current_date)=Projections!B146),"pass","fail"),"") -> fail
A147: General Liability ARL | B147: 2016 | C147: 44.706104 | D147: 44.706104 | E147: 44.706104 | I147: -0.0047554079 | J147: 0.069561773 | K147: =IF(OR(B147<$N$1,B147>$P$1),"fail","pass") -> pass | L147: =IFERROR(IF(AND(MATCH(A147,Projection_classes,0),YEAR(current_date)=Projections!B147),"pass","fail"),"") -> fail
A148: General Liability ARL | B148: 2017 | C148: 45.11655 | D148: 45.11655 | E148: 45.11655 | I148: -0.0051204854 | J148: 0.079010008 | K148: =IF(OR(B148<$N$1,B148>$P$1),"fail","pass") -> pass | L148: =IFERROR(IF(AND(MATCH(A148,Projection_classes,0),YEAR(current_date)=Projections!B148),"pass","fail"),"") -> fail
A149: General Liability ARL | B149: 2018 | C149: 45.596925 | D149: 45.596925 | E149: 45.596925 | I149: 0.012497099 | J149: 0.078738372 | K149: =IF(OR(B149<$N$1,B149>$P$1),"fail","pass") -> pass | L149: =IFERROR(IF(AND(MATCH(A149,Projection_classes,0),YEAR(current_date)=Projections!B149),"pass","fail"),"") -> fail
... A155: General Liability ARL | B155: 2024 | C155: 40.16123 | D155: 40.16123 | E155: 40.16123 | I155: 0.077167475 | J155: 0.084594526 | K155: =IF(OR(B155<$N$1,B155>$P$1),"fail","pass") -> pass | L155: =IFERROR(IF(AND(MATCH(A155,Projection_classes,0),YEAR(current_date)=Projections!B155),"pass","fail"),"") -> fail
A156: General Liability ARL | B156: 2025 | C156: 12.886729 | D156: 12.886729 | E156: 12.886729 | K156: =IF(OR(B156<$N$1,B156>$P$1),"fail","pass") -> pass | L156: =IFERROR(IF(AND(MATCH(A156,Projection_classes,0),YEAR(current_date)=Projections!B156),"pass","fail"),"") -> fail
A157: General Liability ARL | B157: 2026 | C157: 30.3935 | D157: 0 | E157: 0 | K157: =IF(OR(B157<$N$1,B157>$P$1),"fail","pass") -> fail | L157: =IFERROR(IF(AND(MATCH(A157,Projection_classes,0),YEAR(current_date)=Projections!B157),"pass","fail"),"") -> pass
A158: General Liability ex ARL | B158: 2001 | C158: 10.909748 | D158: 10.909748 | E158: 10.909748 | K158: =IF(OR(B158<$N$1,B158>$P$1),"fail","pass") -> pass | L158: =IFERROR(IF(AND(MATCH(A158,Projection_classes,0),YEAR(current_date)=Projections!B158),"pass","fail"),"") -> fail
A159: General Liability ex ARL | B159: 2002 | C159: 11.207217 | D159: 11.207217 | E159: 11.207217 | K159: =IF(OR(B159<$N$1,B159>$P$1),"fail","pass") -> pass | L159: =IFERROR(IF(AND(MATCH(A159,Projection_classes,0),YEAR(current_date)=Projections!B159),"pass","fail"),"") -> fail
A160: General Liability ex ARL | B160: 2003 | C160: 15.383326 | D160: 15.383326 | E160: 15.383326 | K160: =IF(OR(B160<$N$1,B160>$P$1),"fail","pass") -> pass | L160: =IFERROR(IF(AND(MATCH(A160,Projection_classes,0),YEAR(current_date)=Projections!B160),"pass","fail"),"") -> fail
A161: General Liability ex ARL | B161: 2004 | C161: 41.89739 | D161: 41.89739 | E161: 41.89739 | K161: =IF(OR(B161<$N$1,B161>$P$1),"fail","pass") -> pass | L161: =IFERROR(IF(AND(MATCH(A161,Projection_classes,0),YEAR(current_date)=Projections!B161),"pass","fail"),"") -> fail
A162: General Liability ex ARL | B162: 2005 | C162: 54.756795 | D162: 54.756795 | E162: 54.756795 | K162: =IF(OR(B162<$N$1,B162>$P$1),"fail","pass") -> pass | L162: =IFERROR(IF(AND(MATCH(A162,Projection_classes,0),YEAR(current_date)=Projections!B162),"pass","fail"),"") -> fail
...

Sheet admin
A1: template_version | B1: 6

Sheet Other
A1: template_version | B1: 9

Sheet <>

Sheet Example - Parameters
B3: Triangle Shape Parameters | E3: guide | F3: Checks
C4: Triangle start (t=0) date | D4: 38718 | E4: YYYY-MM-DD | F4: =triangle_start_date='Example - Triangles'!F3 -> TRUE | H4: Mandatory
C5: Month of first development | D5: 9 | E5: first month in triangle | H5: Optional
C6: Development period increments (months) | D6: 12 | E6: triangle increments (column)
C7: Origin period increments (months) | D7: 12 | E7: triangle increments (row)
C8: Month of final development | D8: 237 | E8: Latest month in the largest triangle | F8: =IF(ISERROR(MATCH(month_final_development,'Example - Triangles'!$G$2:$FA$2, 0)), "Can't find this development month in triangle. Please be consistent with Triangle.", "OK") -> OK
C9: Inception Date | D9: 46023 | E9: YYYY-MM-DD
C10: Expiry Date | D10: 46387 | E10: YYYY-MM-DD
B11: Triangular data list (LOB/Class)
Q12: Cedant Business Segment Names (Optional)
B13: # | C13: Triangle Name | D13: Proportional/Non-proportional | E13: Start Year | F13: End Year | G13: Region | H13: Country | I13: Re/Ins/Retro | J13: LT LOB 1 (Dropdown List) | K13: LT LOB 1 Allocation | L13: LT LOB 2 (Dropdown List) | M13: LT LOB 2 Allocation | N13: LT LOB 3 (Dropdown List) | O13: LT LOB 3 Allocation | P13: LT LOB 4 (Dropdown List) | Q13: LT LOB 4 Allocation | R13: LT LOB 5 (Dropdown List) | S13: LT LOB 5 Allocation | T13: Allocation Check | U13: Currency | V13: Currency Rate | W13: Segment 1 | X13: Segment 2 | Y13: Segment 3 | Z13: Segment 4 | AA13: Segment 5 | AB13: Premium Triangle Source | AC13: Incurred Triangle Source | AD13: Paid Triangle Source | AE13: Ultimate Triangle Source
B14: 1 | C14: Professional Lines | D14: Mixed | E14: 2006 | F14: 2025 | G14: Worldwide | H14: Multi-country | I14: Retrocession | J14: Professional Liability | K14: 1 | T14: =IF(AND(C14<>"",SUM(K14,M14,O14,Q14,S14)=1),"pass",IF(AND(C14="",SUM(K14,M14,O14,Q14,S14)=0),"pass","fail")) -> pass | AB14: Cedant provided | AC14: Cedant provided | AD14: Cedant provided
B15: 2 | C15: Liability | D15: Mixed | E15: 2006 | F15: 2025 | G15: Worldwide | H15: Multi-country | I15: Retrocession | J15: Casualty | K15: 1 | T15: =IF(AND(C15<>"",SUM(K15,M15,O15,Q15,S15)=1),"pass",IF(AND(C15="",SUM(K15,M15,O15,Q15,S15)=0),"pass","fail")) -> pass | AB15: Cedant provided | AC15: Cedant provided | AD15: Cedant provided
B16: 3 | C16: Credit & Surety | D16: Mixed | E16: 2006 | F16: 2025 | G16: Worldwide | H16: Multi-country | I16: Retrocession | J16: Fidelity & Surety | K16: 1 | T16: =IF(AND(C16<>"",SUM(K16,M16,O16,Q16,S16)=1),"pass",IF(AND(C16="",SUM(K16,M16,O16,Q16,S16)=0),"pass","fail")) -> pass | AB16: Cedant provided | AC16: Cedant provided | AD16: Cedant provided
B17: 4 | C17: Motor NP | D17: Non Proportional | E17: 2006 | F17: 2025 | G17: Worldwide ex US | H17: Multi-country | I17: Retrocession | J17: Motor | K17: 1 | T17: =IF(AND(C17<>"",SUM(K17,M17,O17,Q17,S17)=1),"pass",IF(AND(C17="",SUM(K17,M17,O17,Q17,S17)=0),"pass","fail")) -> pass | AB17: Cedant provided | AC17: Cedant provided | AD17: Cedant provided
B18: 5 | C18: Motor PR | D18: Proportional | E18: 2006 | F18: 2025 | G18: Worldwide ex US | H18: Multi-country | I18: Retrocession | J18: Motor | K18: 1 | T18: =IF(AND(C18<>"",SUM(K18,M18,O18,Q18,S18)=1),"pass",IF(AND(C18="",SUM(K18,M18,O18,Q18,S18)=0),"pass","fail")) -> pass | AB18: Cedant provided | AC18: Cedant provided | AD18: Cedant provided
B19: 6 | C19: Cyber | D19: Mixed | E19: 2006 | F19: 2025 | G19: Worldwide | H19: Multi-country | I19: Retrocession | J19: Cyber | K19: 1 | T19: =IF(AND(C19<>"",SUM(K19,M19,O19,Q19,S19)=1),"pass",IF(AND(C19="",SUM(K19,M19,O19,Q19,S19)=0),"pass","fail")) -> pass | AB19: Cedant provided | AC19: Cedant provided | AD19: Cedant provided
B20: 7 | T20: =IF(AND(C20<>"",SUM(K20,M20,O20,Q20,S20)=1),"pass",IF(AND(C20="",SUM(K20,M20,O20,Q20,S20)=0),"pass","fail")) -> pass
B21: 8 | T21: =IF(AND(C21<>"",SUM(K21,M21,O21,Q21,S21)=1),"pass",IF(AND(C21="",SUM(K21,M21,O21,Q21,S21)=0),"pass","fail")) -> pass
B22: 9 | T22: =IF(AND(C22<>"",SUM(K22,M22,O22,Q22,S22)=1),"pass",IF(AND(C22="",SUM(K22,M22,O22,Q22,S22)=0),"pass","fail")) -> pass
B23: 10 | T23: =IF(AND(C23<>"",SUM(K23,M23,O23,Q23,S23)=1),"pass",IF(AND(C23="",SUM(K23,M23,O23,Q23,S23)=0),"pass","fail")) -> pass
B24: 11 | T24: =IF(AND(C24<>"",SUM(K24,M24,O24,Q24,S24)=1),"pass",IF(AND(C24="",SUM(K24,M24,O24,Q24,S24)=0),"pass","fail")) -> pass
B25: 12 | T25: =IF(AND(C25<>"",SUM(K25,M25,O25,Q25,S25)=1),"pass",IF(AND(C25="",SUM(K25,M25,O25,Q25,S25)=0),"pass","fail")) -> pass
B26: 13 | T26: =IF(AND(C26<>"",SUM(K26,M26,O26,Q26,S26)=1),"pass",IF(AND(C26="",SUM(K26,M26,O26,Q26,S26)=0),"pass","fail")) -> pass
B27: 14 | T27: =IF(AND(C27<>"",SUM(K27,M27,O27,Q27,S27)=1),"pass",IF(AND(C27="",SUM(K27,M27,O27,Q27,S27)=0),"pass","fail")) -> pass
B28: 15 | T28: =IF(AND(C28<>"",SUM(K28,M28,O28,Q28,S28)=1),"pass",IF(AND(C28="",SUM(K28,M28,O28,Q28,S28)=0),"pass","fail")) -> pass
B29: 16 | T29: =IF(AND(C29<>"",SUM(K29,M29,O29,Q29,S29)=1),"pass",IF(AND(C29="",SUM(K29,M29,O29,Q29,S29)=0),"pass","fail")) -> pass
B30: 17 | T30: =IF(AND(C30<>"",SUM(K30,M30,O30,Q30,S30)=1),"pass",IF(AND(C30="",SUM(K30,M30,O30,Q30,S30)=0),"pass","fail")) -> pass
B31: 18 | T31: =IF(AND(C31<>"",SUM(K31,M31,O31,Q31,S31)=1),"pass",IF(AND(C31="",SUM(K31,M31,O31,Q31,S31)=0),"pass","fail")) -> pass
... B35: 22 | T35: =IF(AND(C35<>"",SUM(K35,M35,O35,Q35,S35)=1),"pass",IF(AND(C35="",SUM(K35,M35,O35,Q35,S35)=0),"pass","fail")) -> pass
B36: 23 | R36: =IF(AND(C36<>"",SUM(I36,K36,M36,O36,Q36)=1),"pass",IF(AND(C36="",SUM(I36,K36,M36,O36,Q36)=0),"pass","fail")) -> pass
B37: 24 | R37: =IF(AND(C37<>"",SUM(I37,K37,M37,O37,Q37)=1),"pass",IF(AND(C37="",SUM(I37,K37,M37,O37,Q37)=0),"pass","fail")) -> pass
B38: 25
B39: 26
B40: 27
B41: 28
B42: 29
B43: 30
B44: 31
B45: 32
B46: 33
B47: 34
B48: 35
B49: 36
... B212: 199
B213: 200 | R213: =IF(AND(C213<>"",SUM(I213,K213,M213,O213,Q213)=1),"pass",IF(AND(C213="",SUM(I213,K213,M213,O213,Q213)=0),"pass","fail")) -> pass
B216: Define aggregation/grouping of triangles for projection
S217: Cedant Business Segment Names (Optional)
B218: # | C218: Description (free text) | D218: Proportional/Non-proportional | E218: Triangle 1 | F218: Triangle 2 | G218: Region | H218: Country | I218: Re/Ins/Retro | J218: LT LOB 1 (Dropdown List) | K218: LT LOB 1 Allocation | L218: LT LOB 2 (Dropdown List) | M218: LT LOB 2 Allocation | N218: LT LOB 3 (Dropdown List) | O218: LT LOB 3 Allocation | P218: LT LOB 4 (Dropdown List) | Q218: LT LOB 4 Allocation | R218: LT LOB 5 (Dropdown List) | S218: LT LOB 5 Allocation | T218: Allocation Check | U218: Currency | V218: Currency Rate | W218: Segment 1 | X218: Segment 2 | Y218: Segment 3 | Z218: Segment 4 | AA218: Segment 5
B219: 1 | C219: =C14 -> Professional Lines | D219: =D14 -> Mixed | E219: =C219 -> Professional Lines | G219: Worldwide | H219: Multi-country | I219: Retrocession | J219: Professional Liability | K219: 1 | T219: =IF(AND(C219<>"",SUM(K219,M219,O219,Q219,S219)=1),"pass",IF(AND(C219="",SUM(K219,M219,O219,Q219,S219)=0),"pass","fail")) -> pass
B220: 2 | C220: =C15 -> Liability | D220: =D15 -> Mixed | E220: =C220 -> Liability | G220: Worldwide | H220: Multi-country | I220: Retrocession | J220: Casualty | K220: 1 | T220: =IF(AND(C220<>"",SUM(K220,M220,O220,Q220,S220)=1),"pass",IF(AND(C220="",SUM(K220,M220,O220,Q220,S220)=0),"pass","fail")) -> pass
B221: 3 | C221: =C16 -> Credit & Surety | D221: =D16 -> Mixed | E221: =C221 -> Credit & Surety | G221: Worldwide | H221: Multi-country | I221: Retrocession | J221: Fidelity & Surety | K221: 1 | T221: =IF(AND(C221<>"",SUM(K221,M221,O221,Q221,S221)=1),"pass",IF(AND(C221="",SUM(K221,M221,O221,Q221,S221)=0),"pass","fail")) -> pass
B222: 4 | C222: =C17 -> Motor NP | D222: =D17 -> Non Proportional | E222: =C222 -> Motor NP | G222: Worldwide ex US | H222: Multi-country | I222: Retrocession | J222: Motor | K222: 1 | T222: =IF(AND(C222<>"",SUM(K222,M222,O222,Q222,S222)=1),"pass",IF(AND(C222="",SUM(K222,M222,O222,Q222,S222)=0),"pass","fail")) -> pass
B223: 5 | C223: =C18 -> Motor PR | D223: =D18 -> Proportional | E223: =C223 -> Motor PR | G223: Worldwide ex US | H223: Multi-country | I223: Retrocession | J223: Motor | K223: 1 | T223: =IF(AND(C223<>"",SUM(K223,M223,O223,Q223,S223)=1),"pass",IF(AND(C223="",SUM(K223,M223,O223,Q223,S223)=0),"pass","fail")) -> pass
B224: 6 | C224: =C19 -> Cyber | D224: =D19 -> Mixed | E224: =C224 -> Cyber | G224: Worldwide | H224: Multi-country | I224: Retrocession | J224: Cyber | K224: 1 | T224: =IF(AND(C224<>"",SUM(K224,M224,O224,Q224,S224)=1),"pass",IF(AND(C224="",SUM(K224,M224,O224,Q224,S224)=0),"pass","fail")) -> pass
B225: 7 | T225: =IF(AND(C225<>"",SUM(K225,M225,O225,Q225,S225)=1),"pass",IF(AND(C225="",SUM(K225,M225,O225,Q225,S225)=0),"pass","fail")) -> pass
B226: 8 | T226: =IF(AND(C226<>"",SUM(K226,M226,O226,Q226,S226)=1),"pass",IF(AND(C226="",SUM(K226,M226,O226,Q226,S226)=0),"pass","fail")) -> pass
B227: 9 | T227: =IF(AND(C227<>"",SUM(K227,M227,O227,Q227,S227)=1),"pass",IF(AND(C227="",SUM(K227,M227,O227,Q227,S227)=0),"pass","fail")) -> pass
B228: 10 | T228: =IF(AND(C228<>"",SUM(K228,M228,O228,Q228,S228)=1),"pass",IF(AND(C228="",SUM(K228,M228,O228,Q228,S228)=0),"pass","fail")) -> pass
B229: 11 | T229: =IF(AND(C229<>"",SUM(K229,M229,O229,Q229,S229)=1),"pass",IF(AND(C229="",SUM(K229,M229,O229,Q229,S229)=0),"pass","fail")) -> pass
B230: 12 | T230: =IF(AND(C230<>"",SUM(K230,M230,O230,Q230,S230)=1),"pass",IF(AND(C230="",SUM(K230,M230,O230,Q230,S230)=0),"pass","fail")) -> pass
B231: 13 | T231: =IF(AND(C231<>"",SUM(K231,M231,O231,Q231,S231)=1),"pass",IF(AND(C231="",SUM(K231,M231,O231,Q231,S231)=0),"pass","fail")) -> pass
B232: 14 | T232: =IF(AND(C232<>"",SUM(K232,M232,O232,Q232,S232)=1),"pass",IF(AND(C232="",SUM(K232,M232,O232,Q232,S232)=0),"pass","fail")) -> pass
B233: 15 | T233: =IF(AND(C233<>"",SUM(K233,M233,O233,Q233,S233)=1),"pass",IF(AND(C233="",SUM(K233,M233,O233,Q233,S233)=0),"pass","fail")) -> pass
B234: 16 | T234: =IF(AND(C234<>"",SUM(K234,M234,O234,Q234,S234)=1),"pass",IF(AND(C234="",SUM(K234,M234,O234,Q234,S234)=0),"pass","fail")) -> pass
B235: 17 | T235: =IF(AND(C235<>"",SUM(K235,M235,O235,Q235,S235)=1),"pass",IF(AND(C235="",SUM(K235,M235,O235,Q235,S235)=0),"pass","fail")) -> pass
B236: 18 | T236: =IF(AND(C236<>"",SUM(K236,M236,O236,Q236,S236)=1),"pass",IF(AND(C236="",SUM(K236,M236,O236,Q236,S236)=0),"pass","fail")) -> pass
... B418: 200 | T418: =IF(AND(C418<>"",SUM(K418,M418,O418,Q418,S418)=1),"pass",IF(AND(C418="",SUM(K418,M418,O418,Q418,S418)=0),"pass","fail")) -> pass

Sheet Example - Triangles
G1: Development months
A2: LOB (dropdown) | B2: Type (Incurred / Paid …) | C2: Loss type | D2: Basis (Accident Year / UW Year) | E2: Currency (e.g. USD, GBP …) | F2: Origin Year | G2: =month_first_development -> 6 | H2: =G2+triangle_increments_months -> 18 | I2: =H2+triangle_increments_months -> 30 | J2: =I2+triangle_increments_months -> 42 | K2: =J2+triangle_increments_months -> 54 | L2: =K2+triangle_increments_months -> 66 | M2: =L2+triangle_increments_months -> 78 | N2: =M2+triangle_increments_months -> 90 | O2: =N2+triangle_increments_months -> 102 | ... FA2: =EZ2+triangle_increments_months -> 1806
A3: Professional Lines | B3: Net Written Premium | C3: All | D3: UW Year | E3: USD | F3: =triangle_start_date -> 36892 | G3: 1000000 | H3: 2000000 | I3: 2000000 | J3: 2000000 | K3: 2000000 | L3: 2000000 | M3: 2000000 | N3: 2000000 | O3: 2000000 | P3: 2000000 | Q3: 2000000 | R3: 2000000 | S3: 2000000 | T3: 2000000 | U3: 2000000 | V3: 2000000 | W3: 2000000 | X3: 2000000 | Y3: 2000000 | Z3: 2000000
A4: Professional Lines | B4: Net Written Premium | C4: All | D4: UW Year | E4: USD | F4: =EDATE(F3,12) -> 37257 | G4: 1000000 | H4: 2000000 | I4: 2000000 | J4: 2000000 | K4: 2000000 | L4: 2000000 | M4: 2000000 | N4: 2000000 | O4: 2000000 | P4: 2000000 | Q4: 2000000 | R4: 2000000 | S4: 2000000 | T4: 2000000 | U4: 2000000 | V4: 2000000 | W4: 2000000 | X4: 2000000 | Y4: 2000000
A5: Professional Lines | B5: Net Written Premium | C5: All | D5: UW Year | E5: USD | F5: =EDATE(F4,12) -> 37622 | G5: 1000000 | H5: 2000000 | I5: 2000000 | J5: 2000000 | K5: 2000000 | L5: 2000000 | M5: 2000000 | N5: 2000000 | O5: 2000000 | P5: 2000000 | Q5: 2000000 | R5: 2000000 | S5: 2000000 | T5: 2000000 | U5: 2000000 | V5: 2000000 | W5: 2000000 | X5: 2000000
A6: Professional Lines | B6: Net Written Premium | C6: All | D6: UW Year | E6: USD | F6: =EDATE(F5,12) -> 37987 | G6: 1000000 | H6: 2000000 | I6: 2000000 | J6: 2000000 | K6: 2000000 | L6: 2000000 | M6: 2000000 | N6: 2000000 | O6: 2000000 | P6: 2000000 | Q6: 2000000 | R6: 2000000 | S6: 2000000 | T6: 2000000 | U6: 2000000 | V6: 2000000 | W6: 2000000
A7: Professional Lines | B7: Net Written Premium | C7: All | D7: UW Year | E7: USD | F7: =EDATE(F6,12) -> 38353 | G7: 1000000 | H7: 2000000 | I7: 2000000 | J7: 2000000 | K7: 2000000 | L7: 2000000 | M7: 2000000 | N7: 2000000 | O7: 2000000 | P7: 2000000 | Q7: 2000000 | R7: 2000000 | S7: 2000000 | T7: 2000000 | U7: 2000000 | V7: 2000000
A8: Professional Lines | B8: Net Written Premium | C8: All | D8: UW Year | E8: USD | F8: =EDATE(F7,12) -> 38718 | G8: 1000000 | H8: 2000000 | I8: 2000000 | J8: 2000000 | K8: 2000000 | L8: 2000000 | M8: 2000000 | N8: 2000000 | O8: 2000000 | P8: 2000000 | Q8: 2000000 | R8: 2000000 | S8: 2000000 | T8: 2000000 | U8: 2000000
A9: Professional Lines | B9: Net Written Premium | C9: All | D9: UW Year | E9: USD | F9: =EDATE(F8,12) -> 39083 | G9: 1000000 | H9: 2000000 | I9: 2000000 | J9: 2000000 | K9: 2000000 | L9: 2000000 | M9: 2000000 | N9: 2000000 | O9: 2000000 | P9: 2000000 | Q9: 2000000 | R9: 2000000 | S9: 2000000 | T9: 2000000
A10: Professional Lines | B10: Net Written Premium | C10: All | D10: UW Year | E10: USD | F10: =EDATE(F9,12) -> 39448 | G10: 1000000 | H10: 2000000 | I10: 2000000 | J10: 2000000 | K10: 2000000 | L10: 2000000 | M10: 2000000 | N10: 2000000 | O10: 2000000 | P10: 2000000 | Q10: 2000000 | R10: 2000000 | S10: 2000000
A11: Professional Lines | B11: Net Written Premium | C11: All | D11: UW Year | E11: USD | F11: =EDATE(F10,12) -> 39814 | G11: 1000000 | H11: 2000000 | I11: 2000000 | J11: 2000000 | K11: 2000000 | L11: 2000000 | M11: 2000000 | N11: 2000000 | O11: 2000000 | P11: 2000000 | Q11: 2000000 | R11: 2000000
A12: Professional Lines | B12: Net Written Premium | C12: All | D12: UW Year | E12: USD | F12: =EDATE(F11,12) -> 40179 | G12: 1000000 | H12: 2000000 | I12: 2000000 | J12: 2000000 | K12: 2000000 | L12: 2000000 | M12: 2000000 | N12: 2000000 | O12: 2000000 | P12: 2000000 | Q12: 2000000
A13: Professional Lines | B13: Net Written Premium | C13: All | D13: UW Year | E13: USD | F13: =EDATE(F12,12) -> 40544 | G13: 1000000 | H13: 2000000 | I13: 2000000 | J13: 2000000 | K13: 2000000 | L13: 2000000 | M13: 2000000 | N13: 2000000 | O13: 2000000 | P13: 2000000
A14: Professional Lines | B14: Net Written Premium | C14: All | D14: UW Year | E14: USD | F14: =EDATE(F13,12) -> 40909 | G14: 1000000 | H14: 2000000 | I14: 2000000 | J14: 2000000 | K14: 2000000 | L14: 2000000 | M14: 2000000 | N14: 2000000 | O14: 2000000
A15: Professional Lines | B15: Net Written Premium | C15: All | D15: UW Year | E15: USD | F15: =EDATE(F14,12) -> 41275 | G15: 1000000 | H15: 2000000 | I15: 2000000 | J15: 2000000 | K15: 2000000 | L15: 2000000 | M15: 2000000 | N15: 2000000
A16: Professional Lines | B16: Net Written Premium | C16: All | D16: UW Year | E16: USD | F16: =EDATE(F15,12) -> 41640 | G16: 1000000 | H16: 2000000 | I16: 2000000 | J16: 2000000 | K16: 2000000 | L16: 2000000 | M16: 2000000
A17: Professional Lines | B17: Net Written Premium | C17: All | D17: UW Year | E17: USD | F17: =EDATE(F16,12) -> 42005 | G17: 1000000 | H17: 2000000 | I17: 2000000 | J17: 2000000 | K17: 2000000 | L17: 2000000
A18: Professional Lines | B18: Net Written Premium | C18: All | D18: UW Year | E18: USD | F18: =EDATE(F17,12) -> 42370 | G18: 1000000 | H18: 2000000 | I18: 2000000 | J18: 2000000 | K18: 2000000
A19: Professional Lines | B19: Net Written Premium | C19: All | D19: UW Year | E19: USD | F19: =EDATE(F18,12) -> 42736 | G19: 1000000 | H19: 2000000 | I19: 2000000 | J19: 2000000
A20: Professional Lines | B20: Net Written Premium | C20: All | D20: UW Year | E20: USD | F20: =EDATE(F19,12) -> 43101 | G20: 1000000 | H20: 2000000 | I20: 2000000
A21: Professional Lines | B21: Net Written Premium | C21: All | D21: UW Year | E21: USD | F21: =EDATE(F20,12) -> 43466 | G21: 1000000 | H21: 2000000
A22: Professional Lines | B22: Net Written Premium | C22: All | D22: UW Year | E22: USD | F22: =EDATE(F21,12) -> 43831 | G22: 1000000
A24: Liability | B24: Net Written Premium | C24: All | D24: UW Year | E24: USD | F24: =triangle_start_date -> 36892 | G24: 1000000 | H24: 2000000 | I24: 2000000 | J24: 2000000 | K24: 2000000 | L24: 2000000 | M24: 2000000 | N24: 2000000 | O24: 2000000 | P24: 2000000 | Q24: 2000000 | R24: 2000000 | S24: 2000000 | T24: 2000000 | U24: 2000000 | V24: 2000000 | W24: 2000000 | X24: 2000000 | Y24: 2000000 | Z24: 2000000
A25: Liability | B25: Net Written Premium | C25: All | D25: UW Year | E25: USD | F25: =EDATE(F24,12) -> 37257 | G25: 1000000 | H25: 2000000 | I25: 2000000 | J25: 2000000 | K25: 2000000 | L25: 2000000 | M25: 2000000 | N25: 2000000 | O25: 2000000 | P25: 2000000 | Q25: 2000000 | R25: 2000000 | S25: 2000000 | T25: 2000000 | U25: 2000000 | V25: 2000000 | W25: 2000000 | X25: 2000000 | Y25: 2000000
A26: Liability | B26: Net Written Premium | C26: All | D26: UW Year | E26: USD | F26: =EDATE(F25,12) -> 37622 | G26: 1000000 | H26: 2000000 | I26: 2000000 | J26: 2000000 | K26: 2000000 | L26: 2000000 | M26: 2000000 | N26: 2000000 | O26: 2000000 | P26: 2000000 | Q26: 2000000 | R26: 2000000 | S26: 2000000 | T26: 2000000 | U26: 2000000 | V26: 2000000 | W26: 2000000 | X26: 2000000
A27: Liability | B27: Net Written Premium | C27: All | D27: UW Year | E27: USD | F27: =EDATE(F26,12) -> 37987 | G27: 1000000 | H27: 2000000 | I27: 2000000 | J27: 2000000 | K27: 2000000 | L27: 2000000 | M27: 2000000 | N27: 2000000 | O27: 2000000 | P27: 2000000 | Q27: 2000000 | R27: 2000000 | S27: 2000000 | T27: 2000000 | U27: 2000000 | V27: 2000000 | W27: 2000000
A28: Liability | B28: Net Written Premium | C28: All | D28: UW Year | E28: USD | F28: =EDATE(F27,12) -> 38353 | G28: 1000000 | H28: 2000000 | I28: 2000000 | J28: 2000000 | K28: 2000000 | L28: 2000000 | M28: 2000000 | N28: 2000000 | O28: 2000000 | P28: 2000000 | Q28: 2000000 | R28: 2000000 | S28: 2000000 | T28: 2000000 | U28: 2000000 | V28: 2000000
A29: Liability | B29: Net Written Premium | C29: All | D29: UW Year | E29: USD | F29: =EDATE(F28,12) -> 38718 | G29: 1000000 | H29: 2000000 | I29: 2000000 | J29: 2000000 | K29: 2000000 | L29: 2000000 | M29: 2000000 | N29: 2000000 | O29: 2000000 | P29: 2000000 | Q29: 2000000 | R29: 2000000 | S29: 2000000 | T29: 2000000 | U29: 2000000
A30: Liability | B30: Net Written Premium | C30: All | D30: UW Year | E30: USD | F30: =EDATE(F29,12) -> 39083 | G30: 1000000 | H30: 2000000 | I30: 2000000 | J30: 2000000 | K30: 2000000 | L30: 2000000 | M30: 2000000 | N30: 2000000 | O30: 2000000 | P30: 2000000 | Q30: 2000000 | R30: 2000000 | S30: 2000000 | T30: 2000000
A31: Liability | B31: Net Written Premium | C31: All | D31: UW Year | E31: USD | F31: =EDATE(F30,12) -> 39448 | G31: 1000000 | H31: 2000000 | I31: 2000000 | J31: 2000000 | K31: 2000000 | L31: 2000000 | M31: 2000000 | N31: 2000000 | O31: 2000000 | P31: 2000000 | Q31: 2000000 | R31: 2000000 | S31: 2000000
A32: Liability | B32: Net Written Premium | C32: All | D32: UW Year | E32: USD | F32: =EDATE(F31,12) -> 39814 | G32: 1000000 | H32: 2000000 | I32: 2000000 | J32: 2000000 | K32: 2000000 | L32: 2000000 | M32: 2000000 | N32: 2000000 | O32: 2000000 | P32: 2000000 | Q32: 2000000 | R32: 2000000
A33: Liability | B33: Net Written Premium | C33: All | D33: UW Year | E33: USD | F33: =EDATE(F32,12) -> 40179 | G33: 1000000 | H33: 2000000 | I33: 2000000 | J33: 2000000 | K33: 2000000 | L33: 2000000 | M33: 2000000 | N33: 2000000 | O33: 2000000 | P33: 2000000 | Q33: 2000000
A34: Liability | B34: Net Written Premium | C34: All | D34: UW Year | E34: USD | F34: =EDATE(F33,12) -> 40544 | G34: 1000000 | H34: 2000000 | I34: 2000000 | J34: 2000000 | K34: 2000000 | L34: 2000000 | M34: 2000000 | N34: 2000000 | O34: 2000000 | P34: 2000000
A35: Liability | B35: Net Written Premium | C35: All | D35: UW Year | E35: USD | F35: =EDATE(F34,12) -> 40909 | G35: 1000000 | H35: 2000000 | I35: 2000000 | J35: 2000000 | K35: 2000000 | L35: 2000000 | M35: 2000000 | N35: 2000000 | O35: 2000000
A36: Liability | B36: Net Written Premium | C36: All | D36: UW Year | E36: USD | F36: =EDATE(F35,12) -> 41275 | G36: 1000000 | H36: 2000000 | I36: 2000000 | J36: 2000000 | K36: 2000000 | L36: 2000000 | M36: 2000000 | N36: 2000000
A37: Liability | B37: Net Written Premium | C37: All | D37: UW Year | E37: USD | F37: =EDATE(F36,12) -> 41640 | G37: 1000000 | H37: 2000000 | I37: 2000000 | J37: 2000000 | K37: 2000000 | L37: 2000000 | M37: 2000000
A38: Liability | B38: Net Written Premium | C38: All | D38: UW Year | E38: USD | F38: =EDATE(F37,12) -> 42005 | G38: 1000000 | H38: 2000000 | I38: 2000000 | J38: 2000000 | K38: 2000000 | L38: 2000000
A39: Liability | B39: Net Written Premium | C39: All | D39: UW Year | E39: USD | F39: =EDATE(F38,12) -> 42370 | G39: 1000000 | H39: 2000000 | I39: 2000000 | J39: 2000000 | K39: 2000000
A40: Liability | B40: Net Written Premium | C40: All | D40: UW Year | E40: USD | F40: =EDATE(F39,12) -> 42736 | G40: 1000000 | H40: 2000000 | I40: 2000000 | J40: 2000000
A41: Liability | B41: Net Written Premium | C41: All | D41: UW Year | E41: USD | F41: =EDATE(F40,12) -> 43101 | G41: 1000000 | H41: 2000000 | I41: 2000000
A42: Liability | B42: Net Written Premium | C42: All | D42: UW Year | E42: USD | F42: =EDATE(F41,12) -> 43466 | G42: 1000000 | H42: 2000000
A43: Liability | B43: Net Written Premium | C43: All | D43: UW Year | E43: USD | F43: =EDATE(F42,12) -> 43831 | G43: 1000000
A45: Credit & Surety | B45: Net Written Premium | C45: All | D45: UW Year | E45: USD | F45: =triangle_start_date -> 36892 | G45: 1000000 | H45: 2000000 | I45: 2000000 | J45: 2000000 | K45: 2000000 | L45: 2000000 | M45: 2000000 | N45: 2000000 | O45: 2000000 | P45: 2000000 | Q45: 2000000 | R45: 2000000 | S45: 2000000 | T45: 2000000 | U45: 2000000 | V45: 2000000 | W45: 2000000 | X45: 2000000 | Y45: 2000000 | Z45: 2000000
A46: Credit & Surety | B46: Net Written Premium | C46: All | D46: UW Year | E46: USD | F46: =EDATE(F45,12) -> 37257 | G46: 1000000 | H46: 2000000 | I46: 2000000 | J46: 2000000 | K46: 2000000 | L46: 2000000 | M46: 2000000 | N46: 2000000 | O46: 2000000 | P46: 2000000 | Q46: 2000000 | R46: 2000000 | S46: 2000000 | T46: 2000000 | U46: 2000000 | V46: 2000000 | W46: 2000000 | X46: 2000000 | Y46: 2000000
A47: Credit & Surety | B47: Net Written Premium | C47: All | D47: UW Year | E47: USD | F47: =EDATE(F46,12) -> 37622 | G47: 1000000 | H47: 2000000 | I47: 2000000 | J47: 2000000 | K47: 2000000 | L47: 2000000 | M47: 2000000 | N47: 2000000 | O47: 2000000 | P47: 2000000 | Q47: 2000000 | R47: 2000000 | S47: 2000000 | T47: 2000000 | U47: 2000000 | V47: 2000000 | W47: 2000000 | X47: 2000000
A48: Credit & Surety | B48: Net Written Premium | C48: All | D48: UW Year | E48: USD | F48: =EDATE(F47,12) -> 37987 | G48: 1000000 | H48: 2000000 | I48: 2000000 | J48: 2000000 | K48: 2000000 | L48: 2000000 | M48: 2000000 | N48: 2000000 | O48: 2000000 | P48: 2000000 | Q48: 2000000 | R48: 2000000 | S48: 2000000 | T48: 2000000 | U48: 2000000 | V48: 2000000 | W48: 2000000
A49: Credit & Surety | B49: Net Written Premium | C49: All | D49: UW Year | E49: USD | F49: =EDATE(F48,12) -> 38353 | G49: 1000000 | H49: 2000000 | I49: 2000000 | J49: 2000000 | K49: 2000000 | L49: 2000000 | M49: 2000000 | N49: 2000000 | O49: 2000000 | P49: 2000000 | Q49: 2000000 | R49: 2000000 | S49: 2000000 | T49: 2000000 | U49: 2000000 | V49: 2000000
A50: Credit & Surety | B50: Net Written Premium | C50: All | D50: UW Year | E50: USD | F50: =EDATE(F49,12) -> 38718 | G50: 1000000 | H50: 2000000 | I50: 2000000 | J50: 2000000 | K50: 2000000 | L50: 2000000 | M50: 2000000 | N50: 2000000 | O50: 2000000 | P50: 2000000 | Q50: 2000000 | R50: 2000000 | S50: 2000000 | T50: 2000000 | U50: 2000000
A51: Credit & Surety | B51: Net Written Premium | C51: All | D51: UW Year | E51: USD | F51: =EDATE(F50,12) -> 39083 | G51: 1000000 | H51: 2000000 | I51: 2000000 | J51: 2000000 | K51: 2000000 | L51: 2000000 | M51: 2000000 | N51: 2000000 | O51: 2000000 | P51: 2000000 | Q51: 2000000 | R51: 2000000 | S51: 2000000 | T51: 2000000
A52: Credit & Surety | B52: Net Written Premium | C52: All | D52: UW Year | E52: USD | F52: =EDATE(F51,12) -> 39448 | G52: 1000000 | H52: 2000000 | I52: 2000000 | J52: 2000000 | K52: 2000000 | L52: 2000000 | M52: 2000000 | N52: 2000000 | O52: 2000000 | P52: 2000000 | Q52: 2000000 | R52: 2000000 | S52: 2000000
A53: Credit & Surety | B53: Net Written Premium | C53: All | D53: UW Year | E53: USD | F53: =EDATE(F52,12) -> 39814 | G53: 1000000 | H53: 2000000 | I53: 2000000 | J53: 2000000 | K53: 2000000 | L53: 2000000 | M53: 2000000 | N53: 2000000 | O53: 2000000 | P53: 2000000 | Q53: 2000000 | R53: 2000000
A54: Credit & Surety | B54: Net Written Premium | C54: All | D54: UW Year | E54: USD | F54: =EDATE(F53,12) -> 40179 | G54: 1000000 | H54: 2000000 | I54: 2000000 | J54: 2000000 | K54: 2000000 | L54: 2000000 | M54: 2000000 | N54: 2000000 | O54: 2000000 | P54: 2000000 | Q54: 2000000
A55: Credit & Surety | B55: Net Written Premium | C55: All | D55: UW Year | E55: USD | F55: =EDATE(F54,12) -> 40544 | G55: 1000000 | H55: 2000000 | I55: 2000000 | J55: 2000000 | K55: 2000000 | L55: 2000000 | M55: 2000000 | N55: 2000000 | O55: 2000000 | P55: 2000000
A56: Credit & Surety | B56: Net Written Premium | C56: All | D56: UW Year | E56: USD | F56: =EDATE(F55,12) -> 40909 | G56: 1000000 | H56: 2000000 | I56: 2000000 | J56: 2000000 | K56: 2000000 | L56: 2000000 | M56: 2000000 | N56: 2000000 | O56: 2000000
A57: Credit & Surety | B57: Net Written Premium | C57: All | D57: UW Year | E57: USD | F57: =EDATE(F56,12) -> 41275 | G57: 1000000 | H57: 2000000 | I57: 2000000 | J57: 2000000 | K57: 2000000 | L57: 2000000 | M57: 2000000 | N57: 2000000
A58: Credit & Surety | B58: Net Written Premium | C58: All | D58: UW Year | E58: USD | F58: =EDATE(F57,12) -> 41640 | G58: 1000000 | H58: 2000000 | I58: 2000000 | J58: 2000000 | K58: 2000000 | L58: 2000000 | M58: 2000000
A59: Credit & Surety | B59: Net Written Premium | C59: All | D59: UW Year | E59: USD | F59: =EDATE(F58,12) -> 42005 | G59: 1000000 | H59: 2000000 | I59: 2000000 | J59: 2000000 | K59: 2000000 | L59: 2000000
A60: Credit & Surety | B60: Net Written Premium | C60: All | D60: UW Year | E60: USD | F60: =EDATE(F59,12) -> 42370 | G60: 1000000 | H60: 2000000 | I60: 2000000 | J60: 2000000 | K60: 2000000
A61: Credit & Surety | B61: Net Written Premium | C61: All | D61: UW Year | E61: USD | F61: =EDATE(F60,12) -> 42736 | G61: 1000000 | H61: 2000000 | I61: 2000000 | J61: 2000000
A62: Credit & Surety | B62: Net Written Premium | C62: All | D62: UW Year | E62: USD | F62: =EDATE(F61,12) -> 43101 | G62: 1000000 | H62: 2000000 | I62: 2000000
A63: Credit & Surety | B63: Net Written Premium | C63: All | D63: UW Year | E63: USD | F63: =EDATE(F62,12) -> 43466 | G63: 1000000 | H63: 2000000
A64: Credit & Surety | B64: Net Written Premium | C64: All | D64: UW Year | E64: USD | F64: =EDATE(F63,12) -> 43831 | G64: 1000000
A66: Motor NP | B66: Net Written Premium | C66: All | D66: UW Year | E66: USD | F66: =triangle_start_date -> 36892 | G66: 1000000 | H66: 2000000 | I66: 2000000 | J66: 2000000 | K66: 2000000 | L66: 2000000 | M66: 2000000 | N66: 2000000 | O66: 2000000 | P66: 2000000 | Q66: 2000000 | R66: 2000000 | S66: 2000000 | T66: 2000000 | U66: 2000000 | V66: 2000000 | W66: 2000000 | X66: 2000000 | Y66: 2000000 | Z66: 2000000
A67: Motor NP | B67: Net Written Premium | C67: All | D67: UW Year | E67: USD | F67: =EDATE(F66,12) -> 37257 | G67: 1000000 | H67: 2000000 | I67: 2000000 | J67: 2000000 | K67: 2000000 | L67: 2000000 | M67: 2000000 | N67: 2000000 | O67: 2000000 | P67: 2000000 | Q67: 2000000 | R67: 2000000 | S67: 2000000 | T67: 2000000 | U67: 2000000 | V67: 2000000 | W67: 2000000 | X67: 2000000 | Y67: 2000000
A68: Motor NP | B68: Net Written Premium | C68: All | D68: UW Year | E68: USD | F68: =EDATE(F67,12) -> 37622 | G68: 1000000 | H68: 2000000 | I68: 2000000 | J68: 2000000 | K68: 2000000 | L68: 2000000 | M68: 2000000 | N68: 2000000 | O68: 2000000 | P68: 2000000 | Q68: 2000000 | R68: 2000000 | S68: 2000000 | T68: 2000000 | U68: 2000000 | V68: 2000000 | W68: 2000000 | X68: 2000000
A69: Motor NP | B69: Net Written Premium | C69: All | D69: UW Year | E69: USD | F69: =EDATE(F68,12) -> 37987 | G69: 1000000 | H69: 2000000 | I69: 2000000 | J69: 2000000 | K69: 2000000 | L69: 2000000 | M69: 2000000 | N69: 2000000 | O69: 2000000 | P69: 2000000 | Q69: 2000000 | R69: 2000000 | S69: 2000000 | T69: 2000000 | U69: 2000000 | V69: 2000000 | W69: 2000000
A70: Motor NP | B70: Net Written Premium | C70: All | D70: UW Year | E70: USD | F70: =EDATE(F69,12) -> 38353 | G70: 1000000 | H70: 2000000 | I70: 2000000 | J70: 2000000 | K70: 2000000 | L70: 2000000 | M70: 2000000 | N70: 2000000 | O70: 2000000 | P70: 2000000 | Q70: 2000000 | R70: 2000000 | S70: 2000000 | T70: 2000000 | U70: 2000000 | V70: 2000000
A71: Motor NP | B71: Net Written Premium | C71: All | D71: UW Year | E71: USD | F71: =EDATE(F70,12) -> 38718 | G71: 1000000 | H71: 2000000 | I71: 2000000 | J71: 2000000 | K71: 2000000 | L71: 2000000 | M71: 2000000 | N71: 2000000 | O71: 2000000 | P71: 2000000 | Q71: 2000000 | R71: 2000000 | S71: 2000000 | T71: 2000000 | U71: 2000000
A72: Motor NP | B72: Net Written Premium | C72: All | D72: UW Year | E72: USD | F72: =EDATE(F71,12) -> 39083 | G72: 1000000 | H72: 2000000 | I72: 2000000 | J72: 2000000 | K72: 2000000 | L72: 2000000 | M72: 2000000 | N72: 2000000 | O72: 2000000 | P72: 2000000 | Q72: 2000000 | R72: 2000000 | S72: 2000000 | T72: 2000000
A73: Motor NP | B73: Net Written Premium | C73: All | D73: UW Year | E73: USD | F73: =EDATE(F72,12) -> 39448 | G73: 1000000 | H73: 2000000 | I73: 2000000 | J73: 2000000 | K73: 2000000 | L73: 2000000 | M73: 2000000 | N73: 2000000 | O73: 2000000 | P73: 2000000 | Q73: 2000000 | R73: 2000000 | S73: 2000000
A74: Motor NP | B74: Net Written Premium | C74: All | D74: UW Year | E74: USD | F74: =EDATE(F73,12) -> 39814 | G74: 1000000 | H74: 2000000 | I74: 2000000 | J74: 2000000 | K74: 2000000 | L74: 2000000 | M74: 2000000 | N74: 2000000 | O74: 2000000 | P74: 2000000 | Q74: 2000000 | R74: 2000000
A75: Motor NP | B75: Net Written Premium | C75: All | D75: UW Year | E75: USD | F75: =EDATE(F74,12) -> 40179 | G75: 1000000 | H75: 2000000 | I75: 2000000 | J75: 2000000 | K75: 2000000 | L75: 2000000 | M75: 2000000 | N75: 2000000 | O75: 2000000 | P75: 2000000 | Q75: 2000000
A76: Motor NP | B76: Net Written Premium | C76: All | D76: UW Year | E76: USD | F76: =EDATE(F75,12) -> 40544 | G76: 1000000 | H76: 2000000 | I76: 2000000 | J76: 2000000 | K76: 2000000 | L76: 2000000 | M76: 2000000 | N76: 2000000 | O76: 2000000 | P76: 2000000
A77: Motor NP | B77: Net Written Premium | C77: All | D77: UW Year | E77: USD | F77: =EDATE(F76,12) -> 40909 | G77: 1000000 | H77: 2000000 | I77: 2000000 | J77: 2000000 | K77: 2000000 | L77: 2000000 | M77: 2000000 | N77: 2000000 | O77: 2000000
A78: Motor NP | B78: Net Written Premium | C78: All | D78: UW Year | E78: USD | F78: =EDATE(F77,12) -> 41275 | G78: 1000000 | H78: 2000000 | I78: 2000000 | J78: 2000000 | K78: 2000000 | L78: 2000000 | M78: 2000000 | N78: 2000000
A79: Motor NP | B79: Net Written Premium | C79: All | D79: UW Year | E79: USD | F79: =EDATE(F78,12) -> 41640 | G79: 1000000 | H79: 2000000 | I79: 2000000 | J79: 2000000 | K79: 2000000 | L79: 2000000 | M79: 2000000
A80: Motor NP | B80: Net Written Premium | C80: All | D80: UW Year | E80: USD | F80: =EDATE(F79,12) -> 42005 | G80: 1000000 | H80: 2000000 | I80: 2000000 | J80: 2000000 | K80: 2000000 | L80: 2000000
A81: Motor NP | B81: Net Written Premium | C81: All | D81: UW Year | E81: USD | F81: =EDATE(F80,12) -> 42370 | G81: 1000000 | H81: 2000000 | I81: 2000000 | J81: 2000000 | K81: 2000000
A82: Motor NP | B82: Net Written Premium | C82: All | D82: UW Year | E82: USD | F82: =EDATE(F81,12) -> 42736 | G82: 1000000 | H82: 2000000 | I82: 2000000 | J82: 2000000
A83: Motor NP | B83: Net Written Premium | C83: All | D83: UW Year | E83: USD | F83: =EDATE(F82,12) -> 43101 | G83: 1000000 | H83: 2000000 | I83: 2000000
A84: Motor NP | B84: Net Written Premium | C84: All | D84: UW Year | E84: USD | F84: =EDATE(F83,12) -> 43466 | G84: 1000000 | H84: 2000000
A85: Motor NP | B85: Net Written Premium | C85: All | D85: UW Year | E85: USD | F85: =EDATE(F84,12) -> 43831 | G85: 1000000
A87: Motor PR | B87: Net Written Premium | C87: All | D87: UW Year | E87: USD | F87: =triangle_start_date -> 36892 | G87: 1000000 | H87: 2000000 | I87: 2000000 | J87: 2000000 | K87: 2000000 | L87: 2000000 | M87: 2000000 | N87: 2000000 | O87: 2000000 | P87: 2000000 | Q87: 2000000 | R87: 2000000 | S87: 2000000 | T87: 2000000 | U87: 2000000 | V87: 2000000 | W87: 2000000 | X87: 2000000 | Y87: 2000000 | Z87: 2000000
A88: Motor PR | B88: Net Written Premium | C88: All | D88: UW Year | E88: USD | F88: =EDATE(F87,12) -> 37257 | G88: 1000000 | H88: 2000000 | I88: 2000000 | J88: 2000000 | K88: 2000000 | L88: 2000000 | M88: 2000000 | N88: 2000000 | O88: 2000000 | P88: 2000000 | Q88: 2000000 | R88: 2000000 | S88: 2000000 | T88: 2000000 | U88: 2000000 | V88: 2000000 | W88: 2000000 | X88: 2000000 | Y88: 2000000
A89: Motor PR | B89: Net Written Premium | C89: All | D89: UW Year | E89: USD | F89: =EDATE(F88,12) -> 37622 | G89: 1000000 | H89: 2000000 | I89: 2000000 | J89: 2000000 | K89: 2000000 | L89: 2000000 | M89: 2000000 | N89: 2000000 | O89: 2000000 | P89: 2000000 | Q89: 2000000 | R89: 2000000 | S89: 2000000 | T89: 2000000 | U89: 2000000 | V89: 2000000 | W89: 2000000 | X89: 2000000
A90: Motor PR | B90: Net Written Premium | C90: All | D90: UW Year | E90: USD | F90: =EDATE(F89,12) -> 37987 | G90: 1000000 | H90: 2000000 | I90: 2000000 | J90: 2000000 | K90: 2000000 | L90: 2000000 | M90: 2000000 | N90: 2000000 | O90: 2000000 | P90: 2000000 | Q90: 2000000 | R90: 2000000 | S90: 2000000 | T90: 2000000 | U90: 2000000 | V90: 2000000 | W90: 2000000
A91: Motor PR | B91: Net Written Premium | C91: All | D91: UW Year | E91: USD | F91: =EDATE(F90,12) -> 38353 | G91: 1000000 | H91: 2000000 | I91: 2000000 | J91: 2000000 | K91: 2000000 | L91: 2000000 | M91: 2000000 | N91: 2000000 | O91: 2000000 | P91: 2000000 | Q91: 2000000 | R91: 2000000 | S91: 2000000 | T91: 2000000 | U91: 2000000 | V91: 2000000
A92: Motor PR | B92: Net Written Premium | C92: All | D92: UW Year | E92: USD | F92: =EDATE(F91,12) -> 38718 | G92: 1000000 | H92: 2000000 | I92: 2000000 | J92: 2000000 | K92: 2000000 | L92: 2000000 | M92: 2000000 | N92: 2000000 | O92: 2000000 | P92: 2000000 | Q92: 2000000 | R92: 2000000 | S92: 2000000 | T92: 2000000 | U92: 2000000
A93: Motor PR | B93: Net Written Premium | C93: All | D93: UW Year | E93: USD | F93: =EDATE(F92,12) -> 39083 | G93: 1000000 | H93: 2000000 | I93: 2000000 | J93: 2000000 | K93: 2000000 | L93: 2000000 | M93: 2000000 | N93: 2000000 | O93: 2000000 | P93: 2000000 | Q93: 2000000 | R93: 2000000 | S93: 2000000 | T93: 2000000
A94: Motor PR | B94: Net Written Premium | C94: All | D94: UW Year | E94: USD | F94: =EDATE(F93,12) -> 39448 | G94: 1000000 | H94: 2000000 | I94: 2000000 | J94: 2000000 | K94: 2000000 | L94: 2000000 | M94: 2000000 | N94: 2000000 | O94: 2000000 | P94: 2000000 | Q94: 2000000 | R94: 2000000 | S94: 2000000
A95: Motor PR | B95: Net Written Premium | C95: All | D95: UW Year | E95: USD | F95: =EDATE(F94,12) -> 39814 | G95: 1000000 | H95: 2000000 | I95: 2000000 | J95: 2000000 | K95: 2000000 | L95: 2000000 | M95: 2000000 | N95: 2000000 | O95: 2000000 | P95: 2000000 | Q95: 2000000 | R95: 2000000
A96: Motor PR | B96: Net Written Premium | C96: All | D96: UW Year | E96: USD | F96: =EDATE(F95,12) -> 40179 | G96: 1000000 | H96: 2000000 | I96: 2000000 | J96: 2000000 | K96: 2000000 | L96: 2000000 | M96: 2000000 | N96: 2000000 | O96: 2000000 | P96: 2000000 | Q96: 2000000
A97: Motor PR | B97: Net Written Premium | C97: All | D97: UW Year | E97: USD | F97: =EDATE(F96,12) -> 40544 | G97: 1000000 | H97: 2000000 | I97: 2000000 | J97: 2000000 | K97: 2000000 | L97: 2000000 | M97: 2000000 | N97: 2000000 | O97: 2000000 | P97: 2000000
A98: Motor PR | B98: Net Written Premium | C98: All | D98: UW Year | E98: USD | F98: =EDATE(F97,12) -> 40909 | G98: 1000000 | H98: 2000000 | I98: 2000000 | J98: 2000000 | K98: 2000000 | L98: 2000000 | M98: 2000000 | N98: 2000000 | O98: 2000000
A99: Motor PR | B99: Net Written Premium | C99: All | D99: UW Year | E99: USD | F99: =EDATE(F98,12) -> 41275 | G99: 1000000 | H99: 2000000 | I99: 2000000 | J99: 2000000 | K99: 2000000 | L99: 2000000 | M99: 2000000 | N99: 2000000
A100: Motor PR | B100: Net Written Premium | C100: All | D100: UW Year | E100: USD | F100: =EDATE(F99,12) -> 41640 | G100: 1000000 | H100: 2000000 | I100: 2000000 | J100: 2000000 | K100: 2000000 | L100: 2000000 | M100: 2000000
A101: Motor PR | B101: Net Written Premium | C101: All | D101: UW Year | E101: USD | F101: =EDATE(F100,12) -> 42005 | G101: 1000000 | H101: 2000000 | I101: 2000000 | J101: 2000000 | K101: 2000000 | L101: 2000000
A102: Motor PR | B102: Net Written Premium | C102: All | D102: UW Year | E102: USD | F102: =EDATE(F101,12) -> 42370 | G102: 1000000 | H102: 2000000 | I102: 2000000 | J102: 2000000 | K102: 2000000
A103: Motor PR | B103: Net Written Premium | C103: All | D103: UW Year | E103: USD | F103: =EDATE(F102,12) -> 42736 | G103: 1000000 | H103: 2000000 | I103: 2000000 | J103: 2000000
A104: Motor PR | B104: Net Written Premium | C104: All | D104: UW Year | E104: USD | F104: =EDATE(F103,12) -> 43101 | G104: 1000000 | H104: 2000000 | I104: 2000000
...

Sheet Example - Projections
A1: Longtail Reference | B1: UW Year | C1: Ultimate GG Prem ($M) | D1: Latest GG Prem ($M) | E1: Latest GN Prem ($M) | F1: Acq Cost | G1: Cedant Provided Ultimate Loss Ratio | H1: Cedant Provided CoV | I1: Rate Change | J1: Inflation | K1: Historic Year Check | L1: Current Year Check | M1: Min Origin Year: | N1: =YEAR(triangle_start_date) -> 2001 | O1: Max Origin Year: | P1: =YEAR(current_date)-1 -> 2025 | R1: Checks
A2: ='Example - Parameters'!C219 -> Professional Lines | B2: =YEAR(triangle_start_date) -> 2001 | C2: <in millions> | D2: <in millions> | E2: =IF(D2="", "", IFERROR(D2*(1-F2),"")) | K2: =IF(OR(B2<$N$1,B2>$P$1),"fail","pass") -> pass | L2: =IFERROR(IF(AND(MATCH(A2,Projection_classes,0),YEAR(current_date)='Example - Projections'!B2),"pass","fail"),"") | R2: =IF(S2>0, "RATE CHANGE COLUMN CONTAINS ERROR VALUES. PLEASE SET THEM TO 0s", "Rate Change column no error values.") -> Rate Change column no error values. | S2: {=SUMPRODUCT(--ISERROR(I2:I1000))} -> 0
A3: =A2 -> Professional Lines | B3: =B2+1 -> 2002 | C3: <in millions> | D3: <in millions> | E3: =IF(D3="", "", IFERROR(D3*(1-F3),"")) | K3: =IF(OR(B3<$N$1,B3>$P$1),"fail","pass") -> pass | L3: =IFERROR(IF(AND(MATCH(A3,Projection_classes,0),YEAR(current_date)='Example - Projections'!B3),"pass","fail"),"") | R3: =IF(S3>0, "INFLATION COLUMN CONTAINS ERROR VALUES. PLEASE SET THEM TO 0s", "Inflation column no error values.") -> Inflation column no error values. | S3: {=SUMPRODUCT(--ISERROR(J2:J1000))} -> 0
A4: =A3 -> Professional Lines | B4: =B3+1 -> 2003 | C4: <in millions> | D4: <in millions> | E4: =IF(D4="", "", IFERROR(D4*(1-F4),"")) | K4: =IF(OR(B4<$N$1,B4>$P$1),"fail","pass") -> pass | L4: =IFERROR(IF(AND(MATCH(A4,Projection_classes,0),YEAR(current_date)='Example - Projections'!B4),"pass","fail"),"")
A5: =A4 -> Professional Lines | B5: =B4+1 -> 2004 | C5: <in millions> | D5: <in millions> | E5: =IF(D5="", "", IFERROR(D5*(1-F5),"")) | K5: =IF(OR(B5<$N$1,B5>$P$1),"fail","pass") -> pass | L5: =IFERROR(IF(AND(MATCH(A5,Projection_classes,0),YEAR(current_date)='Example - Projections'!B5),"pass","fail"),"")
A6: =A5 -> Professional Lines | B6: =B5+1 -> 2005 | C6: <in millions> | D6: <in millions> | E6: =IF(D6="", "", IFERROR(D6*(1-F6),"")) | K6: =IF(OR(B6<$N$1,B6>$P$1),"fail","pass") -> pass | L6: =IFERROR(IF(AND(MATCH(A6,Projection_classes,0),YEAR(current_date)='Example - Projections'!B6),"pass","fail"),"") | R6: Mandatory
A7: =A6 -> Professional Lines | B7: =B6+1 -> 2006 | E7: <drag down above formula> | K7: =IF(OR(B7<$N$1,B7>$P$1),"fail","pass") -> pass | L7: =IFERROR(IF(AND(MATCH(A7,Projection_classes,0),YEAR(current_date)='Example - Projections'!B7),"pass","fail"),"") | R7: Optional
A8: =A7 -> Professional Lines | B8: =B7+1 -> 2007 | E8: <drag down above formula> | K8: =IF(OR(B8<$N$1,B8>$P$1),"fail","pass") -> pass | L8: =IFERROR(IF(AND(MATCH(A8,Projection_classes,0),YEAR(current_date)='Example - Projections'!B8),"pass","fail"),"")
A9: =A8 -> Professional Lines | B9: =B8+1 -> 2008 | E9: <drag down above formula> | K9: =IF(OR(B9<$N$1,B9>$P$1),"fail","pass") -> pass | L9: =IFERROR(IF(AND(MATCH(A9,Projection_classes,0),YEAR(current_date)='Example - Projections'!B9),"pass","fail"),"")
A10: =A9 -> Professional Lines | B10: =B9+1 -> 2009 | E10: <drag down above formula> | K10: =IF(OR(B10<$N$1,B10>$P$1),"fail","pass") -> pass | L10: =IFERROR(IF(AND(MATCH(A10,Projection_classes,0),YEAR(current_date)='Example - Projections'!B10),"pass","fail"),"")
A11: =A10 -> Professional Lines | B11: =B10+1 -> 2010 | E11: <drag down above formula> | K11: =IF(OR(B11<$N$1,B11>$P$1),"fail","pass") -> pass | L11: =IFERROR(IF(AND(MATCH(A11,Projection_classes,0),YEAR(current_date)='Example - Projections'!B11),"pass","fail"),"")
A12: =A11 -> Professional Lines | B12: =B11+1 -> 2011 | K12: =IF(OR(B12<$N$1,B12>$P$1),"fail","pass") -> pass | L12: =IFERROR(IF(AND(MATCH(A12,Projection_classes,0),YEAR(current_date)='Example - Projections'!B12),"pass","fail"),"")
A13: =A12 -> Professional Lines | B13: =B12+1 -> 2012 | K13: =IF(OR(B13<$N$1,B13>$P$1),"fail","pass") -> pass | L13: =IFERROR(IF(AND(MATCH(A13,Projection_classes,0),YEAR(current_date)='Example - Projections'!B13),"pass","fail"),"")
A14: =A13 -> Professional Lines | B14: =B13+1 -> 2013 | K14: =IF(OR(B14<$N$1,B14>$P$1),"fail","pass") -> pass | L14: =IFERROR(IF(AND(MATCH(A14,Projection_classes,0),YEAR(current_date)='Example - Projections'!B14),"pass","fail"),"")
A15: =A14 -> Professional Lines | B15: =B14+1 -> 2014 | K15: =IF(OR(B15<$N$1,B15>$P$1),"fail","pass") -> pass | L15: =IFERROR(IF(AND(MATCH(A15,Projection_classes,0),YEAR(current_date)='Example - Projections'!B15),"pass","fail"),"")
A16: =A15 -> Professional Lines | B16: =B15+1 -> 2015 | K16: =IF(OR(B16<$N$1,B16>$P$1),"fail","pass") -> pass | L16: =IFERROR(IF(AND(MATCH(A16,Projection_classes,0),YEAR(current_date)='Example - Projections'!B16),"pass","fail"),"")
A17: =A16 -> Professional Lines | B17: =B16+1 -> 2016 | K17: =IF(OR(B17<$N$1,B17>$P$1),"fail","pass") -> pass | L17: =IFERROR(IF(AND(MATCH(A17,Projection_classes,0),YEAR(current_date)='Example - Projections'!B17),"pass","fail"),"")
A18: =A17 -> Professional Lines | B18: =B17+1 -> 2017 | K18: =IF(OR(B18<$N$1,B18>$P$1),"fail","pass") -> pass | L18: =IFERROR(IF(AND(MATCH(A18,Projection_classes,0),YEAR(current_date)='Example - Projections'!B18),"pass","fail"),"")
A19: =A18 -> Professional Lines | B19: =B18+1 -> 2018 | K19: =IF(OR(B19<$N$1,B19>$P$1),"fail","pass") -> pass | L19: =IFERROR(IF(AND(MATCH(A19,Projection_classes,0),YEAR(current_date)='Example - Projections'!B19),"pass","fail"),"")
A20: =A19 -> Professional Lines | B20: =B19+1 -> 2019 | K20: =IF(OR(B20<$N$1,B20>$P$1),"fail","pass") -> pass | L20: =IFERROR(IF(AND(MATCH(A20,Projection_classes,0),YEAR(current_date)='Example - Projections'!B20),"pass","fail"),"")
A21: =A20 -> Professional Lines | B21: =B20+1 -> 2020 | K21: =IF(OR(B21<$N$1,B21>$P$1),"fail","pass") -> pass | L21: =IFERROR(IF(AND(MATCH(A21,Projection_classes,0),YEAR(current_date)='Example - Projections'!B21),"pass","fail"),"")
A22: ='Example - Parameters'!C220 -> Liability | B22: =YEAR(triangle_start_date) -> 2001 | K22: =IF(OR(B22<$N$1,B22>$P$1),"fail","pass") -> pass | L22: =IFERROR(IF(AND(MATCH(A22,Projection_classes,0),YEAR(current_date)='Example - Projections'!B22),"pass","fail"),"")
A23: =A22 -> Liability | B23: =B22+1 -> 2002 | K23: =IF(OR(B23<$N$1,B23>$P$1),"fail","pass") -> pass | L23: =IFERROR(IF(AND(MATCH(A23,Projection_classes,0),YEAR(current_date)='Example - Projections'!B23),"pass","fail"),"")
A24: =A23 -> Liability | B24: =B23+1 -> 2003 | K24: =IF(OR(B24<$N$1,B24>$P$1),"fail","pass") -> pass | L24: =IFERROR(IF(AND(MATCH(A24,Projection_classes,0),YEAR(current_date)='Example - Projections'!B24),"pass","fail"),"")
A25: =A24 -> Liability | B25: =B24+1 -> 2004 | K25: =IF(OR(B25<$N$1,B25>$P$1),"fail","pass") -> pass | L25: =IFERROR(IF(AND(MATCH(A25,Projection_classes,0),YEAR(current_date)='Example - Projections'!B25),"pass","fail"),"")
A26: =A25 -> Liability | B26: =B25+1 -> 2005 | K26: =IF(OR(B26<$N$1,B26>$P$1),"fail","pass") -> pass | L26: =IFERROR(IF(AND(MATCH(A26,Projection_classes,0),YEAR(current_date)='Example - Projections'!B26),"pass","fail"),"")
A27: =A26 -> Liability | B27: =B26+1 -> 2006 | K27: =IF(OR(B27<$N$1,B27>$P$1),"fail","pass") -> pass | L27: =IFERROR(IF(AND(MATCH(A27,Projection_classes,0),YEAR(current_date)='Example - Projections'!B27),"pass","fail"),"")
A28: =A27 -> Liability | B28: =B27+1 -> 2007 | K28: =IF(OR(B28<$N$1,B28>$P$1),"fail","pass") -> pass | L28: =IFERROR(IF(AND(MATCH(A28,Projection_classes,0),YEAR(current_date)='Example - Projections'!B28),"pass","fail"),"")
A29: =A28 -> Liability | B29: =B28+1 -> 2008 | K29: =IF(OR(B29<$N$1,B29>$P$1),"fail","pass") -> pass | L29: =IFERROR(IF(AND(MATCH(A29,Projection_classes,0),YEAR(current_date)='Example - Projections'!B29),"pass","fail"),"")
A30: =A29 -> Liability | B30: =B29+1 -> 2009 | K30: =IF(OR(B30<$N$1,B30>$P$1),"fail","pass") -> pass | L30: =IFERROR(IF(AND(MATCH(A30,Projection_classes,0),YEAR(current_date)='Example - Projections'!B30),"pass","fail"),"")
A31: =A30 -> Liability | B31: =B30+1 -> 2010 | K31: =IF(OR(B31<$N$1,B31>$P$1),"fail","pass") -> pass | L31: =IFERROR(IF(AND(MATCH(A31,Projection_classes,0),YEAR(current_date)='Example - Projections'!B31),"pass","fail"),"")
A32: =A31 -> Liability | B32: =B31+1 -> 2011 | K32: =IF(OR(B32<$N$1,B32>$P$1),"fail","pass") -> pass | L32: =IFERROR(IF(AND(MATCH(A32,Projection_classes,0),YEAR(current_date)='Example - Projections'!B32),"pass","fail"),"")
A33: =A32 -> Liability | B33: =B32+1 -> 2012 | K33: =IF(OR(B33<$N$1,B33>$P$1),"fail","pass") -> pass | L33: =IFERROR(IF(AND(MATCH(A33,Projection_classes,0),YEAR(current_date)='Example - Projections'!B33),"pass","fail"),"")
A34: =A33 -> Liability | B34: =B33+1 -> 2013 | K34: =IF(OR(B34<$N$1,B34>$P$1),"fail","pass") -> pass | L34: =IFERROR(IF(AND(MATCH(A34,Projection_classes,0),YEAR(current_date)='Example - Projections'!B34),"pass","fail"),"")
... A41: =A40 -> Liability | B41: =B40+1 -> 2020 | K41: =IF(OR(B41<$N$1,B41>$P$1),"fail","pass") -> pass | L41: =IFERROR(IF(AND(MATCH(A41,Projection_classes,0),YEAR(current_date)='Example - Projections'!B41),"pass","fail"),"")
A42: ='Example - Parameters'!C221 -> Credit & Surety | B42: =YEAR(triangle_start_date) -> 2001 | K42: =IF(OR(B42<$N$1,B42>$P$1),"fail","pass") -> pass | L42: =IFERROR(IF(AND(MATCH(A42,Projection_classes,0),YEAR(current_date)='Example - Projections'!B42),"pass","fail"),"")
A43: =A42 -> Credit & Surety | B43: =B42+1 -> 2002 | K43: =IF(OR(B43<$N$1,B43>$P$1),"fail","pass") -> pass | L43: =IFERROR(IF(AND(MATCH(A43,Projection_classes,0),YEAR(current_date)='Example - Projections'!B43),"pass","fail"),"")
A44: =A43 -> Credit & Surety | B44: =B43+1 -> 2003 | K44: =IF(OR(B44<$N$1,B44>$P$1),"fail","pass") -> pass | L44: =IFERROR(IF(AND(MATCH(A44,Projection_classes,0),YEAR(current_date)='Example - Projections'!B44),"pass","fail"),"")
A45: =A44 -> Credit & Surety | B45: =B44+1 -> 2004 | K45: =IF(OR(B45<$N$1,B45>$P$1),"fail","pass") -> pass | L45: =IFERROR(IF(AND(MATCH(A45,Projection_classes,0),YEAR(current_date)='Example - Projections'!B45),"pass","fail"),"")
A46: =A45 -> Credit & Surety | B46: =B45+1 -> 2005 | K46: =IF(OR(B46<$N$1,B46>$P$1),"fail","pass") -> pass | L46: =IFERROR(IF(AND(MATCH(A46,Projection_classes,0),YEAR(current_date)='Example - Projections'!B46),"pass","fail"),"")
A47: =A46 -> Credit & Surety | B47: =B46+1 -> 2006 | K47: =IF(OR(B47<$N$1,B47>$P$1),"fail","pass") -> pass | L47: =IFERROR(IF(AND(MATCH(A47,Projection_classes,0),YEAR(current_date)='Example - Projections'!B47),"pass","fail"),"")
A48: =A47 -> Credit & Surety | B48: =B47+1 -> 2007 | K48: =IF(OR(B48<$N$1,B48>$P$1),"fail","pass") -> pass | L48: =IFERROR(IF(AND(MATCH(A48,Projection_classes,0),YEAR(current_date)='Example - Projections'!B48),"pass","fail"),"")
A49: =A48 -> Credit & Surety | B49: =B48+1 -> 2008 | K49: =IF(OR(B49<$N$1,B49>$P$1),"fail","pass") -> pass | L49: =IFERROR(IF(AND(MATCH(A49,Projection_classes,0),YEAR(current_date)='Example - Projections'!B49),"pass","fail"),"")
A50: =A49 -> Credit & Surety | B50: =B49+1 -> 2009 | K50: =IF(OR(B50<$N$1,B50>$P$1),"fail","pass") -> pass | L50: =IFERROR(IF(AND(MATCH(A50,Projection_classes,0),YEAR(current_date)='Example - Projections'!B50),"pass","fail"),"")
A51: =A50 -> Credit & Surety | B51: =B50+1 -> 2010 | K51: =IF(OR(B51<$N$1,B51>$P$1),"fail","pass") -> pass | L51: =IFERROR(IF(AND(MATCH(A51,Projection_classes,0),YEAR(current_date)='Example - Projections'!B51),"pass","fail"),"")
A52: =A51 -> Credit & Surety | B52: =B51+1 -> 2011 | K52: =IF(OR(B52<$N$1,B52>$P$1),"fail","pass") -> pass | L52: =IFERROR(IF(AND(MATCH(A52,Projection_classes,0),YEAR(current_date)='Example - Projections'!B52),"pass","fail"),"")
A53: =A52 -> Credit & Surety | B53: =B52+1 -> 2012 | K53: =IF(OR(B53<$N$1,B53>$P$1),"fail","pass") -> pass | L53: =IFERROR(IF(AND(MATCH(A53,Projection_classes,0),YEAR(current_date)='Example - Projections'!B53),"pass","fail"),"")
A54: =A53 -> Credit & Surety | B54: =B53+1 -> 2013 | K54: =IF(OR(B54<$N$1,B54>$P$1),"fail","pass") -> pass | L54: =IFERROR(IF(AND(MATCH(A54,Projection_classes,0),YEAR(current_date)='Example - Projections'!B54),"pass","fail"),"")
... A61: =A60 -> Credit & Surety | B61: =B60+1 -> 2020 | K61: =IF(OR(B61<$N$1,B61>$P$1),"fail","pass") -> pass | L61: =IFERROR(IF(AND(MATCH(A61,Projection_classes,0),YEAR(current_date)='Example - Projections'!B61),"pass","fail"),"")
A62: ='Example - Parameters'!C222 -> Motor NP | B62: =YEAR(triangle_start_date) -> 2001 | K62: =IF(OR(B62<$N$1,B62>$P$1),"fail","pass") -> pass | L62: =IFERROR(IF(AND(MATCH(A62,Projection_classes,0),YEAR(current_date)='Example - Projections'!B62),"pass","fail"),"")
A63: =A62 -> Motor NP | B63: =B62+1 -> 2002 | K63: =IF(OR(B63<$N$1,B63>$P$1),"fail","pass") -> pass | L63: =IFERROR(IF(AND(MATCH(A63,Projection_classes,0),YEAR(current_date)='Example - Projections'!B63),"pass","fail"),"")
A64: =A63 -> Motor NP | B64: =B63+1 -> 2003 | K64: =IF(OR(B64<$N$1,B64>$P$1),"fail","pass") -> pass | L64: =IFERROR(IF(AND(MATCH(A64,Projection_classes,0),YEAR(current_date)='Example - Projections'!B64),"pass","fail"),"")
A65: =A64 -> Motor NP | B65: =B64+1 -> 2004 | K65: =IF(OR(B65<$N$1,B65>$P$1),"fail","pass") -> pass | L65: =IFERROR(IF(AND(MATCH(A65,Projection_classes,0),YEAR(current_date)='Example - Projections'!B65),"pass","fail"),"")
A66: =A65 -> Motor NP | B66: =B65+1 -> 2005 | K66: =IF(OR(B66<$N$1,B66>$P$1),"fail","pass") -> pass | L66: =IFERROR(IF(AND(MATCH(A66,Projection_classes,0),YEAR(current_date)='Example - Projections'!B66),"pass","fail"),"")
A67: =A66 -> Motor NP | B67: =B66+1 -> 2006 | K67: =IF(OR(B67<$N$1,B67>$P$1),"fail","pass") -> pass | L67: =IFERROR(IF(AND(MATCH(A67,Projection_classes,0),YEAR(current_date)='Example - Projections'!B67),"pass","fail"),"")
A68: =A67 -> Motor NP | B68: =B67+1 -> 2007 | K68: =IF(OR(B68<$N$1,B68>$P$1),"fail","pass") -> pass | L68: =IFERROR(IF(AND(MATCH(A68,Projection_classes,0),YEAR(current_date)='Example - Projections'!B68),"pass","fail"),"")
A69: =A68 -> Motor NP | B69: =B68+1 -> 2008 | K69: =IF(OR(B69<$N$1,B69>$P$1),"fail","pass") -> pass | L69: =IFERROR(IF(AND(MATCH(A69,Projection_classes,0),YEAR(current_date)='Example - Projections'!B69),"pass","fail"),"")
A70: =A69 -> Motor NP | B70: =B69+1 -> 2009 | K70: =IF(OR(B70<$N$1,B70>$P$1),"fail","pass") -> pass | L70: =IFERROR(IF(AND(MATCH(A70,Projection_classes,0),YEAR(current_date)='Example - Projections'!B70),"pass","fail"),"")
A71: =A70 -> Motor NP | B71: =B70+1 -> 2010 | K71: =IF(OR(B71<$N$1,B71>$P$1),"fail","pass") -> pass | L71: =IFERROR(IF(AND(MATCH(A71,Projection_classes,0),YEAR(current_date)='Example - Projections'!B71),"pass","fail"),"")
A72: =A71 -> Motor NP | B72: =B71+1 -> 2011 | K72: =IF(OR(B72<$N$1,B72>$P$1),"fail","pass") -> pass | L72: =IFERROR(IF(AND(MATCH(A72,Projection_classes,0),YEAR(current_date)='Example - Projections'!B72),"pass","fail"),"")
A73: =A72 -> Motor NP | B73: =B72+1 -> 2012 | K73: =IF(OR(B73<$N$1,B73>$P$1),"fail","pass") -> pass | L73: =IFERROR(IF(AND(MATCH(A73,Projection_classes,0),YEAR(current_date)='Example - Projections'!B73),"pass","fail"),"")
A74: =A73 -> Motor NP | B74: =B73+1 -> 2013 | K74: =IF(OR(B74<$N$1,B74>$P$1),"fail","pass") -> pass | L74: =IFERROR(IF(AND(MATCH(A74,Projection_classes,0),YEAR(current_date)='Example - Projections'!B74),"pass","fail"),"")
... A81: =A80 -> Motor NP | B81: =B80+1 -> 2020 | K81: =IF(OR(B81<$N$1,B81>$P$1),"fail","pass") -> pass | L81: =IFERROR(IF(AND(MATCH(A81,Projection_classes,0),YEAR(current_date)='Example - Projections'!B81),"pass","fail"),"")
A82: ='Example - Parameters'!C223 -> Motor PR | B82: =YEAR(triangle_start_date) -> 2001 | K82: =IF(OR(B82<$N$1,B82>$P$1),"fail","pass") -> pass | L82: =IFERROR(IF(AND(MATCH(A82,Projection_classes,0),YEAR(current_date)='Example - Projections'!B82),"pass","fail"),"")
A83: =A82 -> Motor PR | B83: =B82+1 -> 2002 | K83: =IF(OR(B83<$N$1,B83>$P$1),"fail","pass") -> pass | L83: =IFERROR(IF(AND(MATCH(A83,Projection_classes,0),YEAR(current_date)='Example - Projections'!B83),"pass","fail"),"")
A84: =A83 -> Motor PR | B84: =B83+1 -> 2003 | K84: =IF(OR(B84<$N$1,B84>$P$1),"fail","pass") -> pass | L84: =IFERROR(IF(AND(MATCH(A84,Projection_classes,0),YEAR(current_date)='Example - Projections'!B84),"pass","fail"),"")
A85: =A84 -> Motor PR | B85: =B84+1 -> 2004 | K85: =IF(OR(B85<$N$1,B85>$P$1),"fail","pass") -> pass | L85: =IFERROR(IF(AND(MATCH(A85,Projection_classes,0),YEAR(current_date)='Example - Projections'!B85),"pass","fail"),"")
A86: =A85 -> Motor PR | B86: =B85+1 -> 2005 | K86: =IF(OR(B86<$N$1,B86>$P$1),"fail","pass") -> pass | L86: =IFERROR(IF(AND(MATCH(A86,Projection_classes,0),YEAR(current_date)='Example - Projections'!B86),"pass","fail"),"")
A87: =A86 -> Motor PR | B87: =B86+1 -> 2006 | K87: =IF(OR(B87<$N$1,B87>$P$1),"fail","pass") -> pass | L87: =IFERROR(IF(AND(MATCH(A87,Projection_classes,0),YEAR(current_date)='Example - Projections'!B87),"pass","fail"),"")
A88: =A87 -> Motor PR | B88: =B87+1 -> 2007 | K88: =IF(OR(B88<$N$1,B88>$P$1),"fail","pass") -> pass | L88: =IFERROR(IF(AND(MATCH(A88,Projection_classes,0),YEAR(current_date)='Example - Projections'!B88),"pass","fail"),"")
A89: =A88 -> Motor PR | B89: =B88+1 -> 2008 | K89: =IF(OR(B89<$N$1,B89>$P$1),"fail","pass") -> pass | L89: =IFERROR(IF(AND(MATCH(A89,Projection_classes,0),YEAR(current_date)='Example - Projections'!B89),"pass","fail"),"")
A90: =A89 -> Motor PR | B90: =B89+1 -> 2009 | K90: =IF(OR(B90<$N$1,B90>$P$1),"fail","pass") -> pass | L90: =IFERROR(IF(AND(MATCH(A90,Projection_classes,0),YEAR(current_date)='Example - Projections'!B90),"pass","fail"),"")
A91: =A90 -> Motor PR | B91: =B90+1 -> 2010 | K91: =IF(OR(B91<$N$1,B91>$P$1),"fail","pass") -> pass | L91: =IFERROR(IF(AND(MATCH(A91,Projection_classes,0),YEAR(current_date)='Example - Projections'!B91),"pass","fail"),"")
A92: =A91 -> Motor PR | B92: =B91+1 -> 2011 | K92: =IF(OR(B92<$N$1,B92>$P$1),"fail","pass") -> pass | L92: =IFERROR(IF(AND(MATCH(A92,Projection_classes,0),YEAR(current_date)='Example - Projections'!B92),"pass","fail"),"")
A93: =A92 -> Motor PR | B93: =B92+1 -> 2012 | K93: =IF(OR(B93<$N$1,B93>$P$1),"fail","pass") -> pass | L93: =IFERROR(IF(AND(MATCH(A93,Projection_classes,0),YEAR(current_date)='Example - Projections'!B93),"pass","fail"),"")
A94: =A93 -> Motor PR | B94: =B93+1 -> 2013 | K94: =IF(OR(B94<$N$1,B94>$P$1),"fail","pass") -> pass | L94: =IFERROR(IF(AND(MATCH(A94,Projection_classes,0),YEAR(current_date)='Example - Projections'!B94),"pass","fail"),"")
... A101: =A100 -> Motor PR | B101: =B100+1 -> 2020 | K101: =IF(OR(B101<$N$1,B101>$P$1),"fail","pass") -> pass | L101: =IFERROR(IF(AND(MATCH(A101,Projection_classes,0),YEAR(current_date)='Example - Projections'!B101),"pass","fail"),"")
A102: ='Example - Parameters'!C224 -> Cyber | B102: =YEAR(triangle_start_date) -> 2001 | K102: =IF(OR(B102<$N$1,B102>$P$1),"fail","pass") -> pass | L102: =IFERROR(IF(AND(MATCH(A102,Projection_classes,0),YEAR(current_date)='Example - Projections'!B102),"pass","fail"),"")
A103: =A102 -> Cyber | B103: =B102+1 -> 2002 | K103: =IF(OR(B103<$N$1,B103>$P$1),"fail","pass") -> pass | L103: =IFERROR(IF(AND(MATCH(A103,Projection_classes,0),YEAR(current_date)='Example - Projections'!B103),"pass","fail"),"")
A104: =A103 -> Cyber | B104: =B103+1 -> 2003 | K104: =IF(OR(B104<$N$1,B104>$P$1),"fail","pass") -> pass | L104: =IFERROR(IF(AND(MATCH(A104,Projection_classes,0),YEAR(current_date)='Example - Projections'!B104),"pass","fail"),"")
A105: =A104 -> Cyber | B105: =B104+1 -> 2004 | K105: =IF(OR(B105<$N$1,B105>$P$1),"fail","pass") -> pass | L105: =IFERROR(IF(AND(MATCH(A105,Projection_classes,0),YEAR(current_date)='Example - Projections'!B105),"pass","fail"),"")
A106: =A105 -> Cyber | B106: =B105+1 -> 2005 | K106: =IF(OR(B106<$N$1,B106>$P$1),"fail","pass") -> pass | L106: =IFERROR(IF(AND(MATCH(A106,Projection_classes,0),YEAR(current_date)='Example - Projections'!B106),"pass","fail"),"")
A107: =A106 -> Cyber | B107: =B106+1 -> 2006 | K107: =IF(OR(B107<$N$1,B107>$P$1),"fail","pass") -> pass | L107: =IFERROR(IF(AND(MATCH(A107,Projection_classes,0),YEAR(current_date)='Example - Projections'!B107),"pass","fail"),"")
A108: =A107 -> Cyber | B108: =B107+1 -> 2007 | K108: =IF(OR(B108<$N$1,B108>$P$1),"fail","pass") -> pass | L108: =IFERROR(IF(AND(MATCH(A108,Projection_classes,0),YEAR(current_date)='Example - Projections'!B108),"pass","fail"),"")
A109: =A108 -> Cyber | B109: =B108+1 -> 2008 | K109: =IF(OR(B109<$N$1,B109>$P$1),"fail","pass") -> pass | L109: =IFERROR(IF(AND(MATCH(A109,Projection_classes,0),YEAR(current_date)='Example - Projections'!B109),"pass","fail"),"")
A110: =A109 -> Cyber | B110: =B109+1 -> 2009 | K110: =IF(OR(B110<$N$1,B110>$P$1),"fail","pass") -> pass | L110: =IFERROR(IF(AND(MATCH(A110,Projection_classes,0),YEAR(current_date)='Example - Projections'!B110),"pass","fail"),"")
A111: =A110 -> Cyber | B111: =B110+1 -> 2010 | K111: =IF(OR(B111<$N$1,B111>$P$1),"fail","pass") -> pass | L111: =IFERROR(IF(AND(MATCH(A111,Projection_classes,0),YEAR(current_date)='Example - Projections'!B111),"pass","fail"),"")
A112: =A111 -> Cyber | B112: =B111+1 -> 2011 | K112: =IF(OR(B112<$N$1,B112>$P$1),"fail","pass") -> pass | L112: =IFERROR(IF(AND(MATCH(A112,Projection_classes,0),YEAR(current_date)='Example - Projections'!B112),"pass","fail"),"")
A113: =A112 -> Cyber | B113: =B112+1 -> 2012 | K113: =IF(OR(B113<$N$1,B113>$P$1),"fail","pass") -> pass | L113: =IFERROR(IF(AND(MATCH(A113,Projection_classes,0),YEAR(current_date)='Example - Projections'!B113),"pass","fail"),"")
A114: =A113 -> Cyber | B114: =B113+1 -> 2013 | K114: =IF(OR(B114<$N$1,B114>$P$1),"fail","pass") -> pass | L114: =IFERROR(IF(AND(MATCH(A114,Projection_classes,0),YEAR(current_date)='Example - Projections'!B114),"pass","fail"),"")
... A121: =A120 -> Cyber | B121: =B120+1 -> 2020 | K121: =IF(OR(B121<$N$1,B121>$P$1),"fail","pass") -> pass | L121: =IFERROR(IF(AND(MATCH(A121,Projection_classes,0),YEAR(current_date)='Example - Projections'!B121),"pass","fail"),"")
K122: =IF(OR(B122<$N$1,B122>$P$1),"fail","pass") -> fail | L122: =IFERROR(IF(AND(MATCH(A122,Projection_classes,0),YEAR(current_date)='Example - Projections'!B122),"pass","fail"),"")
K123: =IF(OR(B123<$N$1,B123>$P$1),"fail","pass") -> fail | L123: =IFERROR(IF(AND(MATCH(A123,Projection_classes,0),YEAR(current_date)='Example - Projections'!B123),"pass","fail"),"")
K124: =IF(OR(B124<$N$1,B124>$P$1),"fail","pass") -> fail | L124: =IFERROR(IF(AND(MATCH(A124,Projection_classes,0),YEAR(current_date)='Example - Projections'!B124),"pass","fail"),"")
K125: =IF(OR(B125<$N$1,B125>$P$1),"fail","pass") -> fail | L125: =IFERROR(IF(AND(MATCH(A125,Projection_classes,0),YEAR(current_date)='Example - Projections'!B125),"pass","fail"),"")
K126: =IF(OR(B126<$N$1,B126>$P$1),"fail","pass") -> fail | L126: =IFERROR(IF(AND(MATCH(A126,Projection_classes,0),YEAR(current_date)='Example - Projections'!B126),"pass","fail"),"")
K127: =IF(OR(B127<$N$1,B127>$P$1),"fail","pass") -> fail | L127: =IFERROR(IF(AND(MATCH(A127,Projection_classes,0),YEAR(current_date)='Example - Projections'!B127),"pass","fail"),"")
K128: =IF(OR(B128<$N$1,B128>$P$1),"fail","pass") -> fail | L128: =IFERROR(IF(AND(MATCH(A128,Projection_classes,0),YEAR(current_date)='Example - Projections'!B128),"pass","fail"),"")
K129: =IF(OR(B129<$N$1,B129>$P$1),"fail","pass") -> fail | L129: =IFERROR(IF(AND(MATCH(A129,Projection_classes,0),YEAR(current_date)='Example - Projections'!B129),"pass","fail"),"")
K130: =IF(OR(B130<$N$1,B130>$P$1),"fail","pass") -> fail | L130: =IFERROR(IF(AND(MATCH(A130,Projection_classes,0),YEAR(current_date)='Example - Projections'!B130),"pass","fail"),"")
...

Sheet DevelopmentPatterns
A1: Longtail Reference | B1: Basis (Accident Year / UW Year) | C1: Type (Incurred / Paid …) | D1: Source | E1: Comment | F1: Development Month (the months here are user selectable)
F2: 3 | G2: 6 | H2: 9 | I2: 12 | J2: 18 | K2: 24 | L2: 36
A3: Executive Risk - M&A | B3: UW Year | C3: Incurred | D3: Cedant provided | E3: Cedent pattern from as at | F3: 0.02 | G3: 0.15 | H3: 0.45 | I3: 0.7 | J3: 0.75 | K3: 0.8 | L3: 0.83
A4: Executive Risk - M&A | B4: UW Year | C4: Incurred | D4: Benchmark data | E4: Benchmark from whatever | F4: 0.02 | G4: 0.15 | H4: 0.45 | I4: 0.7 | J4: 0.75 | K4: 0.8 | L4: 0.83

Sheet BusinessPlan
A1: Longtail Reference | B1: Premium Currency | C1: Gross Gross Premium | D1: Gross Net Premium | E1: Net Gross Premium | F1: Net Net Premium | G1: Estimated RI Cost (in addition to this deal) | H1: Loss Ratio type | I1: Loss Ratio (%) | J1: Rate Change (%) (from prior to this year) | K1: Claims inflatio (from prior to this year) (%) | L1: Acquisition Costs basis | M1: Acquisition Costs (exc internal expense ratio) (%) | N1: Internal expense basis | O1: Internal expense ratio (%) | P1: Cession to Longtail (%)
A2: D&O | B2: USD | H2: Gross Gross | I2: 0.65 | J2: -0.021 | L2: Gross Gross | N2: Gross Gross

Sheet Lookups
A1: LOBs | D1: Prop/Non-Prop | G1: Country | J1: Region | M1: Re/Ins/Retro | P1: Currency | R1: LDF Source Options
A2: id | B2: name | D2: id | E2: name | G2: id | H2: value | J2: id | K2: value | M2: id | N2: value | P2: value | R2: value
A3: 1 | B3: UNSPECIFIED | D3: 1 | E3: Proportional | G3: MULTI | H3: Multi-country | J3: 1 | K3: Worldwide | M3: 1 | N3: Insurance | P3: USD | R3: Derived from cedant data
A4: 2 | B4: Casualty | D4: 2 | E4: Non Proportional | G4: UNKNOWN | H4: Unknown | J4: 2 | K4: Worldwide ex US | M4: 2 | N4: Reinsurance | P4: EUR | R4: Benchmark data
A5: 3 | B5: Credit | D5: 3 | E5: Mixed | G5: US | H5: United States | J5: 3 | K5: North America | M5: 3 | N5: Retrocession | P5: GBP | R5: Cedant provided
A6: 4 | B6: Cyber | D6: 4 | E6: Unknown | G6: CA | H6: Canada | J6: 4 | K6: Europe | P6: AED | R6: Broker provided
A7: 5 | B7: D&O | G7: GB | H7: United Kingdom | J7: 5 | K7: Asia/Pac | P7: AFN
A8: 6 | B8: E&O | G8: AF | H8: Afghanistan | J8: 6 | K8: MEA | P8: ALL
A9: 7 | B9: Environmental | G9: AL | H9: Albania | P9: AMD
A10: 8 | B10: Excess Casualty | G10: DZ | H10: Algeria | P10: ANG
A11: 9 | B11: Fidelity & Surety | G11: AS | H11: American Samoa | P11: AOA
A12: 10 | B12: Financial Institutions | G12: AD | H12: Andorra | P12: ARS
A13: 11 | B13: General Liability | G13: AO | H13: Angola | P13: AUD
A14: 12 | B14: Medical Malpractice | G14: AI | H14: Anguilla | P14: AWG
A15: 13 | B15: Motor | G15: AQ | H15: Antarctica | P15: AZN
A16: 14 | B16: Multi Line | G16: AG | H16: Antigua and Barbuda | P16: BAM
A17: 15 | B17: Others | G17: AR | H17: Argentina | P17: BBD
A18: 16 | B18: Primary Casualty | G18: AM | H18: Armenia | P18: BDT
A19: 17 | B19: Product Liability | G19: AW | H19: Aruba | P19: BGN
A20: 18 | B20: Professional Liability | G20: AU | H20: Australia | P20: BHD
... A25: 22 | B25: Workers Compensation | G25: BD | H25: Bangladesh | P25: BOV
G26: BB | H26: Barbados | P26: BRL
G27: BY | H27: Belarus | P27: BSD
G28: BE | H28: Belgium | P28: BTN
G29: BZ | H29: Belize | P29: BWP
G30: BJ | H30: Benin | P30: BYR
G31: BM | H31: Bermuda | P31: BZD
G32: BT | H32: Bhutan | P32: CAD
G33: BO | H33: Bolivia | P33: CDF
G34: BA | H34: Bosnia and Herzegovina | P34: CHE
G35: BW | H35: Botswana | P35: CHF
G36: BV | H36: Bouvet Island | P36: CHW
G37: BR | H37: Brazil | P37: CLF
... G163: NC | H163: New Caledonia | P163: XXX
G164: NZ | H164: New Zealand
G165: NI | H165: Nicaragua
G166: NE | H166: Niger
G167: NG | H167: Nigeria
G168: NU | H168: Niue
G169: NF | H169: Norfolk Island
G170: KP | H170: North Korea
G171: MP | H171: Northern Mariana Islands
G172: NO | H172: Norway
G173: OM | H173: Oman
G174: PK | H174: Pakistan
G175: PW | H175: Palau
... G252: ZW | H252: Zimbabwe

Sheet Questions
B2: Imagine after a lot of analysis is done in hx, the upload file has a change and needs to be uploaded again, can we retain all of the user inputs/decisions made
B3: Best way to update just the triangle data and not lose other inputs
B4: How to refresh 1 piece of information without refreshing all information during the upload (e.g. 1 specific rate change for 1 year)
B5: Uploaded numbers should be "calculated" part of the override field, allowing us to use the override functionality

Sheet Hidden Tab
G1: Development months
A2: LOB (dropdown) | B2: Type (Incurred / Paid …) | C2: Loss type | D2: Basis (Accident Year / UW Year) | E2: Currency (e.g. USD, GBP …) | F2: Origin Year | G2: =month_first_development -> 6 | H2: =G2+triangle_increments_months -> 18 | I2: =H2+triangle_increments_months -> 30 | J2: =I2+triangle_increments_months -> 42 | K2: =J2+triangle_increments_months -> 54 | L2: =K2+triangle_increments_months -> 66 | M2: =L2+triangle_increments_months -> 78 | N2: =M2+triangle_increments_months -> 90 | O2: =N2+triangle_increments_months -> 102 | ... AE2: =AD2+triangle_increments_months -> 294
A3: Directors & Officers US | B3: Net Written Premium | C3: All | D3: UW Year | E3: USD | F3: 2010 | G3: =G38*1.7 -> 5256638.5 | H3: =H38*1.7 -> 7060972.8 | I3: =I38*1.7 -> 13842680 | J3: =J38*1.7 -> 14889484 | K3: =K38*1.7 -> 14889484 | L3: =L38*1.7 -> 14889484 | M3: =M38*1.7 -> 14889484 | N3: =N38*1.7 -> 14889484 | ... P3: =P38*1.7 -> 14889484
A4: Directors & Officers US | B4: Net Written Premium | C4: All | D4: UW Year | E4: USD | F4: 2011 | G4: =G39*1.7 -> 2199597.1 | H4: =H39*1.7 -> 22050071 | I4: =I39*1.7 -> 18841726 | J4: =J39*1.7 -> 19092959 | K4: =K39*1.7 -> 19092959 | L4: =L39*1.7 -> 19092959 | M4: =M39*1.7 -> 19092959 | N4: =N39*1.7 -> 19092959 | O4: =O39*1.7 -> 19092959
A5: Directors & Officers US | B5: Net Written Premium | C5: All | D5: UW Year | E5: USD | F5: 2012 | G5: =G40*1.7 -> 16005598 | H5: =H40*1.7 -> 27315027 | I5: =I40*1.7 -> 28288322 | J5: =J40*1.7 -> 28288322 | K5: =K40*1.7 -> 28288322 | L5: =L40*1.7 -> 28288322 | M5: =M40*1.7 -> 28288322 | N5: =N40*1.7 -> 28288322
A6: Directors & Officers US | B6: Net Written Premium | C6: All | D6: UW Year | E6: USD | F6: 2013 | G6: =G41*1.7 -> 22548448 | H6: =H41*1.7 -> 33252242 | I6: =I41*1.7 -> 33252242 | J6: =J41*1.7 -> 33252242 | K6: =K41*1.7 -> 33252242 | L6: =L41*1.7 -> 33252242 | M6: =M41*1.7 -> 33252242
A7: Directors & Officers US | B7: Net Written Premium | C7: All | D7: UW Year | E7: USD | F7: 2014 | G7: =G42*1.7 -> 36049875 | H7: =H42*1.7 -> 40467032 | I7: =I42*1.7 -> 43769076 | J7: =J42*1.7 -> 44662746 | K7: =K42*1.7 -> 44662746 | L7: =L42*1.7 -> 44662746
A8: Directors & Officers US | B8: Net Written Premium | C8: All | D8: UW Year | E8: USD | F8: 2015 | G8: =G43*1.7 -> 21752447 | H8: =H43*1.7 -> 25614171 | I8: =I43*1.7 -> 24673696 | J8: =J43*1.7 -> 24673696 | K8: =K43*1.7 -> 24673696
A9: Directors & Officers US | B9: Net Written Premium | C9: All | D9: UW Year | E9: USD | F9: 2016 | G9: =G44*1.7 -> 44756997 | H9: =H44*1.7 -> 46630749 | I9: =I44*1.7 -> 47058219 | J9: =J44*1.7 -> 47058219
A10: Directors & Officers US | B10: Net Written Premium | C10: All | D10: UW Year | E10: USD | F10: 2017 | G10: =G45*1.7 -> 63872518 | H10: =H45*1.7 -> 64074803 | I10: =I45*1.7 -> 68151466
A11: Directors & Officers US | B11: Net Written Premium | C11: All | D11: UW Year | E11: USD | F11: 2018 | G11: =G46*1.7 -> 1.0892822e+08 | H11: =H46*1.7 -> 1.1255941e+08
A12: Directors & Officers US | B12: Net Written Premium | C12: All | D12: UW Year | E12: USD | F12: 2019 | G12: =G47*1.7 -> 1.0280669e+08
A14: Directors & Officers US | B14: Incurred | C14: All | D14: UW Year | E14: USD | F14: 2010 | G14: =G49*1.7 -> 0 | H14: =H49*1.7 -> 4.3787879 | I14: =I49*1.7 -> 15325.32 | J14: =J49*1.7 -> 15142.483 | K14: =K49*1.7 -> 10934.972 | L14: =L49*1.7 -> 10934.972 | M14: =M49*1.7 -> 10934.972 | N14: =N49*1.7 -> 10934.972 | ... P14: =P49*1.7 -> 10934.972
A15: Directors & Officers US | B15: Incurred | C15: All | D15: UW Year | E15: USD | F15: 2011 | G15: =G50*1.7 -> 4407.25 | H15: =H50*1.7 -> 410131.24 | I15: =I50*1.7 -> 6057531.9 | J15: =J50*1.7 -> 25489685 | K15: =K50*1.7 -> 24386343 | L15: =L50*1.7 -> 24049172 | M15: =M50*1.7 -> 24049172 | N15: =N50*1.7 -> 24049172 | O15: =O50*1.7 -> 24049172
A16: Directors & Officers US | B16: Incurred | C16: All | D16: UW Year | E16: USD | F16: 2012 | G16: =G51*1.7 -> 1764651.5 | H16: =H51*1.7 -> 1825483.9 | I16: =I51*1.7 -> 6256439.6 | J16: =J51*1.7 -> 10451593 | K16: =K51*1.7 -> 8832632.3 | L16: =L51*1.7 -> 10178498 | M16: =M51*1.7 -> 10186238 | N16: =N51*1.7 -> 10310869
A17: Directors & Officers US | B17: Incurred | C17: All | D17: UW Year | E17: USD | F17: 2013 | G17: =G52*1.7 -> 32840.909 | H17: =H52*1.7 -> 845630.92 | I17: =I52*1.7 -> 1200309.1 | J17: =J52*1.7 -> 1507677.4 | K17: =K52*1.7 -> 2513113.5 | L17: =L52*1.7 -> 2551021.8 | M17: =M52*1.7 -> 2543254.9
A18: Directors & Officers US | B18: Incurred | C18: All | D18: UW Year | E18: USD | F18: 2014 | G18: =G53*1.7 -> 13136.364 | H18: =H53*1.7 -> 78818.182 | I18: =I53*1.7 -> 345920.96 | J18: =J53*1.7 -> 518881.15 | K18: =K53*1.7 -> 518880.43 | L18: =L53*1.7 -> 13541054
A19: Directors & Officers US | B19: Incurred | C19: All | D19: UW Year | E19: USD | F19: 2015 | G19: =G54*1.7 -> 164204.55 | H19: =H54*1.7 -> 21893.939 | I19: =I54*1.7 -> 21893.939 | J19: =J54*1.7 -> 97312.277 | K19: =K54*1.7 -> 87051.682
A20: Directors & Officers US | B20: Incurred | C20: All | D20: UW Year | E20: USD | F20: 2016 | G20: =G55*1.7 -> 0 | H20: =H55*1.7 -> 175151.52 | I20: =I55*1.7 -> 2115063.2 | J20: =J55*1.7 -> 2172468.9
A21: Directors & Officers US | B21: Incurred | C21: All | D21: UW Year | E21: USD | F21: 2017 | G21: =G56*1.7 -> 421458.33 | H21: =H56*1.7 -> 10678769 | I21: =I56*1.7 -> 37324308
A22: Directors & Officers US | B22: Incurred | C22: All | D22: UW Year | E22: USD | F22: 2018 | G22: =G57*1.7 -> 151341.86 | H22: =H57*1.7 -> 965068.82
A23: Directors & Officers US | B23: Incurred | C23: All | D23: UW Year | E23: USD | F23: 2019 | G23: =G58*1.7 -> 492613.64
A25: Directors & Officers US | B25: Paid | C25: All | D25: UW Year | E25: USD | F25: 2010 | G25: =G60*1.7 -> 0 | H25: =H60*1.7 -> 0 | I25: =I60*1.7 -> 5245.35 | J25: =J60*1.7 -> 6739.5895 | K25: =K60*1.7 -> 10934.972 | L25: =L60*1.7 -> 10934.972 | M25: =M60*1.7 -> 10934.972 | N25: =N60*1.7 -> 10934.972 | ... P25: =P60*1.7 -> 10934.972
A26: Directors & Officers US | B26: Paid | C26: All | D26: UW Year | E26: USD | F26: 2011 | G26: =G61*1.7 -> 0 | H26: =H61*1.7 -> 239941.75 | I26: =I61*1.7 -> 893601.72 | J26: =J61*1.7 -> 23840228 | K26: =K61*1.7 -> 24048482 | L26: =L61*1.7 -> 24049172 | M26: =M61*1.7 -> 24049172 | N26: =N61*1.7 -> 24049172 | O26: =O61*1.7 -> 24049172
A27: Directors & Officers US | B27: Paid | C27: All | D27: UW Year | E27: USD | F27: 2012 | G27: =G62*1.7 -> 0 | H27: =H62*1.7 -> 917141.57 | I27: =I62*1.7 -> 4749380.4 | J27: =J62*1.7 -> 6855056.2 | K27: =K62*1.7 -> 8719907 | L27: =L62*1.7 -> 8952248.7 | M27: =M62*1.7 -> 9005544 | N27: =N62*1.7 -> 9151252.5
A28: Directors & Officers US | B28: Paid | C28: All | D28: UW Year | E28: USD | F28: 2013 | G28: =G63*1.7 -> 3908.0682 | H28: =H63*1.7 -> 178091.28 | I28: =I63*1.7 -> 410248.16 | J28: =J63*1.7 -> 868212.91 | K28: =K63*1.7 -> 1484356.9 | L28: =L63*1.7 -> 1712307 | M28: =M63*1.7 -> 1896199.3
A29: Directors & Officers US | B29: Paid | C29: All | D29: UW Year | E29: USD | F29: 2014 | G29: =G64*1.7 -> 4378.7879 | H29: =H64*1.7 -> 68773.242 | I29: =I64*1.7 -> 118245.88 | J29: =J64*1.7 -> 430747.1 | K29: =K64*1.7 -> 470755.36 | L29: =L64*1.7 -> 13541054
A30: Directors & Officers US | B30: Paid | C30: All | D30: UW Year | E30: USD | F30: 2015 | G30: =G65*1.7 -> 0 | H30: =H65*1.7 -> 2371.1136 | I30: =I65*1.7 -> 10164.261 | J30: =J65*1.7 -> 54659.599 | K30: =K65*1.7 -> 54659.599
A31: Directors & Officers US | B31: Paid | C31: All | D31: UW Year | E31: USD | F31: 2016 | G31: =G66*1.7 -> 0 | H31: =H66*1.7 -> 49182.633 | I31: =I66*1.7 -> 2049234.3 | J31: =J66*1.7 -> 2102073.8
A32: Directors & Officers US | B32: Paid | C32: All | D32: UW Year | E32: USD | F32: 2017 | G32: =G67*1.7 -> 28385.317 | H32: =H67*1.7 -> 8855723.7 | I32: =I67*1.7 -> 36769830
A33: Directors & Officers US | B33: Paid | C33: All | D33: UW Year | E33: USD | F33: 2018 | G33: =G68*1.7 -> 18229.989 | H33: =H68*1.7 -> 171919.53
A34: Directors & Officers US | B34: Paid | C34: All | D34: UW Year | E34: USD | F34: 2019 | G34: =G69*1.7 -> 78142.754
A38: Errors & Omissions US | B38: Net Written Premium | C38: All | D38: UW Year | E38: USD | F38: 2010 | G38: =G73*1.7 -> 3092140.3 | H38: =H73*1.7 -> 4153513.4 | I38: =I73*1.7 -> 8142752.7 | J38: =J73*1.7 -> 8758519.8 | K38: =K73*1.7 -> 8758519.8 | L38: =L73*1.7 -> 8758519.8 | M38: =M73*1.7 -> 8758519.8 | N38: =N73*1.7 -> 8758519.8 | ... P38: =P73*1.7 -> 8758519.8
A39: Errors & Omissions US | B39: Net Written Premium | C39: All | D39: UW Year | E39: USD | F39: 2011 | G39: =G74*1.7 -> 1293880.7 | H39: =H74*1.7 -> 12970630 | I39: =I74*1.7 -> 11083368 | J39: =J74*1.7 -> 11231152 | K39: =K74*1.7 -> 11231152 | L39: =L74*1.7 -> 11231152 | M39: =M74*1.7 -> 11231152 | N39: =N74*1.7 -> 11231152 | O39: =O74*1.7 -> 11231152
A40: Errors & Omissions US | B40: Net Written Premium | C40: All | D40: UW Year | E40: USD | F40: 2012 | G40: =G75*1.7 -> 9415057.4 | H40: =H75*1.7 -> 16067663 | I40: =I75*1.7 -> 16640190 | J40: =J75*1.7 -> 16640190 | K40: =K75*1.7 -> 16640190 | L40: =L75*1.7 -> 16640190 | M40: =M75*1.7 -> 16640190 | N40: =N75*1.7 -> 16640190
A41: Errors & Omissions US | B41: Net Written Premium | C41: All | D41: UW Year | E41: USD | F41: 2013 | G41: =G76*1.7 -> 13263793 | H41: =H76*1.7 -> 19560142 | I41: =I76*1.7 -> 19560142 | J41: =J76*1.7 -> 19560142 | K41: =K76*1.7 -> 19560142 | L41: =L76*1.7 -> 19560142 | M41: =M76*1.7 -> 19560142
A42: Errors & Omissions US | B42: Net Written Premium | C42: All | D42: UW Year | E42: USD | F42: 2014 | G42: =G77*1.7 -> 21205809 | H42: =H77*1.7 -> 23804136 | I42: =I77*1.7 -> 25746515 | J42: =J77*1.7 -> 26272204 | K42: =K77*1.7 -> 26272204 | L42: =L77*1.7 -> 26272204
A43: Errors & Omissions US | B43: Net Written Premium | C43: All | D43: UW Year | E43: USD | F43: 2015 | G43: =G78*1.7 -> 12795557 | H43: =H78*1.7 -> 15067159 | I43: =I78*1.7 -> 14513939 | J43: =J78*1.7 -> 14513939 | K43: =K78*1.7 -> 14513939
A44: Errors & Omissions US | B44: Net Written Premium | C44: All | D44: UW Year | E44: USD | F44: 2016 | G44: =G79*1.7 -> 26327645 | H44: =H79*1.7 -> 27429853 | I44: =I79*1.7 -> 27681305 | J44: =J79*1.7 -> 27681305
A45: Errors & Omissions US | B45: Net Written Premium | C45: All | D45: UW Year | E45: USD | F45: 2017 | G45: =G80*1.7 -> 37572069 | H45: =H80*1.7 -> 37691061 | I45: =I80*1.7 -> 40089098
A46: Errors & Omissions US | B46: Net Written Premium | C46: All | D46: UW Year | E46: USD | F46: 2018 | G46: =G81*1.7 -> 64075424 | H46: =H81*1.7 -> 66211418
A47: Errors & Omissions US | B47: Net Written Premium | C47: All | D47: UW Year | E47: USD | F47: 2019 | G47: =G82*1.7 -> 60474526
A49: Errors & Omissions US | B49: Incurred | C49: All | D49: UW Year | E49: USD | F49: 2010 | G49: =G84*1.7 -> 0 | H49: =H84*1.7 -> 2.5757576 | I49: =I84*1.7 -> 9014.8939 | J49: =J84*1.7 -> 8907.3432 | K49: =K84*1.7 -> 6432.3364 | L49: =L84*1.7 -> 6432.3364 | M49: =M84*1.7 -> 6432.3364 | N49: =N84*1.7 -> 6432.3364 | ... P49: =P84*1.7 -> 6432.3364
A50: Errors & Omissions US | B50: Incurred | C50: All | D50: UW Year | E50: USD | F50: 2011 | G50: =G85*1.7 -> 2592.5 | H50: =H85*1.7 -> 241253.67 | I50: =I85*1.7 -> 3563254 | J50: =J85*1.7 -> 14993932 | K50: =K85*1.7 -> 14344907 | L50: =L85*1.7 -> 14146571 | M50: =M85*1.7 -> 14146571 | N50: =N85*1.7 -> 14146571 | O50: =O85*1.7 -> 14146571
A51: Errors & Omissions US | B51: Incurred | C51: All | D51: UW Year | E51: USD | F51: 2012 | G51: =G86*1.7 -> 1038030.3 | H51: =H86*1.7 -> 1073814.1 | I51: =I86*1.7 -> 3680258.6 | J51: =J86*1.7 -> 6147996.1 | K51: =K86*1.7 -> 5195666.1 | L51: =L86*1.7 -> 5987351.5 | M51: =M86*1.7 -> 5991904.8 | N51: =N86*1.7 -> 6065217.3
A52: Errors & Omissions US | B52: Incurred | C52: All | D52: UW Year | E52: USD | F52: 2013 | G52: =G87*1.7 -> 19318.182 | H52: =H87*1.7 -> 497429.96 | I52: =I87*1.7 -> 706064.17 | J52: =J87*1.7 -> 886869.07 | K52: =K87*1.7 -> 1478302.1 | L52: =L87*1.7 -> 1500601.1 | M52: =M87*1.7 -> 1496032.3
A53: Errors & Omissions US | B53: Incurred | C53: All | D53: UW Year | E53: USD | F53: 2014 | G53: =G88*1.7 -> 7727.2727 | H53: =H88*1.7 -> 46363.636 | I53: =I88*1.7 -> 203482.92 | J53: =J88*1.7 -> 305224.21 | K53: =K88*1.7 -> 305223.78 | L53: =L88*1.7 -> 7965325.9
A54: Errors & Omissions US | B54: Incurred | C54: All | D54: UW Year | E54: USD | F54: 2015 | G54: =G89*1.7 -> 96590.909 | H54: =H89*1.7 -> 12878.788 | I54: =I89*1.7 -> 12878.788 | J54: =J89*1.7 -> 57242.516 | K54: =K89*1.7 -> 51206.872
A55: Errors & Omissions US | B55: Incurred | C55: All | D55: UW Year | E55: USD | F55: 2016 | G55: =G90*1.7 -> 0 | H55: =H90*1.7 -> 103030.3 | I55: =I90*1.7 -> 1244154.9 | J55: =J90*1.7 -> 1277922.9
A56: Errors & Omissions US | B56: Incurred | C56: All | D56: UW Year | E56: USD | F56: 2017 | G56: =G91*1.7 -> 247916.67 | H56: =H91*1.7 -> 6281628.8 | I56: =I91*1.7 -> 21955475
A57: Errors & Omissions US | B57: Incurred | C57: All | D57: UW Year | E57: USD | F57: 2018 | G57: =G92*1.7 -> 89024.621 | H57: =H92*1.7 -> 567687.54
A58: Errors & Omissions US | B58: Incurred | C58: All | D58: UW Year | E58: USD | F58: 2019 | G58: =G93*1.7 -> 289772.73
A60: Errors & Omissions US | B60: Paid | C60: All | D60: UW Year | E60: USD | F60: 2010 | G60: =G95*1.7 -> 0 | H60: =H95*1.7 -> 0 | I60: =I95*1.7 -> 3085.5 | J60: =J95*1.7 -> 3964.4644 | K60: =K95*1.7 -> 6432.3364 | L60: =L95*1.7 -> 6432.3364 | M60: =M95*1.7 -> 6432.3364 | N60: =N95*1.7 -> 6432.3364 | ... P60: =P95*1.7 -> 6432.3364
A61: Errors & Omissions US | B61: Paid | C61: All | D61: UW Year | E61: USD | F61: 2011 | G61: =G96*1.7 -> 0 | H61: =H96*1.7 -> 141142.2 | I61: =I96*1.7 -> 525648.07 | J61: =J96*1.7 -> 14023664 | K61: =K96*1.7 -> 14146166 | L61: =L96*1.7 -> 14146571 | M61: =M96*1.7 -> 14146571 | N61: =N96*1.7 -> 14146571 | O61: =O96*1.7 -> 14146571
A62: Errors & Omissions US | B62: Paid | C62: All | D62: UW Year | E62: USD | F62: 2012 | G62: =G97*1.7 -> 0 | H62: =H97*1.7 -> 539495.04 | I62: =I97*1.7 -> 2793753.2 | J62: =J97*1.7 -> 4032386 | K62: =K97*1.7 -> 5129357.1 | L62: =L97*1.7 -> 5266028.6 | M62: =M97*1.7 -> 5297378.8 | N62: =N97*1.7 -> 5383089.7
A63: Errors & Omissions US | B63: Paid | C63: All | D63: UW Year | E63: USD | F63: 2013 | G63: =G98*1.7 -> 2298.8636 | H63: =H98*1.7 -> 104759.58 | I63: =I98*1.7 -> 241322.45 | J63: =J98*1.7 -> 510713.47 | K63: =K98*1.7 -> 873151.11 | L63: =L98*1.7 -> 1007239.4 | M63: =M98*1.7 -> 1115411.4
A64: Errors & Omissions US | B64: Paid | C64: All | D64: UW Year | E64: USD | F64: 2014 | G64: =G99*1.7 -> 2575.7576 | H64: =H99*1.7 -> 40454.848 | I64: =I99*1.7 -> 69556.402 | J64: =J99*1.7 -> 253380.65 | K64: =K99*1.7 -> 276914.92 | L64: =L99*1.7 -> 7965325.9
A65: Errors & Omissions US | B65: Paid | C65: All | D65: UW Year | E65: USD | F65: 2015 | G65: =G100*1.7 -> 0 | H65: =H100*1.7 -> 1394.7727 | I65: =I100*1.7 -> 5978.9773 | J65: =J100*1.7 -> 32152.705 | K65: =K100*1.7 -> 32152.705
A66: Errors & Omissions US | B66: Paid | C66: All | D66: UW Year | E66: USD | F66: 2016 | G66: =G101*1.7 -> 0 | H66: =H101*1.7 -> 28930.961 | I66: =I101*1.7 -> 1205432 | J66: =J101*1.7 -> 1236514
A67: Errors & Omissions US | B67: Paid | C67: All | D67: UW Year | E67: USD | F67: 2017 | G67: =G102*1.7 -> 16697.245 | H67: =H102*1.7 -> 5209249.2 | I67: =I102*1.7 -> 21629312
A68: Errors & Omissions US | B68: Paid | C68: All | D68: UW Year | E68: USD | F68: 2018 | G68: =G103*1.7 -> 10723.523 | H68: =H103*1.7 -> 101129.13
A69: Errors & Omissions US | B69: Paid | C69: All | D69: UW Year | E69: USD | F69: 2019 | G69: =G104*1.7 -> 45966.326
A73: Cyber US | B73: Net Written Premium | C73: All | D73: UW Year | E73: USD | F73: 2010 | G73: 1818906.1 | H73: 2443243.2 | I73: 4789854.6 | J73: 5152070.5 | K73: 5152070.5 | L73: 5152070.5 | M73: 5152070.5 | N73: 5152070.5 | O73: 5152070.5 | P73: 5152070.5
A74: Cyber US | B74: Net Written Premium | C74: All | D74: UW Year | E74: USD | F74: 2011 | G74: 761106.27 | H74: 7629782.5 | I74: 6519628.4 | J74: 6606560.2 | K74: 6606560.2 | L74: 6606560.2 | M74: 6606560.2 | N74: 6606560.2 | O74: 6606560.2
A75: Cyber US | B75: Net Written Premium | C75: All | D75: UW Year | E75: USD | F75: 2012 | G75: 5538269.1 | H75: 9451566.6 | I75: 9788346.9 | J75: 9788346.9 | K75: 9788346.9 | L75: 9788346.9 | M75: 9788346.9 | N75: 9788346.9
A76: Cyber US | B76: Net Written Premium | C76: All | D76: UW Year | E76: USD | F76: 2013 | G76: 7802231.3 | H76: 11505966 | I76: 11505966 | J76: 11505966 | K76: 11505966 | L76: 11505966 | M76: 11505966
A77: Cyber US | B77: Net Written Premium | C77: All | D77: UW Year | E77: USD | F77: 2014 | G77: 12474005 | H77: 14002433 | I77: 15145009 | J77: 15454237 | K77: 15454237 | L77: 15454237 | M77: 0
A78: Cyber US | B78: Net Written Premium | C78: All | D78: UW Year | E78: USD | F78: 2015 | G78: 7526798.3 | H78: 8863034.8 | I78: 8537611.1 | J78: 8537611.1 | K78: 8537611.1 | L78: 0 | M78: 0
A79: Cyber US | B79: Net Written Premium | C79: All | D79: UW Year | E79: USD | F79: 2016 | G79: 15486850 | H79: 16135207 | I79: 16283121 | J79: 16283121 | K79: 0 | L79: 0 | M79: 0
A80: Cyber US | B80: Net Written Premium | C80: All | D80: UW Year | E80: USD | F80: 2017 | G80: 22101217 | H80: 22171212 | I80: 23581822 | J80: 0 | K80: 0 | L80: 0 | M80: 0
A81: Cyber US | B81: Net Written Premium | C81: All | D81: UW Year | E81: USD | F81: 2018 | G81: 37691426 | H81: 38947893 | I81: 0 | J81: 0 | K81: 0 | L81: 0 | M81: 0
A82: Cyber US | B82: Net Written Premium | C82: All | D82: UW Year | E82: USD | F82: 2019 | G82: 35573251 | H82: 0 | I82: 0 | J82: 0 | K82: 0 | L82: 0 | M82: 0
A84: Cyber US | B84: Incurred | C84: All | D84: UW Year | E84: USD | F84: 2010 | G84: 0 | H84: 1.5151515 | I84: 5302.8788 | J84: 5239.6136 | K84: 3783.7273 | L84: 3783.7273 | M84: 3783.7273 | N84: 3783.7273 | O84: 3783.7273 | P84: 3783.7273
A85: Cyber US | B85: Incurred | C85: All | D85: UW Year | E85: USD | F85: 2011 | G85: 1525 | H85: 141913.93 | I85: 2096031.8 | J85: 8819960.2 | K85: 8438180.8 | L85: 8321512.6 | M85: 8321512.6 | N85: 8321512.6 | O85: 8321512.6 | P85: 0
A86: Cyber US | B86: Incurred | C86: All | D86: UW Year | E86: USD | F86: 2012 | G86: 610606.06 | H86: 631655.33 | I86: 2164858 | J86: 3616468.3 | K86: 3056274.2 | L86: 3521971.5 | M86: 3524649.9 | N86: 3567774.9 | O86: 0 | P86: 0
A87: Cyber US | B87: Incurred | C87: All | D87: UW Year | E87: USD | F87: 2013 | G87: 11363.636 | H87: 292605.86 | I87: 415331.87 | J87: 521687.69 | K87: 869589.45 | L87: 882706.52 | M87: 880019 | N87: 0 | O87: 0 | P87: 0
A88: Cyber US | B88: Incurred | C88: All | D88: UW Year | E88: USD | F88: 2014 | G88: 4545.4545 | H88: 27272.727 | I88: 119695.83 | J88: 179543.65 | K88: 179543.4 | L88: 4685485.8 | M88: 0 | N88: 0 | O88: 0 | P88: 0
A89: Cyber US | B89: Incurred | C89: All | D89: UW Year | E89: USD | F89: 2015 | G89: 56818.182 | H89: 7575.7576 | I89: 7575.7576 | J89: 33672.068 | K89: 30121.689 | L89: 0 | M89: 0 | N89: 0 | O89: 0 | P89: 0
A90: Cyber US | B90: Incurred | C90: All | D90: UW Year | E90: USD | F90: 2016 | G90: 0 | H90: 60606.061 | I90: 731855.8 | J90: 751719.33 | K90: 0 | L90: 0 | M90: 0 | N90: 0 | O90: 0 | P90: 0
A91: Cyber US | B91: Incurred | C91: All | D91: UW Year | E91: USD | F91: 2017 | G91: 145833.33 | H91: 3695075.8 | I91: 12914985 | J91: 0 | K91: 0 | L91: 0 | M91: 0 | N91: 0 | O91: 0 | P91: 0
A92: Cyber US | B92: Incurred | C92: All | D92: UW Year | E92: USD | F92: 2018 | G92: 52367.424 | H92: 333933.85 | I92: 0 | J92: 0 | K92: 0 | L92: 0 | M92: 0 | N92: 0 | O92: 0 | P92: 0
A93: Cyber US | B93: Incurred | C93: All | D93: UW Year | E93: USD | F93: 2019 | G93: 170454.55 | H93: 0 | I93: 0 | J93: 0 | K93: 0 | L93: 0 | M93: 0 | N93: 0 | O93: 0 | P93: 0
A95: Cyber US | B95: Paid | C95: All | D95: UW Year | E95: USD | F95: 2010 | G95: 0 | H95: 0 | I95: 1815 | J95: 2332.0379 | K95: 3783.7273 | L95: 3783.7273 | M95: 3783.7273 | N95: 3783.7273 | O95: 3783.7273 | P95: 3783.7273
A96: Cyber US | B96: Paid | C96: All | D96: UW Year | E96: USD | F96: 2011 | G96: 0 | H96: 83024.826 | I96: 309204.75 | J96: 8249213.9 | K96: 8321274 | L96: 8321512.6 | M96: 8321512.6 | N96: 8321512.6 | O96: 8321512.6
A97: Cyber US | B97: Paid | C97: All | D97: UW Year | E97: USD | F97: 2012 | G97: 0 | H97: 317350.02 | I97: 1643384.2 | J97: 2371991.8 | K97: 3017268.9 | L97: 3097663.9 | M97: 3116105.2 | N97: 3166523.4
A98: Cyber US | B98: Paid | C98: All | D98: UW Year | E98: USD | F98: 2013 | G98: 1352.2727 | H98: 61623.28 | I98: 141954.38 | J98: 300419.69 | K98: 513618.3 | L98: 592493.76 | M98: 656124.33
A99: Cyber US | B99: Paid | C99: All | D99: UW Year | E99: USD | F99: 2014 | G99: 1515.1515 | H99: 23796.97 | I99: 40915.53 | J99: 149047.44 | K99: 162891.13 | L99: 4685485.8
A100: Cyber US | B100: Paid | C100: All | D100: UW Year | E100: USD | F100: 2015 | G100: 0 | H100: 820.45455 | I100: 3517.0455 | J100: 18913.356 | K100: 18913.356
A101: Cyber US | B101: Paid | C101: All | D101: UW Year | E101: USD | F101: 2016 | G101: 0 | H101: 17018.212 | I101: 709077.62 | J101: 727361.18
A102: Cyber US | B102: Paid | C102: All | D102: UW Year | E102: USD | F102: 2017 | G102: 9821.9091 | H102: 3064264.3 | I102: 12723125
A103: Cyber US | B103: Paid | C103: All | D103: UW Year | E103: USD | F103: 2018 | G103: 6307.9545 | H103: 59487.725
A104: Cyber US | B104: Paid | C104: All | D104: UW Year | E104: USD | F104: 2019 | G104: 27039.015
