Workbook
Name Country_list: Lookups!$H$3:$H$252
Name Currency_list: Lookups!$P$3:$P$163
Name current_date: 'Example - Parameters'!$D$9
Name current_date: Parameters!$D$9
Name Development_classes: 'Example - Parameters'!$C$14:$C$213
Name Development_classes: Parameters!$C$14:$C$213
Name IQ_CH: 110000
Name IQ_CQ: 5000
Name IQ_CY: 10000
Name IQ_DAILY: 500000
Name IQ_FH: 100000
Name IQ_FQ: 500
Name IQ_FY: 1000
Name IQ_LTM: 2000
Name IQ_MONTH: 15000
Name IQ_NTM: 6000
Name IQ_WEEK: 50000
Name IQ_YTD: 3000
Name LDF_type_options: Lookups!$R$3:$R$6
Name LOBs_names: Lookups!$B$3:$B$25
Name month_final_development: 'Example - Parameters'!$D$8
Name month_final_development: Parameters!$D$8
Name month_first_development: 'Example - Parameters'!$D$5
Name month_first_development: Parameters!$D$5
Name P_NP_types: Lookups!$E$3:$E$6
Name Projection_classes: 'Example - Parameters'!$C$219:$C$418
Name Projection_classes: Parameters!$C$219:$C$418
Name re_insurance_list: Lookups!$N$3:$N$5
Name Region_list: Lookups!$K$3:$K$8
Name triangle_grouping_data: 'Example - Parameters'!$C$219:$AA$418
Name triangle_grouping_data: Parameters!$C$219:$AA$418
Name triangle_increments_months: 'Example - Parameters'!$D$6
Name triangle_increments_months: Parameters!$D$6
Name triangle_start_date: 'Example - Parameters'!$D$4
Name triangle_start_date: Parameters!$D$4

Sheet Parameters
B3: Triangle Shape Parameters | E3: guide | F3: Checks
C4: Triangle start (t=0) date | D4: 38718 | E4: YYYY-MM-DD | F4: =triangle_start_date=Triangles!F3 -> TRUE | H4: Mandatory
C5: Month of first development | D5: 9 | E5: first month in triangle | H5: Optional
C6: Development period increments (months) | D6: 12 | E6: triangle increments (column)
C7: Origin period increments (months) | D7: 12 | E7: triangle increments (row)
C8: Month of final development | D8: 237 | E8: Latest month in the largest triangle | F8: =IF(ISERROR(MATCH(month_final_development,Triangles!$G$2:$FA$2, 0)), "Can't find this development month in triangle. Please be consistent with Triangle.", "OK") -> OK
C9: Inception Date | D9: 46023 | E9: YYYY-MM-DD
C10: Expiry Date | D10: 46387 | E10: YYYY-MM-DD
B11: Triangular data list (LOB/Class)
Q12: Cedant Business Segment Names (Optional)
B13: # | C13: Triangle Name | D13: Proportional/Non-proportional | E13: Region | F13: Country | G13: Re/Ins/Retro | H13: LT LOB 1 (Dropdown List) | I13: LT LOB 1 Allocation | J13: LT LOB 2 (Dropdown List) | K13: LT LOB 2 Allocation | L13: LT LOB 3 (Dropdown List) | M13: LT LOB 3 Allocation | N13: LT LOB 4 (Dropdown List) | O13: LT LOB 4 Allocation | P13: LT LOB 5 (Dropdown List) | Q13: LT LOB 5 Allocation | R13: Allocation Check | S13: Currency | T13: Currency Rate | U13: Segment 1 | V13: Segment 2 | W13: Segment 3 | X13: Segment 4 | Y13: Segment 5 | Z13: Premium Triangle Source | AA13: Incurred Triangle Source | AB13: Paid Triangle Source | AC13: Ultimate Triangle Source
B14: 1 | C14: =[1]INDEX!C31 -> Professional Lines | D14: Mixed | E14: Worldwide | F14: Multi-country | G14: Retrocession | H14: Professional Liability | I14: 1 | R14: =IF(AND(C14<>"",SUM(I14,K14,M14,O14,Q14)=1),"pass",IF(AND(C14="",SUM(I14,K14,M14,O14,Q14)=0),"pass","fail")) -> pass | Z14: Cedant provided | AA14: Cedant provided | AB14: Cedant provided
B15: 2 | C15: =[1]INDEX!C32 -> Liability | D15: Mixed | E15: Worldwide | F15: Multi-country | G15: Retrocession | H15: Casualty | I15: 1 | R15: =IF(AND(C15<>"",SUM(I15,K15,M15,O15,Q15)=1),"pass",IF(AND(C15="",SUM(I15,K15,M15,O15,Q15)=0),"pass","fail")) -> pass | Z15: Cedant provided | AA15: Cedant provided | AB15: Cedant provided
B16: 3 | C16: =[1]INDEX!C33 -> Credit & Surety | D16: Mixed | E16: Worldwide | F16: Multi-country | G16: Retrocession | H16: Fidelity & Surety | I16: 1 | R16: =IF(AND(C16<>"",SUM(I16,K16,M16,O16,Q16)=1),"pass",IF(AND(C16="",SUM(I16,K16,M16,O16,Q16)=0),"pass","fail")) -> pass | Z16: Cedant provided | AA16: Cedant provided | AB16: Cedant provided
B17: 4 | C17: =[1]INDEX!C34 -> Motor NP | D17: Non Proportional | E17: Worldwide ex US | F17: Multi-country | G17: Retrocession | H17: Motor | I17: 1 | R17: =IF(AND(C17<>"",SUM(I17,K17,M17,O17,Q17)=1),"pass",IF(AND(C17="",SUM(I17,K17,M17,O17,Q17)=0),"pass","fail")) -> pass | Z17: Cedant provided | AA17: Cedant provided | AB17: Cedant provided
B18: 5 | C18: =[1]INDEX!C35 -> Motor PR | D18: Proportional | E18: Worldwide ex US | F18: Multi-country | G18: Retrocession | H18: Motor | I18: 1 | R18: =IF(AND(C18<>"",SUM(I18,K18,M18,O18,Q18)=1),"pass",IF(AND(C18="",SUM(I18,K18,M18,O18,Q18)=0),"pass","fail")) -> pass | Z18: Cedant provided | AA18: Cedant provided | AB18: Cedant provided
B19: 6 | C19: =[1]INDEX!C36 -> Cyber | D19: Mixed | E19: Worldwide | F19: Multi-country | G19: Retrocession | H19: Cyber | I19: 1 | R19: =IF(AND(C19<>"",SUM(I19,K19,M19,O19,Q19)=1),"pass",IF(AND(C19="",SUM(I19,K19,M19,O19,Q19)=0),"pass","fail")) -> pass | Z19: Cedant provided | AA19: Cedant provided | AB19: Cedant provided
B20: 7 | R20: =IF(AND(C20<>"",SUM(I20,K20,M20,O20,Q20)=1),"pass",IF(AND(C20="",SUM(I20,K20,M20,O20,Q20)=0),"pass","fail")) -> pass
B21: 8 | R21: =IF(AND(C21<>"",SUM(I21,K21,M21,O21,Q21)=1),"pass",IF(AND(C21="",SUM(I21,K21,M21,O21,Q21)=0),"pass","fail")) -> pass
B22: 9 | R22: =IF(AND(C22<>"",SUM(I22,K22,M22,O22,Q22)=1),"pass",IF(AND(C22="",SUM(I22,K22,M22,O22,Q22)=0),"pass","fail")) -> pass
B23: 10 | R23: =IF(AND(C23<>"",SUM(I23,K23,M23,O23,Q23)=1),"pass",IF(AND(C23="",SUM(I23,K23,M23,O23,Q23)=0),"pass","fail")) -> pass
B24: 11 | R24: =IF(AND(C24<>"",SUM(I24,K24,M24,O24,Q24)=1),"pass",IF(AND(C24="",SUM(I24,K24,M24,O24,Q24)=0),"pass","fail")) -> pass
B25: 12 | R25: =IF(AND(C25<>"",SUM(I25,K25,M25,O25,Q25)=1),"pass",IF(AND(C25="",SUM(I25,K25,M25,O25,Q25)=0),"pass","fail")) -> pass
B26: 13 | R26: =IF(AND(C26<>"",SUM(I26,K26,M26,O26,Q26)=1),"pass",IF(AND(C26="",SUM(I26,K26,M26,O26,Q26)=0),"pass","fail")) -> pass
B27: 14 | R27: =IF(AND(C27<>"",SUM(I27,K27,M27,O27,Q27)=1),"pass",IF(AND(C27="",SUM(I27,K27,M27,O27,Q27)=0),"pass","fail")) -> pass
B28: 15 | R28: =IF(AND(C28<>"",SUM(I28,K28,M28,O28,Q28)=1),"pass",IF(AND(C28="",SUM(I28,K28,M28,O28,Q28)=0),"pass","fail")) -> pass
B29: 16 | R29: =IF(AND(C29<>"",SUM(I29,K29,M29,O29,Q29)=1),"pass",IF(AND(C29="",SUM(I29,K29,M29,O29,Q29)=0),"pass","fail")) -> pass
B30: 17 | R30: =IF(AND(C30<>"",SUM(I30,K30,M30,O30,Q30)=1),"pass",IF(AND(C30="",SUM(I30,K30,M30,O30,Q30)=0),"pass","fail")) -> pass
B31: 18 | R31: =IF(AND(C31<>"",SUM(I31,K31,M31,O31,Q31)=1),"pass",IF(AND(C31="",SUM(I31,K31,M31,O31,Q31)=0),"pass","fail")) -> pass
... B37: 24 | R37: =IF(AND(C37<>"",SUM(I37,K37,M37,O37,Q37)=1),"pass",IF(AND(C37="",SUM(I37,K37,M37,O37,Q37)=0),"pass","fail")) -> pass
B38: 25
B39: 26
B40: 27
B41: 28
B42: 29
B43: 30
B44: 31
B45: 32
B46: 33
B47: 34
B48: 35
B49: 36
... B212: 199
B213: 200 | R213: =IF(AND(C213<>"",SUM(I213,K213,M213,O213,Q213)=1),"pass",IF(AND(C213="",SUM(I213,K213,M213,O213,Q213)=0),"pass","fail")) -> pass
B216: Define aggregation/grouping of triangles for projection
S217: Cedant Business Segment Names (Optional)
B218: # | C218: Description (free text) | D218: Proportional/Non-proportional | E218: Start Year | F218: End Year | G218: Triangle 1 | H218: Triangle 2 | I218: Triangle 3 | J218: Triangle 4 | K218: Triangle 5 | L218: Region | M218: Country | N218: Re/Ins/Retro | O218: LT LOB 1 (Dropdown List) | P218: LT LOB 1 Allocation | Q218: LT LOB 2 (Dropdown List) | R218: LT LOB 2 Allocation | S218: LT LOB 3 (Dropdown List) | T218: LT LOB 3 Allocation | U218: LT LOB 4 (Dropdown List) | V218: LT LOB 4 Allocation | W218: LT LOB 5 (Dropdown List) | X218: LT LOB 5 Allocation | Y218: Allocation Check | Z218: Currency | AA218: Currency Rate | AB218: Segment 1 | AC218: Segment 2 | AD218: Segment 3 | AE218: Segment 4 | AF218: Segment 5
B219: 1 | C219: =C14 -> Professional Lines | D219: =D14 -> Mixed | E219: 2006 | F219: 2025 | G219: =C219 -> Professional Lines | L219: =E14 -> Worldwide | M219: =F14 -> Multi-country | N219: =G14 -> Retrocession | O219: =H14 -> Professional Liability | P219: =I14 -> 1 | Y219: =IF(AND(C219<>"",SUM(P219,R219,T219,V219,X219)=1),"pass",IF(AND(C219="",SUM(P219,R219,T219,V219,X219)=0),"pass","fail")) -> pass
B220: 2 | C220: =C15 -> Liability | D220: =D15 -> Mixed | E220: 2006 | F220: 2025 | G220: =C220 -> Liability | L220: =E15 -> Worldwide | M220: =F15 -> Multi-country | N220: =G15 -> Retrocession | O220: =H15 -> Casualty | P220: =I15 -> 1 | Y220: =IF(AND(C220<>"",SUM(P220,R220,T220,V220,X220)=1),"pass",IF(AND(C220="",SUM(P220,R220,T220,V220,X220)=0),"pass","fail")) -> pass
B221: 3 | C221: =C16 -> Credit & Surety | D221: =D16 -> Mixed | E221: 2006 | F221: 2025 | G221: =C221 -> Credit & Surety | L221: =E16 -> Worldwide | M221: =F16 -> Multi-country | N221: =G16 -> Retrocession | O221: =H16 -> Fidelity & Surety | P221: =I16 -> 1 | Y221: =IF(AND(C221<>"",SUM(P221,R221,T221,V221,X221)=1),"pass",IF(AND(C221="",SUM(P221,R221,T221,V221,X221)=0),"pass","fail")) -> pass
B222: 4 | C222: =C17 -> Motor NP | D222: =D17 -> Non Proportional | E222: 2006 | F222: 2025 | G222: =C222 -> Motor NP | L222: =E17 -> Worldwide ex US | M222: =F17 -> Multi-country | N222: =G17 -> Retrocession | O222: =H17 -> Motor | P222: =I17 -> 1 | Y222: =IF(AND(C222<>"",SUM(P222,R222,T222,V222,X222)=1),"pass",IF(AND(C222="",SUM(P222,R222,T222,V222,X222)=0),"pass","fail")) -> pass
B223: 5 | C223: =C18 -> Motor PR | D223: =D18 -> Proportional | E223: 2006 | F223: 2025 | G223: =C223 -> Motor PR | L223: =E18 -> Worldwide ex US | M223: =F18 -> Multi-country | N223: =G18 -> Retrocession | O223: =H18 -> Motor | P223: =I18 -> 1 | Y223: =IF(AND(C223<>"",SUM(P223,R223,T223,V223,X223)=1),"pass",IF(AND(C223="",SUM(P223,R223,T223,V223,X223)=0),"pass","fail")) -> pass
B224: 6 | C224: =C19 -> Cyber | D224: =D19 -> Mixed | E224: 2006 | F224: 2025 | G224: =C224 -> Cyber | L224: =E19 -> Worldwide | M224: =F19 -> Multi-country | N224: =G19 -> Retrocession | O224: =H19 -> Cyber | P224: =I19 -> 1 | Y224: =IF(AND(C224<>"",SUM(P224,R224,T224,V224,X224)=1),"pass",IF(AND(C224="",SUM(P224,R224,T224,V224,X224)=0),"pass","fail")) -> pass
B225: 7 | Y225: =IF(AND(C225<>"",SUM(P225,R225,T225,V225,X225)=1),"pass",IF(AND(C225="",SUM(P225,R225,T225,V225,X225)=0),"pass","fail")) -> pass
B226: 8 | Y226: =IF(AND(C226<>"",SUM(P226,R226,T226,V226,X226)=1),"pass",IF(AND(C226="",SUM(P226,R226,T226,V226,X226)=0),"pass","fail")) -> pass
B227: 9 | Y227: =IF(AND(C227<>"",SUM(P227,R227,T227,V227,X227)=1),"pass",IF(AND(C227="",SUM(P227,R227,T227,V227,X227)=0),"pass","fail")) -> pass
B228: 10 | Y228: =IF(AND(C228<>"",SUM(P228,R228,T228,V228,X228)=1),"pass",IF(AND(C228="",SUM(P228,R228,T228,V228,X228)=0),"pass","fail")) -> pass
B229: 11 | Y229: =IF(AND(C229<>"",SUM(P229,R229,T229,V229,X229)=1),"pass",IF(AND(C229="",SUM(P229,R229,T229,V229,X229)=0),"pass","fail")) -> pass
B230: 12 | Y230: =IF(AND(C230<>"",SUM(P230,R230,T230,V230,X230)=1),"pass",IF(AND(C230="",SUM(P230,R230,T230,V230,X230)=0),"pass","fail")) -> pass
B231: 13 | Y231: =IF(AND(C231<>"",SUM(P231,R231,T231,V231,X231)=1),"pass",IF(AND(C231="",SUM(P231,R231,T231,V231,X231)=0),"pass","fail")) -> pass
B232: 14 | Y232: =IF(AND(C232<>"",SUM(P232,R232,T232,V232,X232)=1),"pass",IF(AND(C232="",SUM(P232,R232,T232,V232,X232)=0),"pass","fail")) -> pass
B233: 15 | Y233: =IF(AND(C233<>"",SUM(P233,R233,T233,V233,X233)=1),"pass",IF(AND(C233="",SUM(P233,R233,T233,V233,X233)=0),"pass","fail")) -> pass
B234: 16 | Y234: =IF(AND(C234<>"",SUM(P234,R234,T234,V234,X234)=1),"pass",IF(AND(C234="",SUM(P234,R234,T234,V234,X234)=0),"pass","fail")) -> pass
B235: 17 | Y235: =IF(AND(C235<>"",SUM(P235,R235,T235,V235,X235)=1),"pass",IF(AND(C235="",SUM(P235,R235,T235,V235,X235)=0),"pass","fail")) -> pass
B236: 18 | Y236: =IF(AND(C236<>"",SUM(P236,R236,T236,V236,X236)=1),"pass",IF(AND(C236="",SUM(P236,R236,T236,V236,X236)=0),"pass","fail")) -> pass
... B243: 25 | Y243: =IF(AND(C243<>"",SUM(P243,R243,T243,V243,X243)=1),"pass",IF(AND(C243="",SUM(P243,R243,T243,V243,X243)=0),"pass","fail")) -> pass
B244: 26 | T244: =IF(AND(C244<>"",SUM(K244,M244,O244,Q244,S244)=1),"pass",IF(AND(C244="",SUM(K244,M244,O244,Q244,S244)=0),"pass","fail")) -> pass
B245: 27 | T245: =IF(AND(C245<>"",SUM(K245,M245,O245,Q245,S245)=1),"pass",IF(AND(C245="",SUM(K245,M245,O245,Q245,S245)=0),"pass","fail")) -> pass
B246: 28 | T246: =IF(AND(C246<>"",SUM(K246,M246,O246,Q246,S246)=1),"pass",IF(AND(C246="",SUM(K246,M246,O246,Q246,S246)=0),"pass","fail")) -> pass
B247: 29 | T247: =IF(AND(C247<>"",SUM(K247,M247,O247,Q247,S247)=1),"pass",IF(AND(C247="",SUM(K247,M247,O247,Q247,S247)=0),"pass","fail")) -> pass
B248: 30 | T248: =IF(AND(C248<>"",SUM(K248,M248,O248,Q248,S248)=1),"pass",IF(AND(C248="",SUM(K248,M248,O248,Q248,S248)=0),"pass","fail")) -> pass
B249: 31 | T249: =IF(AND(C249<>"",SUM(K249,M249,O249,Q249,S249)=1),"pass",IF(AND(C249="",SUM(K249,M249,O249,Q249,S249)=0),"pass","fail")) -> pass
B250: 32 | T250: =IF(AND(C250<>"",SUM(K250,M250,O250,Q250,S250)=1),"pass",IF(AND(C250="",SUM(K250,M250,O250,Q250,S250)=0),"pass","fail")) -> pass
B251: 33 | T251: =IF(AND(C251<>"",SUM(K251,M251,O251,Q251,S251)=1),"pass",IF(AND(C251="",SUM(K251,M251,O251,Q251,S251)=0),"pass","fail")) -> pass
B252: 34 | T252: =IF(AND(C252<>"",SUM(K252,M252,O252,Q252,S252)=1),"pass",IF(AND(C252="",SUM(K252,M252,O252,Q252,S252)=0),"pass","fail")) -> pass
B253: 35 | T253: =IF(AND(C253<>"",SUM(K253,M253,O253,Q253,S253)=1),"pass",IF(AND(C253="",SUM(K253,M253,O253,Q253,S253)=0),"pass","fail")) -> pass
B254: 36 | T254: =IF(AND(C254<>"",SUM(K254,M254,O254,Q254,S254)=1),"pass",IF(AND(C254="",SUM(K254,M254,O254,Q254,S254)=0),"pass","fail")) -> pass
B255: 37 | T255: =IF(AND(C255<>"",SUM(K255,M255,O255,Q255,S255)=1),"pass",IF(AND(C255="",SUM(K255,M255,O255,Q255,S255)=0),"pass","fail")) -> pass
... B418: 200 | T418: =IF(AND(C418<>"",SUM(K418,M418,O418,Q418,S418)=1),"pass",IF(AND(C418="",SUM(K418,M418,O418,Q418,S418)=0),"pass","fail")) -> pass

Sheet Triangles
G1: Development months
A2: LOB (dropdown) | B2: Type (Incurred / Paid …) | C2: Loss type | D2: Basis (Accident Year / UW Year) | E2: Currency (e.g. USD, GBP …) | F2: Origin Year | G2: =month_first_development -> 9 | H2: =G2+triangle_increments_months -> 21 | I2: =H2+triangle_increments_months -> 33 | J2: =I2+triangle_increments_months -> 45 | K2: =J2+triangle_increments_months -> 57 | L2: =K2+triangle_increments_months -> 69 | M2: =L2+triangle_increments_months -> 81 | N2: =M2+triangle_increments_months -> 93 | O2: =N2+triangle_increments_months -> 105 | ... FA2: =EZ2+triangle_increments_months -> 1809
A3: Professional Lines | B3: Net Written Premium | C3: All | D3: UW Year | E3: USD | F3: =triangle_start_date -> 38718 | G3: {=IF(EDATE($F3,G$2)>DATE(2025,12,31),"",INDEX([1]A1!D$9:D$175,MATCH(1,--(RIGHT([1]A1!$B$9:$B$175,LEN([1]A1!$B$9:$B$175)-4)=$A3)*([1]A1!$C$9:$C$175=YEAR($F3)),0)))} -> 82791142 | H3: {=IF(EDATE($F3,H$2)>DATE(2025,12,31),"",INDEX([1]A1!E$9:E$175,MATCH(1,--(RIGHT([1]A1!$B$9:$B$175,LEN([1]A1!$B$9:$B$175)-4)=$A3)*([1]A1!$C$9:$C$175=YEAR($F3)),0)))} -> 2.2278574e+08 | I3: {=IF(EDATE($F3,I$2)>DATE(2025,12,31),"",INDEX([1]A1!F$9:F$175,MATCH(1,--(RIGHT([1]A1!$B$9:$B$175,LEN([1]A1!$B$9:$B$175)-4)=$A3)*([1]A1!$C$9:$C$175=YEAR($F3)),0)))} -> 2.4786954e+08 | J3: {=IF(EDATE($F3,J$2)>DATE(2025,12,31),"",INDEX([1]A1!G$9:G$175,MATCH(1,--(RIGHT([1]A1!$B$9:$B$175,LEN([1]A1!$B$9:$B$175)-4)=$A3)*([1]A1!$C$9:$C$175=YEAR($F3)),0)))} -> 2.5024867e+08 | K3: {=IF(EDATE($F3,K$2)>DATE(2025,12,31),"",INDEX([1]A1!H$9:H$175,MATCH(1,--(RIGHT([1]A1!$B$9:$B$175,LEN([1]A1!$B$9:$B$175)-4)=$A3)*([1]A1!$C$9:$C$175=YEAR($F3)),0)))} -> 2.470133e+08 | L3: {=IF(EDATE($F3,L$2)>DATE(2025,12,31),"",INDEX([1]A1!I$9:I$175,MATCH(1,--(RIGHT([1]A1!$B$9:$B$175,LEN([1]A1!$B$9:$B$175)-4)=$A3)*([1]A1!$C$9:$C$175=YEAR($F3)),0)))} -> 2.454515e+08 | M3: {=IF(EDATE($F3,M$2)>DATE(2025,12,31),"",INDEX([1]A1!J$9:J$175,MATCH(1,--(RIGHT([1]A1!$B$9:$B$175,LEN([1]A1!$B$9:$B$175)-4)=$A3)*([1]A1!$C$9:$C$175=YEAR($F3)),0)))} -> 2.4630898e+08 | N3: {=IF(EDATE($F3,N$2)>DATE(2025,12,31),"",INDEX([1]A1!K$9:K$175,MATCH(1,--(RIGHT([1]A1!$B$9:$B$175,LEN([1]A1!$B$9:$B$175)-4)=$A3)*([1]A1!$C$9:$C$175=YEAR($F3)),0)))} -> 2.4796129e+08 | ... FA3: {=IF(EDATE($F3,FA$2)>DATE(2025,12,31),"",INDEX([1]A1!EX$9:EX$175,MATCH(1,--(RIGHT([1]A1!$B$9:$B$175,LEN([1]A1!$B$9:$B$175)-4)=$A3)*([1]A1!$C$9:$C$175=YEAR($F3)),0)))}
A4: Professional Lines | B4: Net Written Premium | C4: All | D4: UW Year | E4: USD | F4: =EDATE(F3,12) -> 39083 | G4: {=IF(EDATE($F4,G$2)>DATE(2025,12,31),"",INDEX([1]A1!D$9:D$175,MATCH(1,--(RIGHT([1]A1!$B$9:$B$175,LEN([1]A1!$B$9:$B$175)-4)=$A4)*([1]A1!$C$9:$C$175=YEAR($F4)),0)))} -> 82434469 | H4: {=IF(EDATE($F4,H$2)>DATE(2025,12,31),"",INDEX([1]A1!E$9:E$175,MATCH(1,--(RIGHT([1]A1!$B$9:$B$175,LEN([1]A1!$B$9:$B$175)-4)=$A4)*([1]A1!$C$9:$C$175=YEAR($F4)),0)))} -> 1.7501938e+08 | I4: {=IF(EDATE($F4,I$2)>DATE(2025,12,31),"",INDEX([1]A1!F$9:F$175,MATCH(1,--(RIGHT([1]A1!$B$9:$B$175,LEN([1]A1!$B$9:$B$175)-4)=$A4)*([1]A1!$C$9:$C$175=YEAR($F4)),0)))} -> 2.0186393e+08 | J4: {=IF(EDATE($F4,J$2)>DATE(2025,12,31),"",INDEX([1]A1!G$9:G$175,MATCH(1,--(RIGHT([1]A1!$B$9:$B$175,LEN([1]A1!$B$9:$B$175)-4)=$A4)*([1]A1!$C$9:$C$175=YEAR($F4)),0)))} -> 2.0477241e+08 | K4: {=IF(EDATE($F4,K$2)>DATE(2025,12,31),"",INDEX([1]A1!H$9:H$175,MATCH(1,--(RIGHT([1]A1!$B$9:$B$175,LEN([1]A1!$B$9:$B$175)-4)=$A4)*([1]A1!$C$9:$C$175=YEAR($F4)),0)))} -> 2.0526614e+08 | L4: {=IF(EDATE($F4,L$2)>DATE(2025,12,31),"",INDEX([1]A1!I$9:I$175,MATCH(1,--(RIGHT([1]A1!$B$9:$B$175,LEN([1]A1!$B$9:$B$175)-4)=$A4)*([1]A1!$C$9:$C$175=YEAR($F4)),0)))} -> 2.0522873e+08 | M4: {=IF(EDATE($F4,M$2)>DATE(2025,12,31),"",INDEX([1]A1!J$9:J$175,MATCH(1,--(RIGHT([1]A1!$B$9:$B$175,LEN([1]A1!$B$9:$B$175)-4)=$A4)*([1]A1!$C$9:$C$175=YEAR($F4)),0)))} -> 2.0931202e+08 | N4: {=IF(EDATE($F4,N$2)>DATE(2025,12,31),"",INDEX([1]A1!K$9:K$175,MATCH(1,--(RIGHT([1]A1!$B$9:$B$175,LEN([1]A1!$B$9:$B$175)-4)=$A4)*([1]A1!$C$9:$C$175=YEAR($F4)),0)))} -> 2.087931e+08 | ... FA4: {=IF(EDATE($F4,FA$2)>DATE(2025,12,31),"",INDEX([1]A1!EX$9:EX$175,MATCH(1,--(RIGHT([1]A1!$B$9:$B$175,LEN([1]A1!$B$9:$B$175)-4)=$A4)*([1]A1!$C$9:$C$175=YEAR($F4)),0)))}
A5: Professional Lines | B5: Net Written Premium | C5: All | D5: UW Year | E5: USD | F5: =EDATE(F4,12) -> 39448 | G5: {=IF(EDATE($F5,G$2)>DATE(2025,12,31),"",INDEX([1]A1!D$9:D$175,MATCH(1,--(RIGHT([1]A1!$B$9:$B$175,LEN([1]A1!$B$9:$B$175)-4)=$A5)*([1]A1!$C$9:$C$175=YEAR($F5)),0)))} -> 83119039 | H5: {=IF(EDATE($F5,H$2)>DATE(2025,12,31),"",INDEX([1]A1!E$9:E$175,MATCH(1,--(RIGHT([1]A1!$B$9:$B$175,LEN([1]A1!$B$9:$B$175)-4)=$A5)*([1]A1!$C$9:$C$175=YEAR($F5)),0)))} -> 2.2247764e+08 | I5: {=IF(EDATE($F5,I$2)>DATE(2025,12,31),"",INDEX([1]A1!F$9:F$175,MATCH(1,--(RIGHT([1]A1!$B$9:$B$175,LEN([1]A1!$B$9:$B$175)-4)=$A5)*([1]A1!$C$9:$C$175=YEAR($F5)),0)))} -> 2.5904988e+08 | J5: {=IF(EDATE($F5,J$2)>DATE(2025,12,31),"",INDEX([1]A1!G$9:G$175,MATCH(1,--(RIGHT([1]A1!$B$9:$B$175,LEN([1]A1!$B$9:$B$175)-4)=$A5)*([1]A1!$C$9:$C$175=YEAR($F5)),0)))} -> 2.6019818e+08 | K5: {=IF(EDATE($F5,K$2)>DATE(2025,12,31),"",INDEX([1]A1!H$9:H$175,MATCH(1,--(RIGHT([1]A1!$B$9:$B$175,LEN([1]A1!$B$9:$B$175)-4)=$A5)*([1]A1!$C$9:$C$175=YEAR($F5)),0)))} -> 2.6086502e+08 | L5: {=IF(EDATE($F5,L$2)>DATE(2025,12,31),"",INDEX([1]A1!I$9:I$175,MATCH(1,--(RIGHT([1]A1!$B$9:$B$175,LEN([1]A1!$B$9:$B$175)-4)=$A5)*([1]A1!$C$9:$C$175=YEAR($F5)),0)))} -> 2.6381638e+08 | M5: {=IF(EDATE($F5,M$2)>DATE(2025,12,31),"",INDEX([1]A1!J$9:J$175,MATCH(1,--(RIGHT([1]A1!$B$9:$B$175,LEN([1]A1!$B$9:$B$175)-4)=$A5)*([1]A1!$C$9:$C$175=YEAR($F5)),0)))} -> 2.6232004e+08 | N5: {=IF(EDATE($F5,N$2)>DATE(2025,12,31),"",INDEX([1]A1!K$9:K$175,MATCH(1,--(RIGHT([1]A1!$B$9:$B$175,LEN([1]A1!$B$9:$B$175)-4)=$A5)*([1]A1!$C$9:$C$175=YEAR($F5)),0)))} -> 2.6294334e+08 | ... FA5: {=IF(EDATE($F5,FA$2)>DATE(2025,12,31),"",INDEX([1]A1!EX$9:EX$175,MATCH(1,--(RIGHT([1]A1!$B$9:$B$175,LEN([1]A1!$B$9:$B$175)-4)=$A5)*([1]A1!$C$9:$C$175=YEAR($F5)),0)))}
A6: Professional Lines | B6: Net Written Premium | C6: All | D6: UW Year | E6: USD | F6: =EDATE(F5,12) -> 39814 | G6: {=IF(EDATE($F6,G$2)>DATE(2025,12,31),"",INDEX([1]A1!D$9:D$175,MATCH(1,--(RIGHT([1]A1!$B$9:$B$175,LEN([1]A1!$B$9:$B$175)-4)=$A6)*([1]A1!$C$9:$C$175=YEAR($F6)),0)))} -> 89116218 | H6: {=IF(EDATE($F6,H$2)>DATE(2025,12,31),"",INDEX([1]A1!E$9:E$175,MATCH(1,--(RIGHT([1]A1!$B$9:$B$175,LEN([1]A1!$B$9:$B$175)-4)=$A6)*([1]A1!$C$9:$C$175=YEAR($F6)),0)))} -> 2.5141306e+08 | I6: {=IF(EDATE($F6,I$2)>DATE(2025,12,31),"",INDEX([1]A1!F$9:F$175,MATCH(1,--(RIGHT([1]A1!$B$9:$B$175,LEN([1]A1!$B$9:$B$175)-4)=$A6)*([1]A1!$C$9:$C$175=YEAR($F6)),0)))} -> 2.9932596e+08 | J6: {=IF(EDATE($F6,J$2)>DATE(2025,12,31),"",INDEX([1]A1!G$9:G$175,MATCH(1,--(RIGHT([1]A1!$B$9:$B$175,LEN([1]A1!$B$9:$B$175)-4)=$A6)*([1]A1!$C$9:$C$175=YEAR($F6)),0)))} -> 3.0042299e+08 | K6: {=IF(EDATE($F6,K$2)>DATE(2025,12,31),"",INDEX([1]A1!H$9:H$175,MATCH(1,--(RIGHT([1]A1!$B$9:$B$175,LEN([1]A1!$B$9:$B$175)-4)=$A6)*([1]A1!$C$9:$C$175=YEAR($F6)),0)))} -> 3.0313412e+08 | L6: {=IF(EDATE($F6,L$2)>DATE(2025,12,31),"",INDEX([1]A1!I$9:I$175,MATCH(1,--(RIGHT([1]A1!$B$9:$B$175,LEN([1]A1!$B$9:$B$175)-4)=$A6)*([1]A1!$C$9:$C$175=YEAR($F6)),0)))} -> 3.0246351e+08 | M6: {=IF(EDATE($F6,M$2)>DATE(2025,12,31),"",INDEX([1]A1!J$9:J$175,MATCH(1,--(RIGHT([1]A1!$B$9:$B$175,LEN([1]A1!$B$9:$B$175)-4)=$A6)*([1]A1!$C$9:$C$175=YEAR($F6)),0)))} -> 3.0203602e+08 | N6: {=IF(EDATE($F6,N$2)>DATE(2025,12,31),"",INDEX([1]A1!K$9:K$175,MATCH(1,--(RIGHT([1]A1!$B$9:$B$175,LEN([1]A1!$B$9:$B$175)-4)=$A6)*([1]A1!$C$9:$C$175=YEAR($F6)),0)))} -> 3.0151872e+08 | ... FA6: {=IF(EDATE($F6,FA$2)>DATE(2025,12,31),"",INDEX([1]A1!EX$9:EX$175,MATCH(1,--(RIGHT([1]A1!$B$9:$B$175,LEN([1]A1!$B$9:$B$175)-4)=$A6)*([1]A1!$C$9:$C$175=YEAR($F6)),0)))}
A7: Professional Lines | B7: Net Written Premium | C7: All | D7: UW Year | E7: USD | F7: =EDATE(F6,12) -> 40179 | G7: {=IF(EDATE($F7,G$2)>DATE(2025,12,31),"",INDEX([1]A1!D$9:D$175,MATCH(1,--(RIGHT([1]A1!$B$9:$B$175,LEN([1]A1!$B$9:$B$175)-4)=$A7)*([1]A1!$C$9:$C$175=YEAR($F7)),0)))} -> 83916592 | H7: {=IF(EDATE($F7,H$2)>DATE(2025,12,31),"",INDEX([1]A1!E$9:E$175,MATCH(1,--(RIGHT([1]A1!$B$9:$B$175,LEN([1]A1!$B$9:$B$175)-4)=$A7)*([1]A1!$C$9:$C$175=YEAR($F7)),0)))} -> 2.4892461e+08 | I7: {=IF(EDATE($F7,I$2)>DATE(2025,12,31),"",INDEX([1]A1!F$9:F$175,MATCH(1,--(RIGHT([1]A1!$B$9:$B$175,LEN([1]A1!$B$9:$B$175)-4)=$A7)*([1]A1!$C$9:$C$175=YEAR($F7)),0)))} -> 3.0489379e+08 | J7: {=IF(EDATE($F7,J$2)>DATE(2025,12,31),"",INDEX([1]A1!G$9:G$175,MATCH(1,--(RIGHT([1]A1!$B$9:$B$175,LEN([1]A1!$B$9:$B$175)-4)=$A7)*([1]A1!$C$9:$C$175=YEAR($F7)),0)))} -> 3.0798751e+08 | K7: {=IF(EDATE($F7,K$2)>DATE(2025,12,31),"",INDEX([1]A1!H$9:H$175,MATCH(1,--(RIGHT([1]A1!$B$9:$B$175,LEN([1]A1!$B$9:$B$175)-4)=$A7)*([1]A1!$C$9:$C$175=YEAR($F7)),0)))} -> 3.1182156e+08 | L7: {=IF(EDATE($F7,L$2)>DATE(2025,12,31),"",INDEX([1]A1!I$9:I$175,MATCH(1,--(RIGHT([1]A1!$B$9:$B$175,LEN([1]A1!$B$9:$B$175)-4)=$A7)*([1]A1!$C$9:$C$175=YEAR($F7)),0)))} -> 3.1232055e+08 | M7: {=IF(EDATE($F7,M$2)>DATE(2025,12,31),"",INDEX([1]A1!J$9:J$175,MATCH(1,--(RIGHT([1]A1!$B$9:$B$175,LEN([1]A1!$B$9:$B$175)-4)=$A7)*([1]A1!$C$9:$C$175=YEAR($F7)),0)))} -> 3.1105141e+08 | N7: {=IF(EDATE($F7,N$2)>DATE(2025,12,31),"",INDEX([1]A1!K$9:K$175,MATCH(1,--(RIGHT([1]A1!$B$9:$B$175,LEN([1]A1!$B$9:$B$175)-4)=$A7)*([1]A1!$C$9:$C$175=YEAR($F7)),0)))} -> 3.1073259e+08 | ... FA7: {=IF(EDATE($F7,FA$2)>DATE(2025,12,31),"",INDEX([1]A1!EX$9:EX$175,MATCH(1,--(RIGHT([1]A1!$B$9:$B$175,LEN([1]A1!$B$9:$B$175)-4)=$A7)*([1]A1!$C$9:$C$175=YEAR($F7)),0)))}
A8: Professional Lines | B8: Net Written Premium | C8: All | D8: UW Year | E8: USD | F8: =EDATE(F7,12) -> 40544 | G8: {=IF(EDATE($F8,G$2)>DATE(2025,12,31),"",INDEX([1]A1!D$9:D$175,MATCH(1,--(RIGHT([1]A1!$B$9:$B$175,LEN([1]A1!$B$9:$B$175)-4)=$A8)*([1]A1!$C$9:$C$175=YEAR($F8)),0)))} -> 84620137 | H8: {=IF(EDATE($F8,H$2)>DATE(2025,12,31),"",INDEX([1]A1!E$9:E$175,MATCH(1,--(RIGHT([1]A1!$B$9:$B$175,LEN([1]A1!$B$9:$B$175)-4)=$A8)*([1]A1!$C$9:$C$175=YEAR($F8)),0)))} -> 2.4638227e+08 | I8: {=IF(EDATE($F8,I$2)>DATE(2025,12,31),"",INDEX([1]A1!F$9:F$175,MATCH(1,--(RIGHT([1]A1!$B$9:$B$175,LEN([1]A1!$B$9:$B$175)-4)=$A8)*([1]A1!$C$9:$C$175=YEAR($F8)),0)))} -> 3.0286946e+08 | J8: {=IF(EDATE($F8,J$2)>DATE(2025,12,31),"",INDEX([1]A1!G$9:G$175,MATCH(1,--(RIGHT([1]A1!$B$9:$B$175,LEN([1]A1!$B$9:$B$175)-4)=$A8)*([1]A1!$C$9:$C$175=YEAR($F8)),0)))} -> 3.0591714e+08 | K8: {=IF(EDATE($F8,K$2)>DATE(2025,12,31),"",INDEX([1]A1!H$9:H$175,MATCH(1,--(RIGHT([1]A1!$B$9:$B$175,LEN([1]A1!$B$9:$B$175)-4)=$A8)*([1]A1!$C$9:$C$175=YEAR($F8)),0)))} -> 3.0838051e+08 | L8: {=IF(EDATE($F8,L$2)>DATE(2025,12,31),"",INDEX([1]A1!I$9:I$175,MATCH(1,--(RIGHT([1]A1!$B$9:$B$175,LEN([1]A1!$B$9:$B$175)-4)=$A8)*([1]A1!$C$9:$C$175=YEAR($F8)),0)))} -> 3.0558168e+08 | M8: {=IF(EDATE($F8,M$2)>DATE(2025,12,31),"",INDEX([1]A1!J$9:J$175,MATCH(1,--(RIGHT([1]A1!$B$9:$B$175,LEN([1]A1!$B$9:$B$175)-4)=$A8)*([1]A1!$C$9:$C$175=YEAR($F8)),0)))} -> 3.0591437e+08 | N8: {=IF(EDATE($F8,N$2)>DATE(2025,12,31),"",INDEX([1]A1!K$9:K$175,MATCH(1,--(RIGHT([1]A1!$B$9:$B$175,LEN([1]A1!$B$9:$B$175)-4)=$A8)*([1]A1!$C$9:$C$175=YEAR($F8)),0)))} -> 3.0556627e+08 | ... FA8: {=IF(EDATE($F8,FA$2)>DATE(2025,12,31),"",INDEX([1]A1!EX$9:EX$175,MATCH(1,--(RIGHT([1]A1!$B$9:$B$175,LEN([1]A1!$B$9:$B$175)-4)=$A8)*([1]A1!$C$9:$C$175=YEAR($F8)),0)))}
A9: Professional Lines | B9: Net Written Premium | C9: All | D9: UW Year | E9: USD | F9: =EDATE(F8,12) -> 40909 | G9: {=IF(EDATE($F9,G$2)>DATE(2025,12,31),"",INDEX([1]A1!D$9:D$175,MATCH(1,--(RIGHT([1]A1!$B$9:$B$175,LEN([1]A1!$B$9:$B$175)-4)=$A9)*([1]A1!$C$9:$C$175=YEAR($F9)),0)))} -> 78571029 | H9: {=IF(EDATE($F9,H$2)>DATE(2025,12,31),"",INDEX([1]A1!E$9:E$175,MATCH(1,--(RIGHT([1]A1!$B$9:$B$175,LEN([1]A1!$B$9:$B$175)-4)=$A9)*([1]A1!$C$9:$C$175=YEAR($F9)),0)))} -> 3.0609356e+08 | I9: {=IF(EDATE($F9,I$2)>DATE(2025,12,31),"",INDEX([1]A1!F$9:F$175,MATCH(1,--(RIGHT([1]A1!$B$9:$B$175,LEN([1]A1!$B$9:$B$175)-4)=$A9)*([1]A1!$C$9:$C$175=YEAR($F9)),0)))} -> 3.1354283e+08 | J9: {=IF(EDATE($F9,J$2)>DATE(2025,12,31),"",INDEX([1]A1!G$9:G$175,MATCH(1,--(RIGHT([1]A1!$B$9:$B$175,LEN([1]A1!$B$9:$B$175)-4)=$A9)*([1]A1!$C$9:$C$175=YEAR($F9)),0)))} -> 3.1824168e+08 | K9: {=IF(EDATE($F9,K$2)>DATE(2025,12,31),"",INDEX([1]A1!H$9:H$175,MATCH(1,--(RIGHT([1]A1!$B$9:$B$175,LEN([1]A1!$B$9:$B$175)-4)=$A9)*([1]A1!$C$9:$C$175=YEAR($F9)),0)))} -> 3.1884369e+08 | L9: {=IF(EDATE($F9,L$2)>DATE(2025,12,31),"",INDEX([1]A1!I$9:I$175,MATCH(1,--(RIGHT([1]A1!$B$9:$B$175,LEN([1]A1!$B$9:$B$175)-4)=$A9)*([1]A1!$C$9:$C$175=YEAR($F9)),0)))} -> 3.1933202e+08 | M9: {=IF(EDATE($F9,M$2)>DATE(2025,12,31),"",INDEX([1]A1!J$9:J$175,MATCH(1,--(RIGHT([1]A1!$B$9:$B$175,LEN([1]A1!$B$9:$B$175)-4)=$A9)*([1]A1!$C$9:$C$175=YEAR($F9)),0)))} -> 3.1930067e+08 | N9: {=IF(EDATE($F9,N$2)>DATE(2025,12,31),"",INDEX([1]A1!K$9:K$175,MATCH(1,--(RIGHT([1]A1!$B$9:$B$175,LEN([1]A1!$B$9:$B$175)-4)=$A9)*([1]A1!$C$9:$C$175=YEAR($F9)),0)))} -> 3.1952487e+08 | ... FA9: {=IF(EDATE($F9,FA$2)>DATE(2025,12,31),"",INDEX([1]A1!EX$9:EX$175,MATCH(1,--(RIGHT([1]A1!$B$9:$B$175,LEN([1]A1!$B$9:$B$175)-4)=$A9)*([1]A1!$C$9:$C$175=YEAR($F9)),0)))}
A10: Professional Lines | B10: Net Written Premium | C10: All | D10: UW Year | E10: USD | F10: =EDATE(F9,12) -> 41275 | G10: {=IF(EDATE($F10,G$2)>DATE(2025,12,31),"",INDEX([1]A1!D$9:D$175,MATCH(1,--(RIGHT([1]A1!$B$9:$B$175,LEN([1]A1!$B$9:$B$175)-4)=$A10)*([1]A1!$C$9:$C$175=YEAR($F10)),0)))} -> 2.0895985e+08 | H10: {=IF(EDATE($F10,H$2)>DATE(2025,12,31),"",INDEX([1]A1!E$9:E$175,MATCH(1,--(RIGHT([1]A1!$B$9:$B$175,LEN([1]A1!$B$9:$B$175)-4)=$A10)*([1]A1!$C$9:$C$175=YEAR($F10)),0)))} -> 4.1478955e+08 | I10: {=IF(EDATE($F10,I$2)>DATE(2025,12,31),"",INDEX([1]A1!F$9:F$175,MATCH(1,--(RIGHT([1]A1!$B$9:$B$175,LEN([1]A1!$B$9:$B$175)-4)=$A10)*([1]A1!$C$9:$C$175=YEAR($F10)),0)))} -> 4.1044628e+08 | J10: {=IF(EDATE($F10,J$2)>DATE(2025,12,31),"",INDEX([1]A1!G$9:G$175,MATCH(1,--(RIGHT([1]A1!$B$9:$B$175,LEN([1]A1!$B$9:$B$175)-4)=$A10)*([1]A1!$C$9:$C$175=YEAR($F10)),0)))} -> 4.1445328e+08 | K10: {=IF(EDATE($F10,K$2)>DATE(2025,12,31),"",INDEX([1]A1!H$9:H$175,MATCH(1,--(RIGHT([1]A1!$B$9:$B$175,LEN([1]A1!$B$9:$B$175)-4)=$A10)*([1]A1!$C$9:$C$175=YEAR($F10)),0)))} -> 4.1756304e+08 | L10: {=IF(EDATE($F10,L$2)>DATE(2025,12,31),"",INDEX([1]A1!I$9:I$175,MATCH(1,--(RIGHT([1]A1!$B$9:$B$175,LEN([1]A1!$B$9:$B$175)-4)=$A10)*([1]A1!$C$9:$C$175=YEAR($F10)),0)))} -> 4.1837472e+08 | M10: {=IF(EDATE($F10,M$2)>DATE(2025,12,31),"",INDEX([1]A1!J$9:J$175,MATCH(1,--(RIGHT([1]A1!$B$9:$B$175,LEN([1]A1!$B$9:$B$175)-4)=$A10)*([1]A1!$C$9:$C$175=YEAR($F10)),0)))} -> 4.1754281e+08 | N10: {=IF(EDATE($F10,N$2)>DATE(2025,12,31),"",INDEX([1]A1!K$9:K$175,MATCH(1,--(RIGHT([1]A1!$B$9:$B$175,LEN([1]A1!$B$9:$B$175)-4)=$A10)*([1]A1!$C$9:$C$175=YEAR($F10)),0)))} -> 4.1783407e+08 | ... FA10: {=IF(EDATE($F10,FA$2)>DATE(2025,12,31),"",INDEX([1]A1!EX$9:EX$175,MATCH(1,--(RIGHT([1]A1!$B$9:$B$175,LEN([1]A1!$B$9:$B$175)-4)=$A10)*([1]A1!$C$9:$C$175=YEAR($F10)),0)))}
A11: Professional Lines | B11: Net Written Premium | C11: All | D11: UW Year | E11: USD | F11: =EDATE(F10,12) -> 41640 | G11: {=IF(EDATE($F11,G$2)>DATE(2025,12,31),"",INDEX([1]A1!D$9:D$175,MATCH(1,--(RIGHT([1]A1!$B$9:$B$175,LEN([1]A1!$B$9:$B$175)-4)=$A11)*([1]A1!$C$9:$C$175=YEAR($F11)),0)))} -> 1.7253629e+08 | H11: {=IF(EDATE($F11,H$2)>DATE(2025,12,31),"",INDEX([1]A1!E$9:E$175,MATCH(1,--(RIGHT([1]A1!$B$9:$B$175,LEN([1]A1!$B$9:$B$175)-4)=$A11)*([1]A1!$C$9:$C$175=YEAR($F11)),0)))} -> 2.4663313e+08 | I11: {=IF(EDATE($F11,I$2)>DATE(2025,12,31),"",INDEX([1]A1!F$9:F$175,MATCH(1,--(RIGHT([1]A1!$B$9:$B$175,LEN([1]A1!$B$9:$B$175)-4)=$A11)*([1]A1!$C$9:$C$175=YEAR($F11)),0)))} -> 2.3966737e+08 | J11: {=IF(EDATE($F11,J$2)>DATE(2025,12,31),"",INDEX([1]A1!G$9:G$175,MATCH(1,--(RIGHT([1]A1!$B$9:$B$175,LEN([1]A1!$B$9:$B$175)-4)=$A11)*([1]A1!$C$9:$C$175=YEAR($F11)),0)))} -> 2.4163005e+08 | K11: {=IF(EDATE($F11,K$2)>DATE(2025,12,31),"",INDEX([1]A1!H$9:H$175,MATCH(1,--(RIGHT([1]A1!$B$9:$B$175,LEN([1]A1!$B$9:$B$175)-4)=$A11)*([1]A1!$C$9:$C$175=YEAR($F11)),0)))} -> 2.4354935e+08 | L11: {=IF(EDATE($F11,L$2)>DATE(2025,12,31),"",INDEX([1]A1!I$9:I$175,MATCH(1,--(RIGHT([1]A1!$B$9:$B$175,LEN([1]A1!$B$9:$B$175)-4)=$A11)*([1]A1!$C$9:$C$175=YEAR($F11)),0)))} -> 2.4279856e+08 | M11: {=IF(EDATE($F11,M$2)>DATE(2025,12,31),"",INDEX([1]A1!J$9:J$175,MATCH(1,--(RIGHT([1]A1!$B$9:$B$175,LEN([1]A1!$B$9:$B$175)-4)=$A11)*([1]A1!$C$9:$C$175=YEAR($F11)),0)))} -> 2.4258029e+08 | N11: {=IF(EDATE($F11,N$2)>DATE(2025,12,31),"",INDEX([1]A1!K$9:K$175,MATCH(1,--(RIGHT([1]A1!$B$9:$B$175,LEN([1]A1!$B$9:$B$175)-4)=$A11)*([1]A1!$C$9:$C$175=YEAR($F11)),0)))} -> 2.4278028e+08 | ... FA11: {=IF(EDATE($F11,FA$2)>DATE(2025,12,31),"",INDEX([1]A1!EX$9:EX$175,MATCH(1,--(RIGHT([1]A1!$B$9:$B$175,LEN([1]A1!$B$9:$B$175)-4)=$A11)*([1]A1!$C$9:$C$175=YEAR($F11)),0)))}
A12: Professional Lines | B12: Net Written Premium | C12: All | D12: UW Year | E12: USD | F12: =EDATE(F11,12) -> 42005 | G12: {=IF(EDATE($F12,G$2)>DATE(2025,12,31),"",INDEX([1]A1!D$9:D$175,MATCH(1,--(RIGHT([1]A1!$B$9:$B$175,LEN([1]A1!$B$9:$B$175)-4)=$A12)*([1]A1!$C$9:$C$175=YEAR($F12)),0)))} -> 1.8711415e+08 | H12: {=IF(EDATE($F12,H$2)>DATE(2025,12,31),"",INDEX([1]A1!E$9:E$175,MATCH(1,--(RIGHT([1]A1!$B$9:$B$175,LEN([1]A1!$B$9:$B$175)-4)=$A12)*([1]A1!$C$9:$C$175=YEAR($F12)),0)))} -> 2.7778126e+08 | I12: {=IF(EDATE($F12,I$2)>DATE(2025,12,31),"",INDEX([1]A1!F$9:F$175,MATCH(1,--(RIGHT([1]A1!$B$9:$B$175,LEN([1]A1!$B$9:$B$175)-4)=$A12)*([1]A1!$C$9:$C$175=YEAR($F12)),0)))} -> 2.7361984e+08 | J12: {=IF(EDATE($F12,J$2)>DATE(2025,12,31),"",INDEX([1]A1!G$9:G$175,MATCH(1,--(RIGHT([1]A1!$B$9:$B$175,LEN([1]A1!$B$9:$B$175)-4)=$A12)*([1]A1!$C$9:$C$175=YEAR($F12)),0)))} -> 2.7223321e+08 | K12: {=IF(EDATE($F12,K$2)>DATE(2025,12,31),"",INDEX([1]A1!H$9:H$175,MATCH(1,--(RIGHT([1]A1!$B$9:$B$175,LEN([1]A1!$B$9:$B$175)-4)=$A12)*([1]A1!$C$9:$C$175=YEAR($F12)),0)))} -> 2.7319895e+08 | L12: {=IF(EDATE($F12,L$2)>DATE(2025,12,31),"",INDEX([1]A1!I$9:I$175,MATCH(1,--(RIGHT([1]A1!$B$9:$B$175,LEN([1]A1!$B$9:$B$175)-4)=$A12)*([1]A1!$C$9:$C$175=YEAR($F12)),0)))} -> 2.7394789e+08 | M12: {=IF(EDATE($F12,M$2)>DATE(2025,12,31),"",INDEX([1]A1!J$9:J$175,MATCH(1,--(RIGHT([1]A1!$B$9:$B$175,LEN([1]A1!$B$9:$B$175)-4)=$A12)*([1]A1!$C$9:$C$175=YEAR($F12)),0)))} -> 2.7466413e+08 | N12: {=IF(EDATE($F12,N$2)>DATE(2025,12,31),"",INDEX([1]A1!K$9:K$175,MATCH(1,--(RIGHT([1]A1!$B$9:$B$175,LEN([1]A1!$B$9:$B$175)-4)=$A12)*([1]A1!$C$9:$C$175=YEAR($F12)),0)))} -> 2.7499626e+08 | ... FA12: {=IF(EDATE($F12,FA$2)>DATE(2025,12,31),"",INDEX([1]A1!EX$9:EX$175,MATCH(1,--(RIGHT([1]A1!$B$9:$B$175,LEN([1]A1!$B$9:$B$175)-4)=$A12)*([1]A1!$C$9:$C$175=YEAR($F12)),0)))}
A13: Professional Lines | B13: Net Written Premium | C13: All | D13: UW Year | E13: USD | F13: =EDATE(F12,12) -> 42370 | G13: {=IF(EDATE($F13,G$2)>DATE(2025,12,31),"",INDEX([1]A1!D$9:D$175,MATCH(1,--(RIGHT([1]A1!$B$9:$B$175,LEN([1]A1!$B$9:$B$175)-4)=$A13)*([1]A1!$C$9:$C$175=YEAR($F13)),0)))} -> 2.2105328e+08 | H13: {=IF(EDATE($F13,H$2)>DATE(2025,12,31),"",INDEX([1]A1!E$9:E$175,MATCH(1,--(RIGHT([1]A1!$B$9:$B$175,LEN([1]A1!$B$9:$B$175)-4)=$A13)*([1]A1!$C$9:$C$175=YEAR($F13)),0)))} -> 2.5465534e+08 | I13: {=IF(EDATE($F13,I$2)>DATE(2025,12,31),"",INDEX([1]A1!F$9:F$175,MATCH(1,--(RIGHT([1]A1!$B$9:$B$175,LEN([1]A1!$B$9:$B$175)-4)=$A13)*([1]A1!$C$9:$C$175=YEAR($F13)),0)))} -> 2.5428519e+08 | J13: {=IF(EDATE($F13,J$2)>DATE(2025,12,31),"",INDEX([1]A1!G$9:G$175,MATCH(1,--(RIGHT([1]A1!$B$9:$B$175,LEN([1]A1!$B$9:$B$175)-4)=$A13)*([1]A1!$C$9:$C$175=YEAR($F13)),0)))} -> 2.5634106e+08 | K13: {=IF(EDATE($F13,K$2)>DATE(2025,12,31),"",INDEX([1]A1!H$9:H$175,MATCH(1,--(RIGHT([1]A1!$B$9:$B$175,LEN([1]A1!$B$9:$B$175)-4)=$A13)*([1]A1!$C$9:$C$175=YEAR($F13)),0)))} -> 2.579356e+08 | L13: {=IF(EDATE($F13,L$2)>DATE(2025,12,31),"",INDEX([1]A1!I$9:I$175,MATCH(1,--(RIGHT([1]A1!$B$9:$B$175,LEN([1]A1!$B$9:$B$175)-4)=$A13)*([1]A1!$C$9:$C$175=YEAR($F13)),0)))} -> 2.5813212e+08 | M13: {=IF(EDATE($F13,M$2)>DATE(2025,12,31),"",INDEX([1]A1!J$9:J$175,MATCH(1,--(RIGHT([1]A1!$B$9:$B$175,LEN([1]A1!$B$9:$B$175)-4)=$A13)*([1]A1!$C$9:$C$175=YEAR($F13)),0)))} -> 2.5820069e+08 | N13: {=IF(EDATE($F13,N$2)>DATE(2025,12,31),"",INDEX([1]A1!K$9:K$175,MATCH(1,--(RIGHT([1]A1!$B$9:$B$175,LEN([1]A1!$B$9:$B$175)-4)=$A13)*([1]A1!$C$9:$C$175=YEAR($F13)),0)))} -> 2.584015e+08 | ... FA13: {=IF(EDATE($F13,FA$2)>DATE(2025,12,31),"",INDEX([1]A1!EX$9:EX$175,MATCH(1,--(RIGHT([1]A1!$B$9:$B$175,LEN([1]A1!$B$9:$B$175)-4)=$A13)*([1]A1!$C$9:$C$175=YEAR($F13)),0)))}
A14: Professional Lines | B14: Net Written Premium | C14: All | D14: UW Year | E14: USD | F14: =EDATE(F13,12) -> 42736 | G14: {=IF(EDATE($F14,G$2)>DATE(2025,12,31),"",INDEX([1]A1!D$9:D$175,MATCH(1,--(RIGHT([1]A1!$B$9:$B$175,LEN([1]A1!$B$9:$B$175)-4)=$A14)*([1]A1!$C$9:$C$175=YEAR($F14)),0)))} -> 2.2514495e+08 | H14: {=IF(EDATE($F14,H$2)>DATE(2025,12,31),"",INDEX([1]A1!E$9:E$175,MATCH(1,--(RIGHT([1]A1!$B$9:$B$175,LEN([1]A1!$B$9:$B$175)-4)=$A14)*([1]A1!$C$9:$C$175=YEAR($F14)),0)))} -> 2.5374203e+08 | I14: {=IF(EDATE($F14,I$2)>DATE(2025,12,31),"",INDEX([1]A1!F$9:F$175,MATCH(1,--(RIGHT([1]A1!$B$9:$B$175,LEN([1]A1!$B$9:$B$175)-4)=$A14)*([1]A1!$C$9:$C$175=YEAR($F14)),0)))} -> 2.6124036e+08 | J14: {=IF(EDATE($F14,J$2)>DATE(2025,12,31),"",INDEX([1]A1!G$9:G$175,MATCH(1,--(RIGHT([1]A1!$B$9:$B$175,LEN([1]A1!$B$9:$B$175)-4)=$A14)*([1]A1!$C$9:$C$175=YEAR($F14)),0)))} -> 2.604496e+08 | K14: {=IF(EDATE($F14,K$2)>DATE(2025,12,31),"",INDEX([1]A1!H$9:H$175,MATCH(1,--(RIGHT([1]A1!$B$9:$B$175,LEN([1]A1!$B$9:$B$175)-4)=$A14)*([1]A1!$C$9:$C$175=YEAR($F14)),0)))} -> 2.6232945e+08 | L14: {=IF(EDATE($F14,L$2)>DATE(2025,12,31),"",INDEX([1]A1!I$9:I$175,MATCH(1,--(RIGHT([1]A1!$B$9:$B$175,LEN([1]A1!$B$9:$B$175)-4)=$A14)*([1]A1!$C$9:$C$175=YEAR($F14)),0)))} -> 2.6279266e+08 | M14: {=IF(EDATE($F14,M$2)>DATE(2025,12,31),"",INDEX([1]A1!J$9:J$175,MATCH(1,--(RIGHT([1]A1!$B$9:$B$175,LEN([1]A1!$B$9:$B$175)-4)=$A14)*([1]A1!$C$9:$C$175=YEAR($F14)),0)))} -> 2.6265518e+08 | N14: {=IF(EDATE($F14,N$2)>DATE(2025,12,31),"",INDEX([1]A1!K$9:K$175,MATCH(1,--(RIGHT([1]A1!$B$9:$B$175,LEN([1]A1!$B$9:$B$175)-4)=$A14)*([1]A1!$C$9:$C$175=YEAR($F14)),0)))} -> 2.6289769e+08 | ... FA14: {=IF(EDATE($F14,FA$2)>DATE(2025,12,31),"",INDEX([1]A1!EX$9:EX$175,MATCH(1,--(RIGHT([1]A1!$B$9:$B$175,LEN([1]A1!$B$9:$B$175)-4)=$A14)*([1]A1!$C$9:$C$175=YEAR($F14)),0)))}
A15: Professional Lines | B15: Net Written Premium | C15: All | D15: UW Year | E15: USD | F15: =EDATE(F14,12) -> 43101 | G15: {=IF(EDATE($F15,G$2)>DATE(2025,12,31),"",INDEX([1]A1!D$9:D$175,MATCH(1,--(RIGHT([1]A1!$B$9:$B$175,LEN([1]A1!$B$9:$B$175)-4)=$A15)*([1]A1!$C$9:$C$175=YEAR($F15)),0)))} -> 2.5081672e+08 | H15: {=IF(EDATE($F15,H$2)>DATE(2025,12,31),"",INDEX([1]A1!E$9:E$175,MATCH(1,--(RIGHT([1]A1!$B$9:$B$175,LEN([1]A1!$B$9:$B$175)-4)=$A15)*([1]A1!$C$9:$C$175=YEAR($F15)),0)))} -> 2.726728e+08 | I15: {=IF(EDATE($F15,I$2)>DATE(2025,12,31),"",INDEX([1]A1!F$9:F$175,MATCH(1,--(RIGHT([1]A1!$B$9:$B$175,LEN([1]A1!$B$9:$B$175)-4)=$A15)*([1]A1!$C$9:$C$175=YEAR($F15)),0)))} -> 2.8349804e+08 | J15: {=IF(EDATE($F15,J$2)>DATE(2025,12,31),"",INDEX([1]A1!G$9:G$175,MATCH(1,--(RIGHT([1]A1!$B$9:$B$175,LEN([1]A1!$B$9:$B$175)-4)=$A15)*([1]A1!$C$9:$C$175=YEAR($F15)),0)))} -> 2.8762692e+08 | K15: {=IF(EDATE($F15,K$2)>DATE(2025,12,31),"",INDEX([1]A1!H$9:H$175,MATCH(1,--(RIGHT([1]A1!$B$9:$B$175,LEN([1]A1!$B$9:$B$175)-4)=$A15)*([1]A1!$C$9:$C$175=YEAR($F15)),0)))} -> 2.8856511e+08 | L15: {=IF(EDATE($F15,L$2)>DATE(2025,12,31),"",INDEX([1]A1!I$9:I$175,MATCH(1,--(RIGHT([1]A1!$B$9:$B$175,LEN([1]A1!$B$9:$B$175)-4)=$A15)*([1]A1!$C$9:$C$175=YEAR($F15)),0)))} -> 2.8989975e+08 | M15: {=IF(EDATE($F15,M$2)>DATE(2025,12,31),"",INDEX([1]A1!J$9:J$175,MATCH(1,--(RIGHT([1]A1!$B$9:$B$175,LEN([1]A1!$B$9:$B$175)-4)=$A15)*([1]A1!$C$9:$C$175=YEAR($F15)),0)))} -> 2.9011652e+08 | N15: {=IF(EDATE($F15,N$2)>DATE(2025,12,31),"",INDEX([1]A1!K$9:K$175,MATCH(1,--(RIGHT([1]A1!$B$9:$B$175,LEN([1]A1!$B$9:$B$175)-4)=$A15)*([1]A1!$C$9:$C$175=YEAR($F15)),0)))} -> 2.9016376e+08 | ... FA15: {=IF(EDATE($F15,FA$2)>DATE(2025,12,31),"",INDEX([1]A1!EX$9:EX$175,MATCH(1,--(RIGHT([1]A1!$B$9:$B$175,LEN([1]A1!$B$9:$B$175)-4)=$A15)*([1]A1!$C$9:$C$175=YEAR($F15)),0)))}
... A22: Professional Lines | B22: Net Written Premium | C22: All | D22: UW Year | E22: USD | F22: =EDATE(F21,12) -> 45658 | G22: {=IF(EDATE($F22,G$2)>DATE(2025,12,31),"",INDEX([1]A1!D$9:D$175,MATCH(1,--(RIGHT([1]A1!$B$9:$B$175,LEN([1]A1!$B$9:$B$175)-4)=$A22)*([1]A1!$C$9:$C$175=YEAR($F22)),0)))} -> 2.0142324e+08 | H22: {=IF(EDATE($F22,H$2)>DATE(2025,12,31),"",INDEX([1]A1!E$9:E$175,MATCH(1,--(RIGHT([1]A1!$B$9:$B$175,LEN([1]A1!$B$9:$B$175)-4)=$A22)*([1]A1!$C$9:$C$175=YEAR($F22)),0)))} | I22: {=IF(EDATE($F22,I$2)>DATE(2025,12,31),"",INDEX([1]A1!F$9:F$175,MATCH(1,--(RIGHT([1]A1!$B$9:$B$175,LEN([1]A1!$B$9:$B$175)-4)=$A22)*([1]A1!$C$9:$C$175=YEAR($F22)),0)))} | J22: {=IF(EDATE($F22,J$2)>DATE(2025,12,31),"",INDEX([1]A1!G$9:G$175,MATCH(1,--(RIGHT([1]A1!$B$9:$B$175,LEN([1]A1!$B$9:$B$175)-4)=$A22)*([1]A1!$C$9:$C$175=YEAR($F22)),0)))} | K22: {=IF(EDATE($F22,K$2)>DATE(2025,12,31),"",INDEX([1]A1!H$9:H$175,MATCH(1,--(RIGHT([1]A1!$B$9:$B$175,LEN([1]A1!$B$9:$B$175)-4)=$A22)*([1]A1!$C$9:$C$175=YEAR($F22)),0)))} | L22: {=IF(EDATE($F22,L$2)>DATE(2025,12,31),"",INDEX([1]A1!I$9:I$175,MATCH(1,--(RIGHT([1]A1!$B$9:$B$175,LEN([1]A1!$B$9:$B$175)-4)=$A22)*([1]A1!$C$9:$C$175=YEAR($F22)),0)))} | M22: {=IF(EDATE($F22,M$2)>DATE(2025,12,31),"",INDEX([1]A1!J$9:J$175,MATCH(1,--(RIGHT([1]A1!$B$9:$B$175,LEN([1]A1!$B$9:$B$175)-4)=$A22)*([1]A1!$C$9:$C$175=YEAR($F22)),0)))} | N22: {=IF(EDATE($F22,N$2)>DATE(2025,12,31),"",INDEX([1]A1!K$9:K$175,MATCH(1,--(RIGHT([1]A1!$B$9:$B$175,LEN([1]A1!$B$9:$B$175)-4)=$A22)*([1]A1!$C$9:$C$175=YEAR($F22)),0)))} | ... FA22: {=IF(EDATE($F22,FA$2)>DATE(2025,12,31),"",INDEX([1]A1!EX$9:EX$175,MATCH(1,--(RIGHT([1]A1!$B$9:$B$175,LEN([1]A1!$B$9:$B$175)-4)=$A22)*([1]A1!$C$9:$C$175=YEAR($F22)),0)))}
A24: Liability | B24: Net Written Premium | C24: All | D24: UW Year | E24: USD | F24: =triangle_start_date -> 38718 | G24: {=IF(EDATE($F24,G$2)>DATE(2025,12,31),"",INDEX([1]A1!D$9:D$175,MATCH(1,--(RIGHT([1]A1!$B$9:$B$175,LEN([1]A1!$B$9:$B$175)-4)=$A24)*([1]A1!$C$9:$C$175=YEAR($F24)),0)))} -> 69065431 | H24: {=IF(EDATE($F24,H$2)>DATE(2025,12,31),"",INDEX([1]A1!E$9:E$175,MATCH(1,--(RIGHT([1]A1!$B$9:$B$175,LEN([1]A1!$B$9:$B$175)-4)=$A24)*([1]A1!$C$9:$C$175=YEAR($F24)),0)))} -> 1.3355061e+08 | I24: {=IF(EDATE($F24,I$2)>DATE(2025,12,31),"",INDEX([1]A1!F$9:F$175,MATCH(1,--(RIGHT([1]A1!$B$9:$B$175,LEN([1]A1!$B$9:$B$175)-4)=$A24)*([1]A1!$C$9:$C$175=YEAR($F24)),0)))} -> 1.4327316e+08 | J24: {=IF(EDATE($F24,J$2)>DATE(2025,12,31),"",INDEX([1]A1!G$9:G$175,MATCH(1,--(RIGHT([1]A1!$B$9:$B$175,LEN([1]A1!$B$9:$B$175)-4)=$A24)*([1]A1!$C$9:$C$175=YEAR($F24)),0)))} -> 1.4434176e+08 | K24: {=IF(EDATE($F24,K$2)>DATE(2025,12,31),"",INDEX([1]A1!H$9:H$175,MATCH(1,--(RIGHT([1]A1!$B$9:$B$175,LEN([1]A1!$B$9:$B$175)-4)=$A24)*([1]A1!$C$9:$C$175=YEAR($F24)),0)))} -> 1.428303e+08 | L24: {=IF(EDATE($F24,L$2)>DATE(2025,12,31),"",INDEX([1]A1!I$9:I$175,MATCH(1,--(RIGHT([1]A1!$B$9:$B$175,LEN([1]A1!$B$9:$B$175)-4)=$A24)*([1]A1!$C$9:$C$175=YEAR($F24)),0)))} -> 1.428155e+08 | M24: {=IF(EDATE($F24,M$2)>DATE(2025,12,31),"",INDEX([1]A1!J$9:J$175,MATCH(1,--(RIGHT([1]A1!$B$9:$B$175,LEN([1]A1!$B$9:$B$175)-4)=$A24)*([1]A1!$C$9:$C$175=YEAR($F24)),0)))} -> 1.4287384e+08 | N24: {=IF(EDATE($F24,N$2)>DATE(2025,12,31),"",INDEX([1]A1!K$9:K$175,MATCH(1,--(RIGHT([1]A1!$B$9:$B$175,LEN([1]A1!$B$9:$B$175)-4)=$A24)*([1]A1!$C$9:$C$175=YEAR($F24)),0)))} -> 1.4323372e+08 | ... FA24: {=IF(EDATE($F24,FA$2)>DATE(2025,12,31),"",INDEX([1]A1!EX$9:EX$175,MATCH(1,--(RIGHT([1]A1!$B$9:$B$175,LEN([1]A1!$B$9:$B$175)-4)=$A24)*([1]A1!$C$9:$C$175=YEAR($F24)),0)))}
A25: Liability | B25: Net Written Premium | C25: All | D25: UW Year | E25: USD | F25: =EDATE(F24,12) -> 39083 | G25: {=IF(EDATE($F25,G$2)>DATE(2025,12,31),"",INDEX([1]A1!D$9:D$175,MATCH(1,--(RIGHT([1]A1!$B$9:$B$175,LEN([1]A1!$B$9:$B$175)-4)=$A25)*([1]A1!$C$9:$C$175=YEAR($F25)),0)))} -> 72721921 | H25: {=IF(EDATE($F25,H$2)>DATE(2025,12,31),"",INDEX([1]A1!E$9:E$175,MATCH(1,--(RIGHT([1]A1!$B$9:$B$175,LEN([1]A1!$B$9:$B$175)-4)=$A25)*([1]A1!$C$9:$C$175=YEAR($F25)),0)))} -> 1.4357973e+08 | I25: {=IF(EDATE($F25,I$2)>DATE(2025,12,31),"",INDEX([1]A1!F$9:F$175,MATCH(1,--(RIGHT([1]A1!$B$9:$B$175,LEN([1]A1!$B$9:$B$175)-4)=$A25)*([1]A1!$C$9:$C$175=YEAR($F25)),0)))} -> 1.5503057e+08 | J25: {=IF(EDATE($F25,J$2)>DATE(2025,12,31),"",INDEX([1]A1!G$9:G$175,MATCH(1,--(RIGHT([1]A1!$B$9:$B$175,LEN([1]A1!$B$9:$B$175)-4)=$A25)*([1]A1!$C$9:$C$175=YEAR($F25)),0)))} -> 1.5666513e+08 | K25: {=IF(EDATE($F25,K$2)>DATE(2025,12,31),"",INDEX([1]A1!H$9:H$175,MATCH(1,--(RIGHT([1]A1!$B$9:$B$175,LEN([1]A1!$B$9:$B$175)-4)=$A25)*([1]A1!$C$9:$C$175=YEAR($F25)),0)))} -> 1.5694078e+08 | L25: {=IF(EDATE($F25,L$2)>DATE(2025,12,31),"",INDEX([1]A1!I$9:I$175,MATCH(1,--(RIGHT([1]A1!$B$9:$B$175,LEN([1]A1!$B$9:$B$175)-4)=$A25)*([1]A1!$C$9:$C$175=YEAR($F25)),0)))} -> 1.5692173e+08 | M25: {=IF(EDATE($F25,M$2)>DATE(2025,12,31),"",INDEX([1]A1!J$9:J$175,MATCH(1,--(RIGHT([1]A1!$B$9:$B$175,LEN([1]A1!$B$9:$B$175)-4)=$A25)*([1]A1!$C$9:$C$175=YEAR($F25)),0)))} -> 1.5697278e+08 | N25: {=IF(EDATE($F25,N$2)>DATE(2025,12,31),"",INDEX([1]A1!K$9:K$175,MATCH(1,--(RIGHT([1]A1!$B$9:$B$175,LEN([1]A1!$B$9:$B$175)-4)=$A25)*([1]A1!$C$9:$C$175=YEAR($F25)),0)))} -> 1.5707628e+08 | ... FA25: {=IF(EDATE($F25,FA$2)>DATE(2025,12,31),"",INDEX([1]A1!EX$9:EX$175,MATCH(1,--(RIGHT([1]A1!$B$9:$B$175,LEN([1]A1!$B$9:$B$175)-4)=$A25)*([1]A1!$C$9:$C$175=YEAR($F25)),0)))}
A26: Liability | B26: Net Written Premium | C26: All | D26: UW Year | E26: USD | F26: =EDATE(F25,12) -> 39448 | G26: {=IF(EDATE($F26,G$2)>DATE(2025,12,31),"",INDEX([1]A1!D$9:D$175,MATCH(1,--(RIGHT([1]A1!$B$9:$B$175,LEN([1]A1!$B$9:$B$175)-4)=$A26)*([1]A1!$C$9:$C$175=YEAR($F26)),0)))} -> 72553331 | H26: {=IF(EDATE($F26,H$2)>DATE(2025,12,31),"",INDEX([1]A1!E$9:E$175,MATCH(1,--(RIGHT([1]A1!$B$9:$B$175,LEN([1]A1!$B$9:$B$175)-4)=$A26)*([1]A1!$C$9:$C$175=YEAR($F26)),0)))} -> 1.390936e+08 | I26: {=IF(EDATE($F26,I$2)>DATE(2025,12,31),"",INDEX([1]A1!F$9:F$175,MATCH(1,--(RIGHT([1]A1!$B$9:$B$175,LEN([1]A1!$B$9:$B$175)-4)=$A26)*([1]A1!$C$9:$C$175=YEAR($F26)),0)))} -> 1.4164443e+08 | J26: {=IF(EDATE($F26,J$2)>DATE(2025,12,31),"",INDEX([1]A1!G$9:G$175,MATCH(1,--(RIGHT([1]A1!$B$9:$B$175,LEN([1]A1!$B$9:$B$175)-4)=$A26)*([1]A1!$C$9:$C$175=YEAR($F26)),0)))} -> 1.4224735e+08 | K26: {=IF(EDATE($F26,K$2)>DATE(2025,12,31),"",INDEX([1]A1!H$9:H$175,MATCH(1,--(RIGHT([1]A1!$B$9:$B$175,LEN([1]A1!$B$9:$B$175)-4)=$A26)*([1]A1!$C$9:$C$175=YEAR($F26)),0)))} -> 1.442114e+08 | L26: {=IF(EDATE($F26,L$2)>DATE(2025,12,31),"",INDEX([1]A1!I$9:I$175,MATCH(1,--(RIGHT([1]A1!$B$9:$B$175,LEN([1]A1!$B$9:$B$175)-4)=$A26)*([1]A1!$C$9:$C$175=YEAR($F26)),0)))} -> 1.4500263e+08 | M26: {=IF(EDATE($F26,M$2)>DATE(2025,12,31),"",INDEX([1]A1!J$9:J$175,MATCH(1,--(RIGHT([1]A1!$B$9:$B$175,LEN([1]A1!$B$9:$B$175)-4)=$A26)*([1]A1!$C$9:$C$175=YEAR($F26)),0)))} -> 1.451363e+08 | N26: {=IF(EDATE($F26,N$2)>DATE(2025,12,31),"",INDEX([1]A1!K$9:K$175,MATCH(1,--(RIGHT([1]A1!$B$9:$B$175,LEN([1]A1!$B$9:$B$175)-4)=$A26)*([1]A1!$C$9:$C$175=YEAR($F26)),0)))} -> 1.4517889e+08 | ... FA26: {=IF(EDATE($F26,FA$2)>DATE(2025,12,31),"",INDEX([1]A1!EX$9:EX$175,MATCH(1,--(RIGHT([1]A1!$B$9:$B$175,LEN([1]A1!$B$9:$B$175)-4)=$A26)*([1]A1!$C$9:$C$175=YEAR($F26)),0)))}
A27: Liability | B27: Net Written Premium | C27: All | D27: UW Year | E27: USD | F27: =EDATE(F26,12) -> 39814 | G27: {=IF(EDATE($F27,G$2)>DATE(2025,12,31),"",INDEX([1]A1!D$9:D$175,MATCH(1,--(RIGHT([1]A1!$B$9:$B$175,LEN([1]A1!$B$9:$B$175)-4)=$A27)*([1]A1!$C$9:$C$175=YEAR($F27)),0)))} -> 1.0212799e+08 | H27: {=IF(EDATE($F27,H$2)>DATE(2025,12,31),"",INDEX([1]A1!E$9:E$175,MATCH(1,--(RIGHT([1]A1!$B$9:$B$175,LEN([1]A1!$B$9:$B$175)-4)=$A27)*([1]A1!$C$9:$C$175=YEAR($F27)),0)))} -> 1.943446e+08 | I27: {=IF(EDATE($F27,I$2)>DATE(2025,12,31),"",INDEX([1]A1!F$9:F$175,MATCH(1,--(RIGHT([1]A1!$B$9:$B$175,LEN([1]A1!$B$9:$B$175)-4)=$A27)*([1]A1!$C$9:$C$175=YEAR($F27)),0)))} -> 2.1501244e+08 | J27: {=IF(EDATE($F27,J$2)>DATE(2025,12,31),"",INDEX([1]A1!G$9:G$175,MATCH(1,--(RIGHT([1]A1!$B$9:$B$175,LEN([1]A1!$B$9:$B$175)-4)=$A27)*([1]A1!$C$9:$C$175=YEAR($F27)),0)))} -> 2.1718603e+08 | K27: {=IF(EDATE($F27,K$2)>DATE(2025,12,31),"",INDEX([1]A1!H$9:H$175,MATCH(1,--(RIGHT([1]A1!$B$9:$B$175,LEN([1]A1!$B$9:$B$175)-4)=$A27)*([1]A1!$C$9:$C$175=YEAR($F27)),0)))} -> 2.1714994e+08 | L27: {=IF(EDATE($F27,L$2)>DATE(2025,12,31),"",INDEX([1]A1!I$9:I$175,MATCH(1,--(RIGHT([1]A1!$B$9:$B$175,LEN([1]A1!$B$9:$B$175)-4)=$A27)*([1]A1!$C$9:$C$175=YEAR($F27)),0)))} -> 2.1885141e+08 | M27: {=IF(EDATE($F27,M$2)>DATE(2025,12,31),"",INDEX([1]A1!J$9:J$175,MATCH(1,--(RIGHT([1]A1!$B$9:$B$175,LEN([1]A1!$B$9:$B$175)-4)=$A27)*([1]A1!$C$9:$C$175=YEAR($F27)),0)))} -> 2.1886555e+08 | N27: {=IF(EDATE($F27,N$2)>DATE(2025,12,31),"",INDEX([1]A1!K$9:K$175,MATCH(1,--(RIGHT([1]A1!$B$9:$B$175,LEN([1]A1!$B$9:$B$175)-4)=$A27)*([1]A1!$C$9:$C$175=YEAR($F27)),0)))} -> 2.1886872e+08 | ... FA27: {=IF(EDATE($F27,FA$2)>DATE(2025,12,31),"",INDEX([1]A1!EX$9:EX$175,MATCH(1,--(RIGHT([1]A1!$B$9:$B$175,LEN([1]A1!$B$9:$B$175)-4)=$A27)*([1]A1!$C$9:$C$175=YEAR($F27)),0)))}
A28: Liability | B28: Net Written Premium | C28: All | D28: UW Year | E28: USD | F28: =EDATE(F27,12) -> 40179 | G28: {=IF(EDATE($F28,G$2)>DATE(2025,12,31),"",INDEX([1]A1!D$9:D$175,MATCH(1,--(RIGHT([1]A1!$B$9:$B$175,LEN([1]A1!$B$9:$B$175)-4)=$A28)*([1]A1!$C$9:$C$175=YEAR($F28)),0)))} -> 88467263 | H28: {=IF(EDATE($F28,H$2)>DATE(2025,12,31),"",INDEX([1]A1!E$9:E$175,MATCH(1,--(RIGHT([1]A1!$B$9:$B$175,LEN([1]A1!$B$9:$B$175)-4)=$A28)*([1]A1!$C$9:$C$175=YEAR($F28)),0)))} -> 1.7453668e+08 | I28: {=IF(EDATE($F28,I$2)>DATE(2025,12,31),"",INDEX([1]A1!F$9:F$175,MATCH(1,--(RIGHT([1]A1!$B$9:$B$175,LEN([1]A1!$B$9:$B$175)-4)=$A28)*([1]A1!$C$9:$C$175=YEAR($F28)),0)))} -> 1.8895982e+08 | J28: {=IF(EDATE($F28,J$2)>DATE(2025,12,31),"",INDEX([1]A1!G$9:G$175,MATCH(1,--(RIGHT([1]A1!$B$9:$B$175,LEN([1]A1!$B$9:$B$175)-4)=$A28)*([1]A1!$C$9:$C$175=YEAR($F28)),0)))} -> 1.8914726e+08 | K28: {=IF(EDATE($F28,K$2)>DATE(2025,12,31),"",INDEX([1]A1!H$9:H$175,MATCH(1,--(RIGHT([1]A1!$B$9:$B$175,LEN([1]A1!$B$9:$B$175)-4)=$A28)*([1]A1!$C$9:$C$175=YEAR($F28)),0)))} -> 1.9086425e+08 | L28: {=IF(EDATE($F28,L$2)>DATE(2025,12,31),"",INDEX([1]A1!I$9:I$175,MATCH(1,--(RIGHT([1]A1!$B$9:$B$175,LEN([1]A1!$B$9:$B$175)-4)=$A28)*([1]A1!$C$9:$C$175=YEAR($F28)),0)))} -> 1.9138707e+08 | M28: {=IF(EDATE($F28,M$2)>DATE(2025,12,31),"",INDEX([1]A1!J$9:J$175,MATCH(1,--(RIGHT([1]A1!$B$9:$B$175,LEN([1]A1!$B$9:$B$175)-4)=$A28)*([1]A1!$C$9:$C$175=YEAR($F28)),0)))} -> 1.9148241e+08 | N28: {=IF(EDATE($F28,N$2)>DATE(2025,12,31),"",INDEX([1]A1!K$9:K$175,MATCH(1,--(RIGHT([1]A1!$B$9:$B$175,LEN([1]A1!$B$9:$B$175)-4)=$A28)*([1]A1!$C$9:$C$175=YEAR($F28)),0)))} -> 1.9168688e+08 | ... FA28: {=IF(EDATE($F28,FA$2)>DATE(2025,12,31),"",INDEX([1]A1!EX$9:EX$175,MATCH(1,--(RIGHT([1]A1!$B$9:$B$175,LEN([1]A1!$B$9:$B$175)-4)=$A28)*([1]A1!$C$9:$C$175=YEAR($F28)),0)))}
A29: Liability | B29: Net Written Premium | C29: All | D29: UW Year | E29: USD | F29: =EDATE(F28,12) -> 40544 | G29: {=IF(EDATE($F29,G$2)>DATE(2025,12,31),"",INDEX([1]A1!D$9:D$175,MATCH(1,--(RIGHT([1]A1!$B$9:$B$175,LEN([1]A1!$B$9:$B$175)-4)=$A29)*([1]A1!$C$9:$C$175=YEAR($F29)),0)))} -> 78597903 | H29: {=IF(EDATE($F29,H$2)>DATE(2025,12,31),"",INDEX([1]A1!E$9:E$175,MATCH(1,--(RIGHT([1]A1!$B$9:$B$175,LEN([1]A1!$B$9:$B$175)-4)=$A29)*([1]A1!$C$9:$C$175=YEAR($F29)),0)))} -> 1.6812891e+08 | I29: {=IF(EDATE($F29,I$2)>DATE(2025,12,31),"",INDEX([1]A1!F$9:F$175,MATCH(1,--(RIGHT([1]A1!$B$9:$B$175,LEN([1]A1!$B$9:$B$175)-4)=$A29)*([1]A1!$C$9:$C$175=YEAR($F29)),0)))} -> 1.8914312e+08 | J29: {=IF(EDATE($F29,J$2)>DATE(2025,12,31),"",INDEX([1]A1!G$9:G$175,MATCH(1,--(RIGHT([1]A1!$B$9:$B$175,LEN([1]A1!$B$9:$B$175)-4)=$A29)*([1]A1!$C$9:$C$175=YEAR($F29)),0)))} -> 1.9319467e+08 | K29: {=IF(EDATE($F29,K$2)>DATE(2025,12,31),"",INDEX([1]A1!H$9:H$175,MATCH(1,--(RIGHT([1]A1!$B$9:$B$175,LEN([1]A1!$B$9:$B$175)-4)=$A29)*([1]A1!$C$9:$C$175=YEAR($F29)),0)))} -> 1.937221e+08 | L29: {=IF(EDATE($F29,L$2)>DATE(2025,12,31),"",INDEX([1]A1!I$9:I$175,MATCH(1,--(RIGHT([1]A1!$B$9:$B$175,LEN([1]A1!$B$9:$B$175)-4)=$A29)*([1]A1!$C$9:$C$175=YEAR($F29)),0)))} -> 1.9435378e+08 | M29: {=IF(EDATE($F29,M$2)>DATE(2025,12,31),"",INDEX([1]A1!J$9:J$175,MATCH(1,--(RIGHT([1]A1!$B$9:$B$175,LEN([1]A1!$B$9:$B$175)-4)=$A29)*([1]A1!$C$9:$C$175=YEAR($F29)),0)))} -> 1.9461564e+08 | N29: {=IF(EDATE($F29,N$2)>DATE(2025,12,31),"",INDEX([1]A1!K$9:K$175,MATCH(1,--(RIGHT([1]A1!$B$9:$B$175,LEN([1]A1!$B$9:$B$175)-4)=$A29)*([1]A1!$C$9:$C$175=YEAR($F29)),0)))} -> 1.9468164e+08 | ... FA29: {=IF(EDATE($F29,FA$2)>DATE(2025,12,31),"",INDEX([1]A1!EX$9:EX$175,MATCH(1,--(RIGHT([1]A1!$B$9:$B$175,LEN([1]A1!$B$9:$B$175)-4)=$A29)*([1]A1!$C$9:$C$175=YEAR($F29)),0)))}
A30: Liability | B30: Net Written Premium | C30: All | D30: UW Year | E30: USD | F30: =EDATE(F29,12) -> 40909 | G30: {=IF(EDATE($F30,G$2)>DATE(2025,12,31),"",INDEX([1]A1!D$9:D$175,MATCH(1,--(RIGHT([1]A1!$B$9:$B$175,LEN([1]A1!$B$9:$B$175)-4)=$A30)*([1]A1!$C$9:$C$175=YEAR($F30)),0)))} -> 85387137 | H30: {=IF(EDATE($F30,H$2)>DATE(2025,12,31),"",INDEX([1]A1!E$9:E$175,MATCH(1,--(RIGHT([1]A1!$B$9:$B$175,LEN([1]A1!$B$9:$B$175)-4)=$A30)*([1]A1!$C$9:$C$175=YEAR($F30)),0)))} -> 1.8383553e+08 | I30: {=IF(EDATE($F30,I$2)>DATE(2025,12,31),"",INDEX([1]A1!F$9:F$175,MATCH(1,--(RIGHT([1]A1!$B$9:$B$175,LEN([1]A1!$B$9:$B$175)-4)=$A30)*([1]A1!$C$9:$C$175=YEAR($F30)),0)))} -> 1.9025438e+08 | J30: {=IF(EDATE($F30,J$2)>DATE(2025,12,31),"",INDEX([1]A1!G$9:G$175,MATCH(1,--(RIGHT([1]A1!$B$9:$B$175,LEN([1]A1!$B$9:$B$175)-4)=$A30)*([1]A1!$C$9:$C$175=YEAR($F30)),0)))} -> 1.9560998e+08 | K30: {=IF(EDATE($F30,K$2)>DATE(2025,12,31),"",INDEX([1]A1!H$9:H$175,MATCH(1,--(RIGHT([1]A1!$B$9:$B$175,LEN([1]A1!$B$9:$B$175)-4)=$A30)*([1]A1!$C$9:$C$175=YEAR($F30)),0)))} -> 1.9588295e+08 | L30: {=IF(EDATE($F30,L$2)>DATE(2025,12,31),"",INDEX([1]A1!I$9:I$175,MATCH(1,--(RIGHT([1]A1!$B$9:$B$175,LEN([1]A1!$B$9:$B$175)-4)=$A30)*([1]A1!$C$9:$C$175=YEAR($F30)),0)))} -> 1.9585657e+08 | M30: {=IF(EDATE($F30,M$2)>DATE(2025,12,31),"",INDEX([1]A1!J$9:J$175,MATCH(1,--(RIGHT([1]A1!$B$9:$B$175,LEN([1]A1!$B$9:$B$175)-4)=$A30)*([1]A1!$C$9:$C$175=YEAR($F30)),0)))} -> 1.9614702e+08 | N30: {=IF(EDATE($F30,N$2)>DATE(2025,12,31),"",INDEX([1]A1!K$9:K$175,MATCH(1,--(RIGHT([1]A1!$B$9:$B$175,LEN([1]A1!$B$9:$B$175)-4)=$A30)*([1]A1!$C$9:$C$175=YEAR($F30)),0)))} -> 1.9626503e+08 | ... FA30: {=IF(EDATE($F30,FA$2)>DATE(2025,12,31),"",INDEX([1]A1!EX$9:EX$175,MATCH(1,--(RIGHT([1]A1!$B$9:$B$175,LEN([1]A1!$B$9:$B$175)-4)=$A30)*([1]A1!$C$9:$C$175=YEAR($F30)),0)))}
A31: Liability | B31: Net Written Premium | C31: All | D31: UW Year | E31: USD | F31: =EDATE(F30,12) -> 41275 | G31: {=IF(EDATE($F31,G$2)>DATE(2025,12,31),"",INDEX([1]A1!D$9:D$175,MATCH(1,--(RIGHT([1]A1!$B$9:$B$175,LEN([1]A1!$B$9:$B$175)-4)=$A31)*([1]A1!$C$9:$C$175=YEAR($F31)),0)))} -> 2.0898819e+08 | H31: {=IF(EDATE($F31,H$2)>DATE(2025,12,31),"",INDEX([1]A1!E$9:E$175,MATCH(1,--(RIGHT([1]A1!$B$9:$B$175,LEN([1]A1!$B$9:$B$175)-4)=$A31)*([1]A1!$C$9:$C$175=YEAR($F31)),0)))} -> 2.278122e+08 | I31: {=IF(EDATE($F31,I$2)>DATE(2025,12,31),"",INDEX([1]A1!F$9:F$175,MATCH(1,--(RIGHT([1]A1!$B$9:$B$175,LEN([1]A1!$B$9:$B$175)-4)=$A31)*([1]A1!$C$9:$C$175=YEAR($F31)),0)))} -> 2.3049679e+08 | J31: {=IF(EDATE($F31,J$2)>DATE(2025,12,31),"",INDEX([1]A1!G$9:G$175,MATCH(1,--(RIGHT([1]A1!$B$9:$B$175,LEN([1]A1!$B$9:$B$175)-4)=$A31)*([1]A1!$C$9:$C$175=YEAR($F31)),0)))} -> 2.332634e+08 | K31: {=IF(EDATE($F31,K$2)>DATE(2025,12,31),"",INDEX([1]A1!H$9:H$175,MATCH(1,--(RIGHT([1]A1!$B$9:$B$175,LEN([1]A1!$B$9:$B$175)-4)=$A31)*([1]A1!$C$9:$C$175=YEAR($F31)),0)))} -> 2.3421773e+08 | L31: {=IF(EDATE($F31,L$2)>DATE(2025,12,31),"",INDEX([1]A1!I$9:I$175,MATCH(1,--(RIGHT([1]A1!$B$9:$B$175,LEN([1]A1!$B$9:$B$175)-4)=$A31)*([1]A1!$C$9:$C$175=YEAR($F31)),0)))} -> 2.3487776e+08 | M31: {=IF(EDATE($F31,M$2)>DATE(2025,12,31),"",INDEX([1]A1!J$9:J$175,MATCH(1,--(RIGHT([1]A1!$B$9:$B$175,LEN([1]A1!$B$9:$B$175)-4)=$A31)*([1]A1!$C$9:$C$175=YEAR($F31)),0)))} -> 2.3535885e+08 | N31: {=IF(EDATE($F31,N$2)>DATE(2025,12,31),"",INDEX([1]A1!K$9:K$175,MATCH(1,--(RIGHT([1]A1!$B$9:$B$175,LEN([1]A1!$B$9:$B$175)-4)=$A31)*([1]A1!$C$9:$C$175=YEAR($F31)),0)))} -> 2.3628031e+08 | ... FA31: {=IF(EDATE($F31,FA$2)>DATE(2025,12,31),"",INDEX([1]A1!EX$9:EX$175,MATCH(1,--(RIGHT([1]A1!$B$9:$B$175,LEN([1]A1!$B$9:$B$175)-4)=$A31)*([1]A1!$C$9:$C$175=YEAR($F31)),0)))}
A32: Liability | B32: Net Written Premium | C32: All | D32: UW Year | E32: USD | F32: =EDATE(F31,12) -> 41640 | G32: {=IF(EDATE($F32,G$2)>DATE(2025,12,31),"",INDEX([1]A1!D$9:D$175,MATCH(1,--(RIGHT([1]A1!$B$9:$B$175,LEN([1]A1!$B$9:$B$175)-4)=$A32)*([1]A1!$C$9:$C$175=YEAR($F32)),0)))} -> 2.2033772e+08 | H32: {=IF(EDATE($F32,H$2)>DATE(2025,12,31),"",INDEX([1]A1!E$9:E$175,MATCH(1,--(RIGHT([1]A1!$B$9:$B$175,LEN([1]A1!$B$9:$B$175)-4)=$A32)*([1]A1!$C$9:$C$175=YEAR($F32)),0)))} -> 2.5069404e+08 | I32: {=IF(EDATE($F32,I$2)>DATE(2025,12,31),"",INDEX([1]A1!F$9:F$175,MATCH(1,--(RIGHT([1]A1!$B$9:$B$175,LEN([1]A1!$B$9:$B$175)-4)=$A32)*([1]A1!$C$9:$C$175=YEAR($F32)),0)))} -> 2.5170677e+08 | J32: {=IF(EDATE($F32,J$2)>DATE(2025,12,31),"",INDEX([1]A1!G$9:G$175,MATCH(1,--(RIGHT([1]A1!$B$9:$B$175,LEN([1]A1!$B$9:$B$175)-4)=$A32)*([1]A1!$C$9:$C$175=YEAR($F32)),0)))} -> 2.5459064e+08 | K32: {=IF(EDATE($F32,K$2)>DATE(2025,12,31),"",INDEX([1]A1!H$9:H$175,MATCH(1,--(RIGHT([1]A1!$B$9:$B$175,LEN([1]A1!$B$9:$B$175)-4)=$A32)*([1]A1!$C$9:$C$175=YEAR($F32)),0)))} -> 2.5656969e+08 | L32: {=IF(EDATE($F32,L$2)>DATE(2025,12,31),"",INDEX([1]A1!I$9:I$175,MATCH(1,--(RIGHT([1]A1!$B$9:$B$175,LEN([1]A1!$B$9:$B$175)-4)=$A32)*([1]A1!$C$9:$C$175=YEAR($F32)),0)))} -> 2.5863943e+08 | M32: {=IF(EDATE($F32,M$2)>DATE(2025,12,31),"",INDEX([1]A1!J$9:J$175,MATCH(1,--(RIGHT([1]A1!$B$9:$B$175,LEN([1]A1!$B$9:$B$175)-4)=$A32)*([1]A1!$C$9:$C$175=YEAR($F32)),0)))} -> 2.592705e+08 | N32: {=IF(EDATE($F32,N$2)>DATE(2025,12,31),"",INDEX([1]A1!K$9:K$175,MATCH(1,--(RIGHT([1]A1!$B$9:$B$175,LEN([1]A1!$B$9:$B$175)-4)=$A32)*([1]A1!$C$9:$C$175=YEAR($F32)),0)))} -> 2.5938028e+08 | ... FA32: {=IF(EDATE($F32,FA$2)>DATE(2025,12,31),"",INDEX([1]A1!EX$9:EX$175,MATCH(1,--(RIGHT([1]A1!$B$9:$B$175,LEN([1]A1!$B$9:$B$175)-4)=$A32)*([1]A1!$C$9:$C$175=YEAR($F32)),0)))}
A33: Liability | B33: Net Written Premium | C33: All | D33: UW Year | E33: USD | F33: =EDATE(F32,12) -> 42005 | G33: {=IF(EDATE($F33,G$2)>DATE(2025,12,31),"",INDEX([1]A1!D$9:D$175,MATCH(1,--(RIGHT([1]A1!$B$9:$B$175,LEN([1]A1!$B$9:$B$175)-4)=$A33)*([1]A1!$C$9:$C$175=YEAR($F33)),0)))} -> 2.2760227e+08 | H33: {=IF(EDATE($F33,H$2)>DATE(2025,12,31),"",INDEX([1]A1!E$9:E$175,MATCH(1,--(RIGHT([1]A1!$B$9:$B$175,LEN([1]A1!$B$9:$B$175)-4)=$A33)*([1]A1!$C$9:$C$175=YEAR($F33)),0)))} -> 2.8155861e+08 | I33: {=IF(EDATE($F33,I$2)>DATE(2025,12,31),"",INDEX([1]A1!F$9:F$175,MATCH(1,--(RIGHT([1]A1!$B$9:$B$175,LEN([1]A1!$B$9:$B$175)-4)=$A33)*([1]A1!$C$9:$C$175=YEAR($F33)),0)))} -> 2.7919315e+08 | J33: {=IF(EDATE($F33,J$2)>DATE(2025,12,31),"",INDEX([1]A1!G$9:G$175,MATCH(1,--(RIGHT([1]A1!$B$9:$B$175,LEN([1]A1!$B$9:$B$175)-4)=$A33)*([1]A1!$C$9:$C$175=YEAR($F33)),0)))} -> 2.8254937e+08 | K33: {=IF(EDATE($F33,K$2)>DATE(2025,12,31),"",INDEX([1]A1!H$9:H$175,MATCH(1,--(RIGHT([1]A1!$B$9:$B$175,LEN([1]A1!$B$9:$B$175)-4)=$A33)*([1]A1!$C$9:$C$175=YEAR($F33)),0)))} -> 2.8410302e+08 | L33: {=IF(EDATE($F33,L$2)>DATE(2025,12,31),"",INDEX([1]A1!I$9:I$175,MATCH(1,--(RIGHT([1]A1!$B$9:$B$175,LEN([1]A1!$B$9:$B$175)-4)=$A33)*([1]A1!$C$9:$C$175=YEAR($F33)),0)))} -> 2.850038e+08 | M33: {=IF(EDATE($F33,M$2)>DATE(2025,12,31),"",INDEX([1]A1!J$9:J$175,MATCH(1,--(RIGHT([1]A1!$B$9:$B$175,LEN([1]A1!$B$9:$B$175)-4)=$A33)*([1]A1!$C$9:$C$175=YEAR($F33)),0)))} -> 2.8532352e+08 | N33: {=IF(EDATE($F33,N$2)>DATE(2025,12,31),"",INDEX([1]A1!K$9:K$175,MATCH(1,--(RIGHT([1]A1!$B$9:$B$175,LEN([1]A1!$B$9:$B$175)-4)=$A33)*([1]A1!$C$9:$C$175=YEAR($F33)),0)))} -> 2.8569873e+08 | ... FA33: {=IF(EDATE($F33,FA$2)>DATE(2025,12,31),"",INDEX([1]A1!EX$9:EX$175,MATCH(1,--(RIGHT([1]A1!$B$9:$B$175,LEN([1]A1!$B$9:$B$175)-4)=$A33)*([1]A1!$C$9:$C$175=YEAR($F33)),0)))}
A34: Liability | B34: Net Written Premium | C34: All | D34: UW Year | E34: USD | F34: =EDATE(F33,12) -> 42370 | G34: {=IF(EDATE($F34,G$2)>DATE(2025,12,31),"",INDEX([1]A1!D$9:D$175,MATCH(1,--(RIGHT([1]A1!$B$9:$B$175,LEN([1]A1!$B$9:$B$175)-4)=$A34)*([1]A1!$C$9:$C$175=YEAR($F34)),0)))} -> 3.0499874e+08 | H34: {=IF(EDATE($F34,H$2)>DATE(2025,12,31),"",INDEX([1]A1!E$9:E$175,MATCH(1,--(RIGHT([1]A1!$B$9:$B$175,LEN([1]A1!$B$9:$B$175)-4)=$A34)*([1]A1!$C$9:$C$175=YEAR($F34)),0)))} -> 3.4835083e+08 | I34: {=IF(EDATE($F34,I$2)>DATE(2025,12,31),"",INDEX([1]A1!F$9:F$175,MATCH(1,--(RIGHT([1]A1!$B$9:$B$175,LEN([1]A1!$B$9:$B$175)-4)=$A34)*([1]A1!$C$9:$C$175=YEAR($F34)),0)))} -> 3.5238353e+08 | J34: {=IF(EDATE($F34,J$2)>DATE(2025,12,31),"",INDEX([1]A1!G$9:G$175,MATCH(1,--(RIGHT([1]A1!$B$9:$B$175,LEN([1]A1!$B$9:$B$175)-4)=$A34)*([1]A1!$C$9:$C$175=YEAR($F34)),0)))} -> 3.4601942e+08 | K34: {=IF(EDATE($F34,K$2)>DATE(2025,12,31),"",INDEX([1]A1!H$9:H$175,MATCH(1,--(RIGHT([1]A1!$B$9:$B$175,LEN([1]A1!$B$9:$B$175)-4)=$A34)*([1]A1!$C$9:$C$175=YEAR($F34)),0)))} -> 3.4755634e+08 | L34: {=IF(EDATE($F34,L$2)>DATE(2025,12,31),"",INDEX([1]A1!I$9:I$175,MATCH(1,--(RIGHT([1]A1!$B$9:$B$175,LEN([1]A1!$B$9:$B$175)-4)=$A34)*([1]A1!$C$9:$C$175=YEAR($F34)),0)))} -> 3.4891161e+08 | M34: {=IF(EDATE($F34,M$2)>DATE(2025,12,31),"",INDEX([1]A1!J$9:J$175,MATCH(1,--(RIGHT([1]A1!$B$9:$B$175,LEN([1]A1!$B$9:$B$175)-4)=$A34)*([1]A1!$C$9:$C$175=YEAR($F34)),0)))} -> 3.4947306e+08 | N34: {=IF(EDATE($F34,N$2)>DATE(2025,12,31),"",INDEX([1]A1!K$9:K$175,MATCH(1,--(RIGHT([1]A1!$B$9:$B$175,LEN([1]A1!$B$9:$B$175)-4)=$A34)*([1]A1!$C$9:$C$175=YEAR($F34)),0)))} -> 3.4994779e+08 | ... FA34: {=IF(EDATE($F34,FA$2)>DATE(2025,12,31),"",INDEX([1]A1!EX$9:EX$175,MATCH(1,--(RIGHT([1]A1!$B$9:$B$175,LEN([1]A1!$B$9:$B$175)-4)=$A34)*([1]A1!$C$9:$C$175=YEAR($F34)),0)))}
A35: Liability | B35: Net Written Premium | C35: All | D35: UW Year | E35: USD | F35: =EDATE(F34,12) -> 42736 | G35: {=IF(EDATE($F35,G$2)>DATE(2025,12,31),"",INDEX([1]A1!D$9:D$175,MATCH(1,--(RIGHT([1]A1!$B$9:$B$175,LEN([1]A1!$B$9:$B$175)-4)=$A35)*([1]A1!$C$9:$C$175=YEAR($F35)),0)))} -> 3.1247014e+08 | H35: {=IF(EDATE($F35,H$2)>DATE(2025,12,31),"",INDEX([1]A1!E$9:E$175,MATCH(1,--(RIGHT([1]A1!$B$9:$B$175,LEN([1]A1!$B$9:$B$175)-4)=$A35)*([1]A1!$C$9:$C$175=YEAR($F35)),0)))} -> 3.6900858e+08 | I35: {=IF(EDATE($F35,I$2)>DATE(2025,12,31),"",INDEX([1]A1!F$9:F$175,MATCH(1,--(RIGHT([1]A1!$B$9:$B$175,LEN([1]A1!$B$9:$B$175)-4)=$A35)*([1]A1!$C$9:$C$175=YEAR($F35)),0)))} -> 3.7875941e+08 | J35: {=IF(EDATE($F35,J$2)>DATE(2025,12,31),"",INDEX([1]A1!G$9:G$175,MATCH(1,--(RIGHT([1]A1!$B$9:$B$175,LEN([1]A1!$B$9:$B$175)-4)=$A35)*([1]A1!$C$9:$C$175=YEAR($F35)),0)))} -> 3.7895342e+08 | K35: {=IF(EDATE($F35,K$2)>DATE(2025,12,31),"",INDEX([1]A1!H$9:H$175,MATCH(1,--(RIGHT([1]A1!$B$9:$B$175,LEN([1]A1!$B$9:$B$175)-4)=$A35)*([1]A1!$C$9:$C$175=YEAR($F35)),0)))} -> 3.812484e+08 | L35: {=IF(EDATE($F35,L$2)>DATE(2025,12,31),"",INDEX([1]A1!I$9:I$175,MATCH(1,--(RIGHT([1]A1!$B$9:$B$175,LEN([1]A1!$B$9:$B$175)-4)=$A35)*([1]A1!$C$9:$C$175=YEAR($F35)),0)))} -> 3.8327202e+08 | M35: {=IF(EDATE($F35,M$2)>DATE(2025,12,31),"",INDEX([1]A1!J$9:J$175,MATCH(1,--(RIGHT([1]A1!$B$9:$B$175,LEN([1]A1!$B$9:$B$175)-4)=$A35)*([1]A1!$C$9:$C$175=YEAR($F35)),0)))} -> 3.8441817e+08 | N35: {=IF(EDATE($F35,N$2)>DATE(2025,12,31),"",INDEX([1]A1!K$9:K$175,MATCH(1,--(RIGHT([1]A1!$B$9:$B$175,LEN([1]A1!$B$9:$B$175)-4)=$A35)*([1]A1!$C$9:$C$175=YEAR($F35)),0)))} -> 3.8544773e+08 | ... FA35: {=IF(EDATE($F35,FA$2)>DATE(2025,12,31),"",INDEX([1]A1!EX$9:EX$175,MATCH(1,--(RIGHT([1]A1!$B$9:$B$175,LEN([1]A1!$B$9:$B$175)-4)=$A35)*([1]A1!$C$9:$C$175=YEAR($F35)),0)))}
A36: Liability | B36: Net Written Premium | C36: All | D36: UW Year | E36: USD | F36: =EDATE(F35,12) -> 43101 | G36: {=IF(EDATE($F36,G$2)>DATE(2025,12,31),"",INDEX([1]A1!D$9:D$175,MATCH(1,--(RIGHT([1]A1!$B$9:$B$175,LEN([1]A1!$B$9:$B$175)-4)=$A36)*([1]A1!$C$9:$C$175=YEAR($F36)),0)))} -> 3.0617633e+08 | H36: {=IF(EDATE($F36,H$2)>DATE(2025,12,31),"",INDEX([1]A1!E$9:E$175,MATCH(1,--(RIGHT([1]A1!$B$9:$B$175,LEN([1]A1!$B$9:$B$175)-4)=$A36)*([1]A1!$C$9:$C$175=YEAR($F36)),0)))} -> 3.7597247e+08 | I36: {=IF(EDATE($F36,I$2)>DATE(2025,12,31),"",INDEX([1]A1!F$9:F$175,MATCH(1,--(RIGHT([1]A1!$B$9:$B$175,LEN([1]A1!$B$9:$B$175)-4)=$A36)*([1]A1!$C$9:$C$175=YEAR($F36)),0)))} -> 3.9091174e+08 | J36: {=IF(EDATE($F36,J$2)>DATE(2025,12,31),"",INDEX([1]A1!G$9:G$175,MATCH(1,--(RIGHT([1]A1!$B$9:$B$175,LEN([1]A1!$B$9:$B$175)-4)=$A36)*([1]A1!$C$9:$C$175=YEAR($F36)),0)))} -> 3.8335907e+08 | K36: {=IF(EDATE($F36,K$2)>DATE(2025,12,31),"",INDEX([1]A1!H$9:H$175,MATCH(1,--(RIGHT([1]A1!$B$9:$B$175,LEN([1]A1!$B$9:$B$175)-4)=$A36)*([1]A1!$C$9:$C$175=YEAR($F36)),0)))} -> 3.8472683e+08 | L36: {=IF(EDATE($F36,L$2)>DATE(2025,12,31),"",INDEX([1]A1!I$9:I$175,MATCH(1,--(RIGHT([1]A1!$B$9:$B$175,LEN([1]A1!$B$9:$B$175)-4)=$A36)*([1]A1!$C$9:$C$175=YEAR($F36)),0)))} -> 3.8515627e+08 | M36: {=IF(EDATE($F36,M$2)>DATE(2025,12,31),"",INDEX([1]A1!J$9:J$175,MATCH(1,--(RIGHT([1]A1!$B$9:$B$175,LEN([1]A1!$B$9:$B$175)-4)=$A36)*([1]A1!$C$9:$C$175=YEAR($F36)),0)))} -> 3.8646031e+08 | N36: {=IF(EDATE($F36,N$2)>DATE(2025,12,31),"",INDEX([1]A1!K$9:K$175,MATCH(1,--(RIGHT([1]A1!$B$9:$B$175,LEN([1]A1!$B$9:$B$175)-4)=$A36)*([1]A1!$C$9:$C$175=YEAR($F36)),0)))} -> 3.8713735e+08 | ... FA36: {=IF(EDATE($F36,FA$2)>DATE(2025,12,31),"",INDEX([1]A1!EX$9:EX$175,MATCH(1,--(RIGHT([1]A1!$B$9:$B$175,LEN([1]A1!$B$9:$B$175)-4)=$A36)*([1]A1!$C$9:$C$175=YEAR($F36)),0)))}
... A43: Liability | B43: Net Written Premium | C43: All | D43: UW Year | E43: USD | F43: =EDATE(F42,12) -> 45658 | G43: {=IF(EDATE($F43,G$2)>DATE(2025,12,31),"",INDEX([1]A1!D$9:D$175,MATCH(1,--(RIGHT([1]A1!$B$9:$B$175,LEN([1]A1!$B$9:$B$175)-4)=$A43)*([1]A1!$C$9:$C$175=YEAR($F43)),0)))} -> 4.009371e+08 | H43: {=IF(EDATE($F43,H$2)>DATE(2025,12,31),"",INDEX([1]A1!E$9:E$175,MATCH(1,--(RIGHT([1]A1!$B$9:$B$175,LEN([1]A1!$B$9:$B$175)-4)=$A43)*([1]A1!$C$9:$C$175=YEAR($F43)),0)))} | I43: {=IF(EDATE($F43,I$2)>DATE(2025,12,31),"",INDEX([1]A1!F$9:F$175,MATCH(1,--(RIGHT([1]A1!$B$9:$B$175,LEN([1]A1!$B$9:$B$175)-4)=$A43)*([1]A1!$C$9:$C$175=YEAR($F43)),0)))} | J43: {=IF(EDATE($F43,J$2)>DATE(2025,12,31),"",INDEX([1]A1!G$9:G$175,MATCH(1,--(RIGHT([1]A1!$B$9:$B$175,LEN([1]A1!$B$9:$B$175)-4)=$A43)*([1]A1!$C$9:$C$175=YEAR($F43)),0)))} | K43: {=IF(EDATE($F43,K$2)>DATE(2025,12,31),"",INDEX([1]A1!H$9:H$175,MATCH(1,--(RIGHT([1]A1!$B$9:$B$175,LEN([1]A1!$B$9:$B$175)-4)=$A43)*([1]A1!$C$9:$C$175=YEAR($F43)),0)))} | L43: {=IF(EDATE($F43,L$2)>DATE(2025,12,31),"",INDEX([1]A1!I$9:I$175,MATCH(1,--(RIGHT([1]A1!$B$9:$B$175,LEN([1]A1!$B$9:$B$175)-4)=$A43)*([1]A1!$C$9:$C$175=YEAR($F43)),0)))} | M43: {=IF(EDATE($F43,M$2)>DATE(2025,12,31),"",INDEX([1]A1!J$9:J$175,MATCH(1,--(RIGHT([1]A1!$B$9:$B$175,LEN([1]A1!$B$9:$B$175)-4)=$A43)*([1]A1!$C$9:$C$175=YEAR($F43)),0)))} | N43: {=IF(EDATE($F43,N$2)>DATE(2025,12,31),"",INDEX([1]A1!K$9:K$175,MATCH(1,--(RIGHT([1]A1!$B$9:$B$175,LEN([1]A1!$B$9:$B$175)-4)=$A43)*([1]A1!$C$9:$C$175=YEAR($F43)),0)))} | ... FA43: {=IF(EDATE($F43,FA$2)>DATE(2025,12,31),"",INDEX([1]A1!EX$9:EX$175,MATCH(1,--(RIGHT([1]A1!$B$9:$B$175,LEN([1]A1!$B$9:$B$175)-4)=$A43)*([1]A1!$C$9:$C$175=YEAR($F43)),0)))}
A45: Credit & Surety | B45: Net Written Premium | C45: All | D45: UW Year | E45: USD | F45: =triangle_start_date -> 38718 | G45: {=IF(EDATE($F45,G$2)>DATE(2025,12,31),"",INDEX([1]A1!D$9:D$175,MATCH(1,--(RIGHT([1]A1!$B$9:$B$175,LEN([1]A1!$B$9:$B$175)-4)=$A45)*([1]A1!$C$9:$C$175=YEAR($F45)),0)))} -> 33964946 | H45: {=IF(EDATE($F45,H$2)>DATE(2025,12,31),"",INDEX([1]A1!E$9:E$175,MATCH(1,--(RIGHT([1]A1!$B$9:$B$175,LEN([1]A1!$B$9:$B$175)-4)=$A45)*([1]A1!$C$9:$C$175=YEAR($F45)),0)))} -> 85747183 | I45: {=IF(EDATE($F45,I$2)>DATE(2025,12,31),"",INDEX([1]A1!F$9:F$175,MATCH(1,--(RIGHT([1]A1!$B$9:$B$175,LEN([1]A1!$B$9:$B$175)-4)=$A45)*([1]A1!$C$9:$C$175=YEAR($F45)),0)))} -> 93630331 | J45: {=IF(EDATE($F45,J$2)>DATE(2025,12,31),"",INDEX([1]A1!G$9:G$175,MATCH(1,--(RIGHT([1]A1!$B$9:$B$175,LEN([1]A1!$B$9:$B$175)-4)=$A45)*([1]A1!$C$9:$C$175=YEAR($F45)),0)))} -> 95723804 | K45: {=IF(EDATE($F45,K$2)>DATE(2025,12,31),"",INDEX([1]A1!H$9:H$175,MATCH(1,--(RIGHT([1]A1!$B$9:$B$175,LEN([1]A1!$B$9:$B$175)-4)=$A45)*([1]A1!$C$9:$C$175=YEAR($F45)),0)))} -> 97099222 | L45: {=IF(EDATE($F45,L$2)>DATE(2025,12,31),"",INDEX([1]A1!I$9:I$175,MATCH(1,--(RIGHT([1]A1!$B$9:$B$175,LEN([1]A1!$B$9:$B$175)-4)=$A45)*([1]A1!$C$9:$C$175=YEAR($F45)),0)))} -> 97830984 | M45: {=IF(EDATE($F45,M$2)>DATE(2025,12,31),"",INDEX([1]A1!J$9:J$175,MATCH(1,--(RIGHT([1]A1!$B$9:$B$175,LEN([1]A1!$B$9:$B$175)-4)=$A45)*([1]A1!$C$9:$C$175=YEAR($F45)),0)))} -> 98264253 | N45: {=IF(EDATE($F45,N$2)>DATE(2025,12,31),"",INDEX([1]A1!K$9:K$175,MATCH(1,--(RIGHT([1]A1!$B$9:$B$175,LEN([1]A1!$B$9:$B$175)-4)=$A45)*([1]A1!$C$9:$C$175=YEAR($F45)),0)))} -> 98565729 | ... FA45: {=IF(EDATE($F45,FA$2)>DATE(2025,12,31),"",INDEX([1]A1!EX$9:EX$175,MATCH(1,--(RIGHT([1]A1!$B$9:$B$175,LEN([1]A1!$B$9:$B$175)-4)=$A45)*([1]A1!$C$9:$C$175=YEAR($F45)),0)))}
A46: Credit & Surety | B46: Net Written Premium | C46: All | D46: UW Year | E46: USD | F46: =EDATE(F45,12) -> 39083 | G46: {=IF(EDATE($F46,G$2)>DATE(2025,12,31),"",INDEX([1]A1!D$9:D$175,MATCH(1,--(RIGHT([1]A1!$B$9:$B$175,LEN([1]A1!$B$9:$B$175)-4)=$A46)*([1]A1!$C$9:$C$175=YEAR($F46)),0)))} -> 49047819 | H46: {=IF(EDATE($F46,H$2)>DATE(2025,12,31),"",INDEX([1]A1!E$9:E$175,MATCH(1,--(RIGHT([1]A1!$B$9:$B$175,LEN([1]A1!$B$9:$B$175)-4)=$A46)*([1]A1!$C$9:$C$175=YEAR($F46)),0)))} -> 1.109643e+08 | I46: {=IF(EDATE($F46,I$2)>DATE(2025,12,31),"",INDEX([1]A1!F$9:F$175,MATCH(1,--(RIGHT([1]A1!$B$9:$B$175,LEN([1]A1!$B$9:$B$175)-4)=$A46)*([1]A1!$C$9:$C$175=YEAR($F46)),0)))} -> 1.2594204e+08 | J46: {=IF(EDATE($F46,J$2)>DATE(2025,12,31),"",INDEX([1]A1!G$9:G$175,MATCH(1,--(RIGHT([1]A1!$B$9:$B$175,LEN([1]A1!$B$9:$B$175)-4)=$A46)*([1]A1!$C$9:$C$175=YEAR($F46)),0)))} -> 1.2966947e+08 | K46: {=IF(EDATE($F46,K$2)>DATE(2025,12,31),"",INDEX([1]A1!H$9:H$175,MATCH(1,--(RIGHT([1]A1!$B$9:$B$175,LEN([1]A1!$B$9:$B$175)-4)=$A46)*([1]A1!$C$9:$C$175=YEAR($F46)),0)))} -> 1.3302532e+08 | L46: {=IF(EDATE($F46,L$2)>DATE(2025,12,31),"",INDEX([1]A1!I$9:I$175,MATCH(1,--(RIGHT([1]A1!$B$9:$B$175,LEN([1]A1!$B$9:$B$175)-4)=$A46)*([1]A1!$C$9:$C$175=YEAR($F46)),0)))} -> 1.3426265e+08 | M46: {=IF(EDATE($F46,M$2)>DATE(2025,12,31),"",INDEX([1]A1!J$9:J$175,MATCH(1,--(RIGHT([1]A1!$B$9:$B$175,LEN([1]A1!$B$9:$B$175)-4)=$A46)*([1]A1!$C$9:$C$175=YEAR($F46)),0)))} -> 1.3498011e+08 | N46: {=IF(EDATE($F46,N$2)>DATE(2025,12,31),"",INDEX([1]A1!K$9:K$175,MATCH(1,--(RIGHT([1]A1!$B$9:$B$175,LEN([1]A1!$B$9:$B$175)-4)=$A46)*([1]A1!$C$9:$C$175=YEAR($F46)),0)))} -> 1.3588119e+08 | ... FA46: {=IF(EDATE($F46,FA$2)>DATE(2025,12,31),"",INDEX([1]A1!EX$9:EX$175,MATCH(1,--(RIGHT([1]A1!$B$9:$B$175,LEN([1]A1!$B$9:$B$175)-4)=$A46)*([1]A1!$C$9:$C$175=YEAR($F46)),0)))}
A47: Credit & Surety | B47: Net Written Premium | C47: All | D47: UW Year | E47: USD | F47: =EDATE(F46,12) -> 39448 | G47: {=IF(EDATE($F47,G$2)>DATE(2025,12,31),"",INDEX([1]A1!D$9:D$175,MATCH(1,--(RIGHT([1]A1!$B$9:$B$175,LEN([1]A1!$B$9:$B$175)-4)=$A47)*([1]A1!$C$9:$C$175=YEAR($F47)),0)))} -> 57003214 | H47: {=IF(EDATE($F47,H$2)>DATE(2025,12,31),"",INDEX([1]A1!E$9:E$175,MATCH(1,--(RIGHT([1]A1!$B$9:$B$175,LEN([1]A1!$B$9:$B$175)-4)=$A47)*([1]A1!$C$9:$C$175=YEAR($F47)),0)))} -> 1.3242216e+08 | I47: {=IF(EDATE($F47,I$2)>DATE(2025,12,31),"",INDEX([1]A1!F$9:F$175,MATCH(1,--(RIGHT([1]A1!$B$9:$B$175,LEN([1]A1!$B$9:$B$175)-4)=$A47)*([1]A1!$C$9:$C$175=YEAR($F47)),0)))} -> 143340237 | J47: {=IF(EDATE($F47,J$2)>DATE(2025,12,31),"",INDEX([1]A1!G$9:G$175,MATCH(1,--(RIGHT([1]A1!$B$9:$B$175,LEN([1]A1!$B$9:$B$175)-4)=$A47)*([1]A1!$C$9:$C$175=YEAR($F47)),0)))} -> 1.4654263e+08 | K47: {=IF(EDATE($F47,K$2)>DATE(2025,12,31),"",INDEX([1]A1!H$9:H$175,MATCH(1,--(RIGHT([1]A1!$B$9:$B$175,LEN([1]A1!$B$9:$B$175)-4)=$A47)*([1]A1!$C$9:$C$175=YEAR($F47)),0)))} -> 1.4809748e+08 | L47: {=IF(EDATE($F47,L$2)>DATE(2025,12,31),"",INDEX([1]A1!I$9:I$175,MATCH(1,--(RIGHT([1]A1!$B$9:$B$175,LEN([1]A1!$B$9:$B$175)-4)=$A47)*([1]A1!$C$9:$C$175=YEAR($F47)),0)))} -> 1.4906858e+08 | M47: {=IF(EDATE($F47,M$2)>DATE(2025,12,31),"",INDEX([1]A1!J$9:J$175,MATCH(1,--(RIGHT([1]A1!$B$9:$B$175,LEN([1]A1!$B$9:$B$175)-4)=$A47)*([1]A1!$C$9:$C$175=YEAR($F47)),0)))} -> 1.502409e+08 | N47: {=IF(EDATE($F47,N$2)>DATE(2025,12,31),"",INDEX([1]A1!K$9:K$175,MATCH(1,--(RIGHT([1]A1!$B$9:$B$175,LEN([1]A1!$B$9:$B$175)-4)=$A47)*([1]A1!$C$9:$C$175=YEAR($F47)),0)))} -> 1.5108192e+08 | ... FA47: {=IF(EDATE($F47,FA$2)>DATE(2025,12,31),"",INDEX([1]A1!EX$9:EX$175,MATCH(1,--(RIGHT([1]A1!$B$9:$B$175,LEN([1]A1!$B$9:$B$175)-4)=$A47)*([1]A1!$C$9:$C$175=YEAR($F47)),0)))}
A48: Credit & Surety | B48: Net Written Premium | C48: All | D48: UW Year | E48: USD | F48: =EDATE(F47,12) -> 39814 | G48: {=IF(EDATE($F48,G$2)>DATE(2025,12,31),"",INDEX([1]A1!D$9:D$175,MATCH(1,--(RIGHT([1]A1!$B$9:$B$175,LEN([1]A1!$B$9:$B$175)-4)=$A48)*([1]A1!$C$9:$C$175=YEAR($F48)),0)))} -> 90292546 | H48: {=IF(EDATE($F48,H$2)>DATE(2025,12,31),"",INDEX([1]A1!E$9:E$175,MATCH(1,--(RIGHT([1]A1!$B$9:$B$175,LEN([1]A1!$B$9:$B$175)-4)=$A48)*([1]A1!$C$9:$C$175=YEAR($F48)),0)))} -> 1.9136748e+08 | I48: {=IF(EDATE($F48,I$2)>DATE(2025,12,31),"",INDEX([1]A1!F$9:F$175,MATCH(1,--(RIGHT([1]A1!$B$9:$B$175,LEN([1]A1!$B$9:$B$175)-4)=$A48)*([1]A1!$C$9:$C$175=YEAR($F48)),0)))} -> 2.0475917e+08 | J48: {=IF(EDATE($F48,J$2)>DATE(2025,12,31),"",INDEX([1]A1!G$9:G$175,MATCH(1,--(RIGHT([1]A1!$B$9:$B$175,LEN([1]A1!$B$9:$B$175)-4)=$A48)*([1]A1!$C$9:$C$175=YEAR($F48)),0)))} -> 2.0948928e+08 | K48: {=IF(EDATE($F48,K$2)>DATE(2025,12,31),"",INDEX([1]A1!H$9:H$175,MATCH(1,--(RIGHT([1]A1!$B$9:$B$175,LEN([1]A1!$B$9:$B$175)-4)=$A48)*([1]A1!$C$9:$C$175=YEAR($F48)),0)))} -> 2.1220088e+08 | L48: {=IF(EDATE($F48,L$2)>DATE(2025,12,31),"",INDEX([1]A1!I$9:I$175,MATCH(1,--(RIGHT([1]A1!$B$9:$B$175,LEN([1]A1!$B$9:$B$175)-4)=$A48)*([1]A1!$C$9:$C$175=YEAR($F48)),0)))} -> 2.153092e+08 | M48: {=IF(EDATE($F48,M$2)>DATE(2025,12,31),"",INDEX([1]A1!J$9:J$175,MATCH(1,--(RIGHT([1]A1!$B$9:$B$175,LEN([1]A1!$B$9:$B$175)-4)=$A48)*([1]A1!$C$9:$C$175=YEAR($F48)),0)))} -> 2.1646922e+08 | N48: {=IF(EDATE($F48,N$2)>DATE(2025,12,31),"",INDEX([1]A1!K$9:K$175,MATCH(1,--(RIGHT([1]A1!$B$9:$B$175,LEN([1]A1!$B$9:$B$175)-4)=$A48)*([1]A1!$C$9:$C$175=YEAR($F48)),0)))} -> 2.1760435e+08 | ... FA48: {=IF(EDATE($F48,FA$2)>DATE(2025,12,31),"",INDEX([1]A1!EX$9:EX$175,MATCH(1,--(RIGHT([1]A1!$B$9:$B$175,LEN([1]A1!$B$9:$B$175)-4)=$A48)*([1]A1!$C$9:$C$175=YEAR($F48)),0)))}
A49: Credit & Surety | B49: Net Written Premium | C49: All | D49: UW Year | E49: USD | F49: =EDATE(F48,12) -> 40179 | G49: {=IF(EDATE($F49,G$2)>DATE(2025,12,31),"",INDEX([1]A1!D$9:D$175,MATCH(1,--(RIGHT([1]A1!$B$9:$B$175,LEN([1]A1!$B$9:$B$175)-4)=$A49)*([1]A1!$C$9:$C$175=YEAR($F49)),0)))} -> 1.0600428e+08 | H49: {=IF(EDATE($F49,H$2)>DATE(2025,12,31),"",INDEX([1]A1!E$9:E$175,MATCH(1,--(RIGHT([1]A1!$B$9:$B$175,LEN([1]A1!$B$9:$B$175)-4)=$A49)*([1]A1!$C$9:$C$175=YEAR($F49)),0)))} -> 2.4430183e+08 | I49: {=IF(EDATE($F49,I$2)>DATE(2025,12,31),"",INDEX([1]A1!F$9:F$175,MATCH(1,--(RIGHT([1]A1!$B$9:$B$175,LEN([1]A1!$B$9:$B$175)-4)=$A49)*([1]A1!$C$9:$C$175=YEAR($F49)),0)))} -> 2.6745611e+08 | J49: {=IF(EDATE($F49,J$2)>DATE(2025,12,31),"",INDEX([1]A1!G$9:G$175,MATCH(1,--(RIGHT([1]A1!$B$9:$B$175,LEN([1]A1!$B$9:$B$175)-4)=$A49)*([1]A1!$C$9:$C$175=YEAR($F49)),0)))} -> 2.7982515e+08 | K49: {=IF(EDATE($F49,K$2)>DATE(2025,12,31),"",INDEX([1]A1!H$9:H$175,MATCH(1,--(RIGHT([1]A1!$B$9:$B$175,LEN([1]A1!$B$9:$B$175)-4)=$A49)*([1]A1!$C$9:$C$175=YEAR($F49)),0)))} -> 2.8090257e+08 | L49: {=IF(EDATE($F49,L$2)>DATE(2025,12,31),"",INDEX([1]A1!I$9:I$175,MATCH(1,--(RIGHT([1]A1!$B$9:$B$175,LEN([1]A1!$B$9:$B$175)-4)=$A49)*([1]A1!$C$9:$C$175=YEAR($F49)),0)))} -> 2.8423552e+08 | M49: {=IF(EDATE($F49,M$2)>DATE(2025,12,31),"",INDEX([1]A1!J$9:J$175,MATCH(1,--(RIGHT([1]A1!$B$9:$B$175,LEN([1]A1!$B$9:$B$175)-4)=$A49)*([1]A1!$C$9:$C$175=YEAR($F49)),0)))} -> 2.8651794e+08 | N49: {=IF(EDATE($F49,N$2)>DATE(2025,12,31),"",INDEX([1]A1!K$9:K$175,MATCH(1,--(RIGHT([1]A1!$B$9:$B$175,LEN([1]A1!$B$9:$B$175)-4)=$A49)*([1]A1!$C$9:$C$175=YEAR($F49)),0)))} -> 2.8884321e+08 | ... FA49: {=IF(EDATE($F49,FA$2)>DATE(2025,12,31),"",INDEX([1]A1!EX$9:EX$175,MATCH(1,--(RIGHT([1]A1!$B$9:$B$175,LEN([1]A1!$B$9:$B$175)-4)=$A49)*([1]A1!$C$9:$C$175=YEAR($F49)),0)))}
A50: Credit & Surety | B50: Net Written Premium | C50: All | D50: UW Year | E50: USD | F50: =EDATE(F49,12) -> 40544 | G50: {=IF(EDATE($F50,G$2)>DATE(2025,12,31),"",INDEX([1]A1!D$9:D$175,MATCH(1,--(RIGHT([1]A1!$B$9:$B$175,LEN([1]A1!$B$9:$B$175)-4)=$A50)*([1]A1!$C$9:$C$175=YEAR($F50)),0)))} -> 1.074641e+08 | H50: {=IF(EDATE($F50,H$2)>DATE(2025,12,31),"",INDEX([1]A1!E$9:E$175,MATCH(1,--(RIGHT([1]A1!$B$9:$B$175,LEN([1]A1!$B$9:$B$175)-4)=$A50)*([1]A1!$C$9:$C$175=YEAR($F50)),0)))} -> 2.4652604e+08 | I50: {=IF(EDATE($F50,I$2)>DATE(2025,12,31),"",INDEX([1]A1!F$9:F$175,MATCH(1,--(RIGHT([1]A1!$B$9:$B$175,LEN([1]A1!$B$9:$B$175)-4)=$A50)*([1]A1!$C$9:$C$175=YEAR($F50)),0)))} -> 2.9007492e+08 | J50: {=IF(EDATE($F50,J$2)>DATE(2025,12,31),"",INDEX([1]A1!G$9:G$175,MATCH(1,--(RIGHT([1]A1!$B$9:$B$175,LEN([1]A1!$B$9:$B$175)-4)=$A50)*([1]A1!$C$9:$C$175=YEAR($F50)),0)))} -> 2.8737362e+08 | K50: {=IF(EDATE($F50,K$2)>DATE(2025,12,31),"",INDEX([1]A1!H$9:H$175,MATCH(1,--(RIGHT([1]A1!$B$9:$B$175,LEN([1]A1!$B$9:$B$175)-4)=$A50)*([1]A1!$C$9:$C$175=YEAR($F50)),0)))} -> 2.8785782e+08 | L50: {=IF(EDATE($F50,L$2)>DATE(2025,12,31),"",INDEX([1]A1!I$9:I$175,MATCH(1,--(RIGHT([1]A1!$B$9:$B$175,LEN([1]A1!$B$9:$B$175)-4)=$A50)*([1]A1!$C$9:$C$175=YEAR($F50)),0)))} -> 2.9186248e+08 | M50: {=IF(EDATE($F50,M$2)>DATE(2025,12,31),"",INDEX([1]A1!J$9:J$175,MATCH(1,--(RIGHT([1]A1!$B$9:$B$175,LEN([1]A1!$B$9:$B$175)-4)=$A50)*([1]A1!$C$9:$C$175=YEAR($F50)),0)))} -> 2.9476429e+08 | N50: {=IF(EDATE($F50,N$2)>DATE(2025,12,31),"",INDEX([1]A1!K$9:K$175,MATCH(1,--(RIGHT([1]A1!$B$9:$B$175,LEN([1]A1!$B$9:$B$175)-4)=$A50)*([1]A1!$C$9:$C$175=YEAR($F50)),0)))} -> 2.96532e+08 | ... FA50: {=IF(EDATE($F50,FA$2)>DATE(2025,12,31),"",INDEX([1]A1!EX$9:EX$175,MATCH(1,--(RIGHT([1]A1!$B$9:$B$175,LEN([1]A1!$B$9:$B$175)-4)=$A50)*([1]A1!$C$9:$C$175=YEAR($F50)),0)))}
A51: Credit & Surety | B51: Net Written Premium | C51: All | D51: UW Year | E51: USD | F51: =EDATE(F50,12) -> 40909 | G51: {=IF(EDATE($F51,G$2)>DATE(2025,12,31),"",INDEX([1]A1!D$9:D$175,MATCH(1,--(RIGHT([1]A1!$B$9:$B$175,LEN([1]A1!$B$9:$B$175)-4)=$A51)*([1]A1!$C$9:$C$175=YEAR($F51)),0)))} -> 93982165 | H51: {=IF(EDATE($F51,H$2)>DATE(2025,12,31),"",INDEX([1]A1!E$9:E$175,MATCH(1,--(RIGHT([1]A1!$B$9:$B$175,LEN([1]A1!$B$9:$B$175)-4)=$A51)*([1]A1!$C$9:$C$175=YEAR($F51)),0)))} -> 2.6564598e+08 | I51: {=IF(EDATE($F51,I$2)>DATE(2025,12,31),"",INDEX([1]A1!F$9:F$175,MATCH(1,--(RIGHT([1]A1!$B$9:$B$175,LEN([1]A1!$B$9:$B$175)-4)=$A51)*([1]A1!$C$9:$C$175=YEAR($F51)),0)))} -> 2.6550867e+08 | J51: {=IF(EDATE($F51,J$2)>DATE(2025,12,31),"",INDEX([1]A1!G$9:G$175,MATCH(1,--(RIGHT([1]A1!$B$9:$B$175,LEN([1]A1!$B$9:$B$175)-4)=$A51)*([1]A1!$C$9:$C$175=YEAR($F51)),0)))} -> 2.5664613e+08 | K51: {=IF(EDATE($F51,K$2)>DATE(2025,12,31),"",INDEX([1]A1!H$9:H$175,MATCH(1,--(RIGHT([1]A1!$B$9:$B$175,LEN([1]A1!$B$9:$B$175)-4)=$A51)*([1]A1!$C$9:$C$175=YEAR($F51)),0)))} -> 2.600672e+08 | L51: {=IF(EDATE($F51,L$2)>DATE(2025,12,31),"",INDEX([1]A1!I$9:I$175,MATCH(1,--(RIGHT([1]A1!$B$9:$B$175,LEN([1]A1!$B$9:$B$175)-4)=$A51)*([1]A1!$C$9:$C$175=YEAR($F51)),0)))} -> 2.6306405e+08 | M51: {=IF(EDATE($F51,M$2)>DATE(2025,12,31),"",INDEX([1]A1!J$9:J$175,MATCH(1,--(RIGHT([1]A1!$B$9:$B$175,LEN([1]A1!$B$9:$B$175)-4)=$A51)*([1]A1!$C$9:$C$175=YEAR($F51)),0)))} -> 2.6490088e+08 | N51: {=IF(EDATE($F51,N$2)>DATE(2025,12,31),"",INDEX([1]A1!K$9:K$175,MATCH(1,--(RIGHT([1]A1!$B$9:$B$175,LEN([1]A1!$B$9:$B$175)-4)=$A51)*([1]A1!$C$9:$C$175=YEAR($F51)),0)))} -> 2.6625776e+08 | ... FA51: {=IF(EDATE($F51,FA$2)>DATE(2025,12,31),"",INDEX([1]A1!EX$9:EX$175,MATCH(1,--(RIGHT([1]A1!$B$9:$B$175,LEN([1]A1!$B$9:$B$175)-4)=$A51)*([1]A1!$C$9:$C$175=YEAR($F51)),0)))}
A52: Credit & Surety | B52: Net Written Premium | C52: All | D52: UW Year | E52: USD | F52: =EDATE(F51,12) -> 41275 | G52: {=IF(EDATE($F52,G$2)>DATE(2025,12,31),"",INDEX([1]A1!D$9:D$175,MATCH(1,--(RIGHT([1]A1!$B$9:$B$175,LEN([1]A1!$B$9:$B$175)-4)=$A52)*([1]A1!$C$9:$C$175=YEAR($F52)),0)))} -> 2.397033e+08 | H52: {=IF(EDATE($F52,H$2)>DATE(2025,12,31),"",INDEX([1]A1!E$9:E$175,MATCH(1,--(RIGHT([1]A1!$B$9:$B$175,LEN([1]A1!$B$9:$B$175)-4)=$A52)*([1]A1!$C$9:$C$175=YEAR($F52)),0)))} -> 2.5243441e+08 | I52: {=IF(EDATE($F52,I$2)>DATE(2025,12,31),"",INDEX([1]A1!F$9:F$175,MATCH(1,--(RIGHT([1]A1!$B$9:$B$175,LEN([1]A1!$B$9:$B$175)-4)=$A52)*([1]A1!$C$9:$C$175=YEAR($F52)),0)))} -> 2.4767713e+08 | J52: {=IF(EDATE($F52,J$2)>DATE(2025,12,31),"",INDEX([1]A1!G$9:G$175,MATCH(1,--(RIGHT([1]A1!$B$9:$B$175,LEN([1]A1!$B$9:$B$175)-4)=$A52)*([1]A1!$C$9:$C$175=YEAR($F52)),0)))} -> 2.493493e+08 | K52: {=IF(EDATE($F52,K$2)>DATE(2025,12,31),"",INDEX([1]A1!H$9:H$175,MATCH(1,--(RIGHT([1]A1!$B$9:$B$175,LEN([1]A1!$B$9:$B$175)-4)=$A52)*([1]A1!$C$9:$C$175=YEAR($F52)),0)))} -> 2.4923886e+08 | L52: {=IF(EDATE($F52,L$2)>DATE(2025,12,31),"",INDEX([1]A1!I$9:I$175,MATCH(1,--(RIGHT([1]A1!$B$9:$B$175,LEN([1]A1!$B$9:$B$175)-4)=$A52)*([1]A1!$C$9:$C$175=YEAR($F52)),0)))} -> 2.5181356e+08 | M52: {=IF(EDATE($F52,M$2)>DATE(2025,12,31),"",INDEX([1]A1!J$9:J$175,MATCH(1,--(RIGHT([1]A1!$B$9:$B$175,LEN([1]A1!$B$9:$B$175)-4)=$A52)*([1]A1!$C$9:$C$175=YEAR($F52)),0)))} -> 2.5409071e+08 | N52: {=IF(EDATE($F52,N$2)>DATE(2025,12,31),"",INDEX([1]A1!K$9:K$175,MATCH(1,--(RIGHT([1]A1!$B$9:$B$175,LEN([1]A1!$B$9:$B$175)-4)=$A52)*([1]A1!$C$9:$C$175=YEAR($F52)),0)))} -> 2.5594415e+08 | ... FA52: {=IF(EDATE($F52,FA$2)>DATE(2025,12,31),"",INDEX([1]A1!EX$9:EX$175,MATCH(1,--(RIGHT([1]A1!$B$9:$B$175,LEN([1]A1!$B$9:$B$175)-4)=$A52)*([1]A1!$C$9:$C$175=YEAR($F52)),0)))}
A53: Credit & Surety | B53: Net Written Premium | C53: All | D53: UW Year | E53: USD | F53: =EDATE(F52,12) -> 41640 | G53: {=IF(EDATE($F53,G$2)>DATE(2025,12,31),"",INDEX([1]A1!D$9:D$175,MATCH(1,--(RIGHT([1]A1!$B$9:$B$175,LEN([1]A1!$B$9:$B$175)-4)=$A53)*([1]A1!$C$9:$C$175=YEAR($F53)),0)))} -> 2.4398723e+08 | H53: {=IF(EDATE($F53,H$2)>DATE(2025,12,31),"",INDEX([1]A1!E$9:E$175,MATCH(1,--(RIGHT([1]A1!$B$9:$B$175,LEN([1]A1!$B$9:$B$175)-4)=$A53)*([1]A1!$C$9:$C$175=YEAR($F53)),0)))} -> 2.5511469e+08 | I53: {=IF(EDATE($F53,I$2)>DATE(2025,12,31),"",INDEX([1]A1!F$9:F$175,MATCH(1,--(RIGHT([1]A1!$B$9:$B$175,LEN([1]A1!$B$9:$B$175)-4)=$A53)*([1]A1!$C$9:$C$175=YEAR($F53)),0)))} -> 2.6007243e+08 | J53: {=IF(EDATE($F53,J$2)>DATE(2025,12,31),"",INDEX([1]A1!G$9:G$175,MATCH(1,--(RIGHT([1]A1!$B$9:$B$175,LEN([1]A1!$B$9:$B$175)-4)=$A53)*([1]A1!$C$9:$C$175=YEAR($F53)),0)))} -> 2.5327071e+08 | K53: {=IF(EDATE($F53,K$2)>DATE(2025,12,31),"",INDEX([1]A1!H$9:H$175,MATCH(1,--(RIGHT([1]A1!$B$9:$B$175,LEN([1]A1!$B$9:$B$175)-4)=$A53)*([1]A1!$C$9:$C$175=YEAR($F53)),0)))} -> 2.5474245e+08 | L53: {=IF(EDATE($F53,L$2)>DATE(2025,12,31),"",INDEX([1]A1!I$9:I$175,MATCH(1,--(RIGHT([1]A1!$B$9:$B$175,LEN([1]A1!$B$9:$B$175)-4)=$A53)*([1]A1!$C$9:$C$175=YEAR($F53)),0)))} -> 2.576695e+08 | M53: {=IF(EDATE($F53,M$2)>DATE(2025,12,31),"",INDEX([1]A1!J$9:J$175,MATCH(1,--(RIGHT([1]A1!$B$9:$B$175,LEN([1]A1!$B$9:$B$175)-4)=$A53)*([1]A1!$C$9:$C$175=YEAR($F53)),0)))} -> 2.5955756e+08 | N53: {=IF(EDATE($F53,N$2)>DATE(2025,12,31),"",INDEX([1]A1!K$9:K$175,MATCH(1,--(RIGHT([1]A1!$B$9:$B$175,LEN([1]A1!$B$9:$B$175)-4)=$A53)*([1]A1!$C$9:$C$175=YEAR($F53)),0)))} -> 2.6103521e+08 | ... FA53: {=IF(EDATE($F53,FA$2)>DATE(2025,12,31),"",INDEX([1]A1!EX$9:EX$175,MATCH(1,--(RIGHT([1]A1!$B$9:$B$175,LEN([1]A1!$B$9:$B$175)-4)=$A53)*([1]A1!$C$9:$C$175=YEAR($F53)),0)))}
A54: Credit & Surety | B54: Net Written Premium | C54: All | D54: UW Year | E54: USD | F54: =EDATE(F53,12) -> 42005 | G54: {=IF(EDATE($F54,G$2)>DATE(2025,12,31),"",INDEX([1]A1!D$9:D$175,MATCH(1,--(RIGHT([1]A1!$B$9:$B$175,LEN([1]A1!$B$9:$B$175)-4)=$A54)*([1]A1!$C$9:$C$175=YEAR($F54)),0)))} -> 2.2535875e+08 | H54: {=IF(EDATE($F54,H$2)>DATE(2025,12,31),"",INDEX([1]A1!E$9:E$175,MATCH(1,--(RIGHT([1]A1!$B$9:$B$175,LEN([1]A1!$B$9:$B$175)-4)=$A54)*([1]A1!$C$9:$C$175=YEAR($F54)),0)))} -> 2.3207554e+08 | I54: {=IF(EDATE($F54,I$2)>DATE(2025,12,31),"",INDEX([1]A1!F$9:F$175,MATCH(1,--(RIGHT([1]A1!$B$9:$B$175,LEN([1]A1!$B$9:$B$175)-4)=$A54)*([1]A1!$C$9:$C$175=YEAR($F54)),0)))} -> 2.2860633e+08 | J54: {=IF(EDATE($F54,J$2)>DATE(2025,12,31),"",INDEX([1]A1!G$9:G$175,MATCH(1,--(RIGHT([1]A1!$B$9:$B$175,LEN([1]A1!$B$9:$B$175)-4)=$A54)*([1]A1!$C$9:$C$175=YEAR($F54)),0)))} -> 2.2360703e+08 | K54: {=IF(EDATE($F54,K$2)>DATE(2025,12,31),"",INDEX([1]A1!H$9:H$175,MATCH(1,--(RIGHT([1]A1!$B$9:$B$175,LEN([1]A1!$B$9:$B$175)-4)=$A54)*([1]A1!$C$9:$C$175=YEAR($F54)),0)))} -> 2.2316721e+08 | L54: {=IF(EDATE($F54,L$2)>DATE(2025,12,31),"",INDEX([1]A1!I$9:I$175,MATCH(1,--(RIGHT([1]A1!$B$9:$B$175,LEN([1]A1!$B$9:$B$175)-4)=$A54)*([1]A1!$C$9:$C$175=YEAR($F54)),0)))} -> 2.2557852e+08 | M54: {=IF(EDATE($F54,M$2)>DATE(2025,12,31),"",INDEX([1]A1!J$9:J$175,MATCH(1,--(RIGHT([1]A1!$B$9:$B$175,LEN([1]A1!$B$9:$B$175)-4)=$A54)*([1]A1!$C$9:$C$175=YEAR($F54)),0)))} -> 2.2755354e+08 | N54: {=IF(EDATE($F54,N$2)>DATE(2025,12,31),"",INDEX([1]A1!K$9:K$175,MATCH(1,--(RIGHT([1]A1!$B$9:$B$175,LEN([1]A1!$B$9:$B$175)-4)=$A54)*([1]A1!$C$9:$C$175=YEAR($F54)),0)))} -> 2.2849712e+08 | ... FA54: {=IF(EDATE($F54,FA$2)>DATE(2025,12,31),"",INDEX([1]A1!EX$9:EX$175,MATCH(1,--(RIGHT([1]A1!$B$9:$B$175,LEN([1]A1!$B$9:$B$175)-4)=$A54)*([1]A1!$C$9:$C$175=YEAR($F54)),0)))}
A55: Credit & Surety | B55: Net Written Premium | C55: All | D55: UW Year | E55: USD | F55: =EDATE(F54,12) -> 42370 | G55: {=IF(EDATE($F55,G$2)>DATE(2025,12,31),"",INDEX([1]A1!D$9:D$175,MATCH(1,--(RIGHT([1]A1!$B$9:$B$175,LEN([1]A1!$B$9:$B$175)-4)=$A55)*([1]A1!$C$9:$C$175=YEAR($F55)),0)))} -> 2.1563611e+08 | H55: {=IF(EDATE($F55,H$2)>DATE(2025,12,31),"",INDEX([1]A1!E$9:E$175,MATCH(1,--(RIGHT([1]A1!$B$9:$B$175,LEN([1]A1!$B$9:$B$175)-4)=$A55)*([1]A1!$C$9:$C$175=YEAR($F55)),0)))} -> 2.2424745e+08 | I55: {=IF(EDATE($F55,I$2)>DATE(2025,12,31),"",INDEX([1]A1!F$9:F$175,MATCH(1,--(RIGHT([1]A1!$B$9:$B$175,LEN([1]A1!$B$9:$B$175)-4)=$A55)*([1]A1!$C$9:$C$175=YEAR($F55)),0)))} -> 2.3481575e+08 | J55: {=IF(EDATE($F55,J$2)>DATE(2025,12,31),"",INDEX([1]A1!G$9:G$175,MATCH(1,--(RIGHT([1]A1!$B$9:$B$175,LEN([1]A1!$B$9:$B$175)-4)=$A55)*([1]A1!$C$9:$C$175=YEAR($F55)),0)))} -> 2.3071583e+08 | K55: {=IF(EDATE($F55,K$2)>DATE(2025,12,31),"",INDEX([1]A1!H$9:H$175,MATCH(1,--(RIGHT([1]A1!$B$9:$B$175,LEN([1]A1!$B$9:$B$175)-4)=$A55)*([1]A1!$C$9:$C$175=YEAR($F55)),0)))} -> 2.2918614e+08 | L55: {=IF(EDATE($F55,L$2)>DATE(2025,12,31),"",INDEX([1]A1!I$9:I$175,MATCH(1,--(RIGHT([1]A1!$B$9:$B$175,LEN([1]A1!$B$9:$B$175)-4)=$A55)*([1]A1!$C$9:$C$175=YEAR($F55)),0)))} -> 2.3126737e+08 | M55: {=IF(EDATE($F55,M$2)>DATE(2025,12,31),"",INDEX([1]A1!J$9:J$175,MATCH(1,--(RIGHT([1]A1!$B$9:$B$175,LEN([1]A1!$B$9:$B$175)-4)=$A55)*([1]A1!$C$9:$C$175=YEAR($F55)),0)))} -> 2.3354167e+08 | N55: {=IF(EDATE($F55,N$2)>DATE(2025,12,31),"",INDEX([1]A1!K$9:K$175,MATCH(1,--(RIGHT([1]A1!$B$9:$B$175,LEN([1]A1!$B$9:$B$175)-4)=$A55)*([1]A1!$C$9:$C$175=YEAR($F55)),0)))} -> 2.3612899e+08 | ... FA55: {=IF(EDATE($F55,FA$2)>DATE(2025,12,31),"",INDEX([1]A1!EX$9:EX$175,MATCH(1,--(RIGHT([1]A1!$B$9:$B$175,LEN([1]A1!$B$9:$B$175)-4)=$A55)*([1]A1!$C$9:$C$175=YEAR($F55)),0)))}
A56: Credit & Surety | B56: Net Written Premium | C56: All | D56: UW Year | E56: USD | F56: =EDATE(F55,12) -> 42736 | G56: {=IF(EDATE($F56,G$2)>DATE(2025,12,31),"",INDEX([1]A1!D$9:D$175,MATCH(1,--(RIGHT([1]A1!$B$9:$B$175,LEN([1]A1!$B$9:$B$175)-4)=$A56)*([1]A1!$C$9:$C$175=YEAR($F56)),0)))} -> 2.2445797e+08 | H56: {=IF(EDATE($F56,H$2)>DATE(2025,12,31),"",INDEX([1]A1!E$9:E$175,MATCH(1,--(RIGHT([1]A1!$B$9:$B$175,LEN([1]A1!$B$9:$B$175)-4)=$A56)*([1]A1!$C$9:$C$175=YEAR($F56)),0)))} -> 2.4993937e+08 | I56: {=IF(EDATE($F56,I$2)>DATE(2025,12,31),"",INDEX([1]A1!F$9:F$175,MATCH(1,--(RIGHT([1]A1!$B$9:$B$175,LEN([1]A1!$B$9:$B$175)-4)=$A56)*([1]A1!$C$9:$C$175=YEAR($F56)),0)))} -> 2.539147e+08 | J56: {=IF(EDATE($F56,J$2)>DATE(2025,12,31),"",INDEX([1]A1!G$9:G$175,MATCH(1,--(RIGHT([1]A1!$B$9:$B$175,LEN([1]A1!$B$9:$B$175)-4)=$A56)*([1]A1!$C$9:$C$175=YEAR($F56)),0)))} -> 2.5497367e+08 | K56: {=IF(EDATE($F56,K$2)>DATE(2025,12,31),"",INDEX([1]A1!H$9:H$175,MATCH(1,--(RIGHT([1]A1!$B$9:$B$175,LEN([1]A1!$B$9:$B$175)-4)=$A56)*([1]A1!$C$9:$C$175=YEAR($F56)),0)))} -> 2.5263391e+08 | L56: {=IF(EDATE($F56,L$2)>DATE(2025,12,31),"",INDEX([1]A1!I$9:I$175,MATCH(1,--(RIGHT([1]A1!$B$9:$B$175,LEN([1]A1!$B$9:$B$175)-4)=$A56)*([1]A1!$C$9:$C$175=YEAR($F56)),0)))} -> 2.5577481e+08 | M56: {=IF(EDATE($F56,M$2)>DATE(2025,12,31),"",INDEX([1]A1!J$9:J$175,MATCH(1,--(RIGHT([1]A1!$B$9:$B$175,LEN([1]A1!$B$9:$B$175)-4)=$A56)*([1]A1!$C$9:$C$175=YEAR($F56)),0)))} -> 2.6199504e+08 | N56: {=IF(EDATE($F56,N$2)>DATE(2025,12,31),"",INDEX([1]A1!K$9:K$175,MATCH(1,--(RIGHT([1]A1!$B$9:$B$175,LEN([1]A1!$B$9:$B$175)-4)=$A56)*([1]A1!$C$9:$C$175=YEAR($F56)),0)))} -> 2.6330329e+08 | ... FA56: {=IF(EDATE($F56,FA$2)>DATE(2025,12,31),"",INDEX([1]A1!EX$9:EX$175,MATCH(1,--(RIGHT([1]A1!$B$9:$B$175,LEN([1]A1!$B$9:$B$175)-4)=$A56)*([1]A1!$C$9:$C$175=YEAR($F56)),0)))}
A57: Credit & Surety | B57: Net Written Premium | C57: All | D57: UW Year | E57: USD | F57: =EDATE(F56,12) -> 43101 | G57: {=IF(EDATE($F57,G$2)>DATE(2025,12,31),"",INDEX([1]A1!D$9:D$175,MATCH(1,--(RIGHT([1]A1!$B$9:$B$175,LEN([1]A1!$B$9:$B$175)-4)=$A57)*([1]A1!$C$9:$C$175=YEAR($F57)),0)))} -> 2.3493264e+08 | H57: {=IF(EDATE($F57,H$2)>DATE(2025,12,31),"",INDEX([1]A1!E$9:E$175,MATCH(1,--(RIGHT([1]A1!$B$9:$B$175,LEN([1]A1!$B$9:$B$175)-4)=$A57)*([1]A1!$C$9:$C$175=YEAR($F57)),0)))} -> 2.4094962e+08 | I57: {=IF(EDATE($F57,I$2)>DATE(2025,12,31),"",INDEX([1]A1!F$9:F$175,MATCH(1,--(RIGHT([1]A1!$B$9:$B$175,LEN([1]A1!$B$9:$B$175)-4)=$A57)*([1]A1!$C$9:$C$175=YEAR($F57)),0)))} -> 2.5011281e+08 | J57: {=IF(EDATE($F57,J$2)>DATE(2025,12,31),"",INDEX([1]A1!G$9:G$175,MATCH(1,--(RIGHT([1]A1!$B$9:$B$175,LEN([1]A1!$B$9:$B$175)-4)=$A57)*([1]A1!$C$9:$C$175=YEAR($F57)),0)))} -> 2.4739868e+08 | K57: {=IF(EDATE($F57,K$2)>DATE(2025,12,31),"",INDEX([1]A1!H$9:H$175,MATCH(1,--(RIGHT([1]A1!$B$9:$B$175,LEN([1]A1!$B$9:$B$175)-4)=$A57)*([1]A1!$C$9:$C$175=YEAR($F57)),0)))} -> 2.4570456e+08 | L57: {=IF(EDATE($F57,L$2)>DATE(2025,12,31),"",INDEX([1]A1!I$9:I$175,MATCH(1,--(RIGHT([1]A1!$B$9:$B$175,LEN([1]A1!$B$9:$B$175)-4)=$A57)*([1]A1!$C$9:$C$175=YEAR($F57)),0)))} -> 2.4888746e+08 | M57: {=IF(EDATE($F57,M$2)>DATE(2025,12,31),"",INDEX([1]A1!J$9:J$175,MATCH(1,--(RIGHT([1]A1!$B$9:$B$175,LEN([1]A1!$B$9:$B$175)-4)=$A57)*([1]A1!$C$9:$C$175=YEAR($F57)),0)))} -> 2.5226659e+08 | N57: {=IF(EDATE($F57,N$2)>DATE(2025,12,31),"",INDEX([1]A1!K$9:K$175,MATCH(1,--(RIGHT([1]A1!$B$9:$B$175,LEN([1]A1!$B$9:$B$175)-4)=$A57)*([1]A1!$C$9:$C$175=YEAR($F57)),0)))} -> 2.5449481e+08 | ... FA57: {=IF(EDATE($F57,FA$2)>DATE(2025,12,31),"",INDEX([1]A1!EX$9:EX$175,MATCH(1,--(RIGHT([1]A1!$B$9:$B$175,LEN([1]A1!$B$9:$B$175)-4)=$A57)*([1]A1!$C$9:$C$175=YEAR($F57)),0)))}
... A64: Credit & Surety | B64: Net Written Premium | C64: All | D64: UW Year | E64: USD | F64: =EDATE(F63,12) -> 45658 | G64: {=IF(EDATE($F64,G$2)>DATE(2025,12,31),"",INDEX([1]A1!D$9:D$175,MATCH(1,--(RIGHT([1]A1!$B$9:$B$175,LEN([1]A1!$B$9:$B$175)-4)=$A64)*([1]A1!$C$9:$C$175=YEAR($F64)),0)))} -> 1.8391216e+08 | H64: {=IF(EDATE($F64,H$2)>DATE(2025,12,31),"",INDEX([1]A1!E$9:E$175,MATCH(1,--(RIGHT([1]A1!$B$9:$B$175,LEN([1]A1!$B$9:$B$175)-4)=$A64)*([1]A1!$C$9:$C$175=YEAR($F64)),0)))} | I64: {=IF(EDATE($F64,I$2)>DATE(2025,12,31),"",INDEX([1]A1!F$9:F$175,MATCH(1,--(RIGHT([1]A1!$B$9:$B$175,LEN([1]A1!$B$9:$B$175)-4)=$A64)*([1]A1!$C$9:$C$175=YEAR($F64)),0)))} | J64: {=IF(EDATE($F64,J$2)>DATE(2025,12,31),"",INDEX([1]A1!G$9:G$175,MATCH(1,--(RIGHT([1]A1!$B$9:$B$175,LEN([1]A1!$B$9:$B$175)-4)=$A64)*([1]A1!$C$9:$C$175=YEAR($F64)),0)))} | K64: {=IF(EDATE($F64,K$2)>DATE(2025,12,31),"",INDEX([1]A1!H$9:H$175,MATCH(1,--(RIGHT([1]A1!$B$9:$B$175,LEN([1]A1!$B$9:$B$175)-4)=$A64)*([1]A1!$C$9:$C$175=YEAR($F64)),0)))} | L64: {=IF(EDATE($F64,L$2)>DATE(2025,12,31),"",INDEX([1]A1!I$9:I$175,MATCH(1,--(RIGHT([1]A1!$B$9:$B$175,LEN([1]A1!$B$9:$B$175)-4)=$A64)*([1]A1!$C$9:$C$175=YEAR($F64)),0)))} | M64: {=IF(EDATE($F64,M$2)>DATE(2025,12,31),"",INDEX([1]A1!J$9:J$175,MATCH(1,--(RIGHT([1]A1!$B$9:$B$175,LEN([1]A1!$B$9:$B$175)-4)=$A64)*([1]A1!$C$9:$C$175=YEAR($F64)),0)))} | N64: {=IF(EDATE($F64,N$2)>DATE(2025,12,31),"",INDEX([1]A1!K$9:K$175,MATCH(1,--(RIGHT([1]A1!$B$9:$B$175,LEN([1]A1!$B$9:$B$175)-4)=$A64)*([1]A1!$C$9:$C$175=YEAR($F64)),0)))} | ... FA64: {=IF(EDATE($F64,FA$2)>DATE(2025,12,31),"",INDEX([1]A1!EX$9:EX$175,MATCH(1,--(RIGHT([1]A1!$B$9:$B$175,LEN([1]A1!$B$9:$B$175)-4)=$A64)*([1]A1!$C$9:$C$175=YEAR($F64)),0)))}
A66: Motor NP | B66: Net Written Premium | C66: All | D66: UW Year | E66: USD | F66: =triangle_start_date -> 38718 | G66: {=IF(EDATE($F66,G$2)>DATE(2025,12,31),"",INDEX([1]A1!D$9:D$175,MATCH(1,--(RIGHT([1]A1!$B$9:$B$175,LEN([1]A1!$B$9:$B$175)-4)=$A66)*([1]A1!$C$9:$C$175=YEAR($F66)),0)))} -> 91402590 | H66: {=IF(EDATE($F66,H$2)>DATE(2025,12,31),"",INDEX([1]A1!E$9:E$175,MATCH(1,--(RIGHT([1]A1!$B$9:$B$175,LEN([1]A1!$B$9:$B$175)-4)=$A66)*([1]A1!$C$9:$C$175=YEAR($F66)),0)))} -> 78853632 | I66: {=IF(EDATE($F66,I$2)>DATE(2025,12,31),"",INDEX([1]A1!F$9:F$175,MATCH(1,--(RIGHT([1]A1!$B$9:$B$175,LEN([1]A1!$B$9:$B$175)-4)=$A66)*([1]A1!$C$9:$C$175=YEAR($F66)),0)))} -> 81953558 | J66: {=IF(EDATE($F66,J$2)>DATE(2025,12,31),"",INDEX([1]A1!G$9:G$175,MATCH(1,--(RIGHT([1]A1!$B$9:$B$175,LEN([1]A1!$B$9:$B$175)-4)=$A66)*([1]A1!$C$9:$C$175=YEAR($F66)),0)))} -> 82171657 | K66: {=IF(EDATE($F66,K$2)>DATE(2025,12,31),"",INDEX([1]A1!H$9:H$175,MATCH(1,--(RIGHT([1]A1!$B$9:$B$175,LEN([1]A1!$B$9:$B$175)-4)=$A66)*([1]A1!$C$9:$C$175=YEAR($F66)),0)))} -> 82271939 | L66: {=IF(EDATE($F66,L$2)>DATE(2025,12,31),"",INDEX([1]A1!I$9:I$175,MATCH(1,--(RIGHT([1]A1!$B$9:$B$175,LEN([1]A1!$B$9:$B$175)-4)=$A66)*([1]A1!$C$9:$C$175=YEAR($F66)),0)))} -> 82315382 | M66: {=IF(EDATE($F66,M$2)>DATE(2025,12,31),"",INDEX([1]A1!J$9:J$175,MATCH(1,--(RIGHT([1]A1!$B$9:$B$175,LEN([1]A1!$B$9:$B$175)-4)=$A66)*([1]A1!$C$9:$C$175=YEAR($F66)),0)))} -> 82183167 | N66: {=IF(EDATE($F66,N$2)>DATE(2025,12,31),"",INDEX([1]A1!K$9:K$175,MATCH(1,--(RIGHT([1]A1!$B$9:$B$175,LEN([1]A1!$B$9:$B$175)-4)=$A66)*([1]A1!$C$9:$C$175=YEAR($F66)),0)))} -> 82699557 | ... FA66: {=IF(EDATE($F66,FA$2)>DATE(2025,12,31),"",INDEX([1]A1!EX$9:EX$175,MATCH(1,--(RIGHT([1]A1!$B$9:$B$175,LEN([1]A1!$B$9:$B$175)-4)=$A66)*([1]A1!$C$9:$C$175=YEAR($F66)),0)))}
A67: Motor NP | B67: Net Written Premium | C67: All | D67: UW Year | E67: USD | F67: =EDATE(F66,12) -> 39083 | G67: {=IF(EDATE($F67,G$2)>DATE(2025,12,31),"",INDEX([1]A1!D$9:D$175,MATCH(1,--(RIGHT([1]A1!$B$9:$B$175,LEN([1]A1!$B$9:$B$175)-4)=$A67)*([1]A1!$C$9:$C$175=YEAR($F67)),0)))} -> 78816364 | H67: {=IF(EDATE($F67,H$2)>DATE(2025,12,31),"",INDEX([1]A1!E$9:E$175,MATCH(1,--(RIGHT([1]A1!$B$9:$B$175,LEN([1]A1!$B$9:$B$175)-4)=$A67)*([1]A1!$C$9:$C$175=YEAR($F67)),0)))} -> 88175369 | I67: {=IF(EDATE($F67,I$2)>DATE(2025,12,31),"",INDEX([1]A1!F$9:F$175,MATCH(1,--(RIGHT([1]A1!$B$9:$B$175,LEN([1]A1!$B$9:$B$175)-4)=$A67)*([1]A1!$C$9:$C$175=YEAR($F67)),0)))} -> 89157490 | J67: {=IF(EDATE($F67,J$2)>DATE(2025,12,31),"",INDEX([1]A1!G$9:G$175,MATCH(1,--(RIGHT([1]A1!$B$9:$B$175,LEN([1]A1!$B$9:$B$175)-4)=$A67)*([1]A1!$C$9:$C$175=YEAR($F67)),0)))} -> 89611767 | K67: {=IF(EDATE($F67,K$2)>DATE(2025,12,31),"",INDEX([1]A1!H$9:H$175,MATCH(1,--(RIGHT([1]A1!$B$9:$B$175,LEN([1]A1!$B$9:$B$175)-4)=$A67)*([1]A1!$C$9:$C$175=YEAR($F67)),0)))} -> 89652094 | L67: {=IF(EDATE($F67,L$2)>DATE(2025,12,31),"",INDEX([1]A1!I$9:I$175,MATCH(1,--(RIGHT([1]A1!$B$9:$B$175,LEN([1]A1!$B$9:$B$175)-4)=$A67)*([1]A1!$C$9:$C$175=YEAR($F67)),0)))} -> 89835487 | M67: {=IF(EDATE($F67,M$2)>DATE(2025,12,31),"",INDEX([1]A1!J$9:J$175,MATCH(1,--(RIGHT([1]A1!$B$9:$B$175,LEN([1]A1!$B$9:$B$175)-4)=$A67)*([1]A1!$C$9:$C$175=YEAR($F67)),0)))} -> 92941578 | N67: {=IF(EDATE($F67,N$2)>DATE(2025,12,31),"",INDEX([1]A1!K$9:K$175,MATCH(1,--(RIGHT([1]A1!$B$9:$B$175,LEN([1]A1!$B$9:$B$175)-4)=$A67)*([1]A1!$C$9:$C$175=YEAR($F67)),0)))} -> 92968485 | ... FA67: {=IF(EDATE($F67,FA$2)>DATE(2025,12,31),"",INDEX([1]A1!EX$9:EX$175,MATCH(1,--(RIGHT([1]A1!$B$9:$B$175,LEN([1]A1!$B$9:$B$175)-4)=$A67)*([1]A1!$C$9:$C$175=YEAR($F67)),0)))}
A68: Motor NP | B68: Net Written Premium | C68: All | D68: UW Year | E68: USD | F68: =EDATE(F67,12) -> 39448 | G68: {=IF(EDATE($F68,G$2)>DATE(2025,12,31),"",INDEX([1]A1!D$9:D$175,MATCH(1,--(RIGHT([1]A1!$B$9:$B$175,LEN([1]A1!$B$9:$B$175)-4)=$A68)*([1]A1!$C$9:$C$175=YEAR($F68)),0)))} -> 76151502 | H68: {=IF(EDATE($F68,H$2)>DATE(2025,12,31),"",INDEX([1]A1!E$9:E$175,MATCH(1,--(RIGHT([1]A1!$B$9:$B$175,LEN([1]A1!$B$9:$B$175)-4)=$A68)*([1]A1!$C$9:$C$175=YEAR($F68)),0)))} -> 87282160 | I68: {=IF(EDATE($F68,I$2)>DATE(2025,12,31),"",INDEX([1]A1!F$9:F$175,MATCH(1,--(RIGHT([1]A1!$B$9:$B$175,LEN([1]A1!$B$9:$B$175)-4)=$A68)*([1]A1!$C$9:$C$175=YEAR($F68)),0)))} -> 87686145 | J68: {=IF(EDATE($F68,J$2)>DATE(2025,12,31),"",INDEX([1]A1!G$9:G$175,MATCH(1,--(RIGHT([1]A1!$B$9:$B$175,LEN([1]A1!$B$9:$B$175)-4)=$A68)*([1]A1!$C$9:$C$175=YEAR($F68)),0)))} -> 87749162 | K68: {=IF(EDATE($F68,K$2)>DATE(2025,12,31),"",INDEX([1]A1!H$9:H$175,MATCH(1,--(RIGHT([1]A1!$B$9:$B$175,LEN([1]A1!$B$9:$B$175)-4)=$A68)*([1]A1!$C$9:$C$175=YEAR($F68)),0)))} -> 88091061 | L68: {=IF(EDATE($F68,L$2)>DATE(2025,12,31),"",INDEX([1]A1!I$9:I$175,MATCH(1,--(RIGHT([1]A1!$B$9:$B$175,LEN([1]A1!$B$9:$B$175)-4)=$A68)*([1]A1!$C$9:$C$175=YEAR($F68)),0)))} -> 88422433 | M68: {=IF(EDATE($F68,M$2)>DATE(2025,12,31),"",INDEX([1]A1!J$9:J$175,MATCH(1,--(RIGHT([1]A1!$B$9:$B$175,LEN([1]A1!$B$9:$B$175)-4)=$A68)*([1]A1!$C$9:$C$175=YEAR($F68)),0)))} -> 88318982 | N68: {=IF(EDATE($F68,N$2)>DATE(2025,12,31),"",INDEX([1]A1!K$9:K$175,MATCH(1,--(RIGHT([1]A1!$B$9:$B$175,LEN([1]A1!$B$9:$B$175)-4)=$A68)*([1]A1!$C$9:$C$175=YEAR($F68)),0)))} -> 88426891 | ... FA68: {=IF(EDATE($F68,FA$2)>DATE(2025,12,31),"",INDEX([1]A1!EX$9:EX$175,MATCH(1,--(RIGHT([1]A1!$B$9:$B$175,LEN([1]A1!$B$9:$B$175)-4)=$A68)*([1]A1!$C$9:$C$175=YEAR($F68)),0)))}
A69: Motor NP | B69: Net Written Premium | C69: All | D69: UW Year | E69: USD | F69: =EDATE(F68,12) -> 39814 | G69: {=IF(EDATE($F69,G$2)>DATE(2025,12,31),"",INDEX([1]A1!D$9:D$175,MATCH(1,--(RIGHT([1]A1!$B$9:$B$175,LEN([1]A1!$B$9:$B$175)-4)=$A69)*([1]A1!$C$9:$C$175=YEAR($F69)),0)))} -> 76966933 | H69: {=IF(EDATE($F69,H$2)>DATE(2025,12,31),"",INDEX([1]A1!E$9:E$175,MATCH(1,--(RIGHT([1]A1!$B$9:$B$175,LEN([1]A1!$B$9:$B$175)-4)=$A69)*([1]A1!$C$9:$C$175=YEAR($F69)),0)))} -> 85592967 | I69: {=IF(EDATE($F69,I$2)>DATE(2025,12,31),"",INDEX([1]A1!F$9:F$175,MATCH(1,--(RIGHT([1]A1!$B$9:$B$175,LEN([1]A1!$B$9:$B$175)-4)=$A69)*([1]A1!$C$9:$C$175=YEAR($F69)),0)))} -> 87763406 | J69: {=IF(EDATE($F69,J$2)>DATE(2025,12,31),"",INDEX([1]A1!G$9:G$175,MATCH(1,--(RIGHT([1]A1!$B$9:$B$175,LEN([1]A1!$B$9:$B$175)-4)=$A69)*([1]A1!$C$9:$C$175=YEAR($F69)),0)))} -> 88097778 | K69: {=IF(EDATE($F69,K$2)>DATE(2025,12,31),"",INDEX([1]A1!H$9:H$175,MATCH(1,--(RIGHT([1]A1!$B$9:$B$175,LEN([1]A1!$B$9:$B$175)-4)=$A69)*([1]A1!$C$9:$C$175=YEAR($F69)),0)))} -> 91781293 | L69: {=IF(EDATE($F69,L$2)>DATE(2025,12,31),"",INDEX([1]A1!I$9:I$175,MATCH(1,--(RIGHT([1]A1!$B$9:$B$175,LEN([1]A1!$B$9:$B$175)-4)=$A69)*([1]A1!$C$9:$C$175=YEAR($F69)),0)))} -> 90239959 | M69: {=IF(EDATE($F69,M$2)>DATE(2025,12,31),"",INDEX([1]A1!J$9:J$175,MATCH(1,--(RIGHT([1]A1!$B$9:$B$175,LEN([1]A1!$B$9:$B$175)-4)=$A69)*([1]A1!$C$9:$C$175=YEAR($F69)),0)))} -> 89850202 | N69: {=IF(EDATE($F69,N$2)>DATE(2025,12,31),"",INDEX([1]A1!K$9:K$175,MATCH(1,--(RIGHT([1]A1!$B$9:$B$175,LEN([1]A1!$B$9:$B$175)-4)=$A69)*([1]A1!$C$9:$C$175=YEAR($F69)),0)))} -> 90087376 | ... FA69: {=IF(EDATE($F69,FA$2)>DATE(2025,12,31),"",INDEX([1]A1!EX$9:EX$175,MATCH(1,--(RIGHT([1]A1!$B$9:$B$175,LEN([1]A1!$B$9:$B$175)-4)=$A69)*([1]A1!$C$9:$C$175=YEAR($F69)),0)))}
A70: Motor NP | B70: Net Written Premium | C70: All | D70: UW Year | E70: USD | F70: =EDATE(F69,12) -> 40179 | G70: {=IF(EDATE($F70,G$2)>DATE(2025,12,31),"",INDEX([1]A1!D$9:D$175,MATCH(1,--(RIGHT([1]A1!$B$9:$B$175,LEN([1]A1!$B$9:$B$175)-4)=$A70)*([1]A1!$C$9:$C$175=YEAR($F70)),0)))} -> 75785457 | H70: {=IF(EDATE($F70,H$2)>DATE(2025,12,31),"",INDEX([1]A1!E$9:E$175,MATCH(1,--(RIGHT([1]A1!$B$9:$B$175,LEN([1]A1!$B$9:$B$175)-4)=$A70)*([1]A1!$C$9:$C$175=YEAR($F70)),0)))} -> 93232894 | I70: {=IF(EDATE($F70,I$2)>DATE(2025,12,31),"",INDEX([1]A1!F$9:F$175,MATCH(1,--(RIGHT([1]A1!$B$9:$B$175,LEN([1]A1!$B$9:$B$175)-4)=$A70)*([1]A1!$C$9:$C$175=YEAR($F70)),0)))} -> 95464719 | J70: {=IF(EDATE($F70,J$2)>DATE(2025,12,31),"",INDEX([1]A1!G$9:G$175,MATCH(1,--(RIGHT([1]A1!$B$9:$B$175,LEN([1]A1!$B$9:$B$175)-4)=$A70)*([1]A1!$C$9:$C$175=YEAR($F70)),0)))} -> 96887466 | K70: {=IF(EDATE($F70,K$2)>DATE(2025,12,31),"",INDEX([1]A1!H$9:H$175,MATCH(1,--(RIGHT([1]A1!$B$9:$B$175,LEN([1]A1!$B$9:$B$175)-4)=$A70)*([1]A1!$C$9:$C$175=YEAR($F70)),0)))} -> 96011621 | L70: {=IF(EDATE($F70,L$2)>DATE(2025,12,31),"",INDEX([1]A1!I$9:I$175,MATCH(1,--(RIGHT([1]A1!$B$9:$B$175,LEN([1]A1!$B$9:$B$175)-4)=$A70)*([1]A1!$C$9:$C$175=YEAR($F70)),0)))} -> 96027051 | M70: {=IF(EDATE($F70,M$2)>DATE(2025,12,31),"",INDEX([1]A1!J$9:J$175,MATCH(1,--(RIGHT([1]A1!$B$9:$B$175,LEN([1]A1!$B$9:$B$175)-4)=$A70)*([1]A1!$C$9:$C$175=YEAR($F70)),0)))} -> 95876278 | N70: {=IF(EDATE($F70,N$2)>DATE(2025,12,31),"",INDEX([1]A1!K$9:K$175,MATCH(1,--(RIGHT([1]A1!$B$9:$B$175,LEN([1]A1!$B$9:$B$175)-4)=$A70)*([1]A1!$C$9:$C$175=YEAR($F70)),0)))} -> 95876366 | ... FA70: {=IF(EDATE($F70,FA$2)>DATE(2025,12,31),"",INDEX([1]A1!EX$9:EX$175,MATCH(1,--(RIGHT([1]A1!$B$9:$B$175,LEN([1]A1!$B$9:$B$175)-4)=$A70)*([1]A1!$C$9:$C$175=YEAR($F70)),0)))}
A71: Motor NP | B71: Net Written Premium | C71: All | D71: UW Year | E71: USD | F71: =EDATE(F70,12) -> 40544 | G71: {=IF(EDATE($F71,G$2)>DATE(2025,12,31),"",INDEX([1]A1!D$9:D$175,MATCH(1,--(RIGHT([1]A1!$B$9:$B$175,LEN([1]A1!$B$9:$B$175)-4)=$A71)*([1]A1!$C$9:$C$175=YEAR($F71)),0)))} -> 88495434 | H71: {=IF(EDATE($F71,H$2)>DATE(2025,12,31),"",INDEX([1]A1!E$9:E$175,MATCH(1,--(RIGHT([1]A1!$B$9:$B$175,LEN([1]A1!$B$9:$B$175)-4)=$A71)*([1]A1!$C$9:$C$175=YEAR($F71)),0)))} -> 1.0137626e+08 | I71: {=IF(EDATE($F71,I$2)>DATE(2025,12,31),"",INDEX([1]A1!F$9:F$175,MATCH(1,--(RIGHT([1]A1!$B$9:$B$175,LEN([1]A1!$B$9:$B$175)-4)=$A71)*([1]A1!$C$9:$C$175=YEAR($F71)),0)))} -> 1.107598e+08 | J71: {=IF(EDATE($F71,J$2)>DATE(2025,12,31),"",INDEX([1]A1!G$9:G$175,MATCH(1,--(RIGHT([1]A1!$B$9:$B$175,LEN([1]A1!$B$9:$B$175)-4)=$A71)*([1]A1!$C$9:$C$175=YEAR($F71)),0)))} -> 1.061097e+08 | K71: {=IF(EDATE($F71,K$2)>DATE(2025,12,31),"",INDEX([1]A1!H$9:H$175,MATCH(1,--(RIGHT([1]A1!$B$9:$B$175,LEN([1]A1!$B$9:$B$175)-4)=$A71)*([1]A1!$C$9:$C$175=YEAR($F71)),0)))} -> 1.0555826e+08 | L71: {=IF(EDATE($F71,L$2)>DATE(2025,12,31),"",INDEX([1]A1!I$9:I$175,MATCH(1,--(RIGHT([1]A1!$B$9:$B$175,LEN([1]A1!$B$9:$B$175)-4)=$A71)*([1]A1!$C$9:$C$175=YEAR($F71)),0)))} -> 1.0579622e+08 | M71: {=IF(EDATE($F71,M$2)>DATE(2025,12,31),"",INDEX([1]A1!J$9:J$175,MATCH(1,--(RIGHT([1]A1!$B$9:$B$175,LEN([1]A1!$B$9:$B$175)-4)=$A71)*([1]A1!$C$9:$C$175=YEAR($F71)),0)))} -> 1.0569911e+08 | N71: {=IF(EDATE($F71,N$2)>DATE(2025,12,31),"",INDEX([1]A1!K$9:K$175,MATCH(1,--(RIGHT([1]A1!$B$9:$B$175,LEN([1]A1!$B$9:$B$175)-4)=$A71)*([1]A1!$C$9:$C$175=YEAR($F71)),0)))} -> 1.0548973e+08 | ... FA71: {=IF(EDATE($F71,FA$2)>DATE(2025,12,31),"",INDEX([1]A1!EX$9:EX$175,MATCH(1,--(RIGHT([1]A1!$B$9:$B$175,LEN([1]A1!$B$9:$B$175)-4)=$A71)*([1]A1!$C$9:$C$175=YEAR($F71)),0)))}
A72: Motor NP | B72: Net Written Premium | C72: All | D72: UW Year | E72: USD | F72: =EDATE(F71,12) -> 40909 | G72: {=IF(EDATE($F72,G$2)>DATE(2025,12,31),"",INDEX([1]A1!D$9:D$175,MATCH(1,--(RIGHT([1]A1!$B$9:$B$175,LEN([1]A1!$B$9:$B$175)-4)=$A72)*([1]A1!$C$9:$C$175=YEAR($F72)),0)))} -> 44485862 | H72: {=IF(EDATE($F72,H$2)>DATE(2025,12,31),"",INDEX([1]A1!E$9:E$175,MATCH(1,--(RIGHT([1]A1!$B$9:$B$175,LEN([1]A1!$B$9:$B$175)-4)=$A72)*([1]A1!$C$9:$C$175=YEAR($F72)),0)))} -> 48894120 | I72: {=IF(EDATE($F72,I$2)>DATE(2025,12,31),"",INDEX([1]A1!F$9:F$175,MATCH(1,--(RIGHT([1]A1!$B$9:$B$175,LEN([1]A1!$B$9:$B$175)-4)=$A72)*([1]A1!$C$9:$C$175=YEAR($F72)),0)))} -> 54651422 | J72: {=IF(EDATE($F72,J$2)>DATE(2025,12,31),"",INDEX([1]A1!G$9:G$175,MATCH(1,--(RIGHT([1]A1!$B$9:$B$175,LEN([1]A1!$B$9:$B$175)-4)=$A72)*([1]A1!$C$9:$C$175=YEAR($F72)),0)))} -> 54244304 | K72: {=IF(EDATE($F72,K$2)>DATE(2025,12,31),"",INDEX([1]A1!H$9:H$175,MATCH(1,--(RIGHT([1]A1!$B$9:$B$175,LEN([1]A1!$B$9:$B$175)-4)=$A72)*([1]A1!$C$9:$C$175=YEAR($F72)),0)))} -> 52086256 | L72: {=IF(EDATE($F72,L$2)>DATE(2025,12,31),"",INDEX([1]A1!I$9:I$175,MATCH(1,--(RIGHT([1]A1!$B$9:$B$175,LEN([1]A1!$B$9:$B$175)-4)=$A72)*([1]A1!$C$9:$C$175=YEAR($F72)),0)))} -> 51983808 | M72: {=IF(EDATE($F72,M$2)>DATE(2025,12,31),"",INDEX([1]A1!J$9:J$175,MATCH(1,--(RIGHT([1]A1!$B$9:$B$175,LEN([1]A1!$B$9:$B$175)-4)=$A72)*([1]A1!$C$9:$C$175=YEAR($F72)),0)))} -> 52076797 | N72: {=IF(EDATE($F72,N$2)>DATE(2025,12,31),"",INDEX([1]A1!K$9:K$175,MATCH(1,--(RIGHT([1]A1!$B$9:$B$175,LEN([1]A1!$B$9:$B$175)-4)=$A72)*([1]A1!$C$9:$C$175=YEAR($F72)),0)))} -> 51023928 | ... FA72: {=IF(EDATE($F72,FA$2)>DATE(2025,12,31),"",INDEX([1]A1!EX$9:EX$175,MATCH(1,--(RIGHT([1]A1!$B$9:$B$175,LEN([1]A1!$B$9:$B$175)-4)=$A72)*([1]A1!$C$9:$C$175=YEAR($F72)),0)))}
A73: Motor NP | B73: Net Written Premium | C73: All | D73: UW Year | E73: USD | F73: =EDATE(F72,12) -> 41275 | G73: {=IF(EDATE($F73,G$2)>DATE(2025,12,31),"",INDEX([1]A1!D$9:D$175,MATCH(1,--(RIGHT([1]A1!$B$9:$B$175,LEN([1]A1!$B$9:$B$175)-4)=$A73)*([1]A1!$C$9:$C$175=YEAR($F73)),0)))} -> 55930839 | H73: {=IF(EDATE($F73,H$2)>DATE(2025,12,31),"",INDEX([1]A1!E$9:E$175,MATCH(1,--(RIGHT([1]A1!$B$9:$B$175,LEN([1]A1!$B$9:$B$175)-4)=$A73)*([1]A1!$C$9:$C$175=YEAR($F73)),0)))} -> 68779477 | I73: {=IF(EDATE($F73,I$2)>DATE(2025,12,31),"",INDEX([1]A1!F$9:F$175,MATCH(1,--(RIGHT([1]A1!$B$9:$B$175,LEN([1]A1!$B$9:$B$175)-4)=$A73)*([1]A1!$C$9:$C$175=YEAR($F73)),0)))} -> 71374222 | J73: {=IF(EDATE($F73,J$2)>DATE(2025,12,31),"",INDEX([1]A1!G$9:G$175,MATCH(1,--(RIGHT([1]A1!$B$9:$B$175,LEN([1]A1!$B$9:$B$175)-4)=$A73)*([1]A1!$C$9:$C$175=YEAR($F73)),0)))} -> 68225883 | K73: {=IF(EDATE($F73,K$2)>DATE(2025,12,31),"",INDEX([1]A1!H$9:H$175,MATCH(1,--(RIGHT([1]A1!$B$9:$B$175,LEN([1]A1!$B$9:$B$175)-4)=$A73)*([1]A1!$C$9:$C$175=YEAR($F73)),0)))} -> 67355969 | L73: {=IF(EDATE($F73,L$2)>DATE(2025,12,31),"",INDEX([1]A1!I$9:I$175,MATCH(1,--(RIGHT([1]A1!$B$9:$B$175,LEN([1]A1!$B$9:$B$175)-4)=$A73)*([1]A1!$C$9:$C$175=YEAR($F73)),0)))} -> 67419665 | M73: {=IF(EDATE($F73,M$2)>DATE(2025,12,31),"",INDEX([1]A1!J$9:J$175,MATCH(1,--(RIGHT([1]A1!$B$9:$B$175,LEN([1]A1!$B$9:$B$175)-4)=$A73)*([1]A1!$C$9:$C$175=YEAR($F73)),0)))} -> 63860612 | N73: {=IF(EDATE($F73,N$2)>DATE(2025,12,31),"",INDEX([1]A1!K$9:K$175,MATCH(1,--(RIGHT([1]A1!$B$9:$B$175,LEN([1]A1!$B$9:$B$175)-4)=$A73)*([1]A1!$C$9:$C$175=YEAR($F73)),0)))} -> 63702651 | ... FA73: {=IF(EDATE($F73,FA$2)>DATE(2025,12,31),"",INDEX([1]A1!EX$9:EX$175,MATCH(1,--(RIGHT([1]A1!$B$9:$B$175,LEN([1]A1!$B$9:$B$175)-4)=$A73)*([1]A1!$C$9:$C$175=YEAR($F73)),0)))}
A74: Motor NP | B74: Net Written Premium | C74: All | D74: UW Year | E74: USD | F74: =EDATE(F73,12) -> 41640 | G74: {=IF(EDATE($F74,G$2)>DATE(2025,12,31),"",INDEX([1]A1!D$9:D$175,MATCH(1,--(RIGHT([1]A1!$B$9:$B$175,LEN([1]A1!$B$9:$B$175)-4)=$A74)*([1]A1!$C$9:$C$175=YEAR($F74)),0)))} -> 65390066 | H74: {=IF(EDATE($F74,H$2)>DATE(2025,12,31),"",INDEX([1]A1!E$9:E$175,MATCH(1,--(RIGHT([1]A1!$B$9:$B$175,LEN([1]A1!$B$9:$B$175)-4)=$A74)*([1]A1!$C$9:$C$175=YEAR($F74)),0)))} -> 71720243 | I74: {=IF(EDATE($F74,I$2)>DATE(2025,12,31),"",INDEX([1]A1!F$9:F$175,MATCH(1,--(RIGHT([1]A1!$B$9:$B$175,LEN([1]A1!$B$9:$B$175)-4)=$A74)*([1]A1!$C$9:$C$175=YEAR($F74)),0)))} -> 74510605 | J74: {=IF(EDATE($F74,J$2)>DATE(2025,12,31),"",INDEX([1]A1!G$9:G$175,MATCH(1,--(RIGHT([1]A1!$B$9:$B$175,LEN([1]A1!$B$9:$B$175)-4)=$A74)*([1]A1!$C$9:$C$175=YEAR($F74)),0)))} -> 75817927 | K74: {=IF(EDATE($F74,K$2)>DATE(2025,12,31),"",INDEX([1]A1!H$9:H$175,MATCH(1,--(RIGHT([1]A1!$B$9:$B$175,LEN([1]A1!$B$9:$B$175)-4)=$A74)*([1]A1!$C$9:$C$175=YEAR($F74)),0)))} -> 75778232 | L74: {=IF(EDATE($F74,L$2)>DATE(2025,12,31),"",INDEX([1]A1!I$9:I$175,MATCH(1,--(RIGHT([1]A1!$B$9:$B$175,LEN([1]A1!$B$9:$B$175)-4)=$A74)*([1]A1!$C$9:$C$175=YEAR($F74)),0)))} -> 75582010 | M74: {=IF(EDATE($F74,M$2)>DATE(2025,12,31),"",INDEX([1]A1!J$9:J$175,MATCH(1,--(RIGHT([1]A1!$B$9:$B$175,LEN([1]A1!$B$9:$B$175)-4)=$A74)*([1]A1!$C$9:$C$175=YEAR($F74)),0)))} -> 75356103 | N74: {=IF(EDATE($F74,N$2)>DATE(2025,12,31),"",INDEX([1]A1!K$9:K$175,MATCH(1,--(RIGHT([1]A1!$B$9:$B$175,LEN([1]A1!$B$9:$B$175)-4)=$A74)*([1]A1!$C$9:$C$175=YEAR($F74)),0)))} -> 75359560 | ... FA74: {=IF(EDATE($F74,FA$2)>DATE(2025,12,31),"",INDEX([1]A1!EX$9:EX$175,MATCH(1,--(RIGHT([1]A1!$B$9:$B$175,LEN([1]A1!$B$9:$B$175)-4)=$A74)*([1]A1!$C$9:$C$175=YEAR($F74)),0)))}
A75: Motor NP | B75: Net Written Premium | C75: All | D75: UW Year | E75: USD | F75: =EDATE(F74,12) -> 42005 | G75: {=IF(EDATE($F75,G$2)>DATE(2025,12,31),"",INDEX([1]A1!D$9:D$175,MATCH(1,--(RIGHT([1]A1!$B$9:$B$175,LEN([1]A1!$B$9:$B$175)-4)=$A75)*([1]A1!$C$9:$C$175=YEAR($F75)),0)))} -> 59310619 | H75: {=IF(EDATE($F75,H$2)>DATE(2025,12,31),"",INDEX([1]A1!E$9:E$175,MATCH(1,--(RIGHT([1]A1!$B$9:$B$175,LEN([1]A1!$B$9:$B$175)-4)=$A75)*([1]A1!$C$9:$C$175=YEAR($F75)),0)))} -> 67068316 | I75: {=IF(EDATE($F75,I$2)>DATE(2025,12,31),"",INDEX([1]A1!F$9:F$175,MATCH(1,--(RIGHT([1]A1!$B$9:$B$175,LEN([1]A1!$B$9:$B$175)-4)=$A75)*([1]A1!$C$9:$C$175=YEAR($F75)),0)))} -> 72669317 | J75: {=IF(EDATE($F75,J$2)>DATE(2025,12,31),"",INDEX([1]A1!G$9:G$175,MATCH(1,--(RIGHT([1]A1!$B$9:$B$175,LEN([1]A1!$B$9:$B$175)-4)=$A75)*([1]A1!$C$9:$C$175=YEAR($F75)),0)))} -> 73002909 | K75: {=IF(EDATE($F75,K$2)>DATE(2025,12,31),"",INDEX([1]A1!H$9:H$175,MATCH(1,--(RIGHT([1]A1!$B$9:$B$175,LEN([1]A1!$B$9:$B$175)-4)=$A75)*([1]A1!$C$9:$C$175=YEAR($F75)),0)))} -> 72547637 | L75: {=IF(EDATE($F75,L$2)>DATE(2025,12,31),"",INDEX([1]A1!I$9:I$175,MATCH(1,--(RIGHT([1]A1!$B$9:$B$175,LEN([1]A1!$B$9:$B$175)-4)=$A75)*([1]A1!$C$9:$C$175=YEAR($F75)),0)))} -> 73026578 | M75: {=IF(EDATE($F75,M$2)>DATE(2025,12,31),"",INDEX([1]A1!J$9:J$175,MATCH(1,--(RIGHT([1]A1!$B$9:$B$175,LEN([1]A1!$B$9:$B$175)-4)=$A75)*([1]A1!$C$9:$C$175=YEAR($F75)),0)))} -> 72995395 | N75: {=IF(EDATE($F75,N$2)>DATE(2025,12,31),"",INDEX([1]A1!K$9:K$175,MATCH(1,--(RIGHT([1]A1!$B$9:$B$175,LEN([1]A1!$B$9:$B$175)-4)=$A75)*([1]A1!$C$9:$C$175=YEAR($F75)),0)))} -> 73006828 | ... FA75: {=IF(EDATE($F75,FA$2)>DATE(2025,12,31),"",INDEX([1]A1!EX$9:EX$175,MATCH(1,--(RIGHT([1]A1!$B$9:$B$175,LEN([1]A1!$B$9:$B$175)-4)=$A75)*([1]A1!$C$9:$C$175=YEAR($F75)),0)))}
A76: Motor NP | B76: Net Written Premium | C76: All | D76: UW Year | E76: USD | F76: =EDATE(F75,12) -> 42370 | G76: {=IF(EDATE($F76,G$2)>DATE(2025,12,31),"",INDEX([1]A1!D$9:D$175,MATCH(1,--(RIGHT([1]A1!$B$9:$B$175,LEN([1]A1!$B$9:$B$175)-4)=$A76)*([1]A1!$C$9:$C$175=YEAR($F76)),0)))} -> 64064967 | H76: {=IF(EDATE($F76,H$2)>DATE(2025,12,31),"",INDEX([1]A1!E$9:E$175,MATCH(1,--(RIGHT([1]A1!$B$9:$B$175,LEN([1]A1!$B$9:$B$175)-4)=$A76)*([1]A1!$C$9:$C$175=YEAR($F76)),0)))} -> 81134361 | I76: {=IF(EDATE($F76,I$2)>DATE(2025,12,31),"",INDEX([1]A1!F$9:F$175,MATCH(1,--(RIGHT([1]A1!$B$9:$B$175,LEN([1]A1!$B$9:$B$175)-4)=$A76)*([1]A1!$C$9:$C$175=YEAR($F76)),0)))} -> 85575653 | J76: {=IF(EDATE($F76,J$2)>DATE(2025,12,31),"",INDEX([1]A1!G$9:G$175,MATCH(1,--(RIGHT([1]A1!$B$9:$B$175,LEN([1]A1!$B$9:$B$175)-4)=$A76)*([1]A1!$C$9:$C$175=YEAR($F76)),0)))} -> 86835557 | K76: {=IF(EDATE($F76,K$2)>DATE(2025,12,31),"",INDEX([1]A1!H$9:H$175,MATCH(1,--(RIGHT([1]A1!$B$9:$B$175,LEN([1]A1!$B$9:$B$175)-4)=$A76)*([1]A1!$C$9:$C$175=YEAR($F76)),0)))} -> 87031502 | L76: {=IF(EDATE($F76,L$2)>DATE(2025,12,31),"",INDEX([1]A1!I$9:I$175,MATCH(1,--(RIGHT([1]A1!$B$9:$B$175,LEN([1]A1!$B$9:$B$175)-4)=$A76)*([1]A1!$C$9:$C$175=YEAR($F76)),0)))} -> 86298829 | M76: {=IF(EDATE($F76,M$2)>DATE(2025,12,31),"",INDEX([1]A1!J$9:J$175,MATCH(1,--(RIGHT([1]A1!$B$9:$B$175,LEN([1]A1!$B$9:$B$175)-4)=$A76)*([1]A1!$C$9:$C$175=YEAR($F76)),0)))} -> 86566904 | N76: {=IF(EDATE($F76,N$2)>DATE(2025,12,31),"",INDEX([1]A1!K$9:K$175,MATCH(1,--(RIGHT([1]A1!$B$9:$B$175,LEN([1]A1!$B$9:$B$175)-4)=$A76)*([1]A1!$C$9:$C$175=YEAR($F76)),0)))} -> 86585423 | ... FA76: {=IF(EDATE($F76,FA$2)>DATE(2025,12,31),"",INDEX([1]A1!EX$9:EX$175,MATCH(1,--(RIGHT([1]A1!$B$9:$B$175,LEN([1]A1!$B$9:$B$175)-4)=$A76)*([1]A1!$C$9:$C$175=YEAR($F76)),0)))}
A77: Motor NP | B77: Net Written Premium | C77: All | D77: UW Year | E77: USD | F77: =EDATE(F76,12) -> 42736 | G77: {=IF(EDATE($F77,G$2)>DATE(2025,12,31),"",INDEX([1]A1!D$9:D$175,MATCH(1,--(RIGHT([1]A1!$B$9:$B$175,LEN([1]A1!$B$9:$B$175)-4)=$A77)*([1]A1!$C$9:$C$175=YEAR($F77)),0)))} -> 74848055 | H77: {=IF(EDATE($F77,H$2)>DATE(2025,12,31),"",INDEX([1]A1!E$9:E$175,MATCH(1,--(RIGHT([1]A1!$B$9:$B$175,LEN([1]A1!$B$9:$B$175)-4)=$A77)*([1]A1!$C$9:$C$175=YEAR($F77)),0)))} -> 88364701 | I77: {=IF(EDATE($F77,I$2)>DATE(2025,12,31),"",INDEX([1]A1!F$9:F$175,MATCH(1,--(RIGHT([1]A1!$B$9:$B$175,LEN([1]A1!$B$9:$B$175)-4)=$A77)*([1]A1!$C$9:$C$175=YEAR($F77)),0)))} -> 90538920 | J77: {=IF(EDATE($F77,J$2)>DATE(2025,12,31),"",INDEX([1]A1!G$9:G$175,MATCH(1,--(RIGHT([1]A1!$B$9:$B$175,LEN([1]A1!$B$9:$B$175)-4)=$A77)*([1]A1!$C$9:$C$175=YEAR($F77)),0)))} -> 90937947 | K77: {=IF(EDATE($F77,K$2)>DATE(2025,12,31),"",INDEX([1]A1!H$9:H$175,MATCH(1,--(RIGHT([1]A1!$B$9:$B$175,LEN([1]A1!$B$9:$B$175)-4)=$A77)*([1]A1!$C$9:$C$175=YEAR($F77)),0)))} -> 91961149 | L77: {=IF(EDATE($F77,L$2)>DATE(2025,12,31),"",INDEX([1]A1!I$9:I$175,MATCH(1,--(RIGHT([1]A1!$B$9:$B$175,LEN([1]A1!$B$9:$B$175)-4)=$A77)*([1]A1!$C$9:$C$175=YEAR($F77)),0)))} -> 93332712 | M77: {=IF(EDATE($F77,M$2)>DATE(2025,12,31),"",INDEX([1]A1!J$9:J$175,MATCH(1,--(RIGHT([1]A1!$B$9:$B$175,LEN([1]A1!$B$9:$B$175)-4)=$A77)*([1]A1!$C$9:$C$175=YEAR($F77)),0)))} -> 92322081 | N77: {=IF(EDATE($F77,N$2)>DATE(2025,12,31),"",INDEX([1]A1!K$9:K$175,MATCH(1,--(RIGHT([1]A1!$B$9:$B$175,LEN([1]A1!$B$9:$B$175)-4)=$A77)*([1]A1!$C$9:$C$175=YEAR($F77)),0)))} -> 92304887 | ... FA77: {=IF(EDATE($F77,FA$2)>DATE(2025,12,31),"",INDEX([1]A1!EX$9:EX$175,MATCH(1,--(RIGHT([1]A1!$B$9:$B$175,LEN([1]A1!$B$9:$B$175)-4)=$A77)*([1]A1!$C$9:$C$175=YEAR($F77)),0)))}
A78: Motor NP | B78: Net Written Premium | C78: All | D78: UW Year | E78: USD | F78: =EDATE(F77,12) -> 43101 | G78: {=IF(EDATE($F78,G$2)>DATE(2025,12,31),"",INDEX([1]A1!D$9:D$175,MATCH(1,--(RIGHT([1]A1!$B$9:$B$175,LEN([1]A1!$B$9:$B$175)-4)=$A78)*([1]A1!$C$9:$C$175=YEAR($F78)),0)))} -> 1.2068832e+08 | H78: {=IF(EDATE($F78,H$2)>DATE(2025,12,31),"",INDEX([1]A1!E$9:E$175,MATCH(1,--(RIGHT([1]A1!$B$9:$B$175,LEN([1]A1!$B$9:$B$175)-4)=$A78)*([1]A1!$C$9:$C$175=YEAR($F78)),0)))} -> 1.3163948e+08 | I78: {=IF(EDATE($F78,I$2)>DATE(2025,12,31),"",INDEX([1]A1!F$9:F$175,MATCH(1,--(RIGHT([1]A1!$B$9:$B$175,LEN([1]A1!$B$9:$B$175)-4)=$A78)*([1]A1!$C$9:$C$175=YEAR($F78)),0)))} -> 1.3683719e+08 | J78: {=IF(EDATE($F78,J$2)>DATE(2025,12,31),"",INDEX([1]A1!G$9:G$175,MATCH(1,--(RIGHT([1]A1!$B$9:$B$175,LEN([1]A1!$B$9:$B$175)-4)=$A78)*([1]A1!$C$9:$C$175=YEAR($F78)),0)))} -> 1.3802373e+08 | K78: {=IF(EDATE($F78,K$2)>DATE(2025,12,31),"",INDEX([1]A1!H$9:H$175,MATCH(1,--(RIGHT([1]A1!$B$9:$B$175,LEN([1]A1!$B$9:$B$175)-4)=$A78)*([1]A1!$C$9:$C$175=YEAR($F78)),0)))} -> 1.3766164e+08 | L78: {=IF(EDATE($F78,L$2)>DATE(2025,12,31),"",INDEX([1]A1!I$9:I$175,MATCH(1,--(RIGHT([1]A1!$B$9:$B$175,LEN([1]A1!$B$9:$B$175)-4)=$A78)*([1]A1!$C$9:$C$175=YEAR($F78)),0)))} -> 1.372966e+08 | M78: {=IF(EDATE($F78,M$2)>DATE(2025,12,31),"",INDEX([1]A1!J$9:J$175,MATCH(1,--(RIGHT([1]A1!$B$9:$B$175,LEN([1]A1!$B$9:$B$175)-4)=$A78)*([1]A1!$C$9:$C$175=YEAR($F78)),0)))} -> 1.3719893e+08 | N78: {=IF(EDATE($F78,N$2)>DATE(2025,12,31),"",INDEX([1]A1!K$9:K$175,MATCH(1,--(RIGHT([1]A1!$B$9:$B$175,LEN([1]A1!$B$9:$B$175)-4)=$A78)*([1]A1!$C$9:$C$175=YEAR($F78)),0)))} -> 1.371679e+08 | ... FA78: {=IF(EDATE($F78,FA$2)>DATE(2025,12,31),"",INDEX([1]A1!EX$9:EX$175,MATCH(1,--(RIGHT([1]A1!$B$9:$B$175,LEN([1]A1!$B$9:$B$175)-4)=$A78)*([1]A1!$C$9:$C$175=YEAR($F78)),0)))}
... A85: Motor NP | B85: Net Written Premium | C85: All | D85: UW Year | E85: USD | F85: =EDATE(F84,12) -> 45658 | G85: {=IF(EDATE($F85,G$2)>DATE(2025,12,31),"",INDEX([1]A1!D$9:D$175,MATCH(1,--(RIGHT([1]A1!$B$9:$B$175,LEN([1]A1!$B$9:$B$175)-4)=$A85)*([1]A1!$C$9:$C$175=YEAR($F85)),0)))} -> 1.2403218e+08 | H85: {=IF(EDATE($F85,H$2)>DATE(2025,12,31),"",INDEX([1]A1!E$9:E$175,MATCH(1,--(RIGHT([1]A1!$B$9:$B$175,LEN([1]A1!$B$9:$B$175)-4)=$A85)*([1]A1!$C$9:$C$175=YEAR($F85)),0)))} | I85: {=IF(EDATE($F85,I$2)>DATE(2025,12,31),"",INDEX([1]A1!F$9:F$175,MATCH(1,--(RIGHT([1]A1!$B$9:$B$175,LEN([1]A1!$B$9:$B$175)-4)=$A85)*([1]A1!$C$9:$C$175=YEAR($F85)),0)))} | J85: {=IF(EDATE($F85,J$2)>DATE(2025,12,31),"",INDEX([1]A1!G$9:G$175,MATCH(1,--(RIGHT([1]A1!$B$9:$B$175,LEN([1]A1!$B$9:$B$175)-4)=$A85)*([1]A1!$C$9:$C$175=YEAR($F85)),0)))} | K85: {=IF(EDATE($F85,K$2)>DATE(2025,12,31),"",INDEX([1]A1!H$9:H$175,MATCH(1,--(RIGHT([1]A1!$B$9:$B$175,LEN([1]A1!$B$9:$B$175)-4)=$A85)*([1]A1!$C$9:$C$175=YEAR($F85)),0)))} | L85: {=IF(EDATE($F85,L$2)>DATE(2025,12,31),"",INDEX([1]A1!I$9:I$175,MATCH(1,--(RIGHT([1]A1!$B$9:$B$175,LEN([1]A1!$B$9:$B$175)-4)=$A85)*([1]A1!$C$9:$C$175=YEAR($F85)),0)))} | M85: {=IF(EDATE($F85,M$2)>DATE(2025,12,31),"",INDEX([1]A1!J$9:J$175,MATCH(1,--(RIGHT([1]A1!$B$9:$B$175,LEN([1]A1!$B$9:$B$175)-4)=$A85)*([1]A1!$C$9:$C$175=YEAR($F85)),0)))} | N85: {=IF(EDATE($F85,N$2)>DATE(2025,12,31),"",INDEX([1]A1!K$9:K$175,MATCH(1,--(RIGHT([1]A1!$B$9:$B$175,LEN([1]A1!$B$9:$B$175)-4)=$A85)*([1]A1!$C$9:$C$175=YEAR($F85)),0)))} | ... FA85: {=IF(EDATE($F85,FA$2)>DATE(2025,12,31),"",INDEX([1]A1!EX$9:EX$175,MATCH(1,--(RIGHT([1]A1!$B$9:$B$175,LEN([1]A1!$B$9:$B$175)-4)=$A85)*([1]A1!$C$9:$C$175=YEAR($F85)),0)))}
A87: Motor PR | B87: Net Written Premium | C87: All | D87: UW Year | E87: USD | F87: =triangle_start_date -> 38718 | G87: {=IF(EDATE($F87,G$2)>DATE(2025,12,31),"",INDEX([1]A1!D$9:D$175,MATCH(1,--(RIGHT([1]A1!$B$9:$B$175,LEN([1]A1!$B$9:$B$175)-4)=$A87)*([1]A1!$C$9:$C$175=YEAR($F87)),0)))} -> 4203633.3 | H87: {=IF(EDATE($F87,H$2)>DATE(2025,12,31),"",INDEX([1]A1!E$9:E$175,MATCH(1,--(RIGHT([1]A1!$B$9:$B$175,LEN([1]A1!$B$9:$B$175)-4)=$A87)*([1]A1!$C$9:$C$175=YEAR($F87)),0)))} -> 5468144.8 | I87: {=IF(EDATE($F87,I$2)>DATE(2025,12,31),"",INDEX([1]A1!F$9:F$175,MATCH(1,--(RIGHT([1]A1!$B$9:$B$175,LEN([1]A1!$B$9:$B$175)-4)=$A87)*([1]A1!$C$9:$C$175=YEAR($F87)),0)))} -> 5463562.2 | J87: {=IF(EDATE($F87,J$2)>DATE(2025,12,31),"",INDEX([1]A1!G$9:G$175,MATCH(1,--(RIGHT([1]A1!$B$9:$B$175,LEN([1]A1!$B$9:$B$175)-4)=$A87)*([1]A1!$C$9:$C$175=YEAR($F87)),0)))} -> 5462712.6 | K87: {=IF(EDATE($F87,K$2)>DATE(2025,12,31),"",INDEX([1]A1!H$9:H$175,MATCH(1,--(RIGHT([1]A1!$B$9:$B$175,LEN([1]A1!$B$9:$B$175)-4)=$A87)*([1]A1!$C$9:$C$175=YEAR($F87)),0)))} -> 5462280.9 | L87: {=IF(EDATE($F87,L$2)>DATE(2025,12,31),"",INDEX([1]A1!I$9:I$175,MATCH(1,--(RIGHT([1]A1!$B$9:$B$175,LEN([1]A1!$B$9:$B$175)-4)=$A87)*([1]A1!$C$9:$C$175=YEAR($F87)),0)))} -> 5461987.4 | M87: {=IF(EDATE($F87,M$2)>DATE(2025,12,31),"",INDEX([1]A1!J$9:J$175,MATCH(1,--(RIGHT([1]A1!$B$9:$B$175,LEN([1]A1!$B$9:$B$175)-4)=$A87)*([1]A1!$C$9:$C$175=YEAR($F87)),0)))} -> 5461774.9 | N87: {=IF(EDATE($F87,N$2)>DATE(2025,12,31),"",INDEX([1]A1!K$9:K$175,MATCH(1,--(RIGHT([1]A1!$B$9:$B$175,LEN([1]A1!$B$9:$B$175)-4)=$A87)*([1]A1!$C$9:$C$175=YEAR($F87)),0)))} -> 5461798.2 | ... FA87: {=IF(EDATE($F87,FA$2)>DATE(2025,12,31),"",INDEX([1]A1!EX$9:EX$175,MATCH(1,--(RIGHT([1]A1!$B$9:$B$175,LEN([1]A1!$B$9:$B$175)-4)=$A87)*([1]A1!$C$9:$C$175=YEAR($F87)),0)))}
A88: Motor PR | B88: Net Written Premium | C88: All | D88: UW Year | E88: USD | F88: =EDATE(F87,12) -> 39083 | G88: {=IF(EDATE($F88,G$2)>DATE(2025,12,31),"",INDEX([1]A1!D$9:D$175,MATCH(1,--(RIGHT([1]A1!$B$9:$B$175,LEN([1]A1!$B$9:$B$175)-4)=$A88)*([1]A1!$C$9:$C$175=YEAR($F88)),0)))} -> 4231112 | H88: {=IF(EDATE($F88,H$2)>DATE(2025,12,31),"",INDEX([1]A1!E$9:E$175,MATCH(1,--(RIGHT([1]A1!$B$9:$B$175,LEN([1]A1!$B$9:$B$175)-4)=$A88)*([1]A1!$C$9:$C$175=YEAR($F88)),0)))} -> 7369874 | I88: {=IF(EDATE($F88,I$2)>DATE(2025,12,31),"",INDEX([1]A1!F$9:F$175,MATCH(1,--(RIGHT([1]A1!$B$9:$B$175,LEN([1]A1!$B$9:$B$175)-4)=$A88)*([1]A1!$C$9:$C$175=YEAR($F88)),0)))} -> 7412567.8 | J88: {=IF(EDATE($F88,J$2)>DATE(2025,12,31),"",INDEX([1]A1!G$9:G$175,MATCH(1,--(RIGHT([1]A1!$B$9:$B$175,LEN([1]A1!$B$9:$B$175)-4)=$A88)*([1]A1!$C$9:$C$175=YEAR($F88)),0)))} -> 7412417.6 | K88: {=IF(EDATE($F88,K$2)>DATE(2025,12,31),"",INDEX([1]A1!H$9:H$175,MATCH(1,--(RIGHT([1]A1!$B$9:$B$175,LEN([1]A1!$B$9:$B$175)-4)=$A88)*([1]A1!$C$9:$C$175=YEAR($F88)),0)))} -> 7412871.5 | L88: {=IF(EDATE($F88,L$2)>DATE(2025,12,31),"",INDEX([1]A1!I$9:I$175,MATCH(1,--(RIGHT([1]A1!$B$9:$B$175,LEN([1]A1!$B$9:$B$175)-4)=$A88)*([1]A1!$C$9:$C$175=YEAR($F88)),0)))} -> 7412668.5 | M88: {=IF(EDATE($F88,M$2)>DATE(2025,12,31),"",INDEX([1]A1!J$9:J$175,MATCH(1,--(RIGHT([1]A1!$B$9:$B$175,LEN([1]A1!$B$9:$B$175)-4)=$A88)*([1]A1!$C$9:$C$175=YEAR($F88)),0)))} -> 7412671.7 | N88: {=IF(EDATE($F88,N$2)>DATE(2025,12,31),"",INDEX([1]A1!K$9:K$175,MATCH(1,--(RIGHT([1]A1!$B$9:$B$175,LEN([1]A1!$B$9:$B$175)-4)=$A88)*([1]A1!$C$9:$C$175=YEAR($F88)),0)))} -> 7412702.4 | ... FA88: {=IF(EDATE($F88,FA$2)>DATE(2025,12,31),"",INDEX([1]A1!EX$9:EX$175,MATCH(1,--(RIGHT([1]A1!$B$9:$B$175,LEN([1]A1!$B$9:$B$175)-4)=$A88)*([1]A1!$C$9:$C$175=YEAR($F88)),0)))}
A89: Motor PR | B89: Net Written Premium | C89: All | D89: UW Year | E89: USD | F89: =EDATE(F88,12) -> 39448 | G89: {=IF(EDATE($F89,G$2)>DATE(2025,12,31),"",INDEX([1]A1!D$9:D$175,MATCH(1,--(RIGHT([1]A1!$B$9:$B$175,LEN([1]A1!$B$9:$B$175)-4)=$A89)*([1]A1!$C$9:$C$175=YEAR($F89)),0)))} -> 4928660.4 | H89: {=IF(EDATE($F89,H$2)>DATE(2025,12,31),"",INDEX([1]A1!E$9:E$175,MATCH(1,--(RIGHT([1]A1!$B$9:$B$175,LEN([1]A1!$B$9:$B$175)-4)=$A89)*([1]A1!$C$9:$C$175=YEAR($F89)),0)))} -> 6830225 | I89: {=IF(EDATE($F89,I$2)>DATE(2025,12,31),"",INDEX([1]A1!F$9:F$175,MATCH(1,--(RIGHT([1]A1!$B$9:$B$175,LEN([1]A1!$B$9:$B$175)-4)=$A89)*([1]A1!$C$9:$C$175=YEAR($F89)),0)))} -> 7552664.2 | J89: {=IF(EDATE($F89,J$2)>DATE(2025,12,31),"",INDEX([1]A1!G$9:G$175,MATCH(1,--(RIGHT([1]A1!$B$9:$B$175,LEN([1]A1!$B$9:$B$175)-4)=$A89)*([1]A1!$C$9:$C$175=YEAR($F89)),0)))} -> 7551450.5 | K89: {=IF(EDATE($F89,K$2)>DATE(2025,12,31),"",INDEX([1]A1!H$9:H$175,MATCH(1,--(RIGHT([1]A1!$B$9:$B$175,LEN([1]A1!$B$9:$B$175)-4)=$A89)*([1]A1!$C$9:$C$175=YEAR($F89)),0)))} -> 7550467.4 | L89: {=IF(EDATE($F89,L$2)>DATE(2025,12,31),"",INDEX([1]A1!I$9:I$175,MATCH(1,--(RIGHT([1]A1!$B$9:$B$175,LEN([1]A1!$B$9:$B$175)-4)=$A89)*([1]A1!$C$9:$C$175=YEAR($F89)),0)))} -> 7550507.5 | M89: {=IF(EDATE($F89,M$2)>DATE(2025,12,31),"",INDEX([1]A1!J$9:J$175,MATCH(1,--(RIGHT([1]A1!$B$9:$B$175,LEN([1]A1!$B$9:$B$175)-4)=$A89)*([1]A1!$C$9:$C$175=YEAR($F89)),0)))} -> 7550485.5 | N89: {=IF(EDATE($F89,N$2)>DATE(2025,12,31),"",INDEX([1]A1!K$9:K$175,MATCH(1,--(RIGHT([1]A1!$B$9:$B$175,LEN([1]A1!$B$9:$B$175)-4)=$A89)*([1]A1!$C$9:$C$175=YEAR($F89)),0)))} -> 7799095.8 | ... FA89: {=IF(EDATE($F89,FA$2)>DATE(2025,12,31),"",INDEX([1]A1!EX$9:EX$175,MATCH(1,--(RIGHT([1]A1!$B$9:$B$175,LEN([1]A1!$B$9:$B$175)-4)=$A89)*([1]A1!$C$9:$C$175=YEAR($F89)),0)))}
A90: Motor PR | B90: Net Written Premium | C90: All | D90: UW Year | E90: USD | F90: =EDATE(F89,12) -> 39814 | G90: {=IF(EDATE($F90,G$2)>DATE(2025,12,31),"",INDEX([1]A1!D$9:D$175,MATCH(1,--(RIGHT([1]A1!$B$9:$B$175,LEN([1]A1!$B$9:$B$175)-4)=$A90)*([1]A1!$C$9:$C$175=YEAR($F90)),0)))} -> 3346898.2 | H90: {=IF(EDATE($F90,H$2)>DATE(2025,12,31),"",INDEX([1]A1!E$9:E$175,MATCH(1,--(RIGHT([1]A1!$B$9:$B$175,LEN([1]A1!$B$9:$B$175)-4)=$A90)*([1]A1!$C$9:$C$175=YEAR($F90)),0)))} -> 14119357 | I90: {=IF(EDATE($F90,I$2)>DATE(2025,12,31),"",INDEX([1]A1!F$9:F$175,MATCH(1,--(RIGHT([1]A1!$B$9:$B$175,LEN([1]A1!$B$9:$B$175)-4)=$A90)*([1]A1!$C$9:$C$175=YEAR($F90)),0)))} -> 15875083 | J90: {=IF(EDATE($F90,J$2)>DATE(2025,12,31),"",INDEX([1]A1!G$9:G$175,MATCH(1,--(RIGHT([1]A1!$B$9:$B$175,LEN([1]A1!$B$9:$B$175)-4)=$A90)*([1]A1!$C$9:$C$175=YEAR($F90)),0)))} -> 16177769 | K90: {=IF(EDATE($F90,K$2)>DATE(2025,12,31),"",INDEX([1]A1!H$9:H$175,MATCH(1,--(RIGHT([1]A1!$B$9:$B$175,LEN([1]A1!$B$9:$B$175)-4)=$A90)*([1]A1!$C$9:$C$175=YEAR($F90)),0)))} -> 16176778 | L90: {=IF(EDATE($F90,L$2)>DATE(2025,12,31),"",INDEX([1]A1!I$9:I$175,MATCH(1,--(RIGHT([1]A1!$B$9:$B$175,LEN([1]A1!$B$9:$B$175)-4)=$A90)*([1]A1!$C$9:$C$175=YEAR($F90)),0)))} -> 16153695 | M90: {=IF(EDATE($F90,M$2)>DATE(2025,12,31),"",INDEX([1]A1!J$9:J$175,MATCH(1,--(RIGHT([1]A1!$B$9:$B$175,LEN([1]A1!$B$9:$B$175)-4)=$A90)*([1]A1!$C$9:$C$175=YEAR($F90)),0)))} -> 16089019 | N90: {=IF(EDATE($F90,N$2)>DATE(2025,12,31),"",INDEX([1]A1!K$9:K$175,MATCH(1,--(RIGHT([1]A1!$B$9:$B$175,LEN([1]A1!$B$9:$B$175)-4)=$A90)*([1]A1!$C$9:$C$175=YEAR($F90)),0)))} -> 16091383 | ... FA90: {=IF(EDATE($F90,FA$2)>DATE(2025,12,31),"",INDEX([1]A1!EX$9:EX$175,MATCH(1,--(RIGHT([1]A1!$B$9:$B$175,LEN([1]A1!$B$9:$B$175)-4)=$A90)*([1]A1!$C$9:$C$175=YEAR($F90)),0)))}
A91: Motor PR | B91: Net Written Premium | C91: All | D91: UW Year | E91: USD | F91: =EDATE(F90,12) -> 40179 | G91: {=IF(EDATE($F91,G$2)>DATE(2025,12,31),"",INDEX([1]A1!D$9:D$175,MATCH(1,--(RIGHT([1]A1!$B$9:$B$175,LEN([1]A1!$B$9:$B$175)-4)=$A91)*([1]A1!$C$9:$C$175=YEAR($F91)),0)))} -> 13220189 | H91: {=IF(EDATE($F91,H$2)>DATE(2025,12,31),"",INDEX([1]A1!E$9:E$175,MATCH(1,--(RIGHT([1]A1!$B$9:$B$175,LEN([1]A1!$B$9:$B$175)-4)=$A91)*([1]A1!$C$9:$C$175=YEAR($F91)),0)))} -> 71199820 | I91: {=IF(EDATE($F91,I$2)>DATE(2025,12,31),"",INDEX([1]A1!F$9:F$175,MATCH(1,--(RIGHT([1]A1!$B$9:$B$175,LEN([1]A1!$B$9:$B$175)-4)=$A91)*([1]A1!$C$9:$C$175=YEAR($F91)),0)))} -> 71618307 | J91: {=IF(EDATE($F91,J$2)>DATE(2025,12,31),"",INDEX([1]A1!G$9:G$175,MATCH(1,--(RIGHT([1]A1!$B$9:$B$175,LEN([1]A1!$B$9:$B$175)-4)=$A91)*([1]A1!$C$9:$C$175=YEAR($F91)),0)))} -> 72804050 | K91: {=IF(EDATE($F91,K$2)>DATE(2025,12,31),"",INDEX([1]A1!H$9:H$175,MATCH(1,--(RIGHT([1]A1!$B$9:$B$175,LEN([1]A1!$B$9:$B$175)-4)=$A91)*([1]A1!$C$9:$C$175=YEAR($F91)),0)))} -> 71629910 | L91: {=IF(EDATE($F91,L$2)>DATE(2025,12,31),"",INDEX([1]A1!I$9:I$175,MATCH(1,--(RIGHT([1]A1!$B$9:$B$175,LEN([1]A1!$B$9:$B$175)-4)=$A91)*([1]A1!$C$9:$C$175=YEAR($F91)),0)))} -> 71629747 | M91: {=IF(EDATE($F91,M$2)>DATE(2025,12,31),"",INDEX([1]A1!J$9:J$175,MATCH(1,--(RIGHT([1]A1!$B$9:$B$175,LEN([1]A1!$B$9:$B$175)-4)=$A91)*([1]A1!$C$9:$C$175=YEAR($F91)),0)))} -> 71629681 | N91: {=IF(EDATE($F91,N$2)>DATE(2025,12,31),"",INDEX([1]A1!K$9:K$175,MATCH(1,--(RIGHT([1]A1!$B$9:$B$175,LEN([1]A1!$B$9:$B$175)-4)=$A91)*([1]A1!$C$9:$C$175=YEAR($F91)),0)))} -> 71629637 | ... FA91: {=IF(EDATE($F91,FA$2)>DATE(2025,12,31),"",INDEX([1]A1!EX$9:EX$175,MATCH(1,--(RIGHT([1]A1!$B$9:$B$175,LEN([1]A1!$B$9:$B$175)-4)=$A91)*([1]A1!$C$9:$C$175=YEAR($F91)),0)))}
A92: Motor PR | B92: Net Written Premium | C92: All | D92: UW Year | E92: USD | F92: =EDATE(F91,12) -> 40544 | G92: {=IF(EDATE($F92,G$2)>DATE(2025,12,31),"",INDEX([1]A1!D$9:D$175,MATCH(1,--(RIGHT([1]A1!$B$9:$B$175,LEN([1]A1!$B$9:$B$175)-4)=$A92)*([1]A1!$C$9:$C$175=YEAR($F92)),0)))} -> 81742884 | H92: {=IF(EDATE($F92,H$2)>DATE(2025,12,31),"",INDEX([1]A1!E$9:E$175,MATCH(1,--(RIGHT([1]A1!$B$9:$B$175,LEN([1]A1!$B$9:$B$175)-4)=$A92)*([1]A1!$C$9:$C$175=YEAR($F92)),0)))} -> 1.3274253e+08 | I92: {=IF(EDATE($F92,I$2)>DATE(2025,12,31),"",INDEX([1]A1!F$9:F$175,MATCH(1,--(RIGHT([1]A1!$B$9:$B$175,LEN([1]A1!$B$9:$B$175)-4)=$A92)*([1]A1!$C$9:$C$175=YEAR($F92)),0)))} -> 1.3635865e+08 | J92: {=IF(EDATE($F92,J$2)>DATE(2025,12,31),"",INDEX([1]A1!G$9:G$175,MATCH(1,--(RIGHT([1]A1!$B$9:$B$175,LEN([1]A1!$B$9:$B$175)-4)=$A92)*([1]A1!$C$9:$C$175=YEAR($F92)),0)))} -> 1.3607284e+08 | K92: {=IF(EDATE($F92,K$2)>DATE(2025,12,31),"",INDEX([1]A1!H$9:H$175,MATCH(1,--(RIGHT([1]A1!$B$9:$B$175,LEN([1]A1!$B$9:$B$175)-4)=$A92)*([1]A1!$C$9:$C$175=YEAR($F92)),0)))} -> 1.3634852e+08 | L92: {=IF(EDATE($F92,L$2)>DATE(2025,12,31),"",INDEX([1]A1!I$9:I$175,MATCH(1,--(RIGHT([1]A1!$B$9:$B$175,LEN([1]A1!$B$9:$B$175)-4)=$A92)*([1]A1!$C$9:$C$175=YEAR($F92)),0)))} -> 1.3626768e+08 | M92: {=IF(EDATE($F92,M$2)>DATE(2025,12,31),"",INDEX([1]A1!J$9:J$175,MATCH(1,--(RIGHT([1]A1!$B$9:$B$175,LEN([1]A1!$B$9:$B$175)-4)=$A92)*([1]A1!$C$9:$C$175=YEAR($F92)),0)))} -> 1.3627604e+08 | N92: {=IF(EDATE($F92,N$2)>DATE(2025,12,31),"",INDEX([1]A1!K$9:K$175,MATCH(1,--(RIGHT([1]A1!$B$9:$B$175,LEN([1]A1!$B$9:$B$175)-4)=$A92)*([1]A1!$C$9:$C$175=YEAR($F92)),0)))} -> 1.3622184e+08 | ... FA92: {=IF(EDATE($F92,FA$2)>DATE(2025,12,31),"",INDEX([1]A1!EX$9:EX$175,MATCH(1,--(RIGHT([1]A1!$B$9:$B$175,LEN([1]A1!$B$9:$B$175)-4)=$A92)*([1]A1!$C$9:$C$175=YEAR($F92)),0)))}
A93: Motor PR | B93: Net Written Premium | C93: All | D93: UW Year | E93: USD | F93: =EDATE(F92,12) -> 40909 | G93: {=IF(EDATE($F93,G$2)>DATE(2025,12,31),"",INDEX([1]A1!D$9:D$175,MATCH(1,--(RIGHT([1]A1!$B$9:$B$175,LEN([1]A1!$B$9:$B$175)-4)=$A93)*([1]A1!$C$9:$C$175=YEAR($F93)),0)))} -> 83409417 | H93: {=IF(EDATE($F93,H$2)>DATE(2025,12,31),"",INDEX([1]A1!E$9:E$175,MATCH(1,--(RIGHT([1]A1!$B$9:$B$175,LEN([1]A1!$B$9:$B$175)-4)=$A93)*([1]A1!$C$9:$C$175=YEAR($F93)),0)))} -> 1.4644545e+08 | I93: {=IF(EDATE($F93,I$2)>DATE(2025,12,31),"",INDEX([1]A1!F$9:F$175,MATCH(1,--(RIGHT([1]A1!$B$9:$B$175,LEN([1]A1!$B$9:$B$175)-4)=$A93)*([1]A1!$C$9:$C$175=YEAR($F93)),0)))} -> 1.4499667e+08 | J93: {=IF(EDATE($F93,J$2)>DATE(2025,12,31),"",INDEX([1]A1!G$9:G$175,MATCH(1,--(RIGHT([1]A1!$B$9:$B$175,LEN([1]A1!$B$9:$B$175)-4)=$A93)*([1]A1!$C$9:$C$175=YEAR($F93)),0)))} -> 1.4456869e+08 | K93: {=IF(EDATE($F93,K$2)>DATE(2025,12,31),"",INDEX([1]A1!H$9:H$175,MATCH(1,--(RIGHT([1]A1!$B$9:$B$175,LEN([1]A1!$B$9:$B$175)-4)=$A93)*([1]A1!$C$9:$C$175=YEAR($F93)),0)))} -> 1.4454294e+08 | L93: {=IF(EDATE($F93,L$2)>DATE(2025,12,31),"",INDEX([1]A1!I$9:I$175,MATCH(1,--(RIGHT([1]A1!$B$9:$B$175,LEN([1]A1!$B$9:$B$175)-4)=$A93)*([1]A1!$C$9:$C$175=YEAR($F93)),0)))} -> 1.4455205e+08 | M93: {=IF(EDATE($F93,M$2)>DATE(2025,12,31),"",INDEX([1]A1!J$9:J$175,MATCH(1,--(RIGHT([1]A1!$B$9:$B$175,LEN([1]A1!$B$9:$B$175)-4)=$A93)*([1]A1!$C$9:$C$175=YEAR($F93)),0)))} -> 1.4453006e+08 | N93: {=IF(EDATE($F93,N$2)>DATE(2025,12,31),"",INDEX([1]A1!K$9:K$175,MATCH(1,--(RIGHT([1]A1!$B$9:$B$175,LEN([1]A1!$B$9:$B$175)-4)=$A93)*([1]A1!$C$9:$C$175=YEAR($F93)),0)))} -> 1.4452984e+08 | ... FA93: {=IF(EDATE($F93,FA$2)>DATE(2025,12,31),"",INDEX([1]A1!EX$9:EX$175,MATCH(1,--(RIGHT([1]A1!$B$9:$B$175,LEN([1]A1!$B$9:$B$175)-4)=$A93)*([1]A1!$C$9:$C$175=YEAR($F93)),0)))}
A94: Motor PR | B94: Net Written Premium | C94: All | D94: UW Year | E94: USD | F94: =EDATE(F93,12) -> 41275 | G94: {=IF(EDATE($F94,G$2)>DATE(2025,12,31),"",INDEX([1]A1!D$9:D$175,MATCH(1,--(RIGHT([1]A1!$B$9:$B$175,LEN([1]A1!$B$9:$B$175)-4)=$A94)*([1]A1!$C$9:$C$175=YEAR($F94)),0)))} -> 1.899442e+08 | H94: {=IF(EDATE($F94,H$2)>DATE(2025,12,31),"",INDEX([1]A1!E$9:E$175,MATCH(1,--(RIGHT([1]A1!$B$9:$B$175,LEN([1]A1!$B$9:$B$175)-4)=$A94)*([1]A1!$C$9:$C$175=YEAR($F94)),0)))} -> 1.754411e+08 | I94: {=IF(EDATE($F94,I$2)>DATE(2025,12,31),"",INDEX([1]A1!F$9:F$175,MATCH(1,--(RIGHT([1]A1!$B$9:$B$175,LEN([1]A1!$B$9:$B$175)-4)=$A94)*([1]A1!$C$9:$C$175=YEAR($F94)),0)))} -> 1.8262136e+08 | J94: {=IF(EDATE($F94,J$2)>DATE(2025,12,31),"",INDEX([1]A1!G$9:G$175,MATCH(1,--(RIGHT([1]A1!$B$9:$B$175,LEN([1]A1!$B$9:$B$175)-4)=$A94)*([1]A1!$C$9:$C$175=YEAR($F94)),0)))} -> 1.8208982e+08 | K94: {=IF(EDATE($F94,K$2)>DATE(2025,12,31),"",INDEX([1]A1!H$9:H$175,MATCH(1,--(RIGHT([1]A1!$B$9:$B$175,LEN([1]A1!$B$9:$B$175)-4)=$A94)*([1]A1!$C$9:$C$175=YEAR($F94)),0)))} -> 1.8210923e+08 | L94: {=IF(EDATE($F94,L$2)>DATE(2025,12,31),"",INDEX([1]A1!I$9:I$175,MATCH(1,--(RIGHT([1]A1!$B$9:$B$175,LEN([1]A1!$B$9:$B$175)-4)=$A94)*([1]A1!$C$9:$C$175=YEAR($F94)),0)))} -> 1.8208491e+08 | M94: {=IF(EDATE($F94,M$2)>DATE(2025,12,31),"",INDEX([1]A1!J$9:J$175,MATCH(1,--(RIGHT([1]A1!$B$9:$B$175,LEN([1]A1!$B$9:$B$175)-4)=$A94)*([1]A1!$C$9:$C$175=YEAR($F94)),0)))} -> 1.8185297e+08 | N94: {=IF(EDATE($F94,N$2)>DATE(2025,12,31),"",INDEX([1]A1!K$9:K$175,MATCH(1,--(RIGHT([1]A1!$B$9:$B$175,LEN([1]A1!$B$9:$B$175)-4)=$A94)*([1]A1!$C$9:$C$175=YEAR($F94)),0)))} -> 1.8187651e+08 | ... FA94: {=IF(EDATE($F94,FA$2)>DATE(2025,12,31),"",INDEX([1]A1!EX$9:EX$175,MATCH(1,--(RIGHT([1]A1!$B$9:$B$175,LEN([1]A1!$B$9:$B$175)-4)=$A94)*([1]A1!$C$9:$C$175=YEAR($F94)),0)))}
A95: Motor PR | B95: Net Written Premium | C95: All | D95: UW Year | E95: USD | F95: =EDATE(F94,12) -> 41640 | G95: {=IF(EDATE($F95,G$2)>DATE(2025,12,31),"",INDEX([1]A1!D$9:D$175,MATCH(1,--(RIGHT([1]A1!$B$9:$B$175,LEN([1]A1!$B$9:$B$175)-4)=$A95)*([1]A1!$C$9:$C$175=YEAR($F95)),0)))} -> 203236516 | H95: {=IF(EDATE($F95,H$2)>DATE(2025,12,31),"",INDEX([1]A1!E$9:E$175,MATCH(1,--(RIGHT([1]A1!$B$9:$B$175,LEN([1]A1!$B$9:$B$175)-4)=$A95)*([1]A1!$C$9:$C$175=YEAR($F95)),0)))} -> 2.1849728e+08 | I95: {=IF(EDATE($F95,I$2)>DATE(2025,12,31),"",INDEX([1]A1!F$9:F$175,MATCH(1,--(RIGHT([1]A1!$B$9:$B$175,LEN([1]A1!$B$9:$B$175)-4)=$A95)*([1]A1!$C$9:$C$175=YEAR($F95)),0)))} -> 2.1896432e+08 | J95: {=IF(EDATE($F95,J$2)>DATE(2025,12,31),"",INDEX([1]A1!G$9:G$175,MATCH(1,--(RIGHT([1]A1!$B$9:$B$175,LEN([1]A1!$B$9:$B$175)-4)=$A95)*([1]A1!$C$9:$C$175=YEAR($F95)),0)))} -> 2.1849996e+08 | K95: {=IF(EDATE($F95,K$2)>DATE(2025,12,31),"",INDEX([1]A1!H$9:H$175,MATCH(1,--(RIGHT([1]A1!$B$9:$B$175,LEN([1]A1!$B$9:$B$175)-4)=$A95)*([1]A1!$C$9:$C$175=YEAR($F95)),0)))} -> 2.1846925e+08 | L95: {=IF(EDATE($F95,L$2)>DATE(2025,12,31),"",INDEX([1]A1!I$9:I$175,MATCH(1,--(RIGHT([1]A1!$B$9:$B$175,LEN([1]A1!$B$9:$B$175)-4)=$A95)*([1]A1!$C$9:$C$175=YEAR($F95)),0)))} -> 2.1846652e+08 | M95: {=IF(EDATE($F95,M$2)>DATE(2025,12,31),"",INDEX([1]A1!J$9:J$175,MATCH(1,--(RIGHT([1]A1!$B$9:$B$175,LEN([1]A1!$B$9:$B$175)-4)=$A95)*([1]A1!$C$9:$C$175=YEAR($F95)),0)))} -> 2.1846558e+08 | N95: {=IF(EDATE($F95,N$2)>DATE(2025,12,31),"",INDEX([1]A1!K$9:K$175,MATCH(1,--(RIGHT([1]A1!$B$9:$B$175,LEN([1]A1!$B$9:$B$175)-4)=$A95)*([1]A1!$C$9:$C$175=YEAR($F95)),0)))} -> 2.1846499e+08 | ... FA95: {=IF(EDATE($F95,FA$2)>DATE(2025,12,31),"",INDEX([1]A1!EX$9:EX$175,MATCH(1,--(RIGHT([1]A1!$B$9:$B$175,LEN([1]A1!$B$9:$B$175)-4)=$A95)*([1]A1!$C$9:$C$175=YEAR($F95)),0)))}
A96: Motor PR | B96: Net Written Premium | C96: All | D96: UW Year | E96: USD | F96: =EDATE(F95,12) -> 42005 | G96: {=IF(EDATE($F96,G$2)>DATE(2025,12,31),"",INDEX([1]A1!D$9:D$175,MATCH(1,--(RIGHT([1]A1!$B$9:$B$175,LEN([1]A1!$B$9:$B$175)-4)=$A96)*([1]A1!$C$9:$C$175=YEAR($F96)),0)))} -> 2.2936847e+08 | H96: {=IF(EDATE($F96,H$2)>DATE(2025,12,31),"",INDEX([1]A1!E$9:E$175,MATCH(1,--(RIGHT([1]A1!$B$9:$B$175,LEN([1]A1!$B$9:$B$175)-4)=$A96)*([1]A1!$C$9:$C$175=YEAR($F96)),0)))} -> 2.3354598e+08 | I96: {=IF(EDATE($F96,I$2)>DATE(2025,12,31),"",INDEX([1]A1!F$9:F$175,MATCH(1,--(RIGHT([1]A1!$B$9:$B$175,LEN([1]A1!$B$9:$B$175)-4)=$A96)*([1]A1!$C$9:$C$175=YEAR($F96)),0)))} -> 2.4256568e+08 | J96: {=IF(EDATE($F96,J$2)>DATE(2025,12,31),"",INDEX([1]A1!G$9:G$175,MATCH(1,--(RIGHT([1]A1!$B$9:$B$175,LEN([1]A1!$B$9:$B$175)-4)=$A96)*([1]A1!$C$9:$C$175=YEAR($F96)),0)))} -> 2.4223648e+08 | K96: {=IF(EDATE($F96,K$2)>DATE(2025,12,31),"",INDEX([1]A1!H$9:H$175,MATCH(1,--(RIGHT([1]A1!$B$9:$B$175,LEN([1]A1!$B$9:$B$175)-4)=$A96)*([1]A1!$C$9:$C$175=YEAR($F96)),0)))} -> 2.421326e+08 | L96: {=IF(EDATE($F96,L$2)>DATE(2025,12,31),"",INDEX([1]A1!I$9:I$175,MATCH(1,--(RIGHT([1]A1!$B$9:$B$175,LEN([1]A1!$B$9:$B$175)-4)=$A96)*([1]A1!$C$9:$C$175=YEAR($F96)),0)))} -> 2.4208022e+08 | M96: {=IF(EDATE($F96,M$2)>DATE(2025,12,31),"",INDEX([1]A1!J$9:J$175,MATCH(1,--(RIGHT([1]A1!$B$9:$B$175,LEN([1]A1!$B$9:$B$175)-4)=$A96)*([1]A1!$C$9:$C$175=YEAR($F96)),0)))} -> 2.4207867e+08 | N96: {=IF(EDATE($F96,N$2)>DATE(2025,12,31),"",INDEX([1]A1!K$9:K$175,MATCH(1,--(RIGHT([1]A1!$B$9:$B$175,LEN([1]A1!$B$9:$B$175)-4)=$A96)*([1]A1!$C$9:$C$175=YEAR($F96)),0)))} -> 2.4203638e+08 | ... FA96: {=IF(EDATE($F96,FA$2)>DATE(2025,12,31),"",INDEX([1]A1!EX$9:EX$175,MATCH(1,--(RIGHT([1]A1!$B$9:$B$175,LEN([1]A1!$B$9:$B$175)-4)=$A96)*([1]A1!$C$9:$C$175=YEAR($F96)),0)))}
A97: Motor PR | B97: Net Written Premium | C97: All | D97: UW Year | E97: USD | F97: =EDATE(F96,12) -> 42370 | G97: {=IF(EDATE($F97,G$2)>DATE(2025,12,31),"",INDEX([1]A1!D$9:D$175,MATCH(1,--(RIGHT([1]A1!$B$9:$B$175,LEN([1]A1!$B$9:$B$175)-4)=$A97)*([1]A1!$C$9:$C$175=YEAR($F97)),0)))} -> 2.6905969e+08 | H97: {=IF(EDATE($F97,H$2)>DATE(2025,12,31),"",INDEX([1]A1!E$9:E$175,MATCH(1,--(RIGHT([1]A1!$B$9:$B$175,LEN([1]A1!$B$9:$B$175)-4)=$A97)*([1]A1!$C$9:$C$175=YEAR($F97)),0)))} -> 2.655924e+08 | I97: {=IF(EDATE($F97,I$2)>DATE(2025,12,31),"",INDEX([1]A1!F$9:F$175,MATCH(1,--(RIGHT([1]A1!$B$9:$B$175,LEN([1]A1!$B$9:$B$175)-4)=$A97)*([1]A1!$C$9:$C$175=YEAR($F97)),0)))} -> 2.6802324e+08 | J97: {=IF(EDATE($F97,J$2)>DATE(2025,12,31),"",INDEX([1]A1!G$9:G$175,MATCH(1,--(RIGHT([1]A1!$B$9:$B$175,LEN([1]A1!$B$9:$B$175)-4)=$A97)*([1]A1!$C$9:$C$175=YEAR($F97)),0)))} -> 2.6916605e+08 | K97: {=IF(EDATE($F97,K$2)>DATE(2025,12,31),"",INDEX([1]A1!H$9:H$175,MATCH(1,--(RIGHT([1]A1!$B$9:$B$175,LEN([1]A1!$B$9:$B$175)-4)=$A97)*([1]A1!$C$9:$C$175=YEAR($F97)),0)))} -> 2.6936122e+08 | L97: {=IF(EDATE($F97,L$2)>DATE(2025,12,31),"",INDEX([1]A1!I$9:I$175,MATCH(1,--(RIGHT([1]A1!$B$9:$B$175,LEN([1]A1!$B$9:$B$175)-4)=$A97)*([1]A1!$C$9:$C$175=YEAR($F97)),0)))} -> 2.6938127e+08 | M97: {=IF(EDATE($F97,M$2)>DATE(2025,12,31),"",INDEX([1]A1!J$9:J$175,MATCH(1,--(RIGHT([1]A1!$B$9:$B$175,LEN([1]A1!$B$9:$B$175)-4)=$A97)*([1]A1!$C$9:$C$175=YEAR($F97)),0)))} -> 2.6925632e+08 | N97: {=IF(EDATE($F97,N$2)>DATE(2025,12,31),"",INDEX([1]A1!K$9:K$175,MATCH(1,--(RIGHT([1]A1!$B$9:$B$175,LEN([1]A1!$B$9:$B$175)-4)=$A97)*([1]A1!$C$9:$C$175=YEAR($F97)),0)))} -> 2.6925389e+08 | ... FA97: {=IF(EDATE($F97,FA$2)>DATE(2025,12,31),"",INDEX([1]A1!EX$9:EX$175,MATCH(1,--(RIGHT([1]A1!$B$9:$B$175,LEN([1]A1!$B$9:$B$175)-4)=$A97)*([1]A1!$C$9:$C$175=YEAR($F97)),0)))}
A98: Motor PR | B98: Net Written Premium | C98: All | D98: UW Year | E98: USD | F98: =EDATE(F97,12) -> 42736 | G98: {=IF(EDATE($F98,G$2)>DATE(2025,12,31),"",INDEX([1]A1!D$9:D$175,MATCH(1,--(RIGHT([1]A1!$B$9:$B$175,LEN([1]A1!$B$9:$B$175)-4)=$A98)*([1]A1!$C$9:$C$175=YEAR($F98)),0)))} -> 3.0644732e+08 | H98: {=IF(EDATE($F98,H$2)>DATE(2025,12,31),"",INDEX([1]A1!E$9:E$175,MATCH(1,--(RIGHT([1]A1!$B$9:$B$175,LEN([1]A1!$B$9:$B$175)-4)=$A98)*([1]A1!$C$9:$C$175=YEAR($F98)),0)))} -> 3.1485971e+08 | I98: {=IF(EDATE($F98,I$2)>DATE(2025,12,31),"",INDEX([1]A1!F$9:F$175,MATCH(1,--(RIGHT([1]A1!$B$9:$B$175,LEN([1]A1!$B$9:$B$175)-4)=$A98)*([1]A1!$C$9:$C$175=YEAR($F98)),0)))} -> 3.221971e+08 | J98: {=IF(EDATE($F98,J$2)>DATE(2025,12,31),"",INDEX([1]A1!G$9:G$175,MATCH(1,--(RIGHT([1]A1!$B$9:$B$175,LEN([1]A1!$B$9:$B$175)-4)=$A98)*([1]A1!$C$9:$C$175=YEAR($F98)),0)))} -> 3.173415e+08 | K98: {=IF(EDATE($F98,K$2)>DATE(2025,12,31),"",INDEX([1]A1!H$9:H$175,MATCH(1,--(RIGHT([1]A1!$B$9:$B$175,LEN([1]A1!$B$9:$B$175)-4)=$A98)*([1]A1!$C$9:$C$175=YEAR($F98)),0)))} -> 3.1409523e+08 | L98: {=IF(EDATE($F98,L$2)>DATE(2025,12,31),"",INDEX([1]A1!I$9:I$175,MATCH(1,--(RIGHT([1]A1!$B$9:$B$175,LEN([1]A1!$B$9:$B$175)-4)=$A98)*([1]A1!$C$9:$C$175=YEAR($F98)),0)))} -> 3.1401602e+08 | M98: {=IF(EDATE($F98,M$2)>DATE(2025,12,31),"",INDEX([1]A1!J$9:J$175,MATCH(1,--(RIGHT([1]A1!$B$9:$B$175,LEN([1]A1!$B$9:$B$175)-4)=$A98)*([1]A1!$C$9:$C$175=YEAR($F98)),0)))} -> 3.1401089e+08 | N98: {=IF(EDATE($F98,N$2)>DATE(2025,12,31),"",INDEX([1]A1!K$9:K$175,MATCH(1,--(RIGHT([1]A1!$B$9:$B$175,LEN([1]A1!$B$9:$B$175)-4)=$A98)*([1]A1!$C$9:$C$175=YEAR($F98)),0)))} -> 3.1400578e+08 | ... FA98: {=IF(EDATE($F98,FA$2)>DATE(2025,12,31),"",INDEX([1]A1!EX$9:EX$175,MATCH(1,--(RIGHT([1]A1!$B$9:$B$175,LEN([1]A1!$B$9:$B$175)-4)=$A98)*([1]A1!$C$9:$C$175=YEAR($F98)),0)))}
A99: Motor PR | B99: Net Written Premium | C99: All | D99: UW Year | E99: USD | F99: =EDATE(F98,12) -> 43101 | G99: {=IF(EDATE($F99,G$2)>DATE(2025,12,31),"",INDEX([1]A1!D$9:D$175,MATCH(1,--(RIGHT([1]A1!$B$9:$B$175,LEN([1]A1!$B$9:$B$175)-4)=$A99)*([1]A1!$C$9:$C$175=YEAR($F99)),0)))} -> 3.4868212e+08 | H99: {=IF(EDATE($F99,H$2)>DATE(2025,12,31),"",INDEX([1]A1!E$9:E$175,MATCH(1,--(RIGHT([1]A1!$B$9:$B$175,LEN([1]A1!$B$9:$B$175)-4)=$A99)*([1]A1!$C$9:$C$175=YEAR($F99)),0)))} -> 3.8210592e+08 | I99: {=IF(EDATE($F99,I$2)>DATE(2025,12,31),"",INDEX([1]A1!F$9:F$175,MATCH(1,--(RIGHT([1]A1!$B$9:$B$175,LEN([1]A1!$B$9:$B$175)-4)=$A99)*([1]A1!$C$9:$C$175=YEAR($F99)),0)))} -> 3.7135947e+08 | J99: {=IF(EDATE($F99,J$2)>DATE(2025,12,31),"",INDEX([1]A1!G$9:G$175,MATCH(1,--(RIGHT([1]A1!$B$9:$B$175,LEN([1]A1!$B$9:$B$175)-4)=$A99)*([1]A1!$C$9:$C$175=YEAR($F99)),0)))} -> 3.5402737e+08 | K99: {=IF(EDATE($F99,K$2)>DATE(2025,12,31),"",INDEX([1]A1!H$9:H$175,MATCH(1,--(RIGHT([1]A1!$B$9:$B$175,LEN([1]A1!$B$9:$B$175)-4)=$A99)*([1]A1!$C$9:$C$175=YEAR($F99)),0)))} -> 3.5372558e+08 | L99: {=IF(EDATE($F99,L$2)>DATE(2025,12,31),"",INDEX([1]A1!I$9:I$175,MATCH(1,--(RIGHT([1]A1!$B$9:$B$175,LEN([1]A1!$B$9:$B$175)-4)=$A99)*([1]A1!$C$9:$C$175=YEAR($F99)),0)))} -> 3.537203e+08 | M99: {=IF(EDATE($F99,M$2)>DATE(2025,12,31),"",INDEX([1]A1!J$9:J$175,MATCH(1,--(RIGHT([1]A1!$B$9:$B$175,LEN([1]A1!$B$9:$B$175)-4)=$A99)*([1]A1!$C$9:$C$175=YEAR($F99)),0)))} -> 3.5370611e+08 | N99: {=IF(EDATE($F99,N$2)>DATE(2025,12,31),"",INDEX([1]A1!K$9:K$175,MATCH(1,--(RIGHT([1]A1!$B$9:$B$175,LEN([1]A1!$B$9:$B$175)-4)=$A99)*([1]A1!$C$9:$C$175=YEAR($F99)),0)))} -> 3.5369586e+08 | ... FA99: {=IF(EDATE($F99,FA$2)>DATE(2025,12,31),"",INDEX([1]A1!EX$9:EX$175,MATCH(1,--(RIGHT([1]A1!$B$9:$B$175,LEN([1]A1!$B$9:$B$175)-4)=$A99)*([1]A1!$C$9:$C$175=YEAR($F99)),0)))}
... A106: Motor PR | B106: Net Written Premium | C106: All | D106: UW Year | E106: USD | F106: =EDATE(F105,12) -> 45658 | G106: {=IF(EDATE($F106,G$2)>DATE(2025,12,31),"",INDEX([1]A1!D$9:D$175,MATCH(1,--(RIGHT([1]A1!$B$9:$B$175,LEN([1]A1!$B$9:$B$175)-4)=$A106)*([1]A1!$C$9:$C$175=YEAR($F106)),0)))} -> 33990482 | H106: {=IF(EDATE($F106,H$2)>DATE(2025,12,31),"",INDEX([1]A1!E$9:E$175,MATCH(1,--(RIGHT([1]A1!$B$9:$B$175,LEN([1]A1!$B$9:$B$175)-4)=$A106)*([1]A1!$C$9:$C$175=YEAR($F106)),0)))} | I106: {=IF(EDATE($F106,I$2)>DATE(2025,12,31),"",INDEX([1]A1!F$9:F$175,MATCH(1,--(RIGHT([1]A1!$B$9:$B$175,LEN([1]A1!$B$9:$B$175)-4)=$A106)*([1]A1!$C$9:$C$175=YEAR($F106)),0)))} | J106: {=IF(EDATE($F106,J$2)>DATE(2025,12,31),"",INDEX([1]A1!G$9:G$175,MATCH(1,--(RIGHT([1]A1!$B$9:$B$175,LEN([1]A1!$B$9:$B$175)-4)=$A106)*([1]A1!$C$9:$C$175=YEAR($F106)),0)))} | K106: {=IF(EDATE($F106,K$2)>DATE(2025,12,31),"",INDEX([1]A1!H$9:H$175,MATCH(1,--(RIGHT([1]A1!$B$9:$B$175,LEN([1]A1!$B$9:$B$175)-4)=$A106)*([1]A1!$C$9:$C$175=YEAR($F106)),0)))} | L106: {=IF(EDATE($F106,L$2)>DATE(2025,12,31),"",INDEX([1]A1!I$9:I$175,MATCH(1,--(RIGHT([1]A1!$B$9:$B$175,LEN([1]A1!$B$9:$B$175)-4)=$A106)*([1]A1!$C$9:$C$175=YEAR($F106)),0)))} | M106: {=IF(EDATE($F106,M$2)>DATE(2025,12,31),"",INDEX([1]A1!J$9:J$175,MATCH(1,--(RIGHT([1]A1!$B$9:$B$175,LEN([1]A1!$B$9:$B$175)-4)=$A106)*([1]A1!$C$9:$C$175=YEAR($F106)),0)))} | N106: {=IF(EDATE($F106,N$2)>DATE(2025,12,31),"",INDEX([1]A1!K$9:K$175,MATCH(1,--(RIGHT([1]A1!$B$9:$B$175,LEN([1]A1!$B$9:$B$175)-4)=$A106)*([1]A1!$C$9:$C$175=YEAR($F106)),0)))} | ... FA106: {=IF(EDATE($F106,FA$2)>DATE(2025,12,31),"",INDEX([1]A1!EX$9:EX$175,MATCH(1,--(RIGHT([1]A1!$B$9:$B$175,LEN([1]A1!$B$9:$B$175)-4)=$A106)*([1]A1!$C$9:$C$175=YEAR($F106)),0)))}
A108: Cyber | B108: Net Written Premium | C108: All | D108: UW Year | E108: USD | F108: =triangle_start_date -> 38718 | G108: {=IF(EDATE($F108,G$2)>DATE(2025,12,31),"",INDEX([1]A1!D$9:D$175,MATCH(1,--(RIGHT([1]A1!$B$9:$B$175,LEN([1]A1!$B$9:$B$175)-4)=$A108)*([1]A1!$C$9:$C$175=YEAR($F108)),0)))} -> 0 | H108: {=IF(EDATE($F108,H$2)>DATE(2025,12,31),"",INDEX([1]A1!E$9:E$175,MATCH(1,--(RIGHT([1]A1!$B$9:$B$175,LEN([1]A1!$B$9:$B$175)-4)=$A108)*([1]A1!$C$9:$C$175=YEAR($F108)),0)))} -> 0 | I108: {=IF(EDATE($F108,I$2)>DATE(2025,12,31),"",INDEX([1]A1!F$9:F$175,MATCH(1,--(RIGHT([1]A1!$B$9:$B$175,LEN([1]A1!$B$9:$B$175)-4)=$A108)*([1]A1!$C$9:$C$175=YEAR($F108)),0)))} -> 0 | J108: {=IF(EDATE($F108,J$2)>DATE(2025,12,31),"",INDEX([1]A1!G$9:G$175,MATCH(1,--(RIGHT([1]A1!$B$9:$B$175,LEN([1]A1!$B$9:$B$175)-4)=$A108)*([1]A1!$C$9:$C$175=YEAR($F108)),0)))} -> 0 | K108: {=IF(EDATE($F108,K$2)>DATE(2025,12,31),"",INDEX([1]A1!H$9:H$175,MATCH(1,--(RIGHT([1]A1!$B$9:$B$175,LEN([1]A1!$B$9:$B$175)-4)=$A108)*([1]A1!$C$9:$C$175=YEAR($F108)),0)))} -> 0 | L108: {=IF(EDATE($F108,L$2)>DATE(2025,12,31),"",INDEX([1]A1!I$9:I$175,MATCH(1,--(RIGHT([1]A1!$B$9:$B$175,LEN([1]A1!$B$9:$B$175)-4)=$A108)*([1]A1!$C$9:$C$175=YEAR($F108)),0)))} -> 0 | M108: {=IF(EDATE($F108,M$2)>DATE(2025,12,31),"",INDEX([1]A1!J$9:J$175,MATCH(1,--(RIGHT([1]A1!$B$9:$B$175,LEN([1]A1!$B$9:$B$175)-4)=$A108)*([1]A1!$C$9:$C$175=YEAR($F108)),0)))} -> 0 | N108: {=IF(EDATE($F108,N$2)>DATE(2025,12,31),"",INDEX([1]A1!K$9:K$175,MATCH(1,--(RIGHT([1]A1!$B$9:$B$175,LEN([1]A1!$B$9:$B$175)-4)=$A108)*([1]A1!$C$9:$C$175=YEAR($F108)),0)))} -> 0 | ... FA108: {=IF(EDATE($F108,FA$2)>DATE(2025,12,31),"",INDEX([1]A1!EX$9:EX$175,MATCH(1,--(RIGHT([1]A1!$B$9:$B$175,LEN([1]A1!$B$9:$B$175)-4)=$A108)*([1]A1!$C$9:$C$175=YEAR($F108)),0)))}
A109: Cyber | B109: Net Written Premium | C109: All | D109: UW Year | E109: USD | F109: =EDATE(F108,12) -> 39083 | G109: {=IF(EDATE($F109,G$2)>DATE(2025,12,31),"",INDEX([1]A1!D$9:D$175,MATCH(1,--(RIGHT([1]A1!$B$9:$B$175,LEN([1]A1!$B$9:$B$175)-4)=$A109)*([1]A1!$C$9:$C$175=YEAR($F109)),0)))} -> 0 | H109: {=IF(EDATE($F109,H$2)>DATE(2025,12,31),"",INDEX([1]A1!E$9:E$175,MATCH(1,--(RIGHT([1]A1!$B$9:$B$175,LEN([1]A1!$B$9:$B$175)-4)=$A109)*([1]A1!$C$9:$C$175=YEAR($F109)),0)))} -> 0 | I109: {=IF(EDATE($F109,I$2)>DATE(2025,12,31),"",INDEX([1]A1!F$9:F$175,MATCH(1,--(RIGHT([1]A1!$B$9:$B$175,LEN([1]A1!$B$9:$B$175)-4)=$A109)*([1]A1!$C$9:$C$175=YEAR($F109)),0)))} -> 0 | J109: {=IF(EDATE($F109,J$2)>DATE(2025,12,31),"",INDEX([1]A1!G$9:G$175,MATCH(1,--(RIGHT([1]A1!$B$9:$B$175,LEN([1]A1!$B$9:$B$175)-4)=$A109)*([1]A1!$C$9:$C$175=YEAR($F109)),0)))} -> 0 | K109: {=IF(EDATE($F109,K$2)>DATE(2025,12,31),"",INDEX([1]A1!H$9:H$175,MATCH(1,--(RIGHT([1]A1!$B$9:$B$175,LEN([1]A1!$B$9:$B$175)-4)=$A109)*([1]A1!$C$9:$C$175=YEAR($F109)),0)))} -> 0 | L109: {=IF(EDATE($F109,L$2)>DATE(2025,12,31),"",INDEX([1]A1!I$9:I$175,MATCH(1,--(RIGHT([1]A1!$B$9:$B$175,LEN([1]A1!$B$9:$B$175)-4)=$A109)*([1]A1!$C$9:$C$175=YEAR($F109)),0)))} -> 0 | M109: {=IF(EDATE($F109,M$2)>DATE(2025,12,31),"",INDEX([1]A1!J$9:J$175,MATCH(1,--(RIGHT([1]A1!$B$9:$B$175,LEN([1]A1!$B$9:$B$175)-4)=$A109)*([1]A1!$C$9:$C$175=YEAR($F109)),0)))} -> 0 | N109: {=IF(EDATE($F109,N$2)>DATE(2025,12,31),"",INDEX([1]A1!K$9:K$175,MATCH(1,--(RIGHT([1]A1!$B$9:$B$175,LEN([1]A1!$B$9:$B$175)-4)=$A109)*([1]A1!$C$9:$C$175=YEAR($F109)),0)))} -> 0 | ... FA109: {=IF(EDATE($F109,FA$2)>DATE(2025,12,31),"",INDEX([1]A1!EX$9:EX$175,MATCH(1,--(RIGHT([1]A1!$B$9:$B$175,LEN([1]A1!$B$9:$B$175)-4)=$A109)*([1]A1!$C$9:$C$175=YEAR($F109)),0)))}
A110: Cyber | B110: Net Written Premium | C110: All | D110: UW Year | E110: USD | F110: =EDATE(F109,12) -> 39448 | G110: {=IF(EDATE($F110,G$2)>DATE(2025,12,31),"",INDEX([1]A1!D$9:D$175,MATCH(1,--(RIGHT([1]A1!$B$9:$B$175,LEN([1]A1!$B$9:$B$175)-4)=$A110)*([1]A1!$C$9:$C$175=YEAR($F110)),0)))} -> 0 | H110: {=IF(EDATE($F110,H$2)>DATE(2025,12,31),"",INDEX([1]A1!E$9:E$175,MATCH(1,--(RIGHT([1]A1!$B$9:$B$175,LEN([1]A1!$B$9:$B$175)-4)=$A110)*([1]A1!$C$9:$C$175=YEAR($F110)),0)))} -> 0 | I110: {=IF(EDATE($F110,I$2)>DATE(2025,12,31),"",INDEX([1]A1!F$9:F$175,MATCH(1,--(RIGHT([1]A1!$B$9:$B$175,LEN([1]A1!$B$9:$B$175)-4)=$A110)*([1]A1!$C$9:$C$175=YEAR($F110)),0)))} -> 0 | J110: {=IF(EDATE($F110,J$2)>DATE(2025,12,31),"",INDEX([1]A1!G$9:G$175,MATCH(1,--(RIGHT([1]A1!$B$9:$B$175,LEN([1]A1!$B$9:$B$175)-4)=$A110)*([1]A1!$C$9:$C$175=YEAR($F110)),0)))} -> 0 | K110: {=IF(EDATE($F110,K$2)>DATE(2025,12,31),"",INDEX([1]A1!H$9:H$175,MATCH(1,--(RIGHT([1]A1!$B$9:$B$175,LEN([1]A1!$B$9:$B$175)-4)=$A110)*([1]A1!$C$9:$C$175=YEAR($F110)),0)))} -> 0 | L110: {=IF(EDATE($F110,L$2)>DATE(2025,12,31),"",INDEX([1]A1!I$9:I$175,MATCH(1,--(RIGHT([1]A1!$B$9:$B$175,LEN([1]A1!$B$9:$B$175)-4)=$A110)*([1]A1!$C$9:$C$175=YEAR($F110)),0)))} -> 0 | M110: {=IF(EDATE($F110,M$2)>DATE(2025,12,31),"",INDEX([1]A1!J$9:J$175,MATCH(1,--(RIGHT([1]A1!$B$9:$B$175,LEN([1]A1!$B$9:$B$175)-4)=$A110)*([1]A1!$C$9:$C$175=YEAR($F110)),0)))} -> 0 | N110: {=IF(EDATE($F110,N$2)>DATE(2025,12,31),"",INDEX([1]A1!K$9:K$175,MATCH(1,--(RIGHT([1]A1!$B$9:$B$175,LEN([1]A1!$B$9:$B$175)-4)=$A110)*([1]A1!$C$9:$C$175=YEAR($F110)),0)))} -> 0 | ... FA110: {=IF(EDATE($F110,FA$2)>DATE(2025,12,31),"",INDEX([1]A1!EX$9:EX$175,MATCH(1,--(RIGHT([1]A1!$B$9:$B$175,LEN([1]A1!$B$9:$B$175)-4)=$A110)*([1]A1!$C$9:$C$175=YEAR($F110)),0)))}
A111: Cyber | B111: Net Written Premium | C111: All | D111: UW Year | E111: USD | F111: =EDATE(F110,12) -> 39814 | G111: {=IF(EDATE($F111,G$2)>DATE(2025,12,31),"",INDEX([1]A1!D$9:D$175,MATCH(1,--(RIGHT([1]A1!$B$9:$B$175,LEN([1]A1!$B$9:$B$175)-4)=$A111)*([1]A1!$C$9:$C$175=YEAR($F111)),0)))} -> 0 | H111: {=IF(EDATE($F111,H$2)>DATE(2025,12,31),"",INDEX([1]A1!E$9:E$175,MATCH(1,--(RIGHT([1]A1!$B$9:$B$175,LEN([1]A1!$B$9:$B$175)-4)=$A111)*([1]A1!$C$9:$C$175=YEAR($F111)),0)))} -> 0 | I111: {=IF(EDATE($F111,I$2)>DATE(2025,12,31),"",INDEX([1]A1!F$9:F$175,MATCH(1,--(RIGHT([1]A1!$B$9:$B$175,LEN([1]A1!$B$9:$B$175)-4)=$A111)*([1]A1!$C$9:$C$175=YEAR($F111)),0)))} -> 0 | J111: {=IF(EDATE($F111,J$2)>DATE(2025,12,31),"",INDEX([1]A1!G$9:G$175,MATCH(1,--(RIGHT([1]A1!$B$9:$B$175,LEN([1]A1!$B$9:$B$175)-4)=$A111)*([1]A1!$C$9:$C$175=YEAR($F111)),0)))} -> 0 | K111: {=IF(EDATE($F111,K$2)>DATE(2025,12,31),"",INDEX([1]A1!H$9:H$175,MATCH(1,--(RIGHT([1]A1!$B$9:$B$175,LEN([1]A1!$B$9:$B$175)-4)=$A111)*([1]A1!$C$9:$C$175=YEAR($F111)),0)))} -> 0 | L111: {=IF(EDATE($F111,L$2)>DATE(2025,12,31),"",INDEX([1]A1!I$9:I$175,MATCH(1,--(RIGHT([1]A1!$B$9:$B$175,LEN([1]A1!$B$9:$B$175)-4)=$A111)*([1]A1!$C$9:$C$175=YEAR($F111)),0)))} -> 0 | M111: {=IF(EDATE($F111,M$2)>DATE(2025,12,31),"",INDEX([1]A1!J$9:J$175,MATCH(1,--(RIGHT([1]A1!$B$9:$B$175,LEN([1]A1!$B$9:$B$175)-4)=$A111)*([1]A1!$C$9:$C$175=YEAR($F111)),0)))} -> 0 | N111: {=IF(EDATE($F111,N$2)>DATE(2025,12,31),"",INDEX([1]A1!K$9:K$175,MATCH(1,--(RIGHT([1]A1!$B$9:$B$175,LEN([1]A1!$B$9:$B$175)-4)=$A111)*([1]A1!$C$9:$C$175=YEAR($F111)),0)))} -> 0 | ... FA111: {=IF(EDATE($F111,FA$2)>DATE(2025,12,31),"",INDEX([1]A1!EX$9:EX$175,MATCH(1,--(RIGHT([1]A1!$B$9:$B$175,LEN([1]A1!$B$9:$B$175)-4)=$A111)*([1]A1!$C$9:$C$175=YEAR($F111)),0)))}
A112: Cyber | B112: Net Written Premium | C112: All | D112: UW Year | E112: USD | F112: =EDATE(F111,12) -> 40179 | G112: {=IF(EDATE($F112,G$2)>DATE(2025,12,31),"",INDEX([1]A1!D$9:D$175,MATCH(1,--(RIGHT([1]A1!$B$9:$B$175,LEN([1]A1!$B$9:$B$175)-4)=$A112)*([1]A1!$C$9:$C$175=YEAR($F112)),0)))} -> 0 | H112: {=IF(EDATE($F112,H$2)>DATE(2025,12,31),"",INDEX([1]A1!E$9:E$175,MATCH(1,--(RIGHT([1]A1!$B$9:$B$175,LEN([1]A1!$B$9:$B$175)-4)=$A112)*([1]A1!$C$9:$C$175=YEAR($F112)),0)))} -> 0 | I112: {=IF(EDATE($F112,I$2)>DATE(2025,12,31),"",INDEX([1]A1!F$9:F$175,MATCH(1,--(RIGHT([1]A1!$B$9:$B$175,LEN([1]A1!$B$9:$B$175)-4)=$A112)*([1]A1!$C$9:$C$175=YEAR($F112)),0)))} -> 0 | J112: {=IF(EDATE($F112,J$2)>DATE(2025,12,31),"",INDEX([1]A1!G$9:G$175,MATCH(1,--(RIGHT([1]A1!$B$9:$B$175,LEN([1]A1!$B$9:$B$175)-4)=$A112)*([1]A1!$C$9:$C$175=YEAR($F112)),0)))} -> 0 | K112: {=IF(EDATE($F112,K$2)>DATE(2025,12,31),"",INDEX([1]A1!H$9:H$175,MATCH(1,--(RIGHT([1]A1!$B$9:$B$175,LEN([1]A1!$B$9:$B$175)-4)=$A112)*([1]A1!$C$9:$C$175=YEAR($F112)),0)))} -> 0 | L112: {=IF(EDATE($F112,L$2)>DATE(2025,12,31),"",INDEX([1]A1!I$9:I$175,MATCH(1,--(RIGHT([1]A1!$B$9:$B$175,LEN([1]A1!$B$9:$B$175)-4)=$A112)*([1]A1!$C$9:$C$175=YEAR($F112)),0)))} -> 0 | M112: {=IF(EDATE($F112,M$2)>DATE(2025,12,31),"",INDEX([1]A1!J$9:J$175,MATCH(1,--(RIGHT([1]A1!$B$9:$B$175,LEN([1]A1!$B$9:$B$175)-4)=$A112)*([1]A1!$C$9:$C$175=YEAR($F112)),0)))} -> 0 | N112: {=IF(EDATE($F112,N$2)>DATE(2025,12,31),"",INDEX([1]A1!K$9:K$175,MATCH(1,--(RIGHT([1]A1!$B$9:$B$175,LEN([1]A1!$B$9:$B$175)-4)=$A112)*([1]A1!$C$9:$C$175=YEAR($F112)),0)))} -> 0 | ... FA112: {=IF(EDATE($F112,FA$2)>DATE(2025,12,31),"",INDEX([1]A1!EX$9:EX$175,MATCH(1,--(RIGHT([1]A1!$B$9:$B$175,LEN([1]A1!$B$9:$B$175)-4)=$A112)*([1]A1!$C$9:$C$175=YEAR($F112)),0)))}
A113: Cyber | B113: Net Written Premium | C113: All | D113: UW Year | E113: USD | F113: =EDATE(F112,12) -> 40544 | G113: {=IF(EDATE($F113,G$2)>DATE(2025,12,31),"",INDEX([1]A1!D$9:D$175,MATCH(1,--(RIGHT([1]A1!$B$9:$B$175,LEN([1]A1!$B$9:$B$175)-4)=$A113)*([1]A1!$C$9:$C$175=YEAR($F113)),0)))} -> 0 | H113: {=IF(EDATE($F113,H$2)>DATE(2025,12,31),"",INDEX([1]A1!E$9:E$175,MATCH(1,--(RIGHT([1]A1!$B$9:$B$175,LEN([1]A1!$B$9:$B$175)-4)=$A113)*([1]A1!$C$9:$C$175=YEAR($F113)),0)))} -> 0 | I113: {=IF(EDATE($F113,I$2)>DATE(2025,12,31),"",INDEX([1]A1!F$9:F$175,MATCH(1,--(RIGHT([1]A1!$B$9:$B$175,LEN([1]A1!$B$9:$B$175)-4)=$A113)*([1]A1!$C$9:$C$175=YEAR($F113)),0)))} -> 0 | J113: {=IF(EDATE($F113,J$2)>DATE(2025,12,31),"",INDEX([1]A1!G$9:G$175,MATCH(1,--(RIGHT([1]A1!$B$9:$B$175,LEN([1]A1!$B$9:$B$175)-4)=$A113)*([1]A1!$C$9:$C$175=YEAR($F113)),0)))} -> 0 | K113: {=IF(EDATE($F113,K$2)>DATE(2025,12,31),"",INDEX([1]A1!H$9:H$175,MATCH(1,--(RIGHT([1]A1!$B$9:$B$175,LEN([1]A1!$B$9:$B$175)-4)=$A113)*([1]A1!$C$9:$C$175=YEAR($F113)),0)))} -> 0 | L113: {=IF(EDATE($F113,L$2)>DATE(2025,12,31),"",INDEX([1]A1!I$9:I$175,MATCH(1,--(RIGHT([1]A1!$B$9:$B$175,LEN([1]A1!$B$9:$B$175)-4)=$A113)*([1]A1!$C$9:$C$175=YEAR($F113)),0)))} -> 0 | M113: {=IF(EDATE($F113,M$2)>DATE(2025,12,31),"",INDEX([1]A1!J$9:J$175,MATCH(1,--(RIGHT([1]A1!$B$9:$B$175,LEN([1]A1!$B$9:$B$175)-4)=$A113)*([1]A1!$C$9:$C$175=YEAR($F113)),0)))} -> 0 | N113: {=IF(EDATE($F113,N$2)>DATE(2025,12,31),"",INDEX([1]A1!K$9:K$175,MATCH(1,--(RIGHT([1]A1!$B$9:$B$175,LEN([1]A1!$B$9:$B$175)-4)=$A113)*([1]A1!$C$9:$C$175=YEAR($F113)),0)))} -> 0 | ... FA113: {=IF(EDATE($F113,FA$2)>DATE(2025,12,31),"",INDEX([1]A1!EX$9:EX$175,MATCH(1,--(RIGHT([1]A1!$B$9:$B$175,LEN([1]A1!$B$9:$B$175)-4)=$A113)*([1]A1!$C$9:$C$175=YEAR($F113)),0)))}
A114: Cyber | B114: Net Written Premium | C114: All | D114: UW Year | E114: USD | F114: =EDATE(F113,12) -> 40909 | G114: {=IF(EDATE($F114,G$2)>DATE(2025,12,31),"",INDEX([1]A1!D$9:D$175,MATCH(1,--(RIGHT([1]A1!$B$9:$B$175,LEN([1]A1!$B$9:$B$175)-4)=$A114)*([1]A1!$C$9:$C$175=YEAR($F114)),0)))} -> 0 | H114: {=IF(EDATE($F114,H$2)>DATE(2025,12,31),"",INDEX([1]A1!E$9:E$175,MATCH(1,--(RIGHT([1]A1!$B$9:$B$175,LEN([1]A1!$B$9:$B$175)-4)=$A114)*([1]A1!$C$9:$C$175=YEAR($F114)),0)))} -> 0 | I114: {=IF(EDATE($F114,I$2)>DATE(2025,12,31),"",INDEX([1]A1!F$9:F$175,MATCH(1,--(RIGHT([1]A1!$B$9:$B$175,LEN([1]A1!$B$9:$B$175)-4)=$A114)*([1]A1!$C$9:$C$175=YEAR($F114)),0)))} -> 0 | J114: {=IF(EDATE($F114,J$2)>DATE(2025,12,31),"",INDEX([1]A1!G$9:G$175,MATCH(1,--(RIGHT([1]A1!$B$9:$B$175,LEN([1]A1!$B$9:$B$175)-4)=$A114)*([1]A1!$C$9:$C$175=YEAR($F114)),0)))} -> 0 | K114: {=IF(EDATE($F114,K$2)>DATE(2025,12,31),"",INDEX([1]A1!H$9:H$175,MATCH(1,--(RIGHT([1]A1!$B$9:$B$175,LEN([1]A1!$B$9:$B$175)-4)=$A114)*([1]A1!$C$9:$C$175=YEAR($F114)),0)))} -> 0 | L114: {=IF(EDATE($F114,L$2)>DATE(2025,12,31),"",INDEX([1]A1!I$9:I$175,MATCH(1,--(RIGHT([1]A1!$B$9:$B$175,LEN([1]A1!$B$9:$B$175)-4)=$A114)*([1]A1!$C$9:$C$175=YEAR($F114)),0)))} -> 0 | M114: {=IF(EDATE($F114,M$2)>DATE(2025,12,31),"",INDEX([1]A1!J$9:J$175,MATCH(1,--(RIGHT([1]A1!$B$9:$B$175,LEN([1]A1!$B$9:$B$175)-4)=$A114)*([1]A1!$C$9:$C$175=YEAR($F114)),0)))} -> 0 | N114: {=IF(EDATE($F114,N$2)>DATE(2025,12,31),"",INDEX([1]A1!K$9:K$175,MATCH(1,--(RIGHT([1]A1!$B$9:$B$175,LEN([1]A1!$B$9:$B$175)-4)=$A114)*([1]A1!$C$9:$C$175=YEAR($F114)),0)))} -> 0 | ... FA114: {=IF(EDATE($F114,FA$2)>DATE(2025,12,31),"",INDEX([1]A1!EX$9:EX$175,MATCH(1,--(RIGHT([1]A1!$B$9:$B$175,LEN([1]A1!$B$9:$B$175)-4)=$A114)*([1]A1!$C$9:$C$175=YEAR($F114)),0)))}
A115: Cyber | B115: Net Written Premium | C115: All | D115: UW Year | E115: USD | F115: =EDATE(F114,12) -> 41275 | G115: {=IF(EDATE($F115,G$2)>DATE(2025,12,31),"",INDEX([1]A1!D$9:D$175,MATCH(1,--(RIGHT([1]A1!$B$9:$B$175,LEN([1]A1!$B$9:$B$175)-4)=$A115)*([1]A1!$C$9:$C$175=YEAR($F115)),0)))} -> 0 | H115: {=IF(EDATE($F115,H$2)>DATE(2025,12,31),"",INDEX([1]A1!E$9:E$175,MATCH(1,--(RIGHT([1]A1!$B$9:$B$175,LEN([1]A1!$B$9:$B$175)-4)=$A115)*([1]A1!$C$9:$C$175=YEAR($F115)),0)))} -> 0 | I115: {=IF(EDATE($F115,I$2)>DATE(2025,12,31),"",INDEX([1]A1!F$9:F$175,MATCH(1,--(RIGHT([1]A1!$B$9:$B$175,LEN([1]A1!$B$9:$B$175)-4)=$A115)*([1]A1!$C$9:$C$175=YEAR($F115)),0)))} -> 0 | J115: {=IF(EDATE($F115,J$2)>DATE(2025,12,31),"",INDEX([1]A1!G$9:G$175,MATCH(1,--(RIGHT([1]A1!$B$9:$B$175,LEN([1]A1!$B$9:$B$175)-4)=$A115)*([1]A1!$C$9:$C$175=YEAR($F115)),0)))} -> 0 | K115: {=IF(EDATE($F115,K$2)>DATE(2025,12,31),"",INDEX([1]A1!H$9:H$175,MATCH(1,--(RIGHT([1]A1!$B$9:$B$175,LEN([1]A1!$B$9:$B$175)-4)=$A115)*([1]A1!$C$9:$C$175=YEAR($F115)),0)))} -> 0 | L115: {=IF(EDATE($F115,L$2)>DATE(2025,12,31),"",INDEX([1]A1!I$9:I$175,MATCH(1,--(RIGHT([1]A1!$B$9:$B$175,LEN([1]A1!$B$9:$B$175)-4)=$A115)*([1]A1!$C$9:$C$175=YEAR($F115)),0)))} -> 0 | M115: {=IF(EDATE($F115,M$2)>DATE(2025,12,31),"",INDEX([1]A1!J$9:J$175,MATCH(1,--(RIGHT([1]A1!$B$9:$B$175,LEN([1]A1!$B$9:$B$175)-4)=$A115)*([1]A1!$C$9:$C$175=YEAR($F115)),0)))} -> 0 | N115: {=IF(EDATE($F115,N$2)>DATE(2025,12,31),"",INDEX([1]A1!K$9:K$175,MATCH(1,--(RIGHT([1]A1!$B$9:$B$175,LEN([1]A1!$B$9:$B$175)-4)=$A115)*([1]A1!$C$9:$C$175=YEAR($F115)),0)))} -> 0 | ... FA115: {=IF(EDATE($F115,FA$2)>DATE(2025,12,31),"",INDEX([1]A1!EX$9:EX$175,MATCH(1,--(RIGHT([1]A1!$B$9:$B$175,LEN([1]A1!$B$9:$B$175)-4)=$A115)*([1]A1!$C$9:$C$175=YEAR($F115)),0)))}
A116: Cyber | B116: Net Written Premium | C116: All | D116: UW Year | E116: USD | F116: =EDATE(F115,12) -> 41640 | G116: {=IF(EDATE($F116,G$2)>DATE(2025,12,31),"",INDEX([1]A1!D$9:D$175,MATCH(1,--(RIGHT([1]A1!$B$9:$B$175,LEN([1]A1!$B$9:$B$175)-4)=$A116)*([1]A1!$C$9:$C$175=YEAR($F116)),0)))} -> 0 | H116: {=IF(EDATE($F116,H$2)>DATE(2025,12,31),"",INDEX([1]A1!E$9:E$175,MATCH(1,--(RIGHT([1]A1!$B$9:$B$175,LEN([1]A1!$B$9:$B$175)-4)=$A116)*([1]A1!$C$9:$C$175=YEAR($F116)),0)))} -> 0 | I116: {=IF(EDATE($F116,I$2)>DATE(2025,12,31),"",INDEX([1]A1!F$9:F$175,MATCH(1,--(RIGHT([1]A1!$B$9:$B$175,LEN([1]A1!$B$9:$B$175)-4)=$A116)*([1]A1!$C$9:$C$175=YEAR($F116)),0)))} -> 0 | J116: {=IF(EDATE($F116,J$2)>DATE(2025,12,31),"",INDEX([1]A1!G$9:G$175,MATCH(1,--(RIGHT([1]A1!$B$9:$B$175,LEN([1]A1!$B$9:$B$175)-4)=$A116)*([1]A1!$C$9:$C$175=YEAR($F116)),0)))} -> 0 | K116: {=IF(EDATE($F116,K$2)>DATE(2025,12,31),"",INDEX([1]A1!H$9:H$175,MATCH(1,--(RIGHT([1]A1!$B$9:$B$175,LEN([1]A1!$B$9:$B$175)-4)=$A116)*([1]A1!$C$9:$C$175=YEAR($F116)),0)))} -> 0 | L116: {=IF(EDATE($F116,L$2)>DATE(2025,12,31),"",INDEX([1]A1!I$9:I$175,MATCH(1,--(RIGHT([1]A1!$B$9:$B$175,LEN([1]A1!$B$9:$B$175)-4)=$A116)*([1]A1!$C$9:$C$175=YEAR($F116)),0)))} -> 0 | M116: {=IF(EDATE($F116,M$2)>DATE(2025,12,31),"",INDEX([1]A1!J$9:J$175,MATCH(1,--(RIGHT([1]A1!$B$9:$B$175,LEN([1]A1!$B$9:$B$175)-4)=$A116)*([1]A1!$C$9:$C$175=YEAR($F116)),0)))} -> 0 | N116: {=IF(EDATE($F116,N$2)>DATE(2025,12,31),"",INDEX([1]A1!K$9:K$175,MATCH(1,--(RIGHT([1]A1!$B$9:$B$175,LEN([1]A1!$B$9:$B$175)-4)=$A116)*([1]A1!$C$9:$C$175=YEAR($F116)),0)))} -> 0 | ... FA116: {=IF(EDATE($F116,FA$2)>DATE(2025,12,31),"",INDEX([1]A1!EX$9:EX$175,MATCH(1,--(RIGHT([1]A1!$B$9:$B$175,LEN([1]A1!$B$9:$B$175)-4)=$A116)*([1]A1!$C$9:$C$175=YEAR($F116)),0)))}
A117: Cyber | B117: Net Written Premium | C117: All | D117: UW Year | E117: USD | F117: =EDATE(F116,12) -> 42005 | G117: {=IF(EDATE($F117,G$2)>DATE(2025,12,31),"",INDEX([1]A1!D$9:D$175,MATCH(1,--(RIGHT([1]A1!$B$9:$B$175,LEN([1]A1!$B$9:$B$175)-4)=$A117)*([1]A1!$C$9:$C$175=YEAR($F117)),0)))} -> 0 | H117: {=IF(EDATE($F117,H$2)>DATE(2025,12,31),"",INDEX([1]A1!E$9:E$175,MATCH(1,--(RIGHT([1]A1!$B$9:$B$175,LEN([1]A1!$B$9:$B$175)-4)=$A117)*([1]A1!$C$9:$C$175=YEAR($F117)),0)))} -> 0 | I117: {=IF(EDATE($F117,I$2)>DATE(2025,12,31),"",INDEX([1]A1!F$9:F$175,MATCH(1,--(RIGHT([1]A1!$B$9:$B$175,LEN([1]A1!$B$9:$B$175)-4)=$A117)*([1]A1!$C$9:$C$175=YEAR($F117)),0)))} -> 0 | J117: {=IF(EDATE($F117,J$2)>DATE(2025,12,31),"",INDEX([1]A1!G$9:G$175,MATCH(1,--(RIGHT([1]A1!$B$9:$B$175,LEN([1]A1!$B$9:$B$175)-4)=$A117)*([1]A1!$C$9:$C$175=YEAR($F117)),0)))} -> 0 | K117: {=IF(EDATE($F117,K$2)>DATE(2025,12,31),"",INDEX([1]A1!H$9:H$175,MATCH(1,--(RIGHT([1]A1!$B$9:$B$175,LEN([1]A1!$B$9:$B$175)-4)=$A117)*([1]A1!$C$9:$C$175=YEAR($F117)),0)))} -> 0 | L117: {=IF(EDATE($F117,L$2)>DATE(2025,12,31),"",INDEX([1]A1!I$9:I$175,MATCH(1,--(RIGHT([1]A1!$B$9:$B$175,LEN([1]A1!$B$9:$B$175)-4)=$A117)*([1]A1!$C$9:$C$175=YEAR($F117)),0)))} -> 0 | M117: {=IF(EDATE($F117,M$2)>DATE(2025,12,31),"",INDEX([1]A1!J$9:J$175,MATCH(1,--(RIGHT([1]A1!$B$9:$B$175,LEN([1]A1!$B$9:$B$175)-4)=$A117)*([1]A1!$C$9:$C$175=YEAR($F117)),0)))} -> 0 | N117: {=IF(EDATE($F117,N$2)>DATE(2025,12,31),"",INDEX([1]A1!K$9:K$175,MATCH(1,--(RIGHT([1]A1!$B$9:$B$175,LEN([1]A1!$B$9:$B$175)-4)=$A117)*([1]A1!$C$9:$C$175=YEAR($F117)),0)))} -> 0 | ... FA117: {=IF(EDATE($F117,FA$2)>DATE(2025,12,31),"",INDEX([1]A1!EX$9:EX$175,MATCH(1,--(RIGHT([1]A1!$B$9:$B$175,LEN([1]A1!$B$9:$B$175)-4)=$A117)*([1]A1!$C$9:$C$175=YEAR($F117)),0)))}
A118: Cyber | B118: Net Written Premium | C118: All | D118: UW Year | E118: USD | F118: =EDATE(F117,12) -> 42370 | G118: {=IF(EDATE($F118,G$2)>DATE(2025,12,31),"",INDEX([1]A1!D$9:D$175,MATCH(1,--(RIGHT([1]A1!$B$9:$B$175,LEN([1]A1!$B$9:$B$175)-4)=$A118)*([1]A1!$C$9:$C$175=YEAR($F118)),0)))} -> 0 | H118: {=IF(EDATE($F118,H$2)>DATE(2025,12,31),"",INDEX([1]A1!E$9:E$175,MATCH(1,--(RIGHT([1]A1!$B$9:$B$175,LEN([1]A1!$B$9:$B$175)-4)=$A118)*([1]A1!$C$9:$C$175=YEAR($F118)),0)))} -> 0 | I118: {=IF(EDATE($F118,I$2)>DATE(2025,12,31),"",INDEX([1]A1!F$9:F$175,MATCH(1,--(RIGHT([1]A1!$B$9:$B$175,LEN([1]A1!$B$9:$B$175)-4)=$A118)*([1]A1!$C$9:$C$175=YEAR($F118)),0)))} -> 0 | J118: {=IF(EDATE($F118,J$2)>DATE(2025,12,31),"",INDEX([1]A1!G$9:G$175,MATCH(1,--(RIGHT([1]A1!$B$9:$B$175,LEN([1]A1!$B$9:$B$175)-4)=$A118)*([1]A1!$C$9:$C$175=YEAR($F118)),0)))} -> 0 | K118: {=IF(EDATE($F118,K$2)>DATE(2025,12,31),"",INDEX([1]A1!H$9:H$175,MATCH(1,--(RIGHT([1]A1!$B$9:$B$175,LEN([1]A1!$B$9:$B$175)-4)=$A118)*([1]A1!$C$9:$C$175=YEAR($F118)),0)))} -> 0 | L118: {=IF(EDATE($F118,L$2)>DATE(2025,12,31),"",INDEX([1]A1!I$9:I$175,MATCH(1,--(RIGHT([1]A1!$B$9:$B$175,LEN([1]A1!$B$9:$B$175)-4)=$A118)*([1]A1!$C$9:$C$175=YEAR($F118)),0)))} -> 0 | M118: {=IF(EDATE($F118,M$2)>DATE(2025,12,31),"",INDEX([1]A1!J$9:J$175,MATCH(1,--(RIGHT([1]A1!$B$9:$B$175,LEN([1]A1!$B$9:$B$175)-4)=$A118)*([1]A1!$C$9:$C$175=YEAR($F118)),0)))} -> 0 | N118: {=IF(EDATE($F118,N$2)>DATE(2025,12,31),"",INDEX([1]A1!K$9:K$175,MATCH(1,--(RIGHT([1]A1!$B$9:$B$175,LEN([1]A1!$B$9:$B$175)-4)=$A118)*([1]A1!$C$9:$C$175=YEAR($F118)),0)))} -> 0 | ... FA118: {=IF(EDATE($F118,FA$2)>DATE(2025,12,31),"",INDEX([1]A1!EX$9:EX$175,MATCH(1,--(RIGHT([1]A1!$B$9:$B$175,LEN([1]A1!$B$9:$B$175)-4)=$A118)*([1]A1!$C$9:$C$175=YEAR($F118)),0)))}
A119: Cyber | B119: Net Written Premium | C119: All | D119: UW Year | E119: USD | F119: =EDATE(F118,12) -> 42736 | G119: {=IF(EDATE($F119,G$2)>DATE(2025,12,31),"",INDEX([1]A1!D$9:D$175,MATCH(1,--(RIGHT([1]A1!$B$9:$B$175,LEN([1]A1!$B$9:$B$175)-4)=$A119)*([1]A1!$C$9:$C$175=YEAR($F119)),0)))} -> 0 | H119: {=IF(EDATE($F119,H$2)>DATE(2025,12,31),"",INDEX([1]A1!E$9:E$175,MATCH(1,--(RIGHT([1]A1!$B$9:$B$175,LEN([1]A1!$B$9:$B$175)-4)=$A119)*([1]A1!$C$9:$C$175=YEAR($F119)),0)))} -> 0 | I119: {=IF(EDATE($F119,I$2)>DATE(2025,12,31),"",INDEX([1]A1!F$9:F$175,MATCH(1,--(RIGHT([1]A1!$B$9:$B$175,LEN([1]A1!$B$9:$B$175)-4)=$A119)*([1]A1!$C$9:$C$175=YEAR($F119)),0)))} -> 0 | J119: {=IF(EDATE($F119,J$2)>DATE(2025,12,31),"",INDEX([1]A1!G$9:G$175,MATCH(1,--(RIGHT([1]A1!$B$9:$B$175,LEN([1]A1!$B$9:$B$175)-4)=$A119)*([1]A1!$C$9:$C$175=YEAR($F119)),0)))} -> 0 | K119: {=IF(EDATE($F119,K$2)>DATE(2025,12,31),"",INDEX([1]A1!H$9:H$175,MATCH(1,--(RIGHT([1]A1!$B$9:$B$175,LEN([1]A1!$B$9:$B$175)-4)=$A119)*([1]A1!$C$9:$C$175=YEAR($F119)),0)))} -> 0 | L119: {=IF(EDATE($F119,L$2)>DATE(2025,12,31),"",INDEX([1]A1!I$9:I$175,MATCH(1,--(RIGHT([1]A1!$B$9:$B$175,LEN([1]A1!$B$9:$B$175)-4)=$A119)*([1]A1!$C$9:$C$175=YEAR($F119)),0)))} -> 0 | M119: {=IF(EDATE($F119,M$2)>DATE(2025,12,31),"",INDEX([1]A1!J$9:J$175,MATCH(1,--(RIGHT([1]A1!$B$9:$B$175,LEN([1]A1!$B$9:$B$175)-4)=$A119)*([1]A1!$C$9:$C$175=YEAR($F119)),0)))} -> 0 | N119: {=IF(EDATE($F119,N$2)>DATE(2025,12,31),"",INDEX([1]A1!K$9:K$175,MATCH(1,--(RIGHT([1]A1!$B$9:$B$175,LEN([1]A1!$B$9:$B$175)-4)=$A119)*([1]A1!$C$9:$C$175=YEAR($F119)),0)))} -> 0 | ... FA119: {=IF(EDATE($F119,FA$2)>DATE(2025,12,31),"",INDEX([1]A1!EX$9:EX$175,MATCH(1,--(RIGHT([1]A1!$B$9:$B$175,LEN([1]A1!$B$9:$B$175)-4)=$A119)*([1]A1!$C$9:$C$175=YEAR($F119)),0)))}
A120: Cyber | B120: Net Written Premium | C120: All | D120: UW Year | E120: USD | F120: =EDATE(F119,12) -> 43101 | G120: {=IF(EDATE($F120,G$2)>DATE(2025,12,31),"",INDEX([1]A1!D$9:D$175,MATCH(1,--(RIGHT([1]A1!$B$9:$B$175,LEN([1]A1!$B$9:$B$175)-4)=$A120)*([1]A1!$C$9:$C$175=YEAR($F120)),0)))} -> 0 | H120: {=IF(EDATE($F120,H$2)>DATE(2025,12,31),"",INDEX([1]A1!E$9:E$175,MATCH(1,--(RIGHT([1]A1!$B$9:$B$175,LEN([1]A1!$B$9:$B$175)-4)=$A120)*([1]A1!$C$9:$C$175=YEAR($F120)),0)))} -> 0 | I120: {=IF(EDATE($F120,I$2)>DATE(2025,12,31),"",INDEX([1]A1!F$9:F$175,MATCH(1,--(RIGHT([1]A1!$B$9:$B$175,LEN([1]A1!$B$9:$B$175)-4)=$A120)*([1]A1!$C$9:$C$175=YEAR($F120)),0)))} -> 0 | J120: {=IF(EDATE($F120,J$2)>DATE(2025,12,31),"",INDEX([1]A1!G$9:G$175,MATCH(1,--(RIGHT([1]A1!$B$9:$B$175,LEN([1]A1!$B$9:$B$175)-4)=$A120)*([1]A1!$C$9:$C$175=YEAR($F120)),0)))} -> 0 | K120: {=IF(EDATE($F120,K$2)>DATE(2025,12,31),"",INDEX([1]A1!H$9:H$175,MATCH(1,--(RIGHT([1]A1!$B$9:$B$175,LEN([1]A1!$B$9:$B$175)-4)=$A120)*([1]A1!$C$9:$C$175=YEAR($F120)),0)))} -> 0 | L120: {=IF(EDATE($F120,L$2)>DATE(2025,12,31),"",INDEX([1]A1!I$9:I$175,MATCH(1,--(RIGHT([1]A1!$B$9:$B$175,LEN([1]A1!$B$9:$B$175)-4)=$A120)*([1]A1!$C$9:$C$175=YEAR($F120)),0)))} -> 0 | M120: {=IF(EDATE($F120,M$2)>DATE(2025,12,31),"",INDEX([1]A1!J$9:J$175,MATCH(1,--(RIGHT([1]A1!$B$9:$B$175,LEN([1]A1!$B$9:$B$175)-4)=$A120)*([1]A1!$C$9:$C$175=YEAR($F120)),0)))} -> 0 | N120: {=IF(EDATE($F120,N$2)>DATE(2025,12,31),"",INDEX([1]A1!K$9:K$175,MATCH(1,--(RIGHT([1]A1!$B$9:$B$175,LEN([1]A1!$B$9:$B$175)-4)=$A120)*([1]A1!$C$9:$C$175=YEAR($F120)),0)))} -> 0 | ... FA120: {=IF(EDATE($F120,FA$2)>DATE(2025,12,31),"",INDEX([1]A1!EX$9:EX$175,MATCH(1,--(RIGHT([1]A1!$B$9:$B$175,LEN([1]A1!$B$9:$B$175)-4)=$A120)*([1]A1!$C$9:$C$175=YEAR($F120)),0)))}
... A127: Cyber | B127: Net Written Premium | C127: All | D127: UW Year | E127: USD | F127: =EDATE(F126,12) -> 45658 | G127: {=IF(EDATE($F127,G$2)>DATE(2025,12,31),"",INDEX([1]A1!D$9:D$175,MATCH(1,--(RIGHT([1]A1!$B$9:$B$175,LEN([1]A1!$B$9:$B$175)-4)=$A127)*([1]A1!$C$9:$C$175=YEAR($F127)),0)))} -> 1.8000697e+08 | H127: {=IF(EDATE($F127,H$2)>DATE(2025,12,31),"",INDEX([1]A1!E$9:E$175,MATCH(1,--(RIGHT([1]A1!$B$9:$B$175,LEN([1]A1!$B$9:$B$175)-4)=$A127)*([1]A1!$C$9:$C$175=YEAR($F127)),0)))} | I127: {=IF(EDATE($F127,I$2)>DATE(2025,12,31),"",INDEX([1]A1!F$9:F$175,MATCH(1,--(RIGHT([1]A1!$B$9:$B$175,LEN([1]A1!$B$9:$B$175)-4)=$A127)*([1]A1!$C$9:$C$175=YEAR($F127)),0)))} | J127: {=IF(EDATE($F127,J$2)>DATE(2025,12,31),"",INDEX([1]A1!G$9:G$175,MATCH(1,--(RIGHT([1]A1!$B$9:$B$175,LEN([1]A1!$B$9:$B$175)-4)=$A127)*([1]A1!$C$9:$C$175=YEAR($F127)),0)))} | K127: {=IF(EDATE($F127,K$2)>DATE(2025,12,31),"",INDEX([1]A1!H$9:H$175,MATCH(1,--(RIGHT([1]A1!$B$9:$B$175,LEN([1]A1!$B$9:$B$175)-4)=$A127)*([1]A1!$C$9:$C$175=YEAR($F127)),0)))} | L127: {=IF(EDATE($F127,L$2)>DATE(2025,12,31),"",INDEX([1]A1!I$9:I$175,MATCH(1,--(RIGHT([1]A1!$B$9:$B$175,LEN([1]A1!$B$9:$B$175)-4)=$A127)*([1]A1!$C$9:$C$175=YEAR($F127)),0)))} | M127: {=IF(EDATE($F127,M$2)>DATE(2025,12,31),"",INDEX([1]A1!J$9:J$175,MATCH(1,--(RIGHT([1]A1!$B$9:$B$175,LEN([1]A1!$B$9:$B$175)-4)=$A127)*([1]A1!$C$9:$C$175=YEAR($F127)),0)))} | N127: {=IF(EDATE($F127,N$2)>DATE(2025,12,31),"",INDEX([1]A1!K$9:K$175,MATCH(1,--(RIGHT([1]A1!$B$9:$B$175,LEN([1]A1!$B$9:$B$175)-4)=$A127)*([1]A1!$C$9:$C$175=YEAR($F127)),0)))} | ... FA127: {=IF(EDATE($F127,FA$2)>DATE(2025,12,31),"",INDEX([1]A1!EX$9:EX$175,MATCH(1,--(RIGHT([1]A1!$B$9:$B$175,LEN([1]A1!$B$9:$B$175)-4)=$A127)*([1]A1!$C$9:$C$175=YEAR($F127)),0)))}
A129: Professional Lines | B129: Paid | C129: All | D129: UW Year | E129: USD | F129: =triangle_start_date -> 38718 | G129: {=IF(EDATE($F129,G$2)>DATE(2025,12,31),"",INDEX([1]A2!D$9:D$175,MATCH(1,--(RIGHT([1]A2!$B$9:$B$175,LEN([1]A2!$B$9:$B$175)-4)=$A129)*([1]A2!$C$9:$C$175=YEAR($F129)),0)))} -> 91625.52 | H129: {=IF(EDATE($F129,H$2)>DATE(2025,12,31),"",INDEX([1]A2!E$9:E$175,MATCH(1,--(RIGHT([1]A2!$B$9:$B$175,LEN([1]A2!$B$9:$B$175)-4)=$A129)*([1]A2!$C$9:$C$175=YEAR($F129)),0)))} -> 1060515.5 | I129: {=IF(EDATE($F129,I$2)>DATE(2025,12,31),"",INDEX([1]A2!F$9:F$175,MATCH(1,--(RIGHT([1]A2!$B$9:$B$175,LEN([1]A2!$B$9:$B$175)-4)=$A129)*([1]A2!$C$9:$C$175=YEAR($F129)),0)))} -> 6707193.8 | J129: {=IF(EDATE($F129,J$2)>DATE(2025,12,31),"",INDEX([1]A2!G$9:G$175,MATCH(1,--(RIGHT([1]A2!$B$9:$B$175,LEN([1]A2!$B$9:$B$175)-4)=$A129)*([1]A2!$C$9:$C$175=YEAR($F129)),0)))} -> 25840712 | K129: {=IF(EDATE($F129,K$2)>DATE(2025,12,31),"",INDEX([1]A2!H$9:H$175,MATCH(1,--(RIGHT([1]A2!$B$9:$B$175,LEN([1]A2!$B$9:$B$175)-4)=$A129)*([1]A2!$C$9:$C$175=YEAR($F129)),0)))} -> 43854207 | L129: {=IF(EDATE($F129,L$2)>DATE(2025,12,31),"",INDEX([1]A2!I$9:I$175,MATCH(1,--(RIGHT([1]A2!$B$9:$B$175,LEN([1]A2!$B$9:$B$175)-4)=$A129)*([1]A2!$C$9:$C$175=YEAR($F129)),0)))} -> 63379359 | M129: {=IF(EDATE($F129,M$2)>DATE(2025,12,31),"",INDEX([1]A2!J$9:J$175,MATCH(1,--(RIGHT([1]A2!$B$9:$B$175,LEN([1]A2!$B$9:$B$175)-4)=$A129)*([1]A2!$C$9:$C$175=YEAR($F129)),0)))} -> 75542199 | N129: {=IF(EDATE($F129,N$2)>DATE(2025,12,31),"",INDEX([1]A2!K$9:K$175,MATCH(1,--(RIGHT([1]A2!$B$9:$B$175,LEN([1]A2!$B$9:$B$175)-4)=$A129)*([1]A2!$C$9:$C$175=YEAR($F129)),0)))} -> 87081092 | ... FA129: {=IF(EDATE($F129,FA$2)>DATE(2025,12,31),"",INDEX([1]A2!EX$9:EX$175,MATCH(1,--(RIGHT([1]A2!$B$9:$B$175,LEN([1]A2!$B$9:$B$175)-4)=$A129)*([1]A2!$C$9:$C$175=YEAR($F129)),0)))}
A130: Professional Lines | B130: Paid | C130: All | D130: UW Year | E130: USD | F130: =EDATE(F129,12) -> 39083 | G130: {=IF(EDATE($F130,G$2)>DATE(2025,12,31),"",INDEX([1]A2!D$9:D$175,MATCH(1,--(RIGHT([1]A2!$B$9:$B$175,LEN([1]A2!$B$9:$B$175)-4)=$A130)*([1]A2!$C$9:$C$175=YEAR($F130)),0)))} -> 0 | H130: {=IF(EDATE($F130,H$2)>DATE(2025,12,31),"",INDEX([1]A2!E$9:E$175,MATCH(1,--(RIGHT([1]A2!$B$9:$B$175,LEN([1]A2!$B$9:$B$175)-4)=$A130)*([1]A2!$C$9:$C$175=YEAR($F130)),0)))} -> 383300.81 | I130: {=IF(EDATE($F130,I$2)>DATE(2025,12,31),"",INDEX([1]A2!F$9:F$175,MATCH(1,--(RIGHT([1]A2!$B$9:$B$175,LEN([1]A2!$B$9:$B$175)-4)=$A130)*([1]A2!$C$9:$C$175=YEAR($F130)),0)))} -> 4334138.7 | J130: {=IF(EDATE($F130,J$2)>DATE(2025,12,31),"",INDEX([1]A2!G$9:G$175,MATCH(1,--(RIGHT([1]A2!$B$9:$B$175,LEN([1]A2!$B$9:$B$175)-4)=$A130)*([1]A2!$C$9:$C$175=YEAR($F130)),0)))} -> 13466637 | K130: {=IF(EDATE($F130,K$2)>DATE(2025,12,31),"",INDEX([1]A2!H$9:H$175,MATCH(1,--(RIGHT([1]A2!$B$9:$B$175,LEN([1]A2!$B$9:$B$175)-4)=$A130)*([1]A2!$C$9:$C$175=YEAR($F130)),0)))} -> 29986952 | L130: {=IF(EDATE($F130,L$2)>DATE(2025,12,31),"",INDEX([1]A2!I$9:I$175,MATCH(1,--(RIGHT([1]A2!$B$9:$B$175,LEN([1]A2!$B$9:$B$175)-4)=$A130)*([1]A2!$C$9:$C$175=YEAR($F130)),0)))} -> 55543069 | M130: {=IF(EDATE($F130,M$2)>DATE(2025,12,31),"",INDEX([1]A2!J$9:J$175,MATCH(1,--(RIGHT([1]A2!$B$9:$B$175,LEN([1]A2!$B$9:$B$175)-4)=$A130)*([1]A2!$C$9:$C$175=YEAR($F130)),0)))} -> 73112752 | N130: {=IF(EDATE($F130,N$2)>DATE(2025,12,31),"",INDEX([1]A2!K$9:K$175,MATCH(1,--(RIGHT([1]A2!$B$9:$B$175,LEN([1]A2!$B$9:$B$175)-4)=$A130)*([1]A2!$C$9:$C$175=YEAR($F130)),0)))} -> 94888711 | ... FA130: {=IF(EDATE($F130,FA$2)>DATE(2025,12,31),"",INDEX([1]A2!EX$9:EX$175,MATCH(1,--(RIGHT([1]A2!$B$9:$B$175,LEN([1]A2!$B$9:$B$175)-4)=$A130)*([1]A2!$C$9:$C$175=YEAR($F130)),0)))}
A131: Professional Lines | B131: Paid | C131: All | D131: UW Year | E131: USD | F131: =EDATE(F130,12) -> 39448 | G131: {=IF(EDATE($F131,G$2)>DATE(2025,12,31),"",INDEX([1]A2!D$9:D$175,MATCH(1,--(RIGHT([1]A2!$B$9:$B$175,LEN([1]A2!$B$9:$B$175)-4)=$A131)*([1]A2!$C$9:$C$175=YEAR($F131)),0)))} -> 0 | H131: {=IF(EDATE($F131,H$2)>DATE(2025,12,31),"",INDEX([1]A2!E$9:E$175,MATCH(1,--(RIGHT([1]A2!$B$9:$B$175,LEN([1]A2!$B$9:$B$175)-4)=$A131)*([1]A2!$C$9:$C$175=YEAR($F131)),0)))} -> 2203181.8 | I131: {=IF(EDATE($F131,I$2)>DATE(2025,12,31),"",INDEX([1]A2!F$9:F$175,MATCH(1,--(RIGHT([1]A2!$B$9:$B$175,LEN([1]A2!$B$9:$B$175)-4)=$A131)*([1]A2!$C$9:$C$175=YEAR($F131)),0)))} -> 9126088.4 | J131: {=IF(EDATE($F131,J$2)>DATE(2025,12,31),"",INDEX([1]A2!G$9:G$175,MATCH(1,--(RIGHT([1]A2!$B$9:$B$175,LEN([1]A2!$B$9:$B$175)-4)=$A131)*([1]A2!$C$9:$C$175=YEAR($F131)),0)))} -> 35001993 | K131: {=IF(EDATE($F131,K$2)>DATE(2025,12,31),"",INDEX([1]A2!H$9:H$175,MATCH(1,--(RIGHT([1]A2!$B$9:$B$175,LEN([1]A2!$B$9:$B$175)-4)=$A131)*([1]A2!$C$9:$C$175=YEAR($F131)),0)))} -> 63858397 | L131: {=IF(EDATE($F131,L$2)>DATE(2025,12,31),"",INDEX([1]A2!I$9:I$175,MATCH(1,--(RIGHT([1]A2!$B$9:$B$175,LEN([1]A2!$B$9:$B$175)-4)=$A131)*([1]A2!$C$9:$C$175=YEAR($F131)),0)))} -> 83450018 | M131: {=IF(EDATE($F131,M$2)>DATE(2025,12,31),"",INDEX([1]A2!J$9:J$175,MATCH(1,--(RIGHT([1]A2!$B$9:$B$175,LEN([1]A2!$B$9:$B$175)-4)=$A131)*([1]A2!$C$9:$C$175=YEAR($F131)),0)))} -> 1.0675063e+08 | N131: {=IF(EDATE($F131,N$2)>DATE(2025,12,31),"",INDEX([1]A2!K$9:K$175,MATCH(1,--(RIGHT([1]A2!$B$9:$B$175,LEN([1]A2!$B$9:$B$175)-4)=$A131)*([1]A2!$C$9:$C$175=YEAR($F131)),0)))} -> 1.2612553e+08 | ... FA131: {=IF(EDATE($F131,FA$2)>DATE(2025,12,31),"",INDEX([1]A2!EX$9:EX$175,MATCH(1,--(RIGHT([1]A2!$B$9:$B$175,LEN([1]A2!$B$9:$B$175)-4)=$A131)*([1]A2!$C$9:$C$175=YEAR($F131)),0)))}
A132: Professional Lines | B132: Paid | C132: All | D132: UW Year | E132: USD | F132: =EDATE(F131,12) -> 39814 | G132: {=IF(EDATE($F132,G$2)>DATE(2025,12,31),"",INDEX([1]A2!D$9:D$175,MATCH(1,--(RIGHT([1]A2!$B$9:$B$175,LEN([1]A2!$B$9:$B$175)-4)=$A132)*([1]A2!$C$9:$C$175=YEAR($F132)),0)))} -> 15849.18 | H132: {=IF(EDATE($F132,H$2)>DATE(2025,12,31),"",INDEX([1]A2!E$9:E$175,MATCH(1,--(RIGHT([1]A2!$B$9:$B$175,LEN([1]A2!$B$9:$B$175)-4)=$A132)*([1]A2!$C$9:$C$175=YEAR($F132)),0)))} -> 1562525.8 | I132: {=IF(EDATE($F132,I$2)>DATE(2025,12,31),"",INDEX([1]A2!F$9:F$175,MATCH(1,--(RIGHT([1]A2!$B$9:$B$175,LEN([1]A2!$B$9:$B$175)-4)=$A132)*([1]A2!$C$9:$C$175=YEAR($F132)),0)))} -> 11189698 | J132: {=IF(EDATE($F132,J$2)>DATE(2025,12,31),"",INDEX([1]A2!G$9:G$175,MATCH(1,--(RIGHT([1]A2!$B$9:$B$175,LEN([1]A2!$B$9:$B$175)-4)=$A132)*([1]A2!$C$9:$C$175=YEAR($F132)),0)))} -> 30199209 | K132: {=IF(EDATE($F132,K$2)>DATE(2025,12,31),"",INDEX([1]A2!H$9:H$175,MATCH(1,--(RIGHT([1]A2!$B$9:$B$175,LEN([1]A2!$B$9:$B$175)-4)=$A132)*([1]A2!$C$9:$C$175=YEAR($F132)),0)))} -> 48089902 | L132: {=IF(EDATE($F132,L$2)>DATE(2025,12,31),"",INDEX([1]A2!I$9:I$175,MATCH(1,--(RIGHT([1]A2!$B$9:$B$175,LEN([1]A2!$B$9:$B$175)-4)=$A132)*([1]A2!$C$9:$C$175=YEAR($F132)),0)))} -> 66997099 | M132: {=IF(EDATE($F132,M$2)>DATE(2025,12,31),"",INDEX([1]A2!J$9:J$175,MATCH(1,--(RIGHT([1]A2!$B$9:$B$175,LEN([1]A2!$B$9:$B$175)-4)=$A132)*([1]A2!$C$9:$C$175=YEAR($F132)),0)))} -> 88681049 | N132: {=IF(EDATE($F132,N$2)>DATE(2025,12,31),"",INDEX([1]A2!K$9:K$175,MATCH(1,--(RIGHT([1]A2!$B$9:$B$175,LEN([1]A2!$B$9:$B$175)-4)=$A132)*([1]A2!$C$9:$C$175=YEAR($F132)),0)))} -> 1.0370657e+08 | ... FA132: {=IF(EDATE($F132,FA$2)>DATE(2025,12,31),"",INDEX([1]A2!EX$9:EX$175,MATCH(1,--(RIGHT([1]A2!$B$9:$B$175,LEN([1]A2!$B$9:$B$175)-4)=$A132)*([1]A2!$C$9:$C$175=YEAR($F132)),0)))}
A133: Professional Lines | B133: Paid | C133: All | D133: UW Year | E133: USD | F133: =EDATE(F132,12) -> 40179 | G133: {=IF(EDATE($F133,G$2)>DATE(2025,12,31),"",INDEX([1]A2!D$9:D$175,MATCH(1,--(RIGHT([1]A2!$B$9:$B$175,LEN([1]A2!$B$9:$B$175)-4)=$A133)*([1]A2!$C$9:$C$175=YEAR($F133)),0)))} -> 12310.54 | H133: {=IF(EDATE($F133,H$2)>DATE(2025,12,31),"",INDEX([1]A2!E$9:E$175,MATCH(1,--(RIGHT([1]A2!$B$9:$B$175,LEN([1]A2!$B$9:$B$175)-4)=$A133)*([1]A2!$C$9:$C$175=YEAR($F133)),0)))} -> 1910919.4 | I133: {=IF(EDATE($F133,I$2)>DATE(2025,12,31),"",INDEX([1]A2!F$9:F$175,MATCH(1,--(RIGHT([1]A2!$B$9:$B$175,LEN([1]A2!$B$9:$B$175)-4)=$A133)*([1]A2!$C$9:$C$175=YEAR($F133)),0)))} -> 10539347 | J133: {=IF(EDATE($F133,J$2)>DATE(2025,12,31),"",INDEX([1]A2!G$9:G$175,MATCH(1,--(RIGHT([1]A2!$B$9:$B$175,LEN([1]A2!$B$9:$B$175)-4)=$A133)*([1]A2!$C$9:$C$175=YEAR($F133)),0)))} -> 24760756 | K133: {=IF(EDATE($F133,K$2)>DATE(2025,12,31),"",INDEX([1]A2!H$9:H$175,MATCH(1,--(RIGHT([1]A2!$B$9:$B$175,LEN([1]A2!$B$9:$B$175)-4)=$A133)*([1]A2!$C$9:$C$175=YEAR($F133)),0)))} -> 52022788 | L133: {=IF(EDATE($F133,L$2)>DATE(2025,12,31),"",INDEX([1]A2!I$9:I$175,MATCH(1,--(RIGHT([1]A2!$B$9:$B$175,LEN([1]A2!$B$9:$B$175)-4)=$A133)*([1]A2!$C$9:$C$175=YEAR($F133)),0)))} -> 78799842 | M133: {=IF(EDATE($F133,M$2)>DATE(2025,12,31),"",INDEX([1]A2!J$9:J$175,MATCH(1,--(RIGHT([1]A2!$B$9:$B$175,LEN([1]A2!$B$9:$B$175)-4)=$A133)*([1]A2!$C$9:$C$175=YEAR($F133)),0)))} -> 1.0119263e+08 | N133: {=IF(EDATE($F133,N$2)>DATE(2025,12,31),"",INDEX([1]A2!K$9:K$175,MATCH(1,--(RIGHT([1]A2!$B$9:$B$175,LEN([1]A2!$B$9:$B$175)-4)=$A133)*([1]A2!$C$9:$C$175=YEAR($F133)),0)))} -> 1.1765964e+08 | ... FA133: {=IF(EDATE($F133,FA$2)>DATE(2025,12,31),"",INDEX([1]A2!EX$9:EX$175,MATCH(1,--(RIGHT([1]A2!$B$9:$B$175,LEN([1]A2!$B$9:$B$175)-4)=$A133)*([1]A2!$C$9:$C$175=YEAR($F133)),0)))}
A134: Professional Lines | B134: Paid | C134: All | D134: UW Year | E134: USD | F134: =EDATE(F133,12) -> 40544 | G134: {=IF(EDATE($F134,G$2)>DATE(2025,12,31),"",INDEX([1]A2!D$9:D$175,MATCH(1,--(RIGHT([1]A2!$B$9:$B$175,LEN([1]A2!$B$9:$B$175)-4)=$A134)*([1]A2!$C$9:$C$175=YEAR($F134)),0)))} -> 4513.66 | H134: {=IF(EDATE($F134,H$2)>DATE(2025,12,31),"",INDEX([1]A2!E$9:E$175,MATCH(1,--(RIGHT([1]A2!$B$9:$B$175,LEN([1]A2!$B$9:$B$175)-4)=$A134)*([1]A2!$C$9:$C$175=YEAR($F134)),0)))} -> 1803504.3 | I134: {=IF(EDATE($F134,I$2)>DATE(2025,12,31),"",INDEX([1]A2!F$9:F$175,MATCH(1,--(RIGHT([1]A2!$B$9:$B$175,LEN([1]A2!$B$9:$B$175)-4)=$A134)*([1]A2!$C$9:$C$175=YEAR($F134)),0)))} -> 10001255 | J134: {=IF(EDATE($F134,J$2)>DATE(2025,12,31),"",INDEX([1]A2!G$9:G$175,MATCH(1,--(RIGHT([1]A2!$B$9:$B$175,LEN([1]A2!$B$9:$B$175)-4)=$A134)*([1]A2!$C$9:$C$175=YEAR($F134)),0)))} -> 31962426 | K134: {=IF(EDATE($F134,K$2)>DATE(2025,12,31),"",INDEX([1]A2!H$9:H$175,MATCH(1,--(RIGHT([1]A2!$B$9:$B$175,LEN([1]A2!$B$9:$B$175)-4)=$A134)*([1]A2!$C$9:$C$175=YEAR($F134)),0)))} -> 53485055 | L134: {=IF(EDATE($F134,L$2)>DATE(2025,12,31),"",INDEX([1]A2!I$9:I$175,MATCH(1,--(RIGHT([1]A2!$B$9:$B$175,LEN([1]A2!$B$9:$B$175)-4)=$A134)*([1]A2!$C$9:$C$175=YEAR($F134)),0)))} -> 85699787 | M134: {=IF(EDATE($F134,M$2)>DATE(2025,12,31),"",INDEX([1]A2!J$9:J$175,MATCH(1,--(RIGHT([1]A2!$B$9:$B$175,LEN([1]A2!$B$9:$B$175)-4)=$A134)*([1]A2!$C$9:$C$175=YEAR($F134)),0)))} -> 1.0952568e+08 | N134: {=IF(EDATE($F134,N$2)>DATE(2025,12,31),"",INDEX([1]A2!K$9:K$175,MATCH(1,--(RIGHT([1]A2!$B$9:$B$175,LEN([1]A2!$B$9:$B$175)-4)=$A134)*([1]A2!$C$9:$C$175=YEAR($F134)),0)))} -> 1.2951593e+08 | ... FA134: {=IF(EDATE($F134,FA$2)>DATE(2025,12,31),"",INDEX([1]A2!EX$9:EX$175,MATCH(1,--(RIGHT([1]A2!$B$9:$B$175,LEN([1]A2!$B$9:$B$175)-4)=$A134)*([1]A2!$C$9:$C$175=YEAR($F134)),0)))}
A135: Professional Lines | B135: Paid | C135: All | D135: UW Year | E135: USD | F135: =EDATE(F134,12) -> 40909 | G135: {=IF(EDATE($F135,G$2)>DATE(2025,12,31),"",INDEX([1]A2!D$9:D$175,MATCH(1,--(RIGHT([1]A2!$B$9:$B$175,LEN([1]A2!$B$9:$B$175)-4)=$A135)*([1]A2!$C$9:$C$175=YEAR($F135)),0)))} -> 7202.46 | H135: {=IF(EDATE($F135,H$2)>DATE(2025,12,31),"",INDEX([1]A2!E$9:E$175,MATCH(1,--(RIGHT([1]A2!$B$9:$B$175,LEN([1]A2!$B$9:$B$175)-4)=$A135)*([1]A2!$C$9:$C$175=YEAR($F135)),0)))} -> 2091287.7 | I135: {=IF(EDATE($F135,I$2)>DATE(2025,12,31),"",INDEX([1]A2!F$9:F$175,MATCH(1,--(RIGHT([1]A2!$B$9:$B$175,LEN([1]A2!$B$9:$B$175)-4)=$A135)*([1]A2!$C$9:$C$175=YEAR($F135)),0)))} -> 14025355 | J135: {=IF(EDATE($F135,J$2)>DATE(2025,12,31),"",INDEX([1]A2!G$9:G$175,MATCH(1,--(RIGHT([1]A2!$B$9:$B$175,LEN([1]A2!$B$9:$B$175)-4)=$A135)*([1]A2!$C$9:$C$175=YEAR($F135)),0)))} -> 31504805 | K135: {=IF(EDATE($F135,K$2)>DATE(2025,12,31),"",INDEX([1]A2!H$9:H$175,MATCH(1,--(RIGHT([1]A2!$B$9:$B$175,LEN([1]A2!$B$9:$B$175)-4)=$A135)*([1]A2!$C$9:$C$175=YEAR($F135)),0)))} -> 60440064 | L135: {=IF(EDATE($F135,L$2)>DATE(2025,12,31),"",INDEX([1]A2!I$9:I$175,MATCH(1,--(RIGHT([1]A2!$B$9:$B$175,LEN([1]A2!$B$9:$B$175)-4)=$A135)*([1]A2!$C$9:$C$175=YEAR($F135)),0)))} -> 83781745 | M135: {=IF(EDATE($F135,M$2)>DATE(2025,12,31),"",INDEX([1]A2!J$9:J$175,MATCH(1,--(RIGHT([1]A2!$B$9:$B$175,LEN([1]A2!$B$9:$B$175)-4)=$A135)*([1]A2!$C$9:$C$175=YEAR($F135)),0)))} -> 1.0083988e+08 | N135: {=IF(EDATE($F135,N$2)>DATE(2025,12,31),"",INDEX([1]A2!K$9:K$175,MATCH(1,--(RIGHT([1]A2!$B$9:$B$175,LEN([1]A2!$B$9:$B$175)-4)=$A135)*([1]A2!$C$9:$C$175=YEAR($F135)),0)))} -> 1.1787924e+08 | ... FA135: {=IF(EDATE($F135,FA$2)>DATE(2025,12,31),"",INDEX([1]A2!EX$9:EX$175,MATCH(1,--(RIGHT([1]A2!$B$9:$B$175,LEN([1]A2!$B$9:$B$175)-4)=$A135)*([1]A2!$C$9:$C$175=YEAR($F135)),0)))}
A136: Professional Lines | B136: Paid | C136: All | D136: UW Year | E136: USD | F136: =EDATE(F135,12) -> 41275 | G136: {=IF(EDATE($F136,G$2)>DATE(2025,12,31),"",INDEX([1]A2!D$9:D$175,MATCH(1,--(RIGHT([1]A2!$B$9:$B$175,LEN([1]A2!$B$9:$B$175)-4)=$A136)*([1]A2!$C$9:$C$175=YEAR($F136)),0)))} -> 2280.27 | H136: {=IF(EDATE($F136,H$2)>DATE(2025,12,31),"",INDEX([1]A2!E$9:E$175,MATCH(1,--(RIGHT([1]A2!$B$9:$B$175,LEN([1]A2!$B$9:$B$175)-4)=$A136)*([1]A2!$C$9:$C$175=YEAR($F136)),0)))} -> 1626291.2 | I136: {=IF(EDATE($F136,I$2)>DATE(2025,12,31),"",INDEX([1]A2!F$9:F$175,MATCH(1,--(RIGHT([1]A2!$B$9:$B$175,LEN([1]A2!$B$9:$B$175)-4)=$A136)*([1]A2!$C$9:$C$175=YEAR($F136)),0)))} -> 9634052.3 | J136: {=IF(EDATE($F136,J$2)>DATE(2025,12,31),"",INDEX([1]A2!G$9:G$175,MATCH(1,--(RIGHT([1]A2!$B$9:$B$175,LEN([1]A2!$B$9:$B$175)-4)=$A136)*([1]A2!$C$9:$C$175=YEAR($F136)),0)))} -> 46446083 | K136: {=IF(EDATE($F136,K$2)>DATE(2025,12,31),"",INDEX([1]A2!H$9:H$175,MATCH(1,--(RIGHT([1]A2!$B$9:$B$175,LEN([1]A2!$B$9:$B$175)-4)=$A136)*([1]A2!$C$9:$C$175=YEAR($F136)),0)))} -> 76589499 | L136: {=IF(EDATE($F136,L$2)>DATE(2025,12,31),"",INDEX([1]A2!I$9:I$175,MATCH(1,--(RIGHT([1]A2!$B$9:$B$175,LEN([1]A2!$B$9:$B$175)-4)=$A136)*([1]A2!$C$9:$C$175=YEAR($F136)),0)))} -> 1.2237417e+08 | M136: {=IF(EDATE($F136,M$2)>DATE(2025,12,31),"",INDEX([1]A2!J$9:J$175,MATCH(1,--(RIGHT([1]A2!$B$9:$B$175,LEN([1]A2!$B$9:$B$175)-4)=$A136)*([1]A2!$C$9:$C$175=YEAR($F136)),0)))} -> 1.7182979e+08 | N136: {=IF(EDATE($F136,N$2)>DATE(2025,12,31),"",INDEX([1]A2!K$9:K$175,MATCH(1,--(RIGHT([1]A2!$B$9:$B$175,LEN([1]A2!$B$9:$B$175)-4)=$A136)*([1]A2!$C$9:$C$175=YEAR($F136)),0)))} -> 1.9467381e+08 | ... FA136: {=IF(EDATE($F136,FA$2)>DATE(2025,12,31),"",INDEX([1]A2!EX$9:EX$175,MATCH(1,--(RIGHT([1]A2!$B$9:$B$175,LEN([1]A2!$B$9:$B$175)-4)=$A136)*([1]A2!$C$9:$C$175=YEAR($F136)),0)))}
A137: Professional Lines | B137: Paid | C137: All | D137: UW Year | E137: USD | F137: =EDATE(F136,12) -> 41640 | G137: {=IF(EDATE($F137,G$2)>DATE(2025,12,31),"",INDEX([1]A2!D$9:D$175,MATCH(1,--(RIGHT([1]A2!$B$9:$B$175,LEN([1]A2!$B$9:$B$175)-4)=$A137)*([1]A2!$C$9:$C$175=YEAR($F137)),0)))} -> 0 | H137: {=IF(EDATE($F137,H$2)>DATE(2025,12,31),"",INDEX([1]A2!E$9:E$175,MATCH(1,--(RIGHT([1]A2!$B$9:$B$175,LEN([1]A2!$B$9:$B$175)-4)=$A137)*([1]A2!$C$9:$C$175=YEAR($F137)),0)))} -> 1563486.3 | I137: {=IF(EDATE($F137,I$2)>DATE(2025,12,31),"",INDEX([1]A2!F$9:F$175,MATCH(1,--(RIGHT([1]A2!$B$9:$B$175,LEN([1]A2!$B$9:$B$175)-4)=$A137)*([1]A2!$C$9:$C$175=YEAR($F137)),0)))} -> 12632666 | J137: {=IF(EDATE($F137,J$2)>DATE(2025,12,31),"",INDEX([1]A2!G$9:G$175,MATCH(1,--(RIGHT([1]A2!$B$9:$B$175,LEN([1]A2!$B$9:$B$175)-4)=$A137)*([1]A2!$C$9:$C$175=YEAR($F137)),0)))} -> 29550966 | K137: {=IF(EDATE($F137,K$2)>DATE(2025,12,31),"",INDEX([1]A2!H$9:H$175,MATCH(1,--(RIGHT([1]A2!$B$9:$B$175,LEN([1]A2!$B$9:$B$175)-4)=$A137)*([1]A2!$C$9:$C$175=YEAR($F137)),0)))} -> 56017954 | L137: {=IF(EDATE($F137,L$2)>DATE(2025,12,31),"",INDEX([1]A2!I$9:I$175,MATCH(1,--(RIGHT([1]A2!$B$9:$B$175,LEN([1]A2!$B$9:$B$175)-4)=$A137)*([1]A2!$C$9:$C$175=YEAR($F137)),0)))} -> 87689744 | M137: {=IF(EDATE($F137,M$2)>DATE(2025,12,31),"",INDEX([1]A2!J$9:J$175,MATCH(1,--(RIGHT([1]A2!$B$9:$B$175,LEN([1]A2!$B$9:$B$175)-4)=$A137)*([1]A2!$C$9:$C$175=YEAR($F137)),0)))} -> 1.1474248e+08 | N137: {=IF(EDATE($F137,N$2)>DATE(2025,12,31),"",INDEX([1]A2!K$9:K$175,MATCH(1,--(RIGHT([1]A2!$B$9:$B$175,LEN([1]A2!$B$9:$B$175)-4)=$A137)*([1]A2!$C$9:$C$175=YEAR($F137)),0)))} -> 1.3012964e+08 | ... FA137: {=IF(EDATE($F137,FA$2)>DATE(2025,12,31),"",INDEX([1]A2!EX$9:EX$175,MATCH(1,--(RIGHT([1]A2!$B$9:$B$175,LEN([1]A2!$B$9:$B$175)-4)=$A137)*([1]A2!$C$9:$C$175=YEAR($F137)),0)))}
A138: Professional Lines | B138: Paid | C138: All | D138: UW Year | E138: USD | F138: =EDATE(F137,12) -> 42005 | G138: {=IF(EDATE($F138,G$2)>DATE(2025,12,31),"",INDEX([1]A2!D$9:D$175,MATCH(1,--(RIGHT([1]A2!$B$9:$B$175,LEN([1]A2!$B$9:$B$175)-4)=$A138)*([1]A2!$C$9:$C$175=YEAR($F138)),0)))} -> 148.28 | H138: {=IF(EDATE($F138,H$2)>DATE(2025,12,31),"",INDEX([1]A2!E$9:E$175,MATCH(1,--(RIGHT([1]A2!$B$9:$B$175,LEN([1]A2!$B$9:$B$175)-4)=$A138)*([1]A2!$C$9:$C$175=YEAR($F138)),0)))} -> 1469389.3 | I138: {=IF(EDATE($F138,I$2)>DATE(2025,12,31),"",INDEX([1]A2!F$9:F$175,MATCH(1,--(RIGHT([1]A2!$B$9:$B$175,LEN([1]A2!$B$9:$B$175)-4)=$A138)*([1]A2!$C$9:$C$175=YEAR($F138)),0)))} -> 13908460 | J138: {=IF(EDATE($F138,J$2)>DATE(2025,12,31),"",INDEX([1]A2!G$9:G$175,MATCH(1,--(RIGHT([1]A2!$B$9:$B$175,LEN([1]A2!$B$9:$B$175)-4)=$A138)*([1]A2!$C$9:$C$175=YEAR($F138)),0)))} -> 43411465 | K138: {=IF(EDATE($F138,K$2)>DATE(2025,12,31),"",INDEX([1]A2!H$9:H$175,MATCH(1,--(RIGHT([1]A2!$B$9:$B$175,LEN([1]A2!$B$9:$B$175)-4)=$A138)*([1]A2!$C$9:$C$175=YEAR($F138)),0)))} -> 91643984 | L138: {=IF(EDATE($F138,L$2)>DATE(2025,12,31),"",INDEX([1]A2!I$9:I$175,MATCH(1,--(RIGHT([1]A2!$B$9:$B$175,LEN([1]A2!$B$9:$B$175)-4)=$A138)*([1]A2!$C$9:$C$175=YEAR($F138)),0)))} -> 1.2806122e+08 | M138: {=IF(EDATE($F138,M$2)>DATE(2025,12,31),"",INDEX([1]A2!J$9:J$175,MATCH(1,--(RIGHT([1]A2!$B$9:$B$175,LEN([1]A2!$B$9:$B$175)-4)=$A138)*([1]A2!$C$9:$C$175=YEAR($F138)),0)))} -> 1.4913857e+08 | N138: {=IF(EDATE($F138,N$2)>DATE(2025,12,31),"",INDEX([1]A2!K$9:K$175,MATCH(1,--(RIGHT([1]A2!$B$9:$B$175,LEN([1]A2!$B$9:$B$175)-4)=$A138)*([1]A2!$C$9:$C$175=YEAR($F138)),0)))} -> 1.8257731e+08 | ... FA138: {=IF(EDATE($F138,FA$2)>DATE(2025,12,31),"",INDEX([1]A2!EX$9:EX$175,MATCH(1,--(RIGHT([1]A2!$B$9:$B$175,LEN([1]A2!$B$9:$B$175)-4)=$A138)*([1]A2!$C$9:$C$175=YEAR($F138)),0)))}
A139: Professional Lines | B139: Paid | C139: All | D139: UW Year | E139: USD | F139: =EDATE(F138,12) -> 42370 | G139: {=IF(EDATE($F139,G$2)>DATE(2025,12,31),"",INDEX([1]A2!D$9:D$175,MATCH(1,--(RIGHT([1]A2!$B$9:$B$175,LEN([1]A2!$B$9:$B$175)-4)=$A139)*([1]A2!$C$9:$C$175=YEAR($F139)),0)))} -> 0 | H139: {=IF(EDATE($F139,H$2)>DATE(2025,12,31),"",INDEX([1]A2!E$9:E$175,MATCH(1,--(RIGHT([1]A2!$B$9:$B$175,LEN([1]A2!$B$9:$B$175)-4)=$A139)*([1]A2!$C$9:$C$175=YEAR($F139)),0)))} -> 2092364.3 | I139: {=IF(EDATE($F139,I$2)>DATE(2025,12,31),"",INDEX([1]A2!F$9:F$175,MATCH(1,--(RIGHT([1]A2!$B$9:$B$175,LEN([1]A2!$B$9:$B$175)-4)=$A139)*([1]A2!$C$9:$C$175=YEAR($F139)),0)))} -> 15766097 | J139: {=IF(EDATE($F139,J$2)>DATE(2025,12,31),"",INDEX([1]A2!G$9:G$175,MATCH(1,--(RIGHT([1]A2!$B$9:$B$175,LEN([1]A2!$B$9:$B$175)-4)=$A139)*([1]A2!$C$9:$C$175=YEAR($F139)),0)))} -> 40820498 | K139: {=IF(EDATE($F139,K$2)>DATE(2025,12,31),"",INDEX([1]A2!H$9:H$175,MATCH(1,--(RIGHT([1]A2!$B$9:$B$175,LEN([1]A2!$B$9:$B$175)-4)=$A139)*([1]A2!$C$9:$C$175=YEAR($F139)),0)))} -> 74369165 | L139: {=IF(EDATE($F139,L$2)>DATE(2025,12,31),"",INDEX([1]A2!I$9:I$175,MATCH(1,--(RIGHT([1]A2!$B$9:$B$175,LEN([1]A2!$B$9:$B$175)-4)=$A139)*([1]A2!$C$9:$C$175=YEAR($F139)),0)))} -> 97510537 | M139: {=IF(EDATE($F139,M$2)>DATE(2025,12,31),"",INDEX([1]A2!J$9:J$175,MATCH(1,--(RIGHT([1]A2!$B$9:$B$175,LEN([1]A2!$B$9:$B$175)-4)=$A139)*([1]A2!$C$9:$C$175=YEAR($F139)),0)))} -> 1.4064161e+08 | N139: {=IF(EDATE($F139,N$2)>DATE(2025,12,31),"",INDEX([1]A2!K$9:K$175,MATCH(1,--(RIGHT([1]A2!$B$9:$B$175,LEN([1]A2!$B$9:$B$175)-4)=$A139)*([1]A2!$C$9:$C$175=YEAR($F139)),0)))} -> 1.6854029e+08 | ... FA139: {=IF(EDATE($F139,FA$2)>DATE(2025,12,31),"",INDEX([1]A2!EX$9:EX$175,MATCH(1,--(RIGHT([1]A2!$B$9:$B$175,LEN([1]A2!$B$9:$B$175)-4)=$A139)*([1]A2!$C$9:$C$175=YEAR($F139)),0)))}
A140: Professional Lines | B140: Paid | C140: All | D140: UW Year | E140: USD | F140: =EDATE(F139,12) -> 42736 | G140: {=IF(EDATE($F140,G$2)>DATE(2025,12,31),"",INDEX([1]A2!D$9:D$175,MATCH(1,--(RIGHT([1]A2!$B$9:$B$175,LEN([1]A2!$B$9:$B$175)-4)=$A140)*([1]A2!$C$9:$C$175=YEAR($F140)),0)))} -> 67386.82 | H140: {=IF(EDATE($F140,H$2)>DATE(2025,12,31),"",INDEX([1]A2!E$9:E$175,MATCH(1,--(RIGHT([1]A2!$B$9:$B$175,LEN([1]A2!$B$9:$B$175)-4)=$A140)*([1]A2!$C$9:$C$175=YEAR($F140)),0)))} -> 2235596.7 | I140: {=IF(EDATE($F140,I$2)>DATE(2025,12,31),"",INDEX([1]A2!F$9:F$175,MATCH(1,--(RIGHT([1]A2!$B$9:$B$175,LEN([1]A2!$B$9:$B$175)-4)=$A140)*([1]A2!$C$9:$C$175=YEAR($F140)),0)))} -> 17572395 | J140: {=IF(EDATE($F140,J$2)>DATE(2025,12,31),"",INDEX([1]A2!G$9:G$175,MATCH(1,--(RIGHT([1]A2!$B$9:$B$175,LEN([1]A2!$B$9:$B$175)-4)=$A140)*([1]A2!$C$9:$C$175=YEAR($F140)),0)))} -> 42097619 | K140: {=IF(EDATE($F140,K$2)>DATE(2025,12,31),"",INDEX([1]A2!H$9:H$175,MATCH(1,--(RIGHT([1]A2!$B$9:$B$175,LEN([1]A2!$B$9:$B$175)-4)=$A140)*([1]A2!$C$9:$C$175=YEAR($F140)),0)))} -> 65906919 | L140: {=IF(EDATE($F140,L$2)>DATE(2025,12,31),"",INDEX([1]A2!I$9:I$175,MATCH(1,--(RIGHT([1]A2!$B$9:$B$175,LEN([1]A2!$B$9:$B$175)-4)=$A140)*([1]A2!$C$9:$C$175=YEAR($F140)),0)))} -> 1.018941e+08 | M140: {=IF(EDATE($F140,M$2)>DATE(2025,12,31),"",INDEX([1]A2!J$9:J$175,MATCH(1,--(RIGHT([1]A2!$B$9:$B$175,LEN([1]A2!$B$9:$B$175)-4)=$A140)*([1]A2!$C$9:$C$175=YEAR($F140)),0)))} -> 1.3994153e+08 | N140: {=IF(EDATE($F140,N$2)>DATE(2025,12,31),"",INDEX([1]A2!K$9:K$175,MATCH(1,--(RIGHT([1]A2!$B$9:$B$175,LEN([1]A2!$B$9:$B$175)-4)=$A140)*([1]A2!$C$9:$C$175=YEAR($F140)),0)))} -> 1.7421517e+08 | ... FA140: {=IF(EDATE($F140,FA$2)>DATE(2025,12,31),"",INDEX([1]A2!EX$9:EX$175,MATCH(1,--(RIGHT([1]A2!$B$9:$B$175,LEN([1]A2!$B$9:$B$175)-4)=$A140)*([1]A2!$C$9:$C$175=YEAR($F140)),0)))}
A141: Professional Lines | B141: Paid | C141: All | D141: UW Year | E141: USD | F141: =EDATE(F140,12) -> 43101 | G141: {=IF(EDATE($F141,G$2)>DATE(2025,12,31),"",INDEX([1]A2!D$9:D$175,MATCH(1,--(RIGHT([1]A2!$B$9:$B$175,LEN([1]A2!$B$9:$B$175)-4)=$A141)*([1]A2!$C$9:$C$175=YEAR($F141)),0)))} -> 79383.79 | H141: {=IF(EDATE($F141,H$2)>DATE(2025,12,31),"",INDEX([1]A2!E$9:E$175,MATCH(1,--(RIGHT([1]A2!$B$9:$B$175,LEN([1]A2!$B$9:$B$175)-4)=$A141)*([1]A2!$C$9:$C$175=YEAR($F141)),0)))} -> 2805060.4 | I141: {=IF(EDATE($F141,I$2)>DATE(2025,12,31),"",INDEX([1]A2!F$9:F$175,MATCH(1,--(RIGHT([1]A2!$B$9:$B$175,LEN([1]A2!$B$9:$B$175)-4)=$A141)*([1]A2!$C$9:$C$175=YEAR($F141)),0)))} -> 20443713 | J141: {=IF(EDATE($F141,J$2)>DATE(2025,12,31),"",INDEX([1]A2!G$9:G$175,MATCH(1,--(RIGHT([1]A2!$B$9:$B$175,LEN([1]A2!$B$9:$B$175)-4)=$A141)*([1]A2!$C$9:$C$175=YEAR($F141)),0)))} -> 44295720 | K141: {=IF(EDATE($F141,K$2)>DATE(2025,12,31),"",INDEX([1]A2!H$9:H$175,MATCH(1,--(RIGHT([1]A2!$B$9:$B$175,LEN([1]A2!$B$9:$B$175)-4)=$A141)*([1]A2!$C$9:$C$175=YEAR($F141)),0)))} -> 72541541 | L141: {=IF(EDATE($F141,L$2)>DATE(2025,12,31),"",INDEX([1]A2!I$9:I$175,MATCH(1,--(RIGHT([1]A2!$B$9:$B$175,LEN([1]A2!$B$9:$B$175)-4)=$A141)*([1]A2!$C$9:$C$175=YEAR($F141)),0)))} -> 1.044243e+08 | M141: {=IF(EDATE($F141,M$2)>DATE(2025,12,31),"",INDEX([1]A2!J$9:J$175,MATCH(1,--(RIGHT([1]A2!$B$9:$B$175,LEN([1]A2!$B$9:$B$175)-4)=$A141)*([1]A2!$C$9:$C$175=YEAR($F141)),0)))} -> 1.3956673e+08 | N141: {=IF(EDATE($F141,N$2)>DATE(2025,12,31),"",INDEX([1]A2!K$9:K$175,MATCH(1,--(RIGHT([1]A2!$B$9:$B$175,LEN([1]A2!$B$9:$B$175)-4)=$A141)*([1]A2!$C$9:$C$175=YEAR($F141)),0)))} -> 1.7406233e+08 | ... FA141: {=IF(EDATE($F141,FA$2)>DATE(2025,12,31),"",INDEX([1]A2!EX$9:EX$175,MATCH(1,--(RIGHT([1]A2!$B$9:$B$175,LEN([1]A2!$B$9:$B$175)-4)=$A141)*([1]A2!$C$9:$C$175=YEAR($F141)),0)))}
... A148: Professional Lines | B148: Paid | C148: All | D148: UW Year | E148: USD | F148: =EDATE(F147,12) -> 45658 | G148: {=IF(EDATE($F148,G$2)>DATE(2025,12,31),"",INDEX([1]A2!D$9:D$175,MATCH(1,--(RIGHT([1]A2!$B$9:$B$175,LEN([1]A2!$B$9:$B$175)-4)=$A148)*([1]A2!$C$9:$C$175=YEAR($F148)),0)))} -> 3221.37 | H148: {=IF(EDATE($F148,H$2)>DATE(2025,12,31),"",INDEX([1]A2!E$9:E$175,MATCH(1,--(RIGHT([1]A2!$B$9:$B$175,LEN([1]A2!$B$9:$B$175)-4)=$A148)*([1]A2!$C$9:$C$175=YEAR($F148)),0)))} | I148: {=IF(EDATE($F148,I$2)>DATE(2025,12,31),"",INDEX([1]A2!F$9:F$175,MATCH(1,--(RIGHT([1]A2!$B$9:$B$175,LEN([1]A2!$B$9:$B$175)-4)=$A148)*([1]A2!$C$9:$C$175=YEAR($F148)),0)))} | J148: {=IF(EDATE($F148,J$2)>DATE(2025,12,31),"",INDEX([1]A2!G$9:G$175,MATCH(1,--(RIGHT([1]A2!$B$9:$B$175,LEN([1]A2!$B$9:$B$175)-4)=$A148)*([1]A2!$C$9:$C$175=YEAR($F148)),0)))} | K148: {=IF(EDATE($F148,K$2)>DATE(2025,12,31),"",INDEX([1]A2!H$9:H$175,MATCH(1,--(RIGHT([1]A2!$B$9:$B$175,LEN([1]A2!$B$9:$B$175)-4)=$A148)*([1]A2!$C$9:$C$175=YEAR($F148)),0)))} | L148: {=IF(EDATE($F148,L$2)>DATE(2025,12,31),"",INDEX([1]A2!I$9:I$175,MATCH(1,--(RIGHT([1]A2!$B$9:$B$175,LEN([1]A2!$B$9:$B$175)-4)=$A148)*([1]A2!$C$9:$C$175=YEAR($F148)),0)))} | M148: {=IF(EDATE($F148,M$2)>DATE(2025,12,31),"",INDEX([1]A2!J$9:J$175,MATCH(1,--(RIGHT([1]A2!$B$9:$B$175,LEN([1]A2!$B$9:$B$175)-4)=$A148)*([1]A2!$C$9:$C$175=YEAR($F148)),0)))} | N148: {=IF(EDATE($F148,N$2)>DATE(2025,12,31),"",INDEX([1]A2!K$9:K$175,MATCH(1,--(RIGHT([1]A2!$B$9:$B$175,LEN([1]A2!$B$9:$B$175)-4)=$A148)*([1]A2!$C$9:$C$175=YEAR($F148)),0)))} | ... FA148: {=IF(EDATE($F148,FA$2)>DATE(2025,12,31),"",INDEX([1]A2!EX$9:EX$175,MATCH(1,--(RIGHT([1]A2!$B$9:$B$175,LEN([1]A2!$B$9:$B$175)-4)=$A148)*([1]A2!$C$9:$C$175=YEAR($F148)),0)))}
...

Sheet Projections
A1: Longtail Reference | B1: UW Year | C1: Ultimate GG Prem ($M) | D1: Latest GG Prem ($M) | E1: Latest GN Prem ($M) | F1: Acq Cost | G1: Cedant Provided Ultimate Loss Ratio | H1: Cedant Provided CoV | I1: Rate Change | J1: Inflation | K1: Historic Year Check | L1: Current Year Check | M1: Min Origin Year: | N1: =YEAR(triangle_start_date) -> 2006 | O1: Max Origin Year: | P1: =YEAR(current_date)-1 -> 2025 | R1: Checks
A2: =Parameters!C219 -> Professional Lines | B2: =YEAR(triangle_start_date) -> 2006 | K2: =IF(OR(B2<$N$1,B2>$P$1),"fail","pass") -> pass | L2: =IFERROR(IF(AND(MATCH(A2,Projection_classes,0),YEAR(current_date)=Projections!B2),"pass","fail"),"") -> fail | R2: =IF(S2>0, "RATE CHANGE COLUMN CONTAINS ERROR VALUES. PLEASE SET THEM TO 0s", "Rate Change column no error values.") -> Rate Change column no error values. | S2: {=SUMPRODUCT(--ISERROR(I2:I1000))} -> 0
A3: =A2 -> Professional Lines | B3: =B2+1 -> 2007 | K3: =IF(OR(B3<$N$1,B3>$P$1),"fail","pass") -> pass | L3: =IFERROR(IF(AND(MATCH(A3,Projection_classes,0),YEAR(current_date)=Projections!B3),"pass","fail"),"") -> fail | R3: =IF(S3>0, "INFLATION COLUMN CONTAINS ERROR VALUES. PLEASE SET THEM TO 0s", "Inflation column no error values.") -> Inflation column no error values. | S3: {=SUMPRODUCT(--ISERROR(J2:J1000))} -> 0
A4: =A3 -> Professional Lines | B4: =B3+1 -> 2008 | K4: =IF(OR(B4<$N$1,B4>$P$1),"fail","pass") -> pass | L4: =IFERROR(IF(AND(MATCH(A4,Projection_classes,0),YEAR(current_date)=Projections!B4),"pass","fail"),"") -> fail
A5: =A4 -> Professional Lines | B5: =B4+1 -> 2009 | K5: =IF(OR(B5<$N$1,B5>$P$1),"fail","pass") -> pass | L5: =IFERROR(IF(AND(MATCH(A5,Projection_classes,0),YEAR(current_date)=Projections!B5),"pass","fail"),"") -> fail
A6: =A5 -> Professional Lines | B6: =B5+1 -> 2010 | K6: =IF(OR(B6<$N$1,B6>$P$1),"fail","pass") -> pass | L6: =IFERROR(IF(AND(MATCH(A6,Projection_classes,0),YEAR(current_date)=Projections!B6),"pass","fail"),"") -> fail | R6: Mandatory
A7: =A6 -> Professional Lines | B7: =B6+1 -> 2011 | K7: =IF(OR(B7<$N$1,B7>$P$1),"fail","pass") -> pass | L7: =IFERROR(IF(AND(MATCH(A7,Projection_classes,0),YEAR(current_date)=Projections!B7),"pass","fail"),"") -> fail | R7: Optional
A8: =A7 -> Professional Lines | B8: =B7+1 -> 2012 | K8: =IF(OR(B8<$N$1,B8>$P$1),"fail","pass") -> pass | L8: =IFERROR(IF(AND(MATCH(A8,Projection_classes,0),YEAR(current_date)=Projections!B8),"pass","fail"),"") -> fail
A9: =A8 -> Professional Lines | B9: =B8+1 -> 2013 | K9: =IF(OR(B9<$N$1,B9>$P$1),"fail","pass") -> pass | L9: =IFERROR(IF(AND(MATCH(A9,Projection_classes,0),YEAR(current_date)=Projections!B9),"pass","fail"),"") -> fail
A10: =A9 -> Professional Lines | B10: =B9+1 -> 2014 | K10: =IF(OR(B10<$N$1,B10>$P$1),"fail","pass") -> pass | L10: =IFERROR(IF(AND(MATCH(A10,Projection_classes,0),YEAR(current_date)=Projections!B10),"pass","fail"),"") -> fail
A11: =A10 -> Professional Lines | B11: =B10+1 -> 2015 | K11: =IF(OR(B11<$N$1,B11>$P$1),"fail","pass") -> pass | L11: =IFERROR(IF(AND(MATCH(A11,Projection_classes,0),YEAR(current_date)=Projections!B11),"pass","fail"),"") -> fail
A12: =A11 -> Professional Lines | B12: =B11+1 -> 2016 | K12: =IF(OR(B12<$N$1,B12>$P$1),"fail","pass") -> pass | L12: =IFERROR(IF(AND(MATCH(A12,Projection_classes,0),YEAR(current_date)=Projections!B12),"pass","fail"),"") -> fail
A13: =A12 -> Professional Lines | B13: =B12+1 -> 2017 | K13: =IF(OR(B13<$N$1,B13>$P$1),"fail","pass") -> pass | L13: =IFERROR(IF(AND(MATCH(A13,Projection_classes,0),YEAR(current_date)=Projections!B13),"pass","fail"),"") -> fail
A14: =A13 -> Professional Lines | B14: =B13+1 -> 2018 | K14: =IF(OR(B14<$N$1,B14>$P$1),"fail","pass") -> pass | L14: =IFERROR(IF(AND(MATCH(A14,Projection_classes,0),YEAR(current_date)=Projections!B14),"pass","fail"),"") -> fail
A15: =A14 -> Professional Lines | B15: =B14+1 -> 2019 | K15: =IF(OR(B15<$N$1,B15>$P$1),"fail","pass") -> pass | L15: =IFERROR(IF(AND(MATCH(A15,Projection_classes,0),YEAR(current_date)=Projections!B15),"pass","fail"),"") -> fail
A16: =A15 -> Professional Lines | B16: =B15+1 -> 2020 | K16: =IF(OR(B16<$N$1,B16>$P$1),"fail","pass") -> pass | L16: =IFERROR(IF(AND(MATCH(A16,Projection_classes,0),YEAR(current_date)=Projections!B16),"pass","fail"),"") -> fail
A17: =A16 -> Professional Lines | B17: =B16+1 -> 2021 | K17: =IF(OR(B17<$N$1,B17>$P$1),"fail","pass") -> pass | L17: =IFERROR(IF(AND(MATCH(A17,Projection_classes,0),YEAR(current_date)=Projections!B17),"pass","fail"),"") -> fail
A18: =A17 -> Professional Lines | B18: =B17+1 -> 2022 | K18: =IF(OR(B18<$N$1,B18>$P$1),"fail","pass") -> pass | L18: =IFERROR(IF(AND(MATCH(A18,Projection_classes,0),YEAR(current_date)=Projections!B18),"pass","fail"),"") -> fail
A19: =A18 -> Professional Lines | B19: =B18+1 -> 2023 | K19: =IF(OR(B19<$N$1,B19>$P$1),"fail","pass") -> pass | L19: =IFERROR(IF(AND(MATCH(A19,Projection_classes,0),YEAR(current_date)=Projections!B19),"pass","fail"),"") -> fail
... A21: =A20 -> Professional Lines | B21: =B20+1 -> 2025 | K21: =IF(OR(B21<$N$1,B21>$P$1),"fail","pass") -> pass | L21: =IFERROR(IF(AND(MATCH(A21,Projection_classes,0),YEAR(current_date)=Projections!B21),"pass","fail"),"") -> fail
A22: =Parameters!C220 -> Liability | B22: =YEAR(triangle_start_date) -> 2006 | K22: =IF(OR(B22<$N$1,B22>$P$1),"fail","pass") -> pass | L22: =IFERROR(IF(AND(MATCH(A22,Projection_classes,0),YEAR(current_date)=Projections!B22),"pass","fail"),"") -> fail
A23: =A22 -> Liability | B23: =B22+1 -> 2007 | K23: =IF(OR(B23<$N$1,B23>$P$1),"fail","pass") -> pass | L23: =IFERROR(IF(AND(MATCH(A23,Projection_classes,0),YEAR(current_date)=Projections!B23),"pass","fail"),"") -> fail
A24: =A23 -> Liability | B24: =B23+1 -> 2008 | K24: =IF(OR(B24<$N$1,B24>$P$1),"fail","pass") -> pass | L24: =IFERROR(IF(AND(MATCH(A24,Projection_classes,0),YEAR(current_date)=Projections!B24),"pass","fail"),"") -> fail
A25: =A24 -> Liability | B25: =B24+1 -> 2009 | K25: =IF(OR(B25<$N$1,B25>$P$1),"fail","pass") -> pass | L25: =IFERROR(IF(AND(MATCH(A25,Projection_classes,0),YEAR(current_date)=Projections!B25),"pass","fail"),"") -> fail
A26: =A25 -> Liability | B26: =B25+1 -> 2010 | K26: =IF(OR(B26<$N$1,B26>$P$1),"fail","pass") -> pass | L26: =IFERROR(IF(AND(MATCH(A26,Projection_classes,0),YEAR(current_date)=Projections!B26),"pass","fail"),"") -> fail
A27: =A26 -> Liability | B27: =B26+1 -> 2011 | K27: =IF(OR(B27<$N$1,B27>$P$1),"fail","pass") -> pass | L27: =IFERROR(IF(AND(MATCH(A27,Projection_classes,0),YEAR(current_date)=Projections!B27),"pass","fail"),"") -> fail
A28: =A27 -> Liability | B28: =B27+1 -> 2012 | K28: =IF(OR(B28<$N$1,B28>$P$1),"fail","pass") -> pass | L28: =IFERROR(IF(AND(MATCH(A28,Projection_classes,0),YEAR(current_date)=Projections!B28),"pass","fail"),"") -> fail
A29: =A28 -> Liability | B29: =B28+1 -> 2013 | K29: =IF(OR(B29<$N$1,B29>$P$1),"fail","pass") -> pass | L29: =IFERROR(IF(AND(MATCH(A29,Projection_classes,0),YEAR(current_date)=Projections!B29),"pass","fail"),"") -> fail
A30: =A29 -> Liability | B30: =B29+1 -> 2014 | K30: =IF(OR(B30<$N$1,B30>$P$1),"fail","pass") -> pass | L30: =IFERROR(IF(AND(MATCH(A30,Projection_classes,0),YEAR(current_date)=Projections!B30),"pass","fail"),"") -> fail
A31: =A30 -> Liability | B31: =B30+1 -> 2015 | K31: =IF(OR(B31<$N$1,B31>$P$1),"fail","pass") -> pass | L31: =IFERROR(IF(AND(MATCH(A31,Projection_classes,0),YEAR(current_date)=Projections!B31),"pass","fail"),"") -> fail
A32: =A31 -> Liability | B32: =B31+1 -> 2016 | K32: =IF(OR(B32<$N$1,B32>$P$1),"fail","pass") -> pass | L32: =IFERROR(IF(AND(MATCH(A32,Projection_classes,0),YEAR(current_date)=Projections!B32),"pass","fail"),"") -> fail
A33: =A32 -> Liability | B33: =B32+1 -> 2017 | K33: =IF(OR(B33<$N$1,B33>$P$1),"fail","pass") -> pass | L33: =IFERROR(IF(AND(MATCH(A33,Projection_classes,0),YEAR(current_date)=Projections!B33),"pass","fail"),"") -> fail
A34: =A33 -> Liability | B34: =B33+1 -> 2018 | K34: =IF(OR(B34<$N$1,B34>$P$1),"fail","pass") -> pass | L34: =IFERROR(IF(AND(MATCH(A34,Projection_classes,0),YEAR(current_date)=Projections!B34),"pass","fail"),"") -> fail
... A41: =A40 -> Liability | B41: =B40+1 -> 2025 | K41: =IF(OR(B41<$N$1,B41>$P$1),"fail","pass") -> pass | L41: =IFERROR(IF(AND(MATCH(A41,Projection_classes,0),YEAR(current_date)=Projections!B41),"pass","fail"),"") -> fail
A42: =Parameters!C221 -> Credit & Surety | B42: =YEAR(triangle_start_date) -> 2006 | K42: =IF(OR(B42<$N$1,B42>$P$1),"fail","pass") -> pass | L42: =IFERROR(IF(AND(MATCH(A42,Projection_classes,0),YEAR(current_date)=Projections!B42),"pass","fail"),"") -> fail
A43: =A42 -> Credit & Surety | B43: =B42+1 -> 2007 | K43: =IF(OR(B43<$N$1,B43>$P$1),"fail","pass") -> pass | L43: =IFERROR(IF(AND(MATCH(A43,Projection_classes,0),YEAR(current_date)=Projections!B43),"pass","fail"),"") -> fail
A44: =A43 -> Credit & Surety | B44: =B43+1 -> 2008 | K44: =IF(OR(B44<$N$1,B44>$P$1),"fail","pass") -> pass | L44: =IFERROR(IF(AND(MATCH(A44,Projection_classes,0),YEAR(current_date)=Projections!B44),"pass","fail"),"") -> fail
A45: =A44 -> Credit & Surety | B45: =B44+1 -> 2009 | K45: =IF(OR(B45<$N$1,B45>$P$1),"fail","pass") -> pass | L45: =IFERROR(IF(AND(MATCH(A45,Projection_classes,0),YEAR(current_date)=Projections!B45),"pass","fail"),"") -> fail
